Workbook

Sheet Inputs
A1: Tail-Expert Value Model — Inputs
A2: Edit the blue/yellow cells only. Every other sheet recalculates from these.
A4: DISTRIBUTION
A5: Distribution (1=Pareto, 2=Lognormal, 3=Weibull, 4=Normal) | B5: 1 | C5: All four are fitted to the same anchors below; the Compare sheet shows all four side by side.
A6: Fitted shape applies to (1 = value added V, 2 = skill S, so V is proportional to S^2) | B6: 1 | C6: Option 2 squares the fitted variable. For a Pareto this halves the effective exponent.
A8: FITTING ANCHORS — two upper-tail quantiles
A9: Anchor 1 — upper-tail probability (0.5 = median) | B9: 0.5
A10: Anchor 1 — skill value (bp per month) | B10: 43 | C10: PST (2015) report 42 bp/month as the MEAN, not the median. See the Notes sheet.
A11: Anchor 2 — upper-tail probability (0.1 = 90th percentile) | B11: 0.1
A12: Anchor 2 — skill value (bp per month) | B12: 123 | C12: PST (2015): 90th percentile of fund skill, 123 bp/month in 2011.
A13: Target mean for Goal Seek (bp per month) | B13: 42 | C13: Not used in the calculation. The Diagnostics block on Results shows the gap; run Goal Seek on it to solve an anchor.
A15: POPULATION
A16: Number of decision-makers (N) | B16: 2264400
A17: Rank-1 plotting constant (0.5 = Hazen, 1.0 = Weibull) | B17: 0.5 | C17: Affects the single best person only; ranks past about 50 are insensitive to it.
A18: Bands per tier segment (fixed when the Grid was built) | B18: 60 | C18: Read-only — changing this requires rebuilding the Grid sheet.
A20: TIER BOUNDARIES — upper-tail fraction of the population
A21: Tier 1 upper edge (top 0.01%) | B21: 0.0001
A22: Tier 2 upper edge (top 0.1%) | B22: 0.001
A23: Tier 3 upper edge (top 1%) | B23: 0.01
A24: Tier 4 upper edge (top 10%) | B24: 0.1
A25: Tier 5 upper edge (all) | B25: 1
A27: ALPHA POOL SCENARIOS ($ per year)
A28: Pool 1 — primary; drives A* and S | B28: 1200000000000
A29: Pool 2 | B29: 840000000000
A30: Pool 3 | B30: 600000000000
A31: Pool 4 | B31: 400000000000
C32: Total gross alpha available to the whole population each year.
A34: CAPITAL AND COMPARATORS
A35: Capital run by the top 1% ($) | B35: 30000000000000 | C35: An assumption, not a measurement. See the Diagnostics block on the Results sheet for the gross alpha it implies.
A36: Reference gross alpha for comparison | B36: 0.008 | C36: Berk & van Binsbergen (2015) Table 8: 6.5 bp/month value-weighted, about 0.80%/yr.
A37: Average financial services salary ($) | B37: 52804 | C37: User-supplied.

Sheet Results
A1: Value added and optimal book size by tier
A2: ="Distribution: "&Fit!B33&" | shape applied to "&IF(Inputs!B6=1,"value added V","skill S (V proportional to S^2)")&" | N = "&TEXT(Inputs!B16,"#,##0") -> Distribution: Pareto | shape applied to value added V | N = 2,264,400
A4: Tier | B4: People | C4: Share of pool | D4: V* at Pool 1 | E4: V* at Pool 2 | F4: V* at Pool 3 | G4: V* at Pool 4 | H4: A* (Pool 1) | I4: S (Pool 1) | J4: x avg salary
A5: Single best (rank 1) | B5: =Grid!F3 -> 1 | C5: =Grid!O3/Grid!$AB$1 -> 0.0034124819 | D5: =$C5*Inputs!$B$28/$B5 -> 4.0949783e+09 | E5: =$C5*Inputs!$B$29/$B5 -> 2.8664848e+09 | F5: =$C5*Inputs!$B$30/$B5 -> 2.0474891e+09 | G5: =$C5*Inputs!$B$31/$B5 -> 1.3649928e+09 | H5: =Grid!R3 -> 2.9566732e+10 | I5: =Grid!S3 -> 0.27699904 | J5: =D5/Inputs!$B$37 -> 77550.531
A6: Top 0.01% | B6: =SUMIF(Grid!$G$3:$G$303,1,Grid!$F$3:$F$303) -> 226.44 | C6: =SUMIF(Grid!$G$3:$G$303,1,Grid!$O$3:$O$303)/Grid!$AB$1 -> 0.038195879 | D6: =$C6*Inputs!$B$28/$B6 -> 2.0241589e+08 | E6: =$C6*Inputs!$B$29/$B6 -> 1.4169113e+08 | F6: =$C6*Inputs!$B$30/$B6 -> 1.0120795e+08 | G6: =$C6*Inputs!$B$31/$B6 -> 67471964 | H6: =SUMIF(Grid!$G$3:$G$303,1,Grid!$T$3:$T$303)/B6 -> 5.93549e+09 | I6: =2*Grid!$AB$6*H6 -> 0.055607262 | J6: =D6/Inputs!$B$37 -> 3833.3439
A7: Rest of top 0.1% | B7: =SUMIF(Grid!$G$3:$G$303,2,Grid!$F$3:$F$303) -> 2037.96 | C7: =SUMIF(Grid!$G$3:$G$303,2,Grid!$O$3:$O$303)/Grid!$AB$1 -> 0.050211379 | D7: =$C7*Inputs!$B$28/$B7 -> 29565671 | E7: =$C7*Inputs!$B$29/$B7 -> 20695970 | F7: =$C7*Inputs!$B$30/$B7 -> 14782836 | G7: =$C7*Inputs!$B$31/$B7 -> 9855223.7 | H7: =SUMIF(Grid!$G$3:$G$303,2,Grid!$T$3:$T$303)/B7 -> 2.460331e+09 | I7: =2*Grid!$AB$6*H7 -> 0.02304987 | J7: =D7/Inputs!$B$37 -> 559.91347
A8: Rest of top 1% | B8: =SUMIF(Grid!$G$3:$G$303,3,Grid!$F$3:$F$303) -> 20379.6 | C8: =SUMIF(Grid!$G$3:$G$303,3,Grid!$O$3:$O$303)/Grid!$AB$1 -> 0.11163206 | D8: =$C8*Inputs!$B$28/$B8 -> 6573164.8 | E8: =$C8*Inputs!$B$29/$B8 -> 4601215.3 | F8: =$C8*Inputs!$B$30/$B8 -> 3286582.4 | G8: =$C8*Inputs!$B$31/$B8 -> 2191054.9 | H8: =SUMIF(Grid!$G$3:$G$303,3,Grid!$T$3:$T$303)/B8 -> 1.1600773e+09 | I8: =2*Grid!$AB$6*H8 -> 0.010868306 | J8: =D8/Inputs!$B$37 -> 124.48233
A9: Top 1% (cumulative) | B9: =SUMIF(Grid!$G$3:$G$303,"<=3",Grid!$F$3:$F$303) -> 22644 | C9: =SUMIF(Grid!$G$3:$G$303,"<=3",Grid!$O$3:$O$303)/Grid!$AB$1 -> 0.20003932 | D9: =$C9*Inputs!$B$28/$B9 -> 10600918 | E9: =$C9*Inputs!$B$29/$B9 -> 7420642.3 | F9: =$C9*Inputs!$B$30/$B9 -> 5300458.8 | G9: =$C9*Inputs!$B$31/$B9 -> 3533639.2 | H9: =Grid!$AB$8/B9 -> 1.3248543e+09 | I9: =2*Grid!$AB$6*H9 -> 0.012412036 | J9: =D9/Inputs!$B$37 -> 200.75975
A10: Rest of top 10% | B10: =SUMIF(Grid!$G$3:$G$303,4,Grid!$F$3:$F$303) -> 203796 | C10: =SUMIF(Grid!$G$3:$G$303,4,Grid!$O$3:$O$303)/Grid!$AB$1 -> 0.2481851 | D10: =$C10*Inputs!$B$28/$B10 -> 1461373.7 | E10: =$C10*Inputs!$B$29/$B10 -> 1022961.6 | F10: =$C10*Inputs!$B$30/$B10 -> 730686.86 | G10: =$C10*Inputs!$B$31/$B10 -> 487124.57 | H10: — | I10: — | J10: =D10/Inputs!$B$37 -> 27.675436
A11: Bottom 90% | B11: =SUMIF(Grid!$G$3:$G$303,5,Grid!$F$3:$F$303) -> 2037960 | C11: =SUMIF(Grid!$G$3:$G$303,5,Grid!$O$3:$O$303)/Grid!$AB$1 -> 0.55177559 | D11: =$C11*Inputs!$B$28/$B11 -> 324898.77 | E11: =$C11*Inputs!$B$29/$B11 -> 227429.14 | F11: =$C11*Inputs!$B$30/$B11 -> 162449.39 | G11: =$C11*Inputs!$B$31/$B11 -> 108299.59 | H11: — | I11: — | J11: =D11/Inputs!$B$37 -> 6.1529197
A12: Total | B12: =SUM(Grid!$F$3:$F$303) -> 2264400 | C12: =SUM(Grid!$O$3:$O$303)/Grid!$AB$1 -> 1 | D12: =$C12*Inputs!$B$28/$B12 -> 529941.71 | E12: =$C12*Inputs!$B$29/$B12 -> 370959.19 | F12: =$C12*Inputs!$B$30/$B12 -> 264970.85 | G12: =$C12*Inputs!$B$31/$B12 -> 176647.24 | J12: =D12/Inputs!$B$37 -> 10.036014
A13: V* and A* are per person, per year. S is raw alpha on the first dollar; the alpha earned at the optimum is S/2.
A14: A* and S are shown for Pool 1 only, and are computed on the top 1% (the book-running population). A* scales linearly with the pool.
A16: DIAGNOSTICS
A17: Active distribution | B17: =Fit!B33 -> Pareto
A18: b — decay parameter (per $ of AUM) | B18: =Grid!$AB$6 -> 4.6843026e-12
A19: Total A* of the top 1% ($) | B19: =Grid!$AB$8 -> 30000000000000
A20: Capital input, top 1% ($) | B20: =Inputs!$B$35 -> 30000000000000
A21: Difference (should be zero) | B21: =B19-B20 -> 0
A22: Top 1% total value added ($/yr) | B22: =C9*Inputs!$B$28 -> 2.4004718e+11
A23: Implied gross alpha on top-1% books | B23: =B22/Inputs!$B$35 -> 0.0080015726
A24: Reference gross alpha (Berk & van Binsbergen 2015) | B24: =Inputs!$B$36 -> 0.008
A25: Difference (implied minus reference) | B25: =B23-B24 -> 1.5726137e-06
A26: Implied mean skill, finite population (bp/mo) | B26: =Grid!$AB$2 -> 78.580248
A27: Theoretical mean of the fitted distribution (bp/mo) | B27: =Fit!$B$34 -> 78.809571
A28: Target mean (bp/mo) | B28: =Inputs!$B$13 -> 42
A29: Gap vs target — Goal Seek this cell to zero | B29: =B26-B28 -> 36.580248
A30: Pareto feasibility flag | B30: =Fit!$B$48 -> NO - no Pareto matches this mean with this 90th percentile
A32: The implied gross alpha above is an OUTPUT. It equals the reference only if the capital input happens to make it so; it is not a test that can pass on its own.

Sheet Compare
A1: All four distributions, same anchors — share of the alpha pool by tier
A2: Independent of the pool size and of the capital assumption. Shape only.
A4: Tier | B4: Pareto | C4: Lognormal | D4: Weibull | E4: Normal
A5: Single best (rank 1) | B5: =Grid!V3/SUM(Grid!$V$3:$V$303) -> 0.0034124819 | C5: =Grid!W3/SUM(Grid!$W$3:$W$303) -> 1.9840526e-05 | D5: =Grid!X3/SUM(Grid!$X$3:$X$303) -> 5.0517681e-06 | E5: =Grid!Y3/SUM(Grid!$Y$3:$Y$303) -> 3.0378068e-06
A6: Top 0.01% | B6: =SUMIF(Grid!$G$3:$G$303,1,Grid!$V$3:$V$303)/SUM(Grid!$V$3:$V$303) -> 0.038195879 | C6: =SUMIF(Grid!$G$3:$G$303,1,Grid!$W$3:$W$303)/SUM(Grid!$W$3:$W$303) -> 0.0018705018 | D6: =SUMIF(Grid!$G$3:$G$303,1,Grid!$X$3:$X$303)/SUM(Grid!$X$3:$X$303) -> 0.00080114188 | E6: =SUMIF(Grid!$G$3:$G$303,1,Grid!$Y$3:$Y$303)/SUM(Grid!$Y$3:$Y$303) -> 0.00055700024
A7: Rest of top 0.1% | B7: =SUMIF(Grid!$G$3:$G$303,2,Grid!$V$3:$V$303)/SUM(Grid!$V$3:$V$303) -> 0.050211379 | C7: =SUMIF(Grid!$G$3:$G$303,2,Grid!$W$3:$W$303)/SUM(Grid!$W$3:$W$303) -> 0.0097250826 | D7: =SUMIF(Grid!$G$3:$G$303,2,Grid!$X$3:$X$303)/SUM(Grid!$X$3:$X$303) -> 0.0056030045 | E7: =SUMIF(Grid!$G$3:$G$303,2,Grid!$Y$3:$Y$303)/SUM(Grid!$Y$3:$Y$303) -> 0.0043044763
A8: Rest of top 1% | B8: =SUMIF(Grid!$G$3:$G$303,3,Grid!$V$3:$V$303)/SUM(Grid!$V$3:$V$303) -> 0.11163206 | C8: =SUMIF(Grid!$G$3:$G$303,3,Grid!$W$3:$W$303)/SUM(Grid!$W$3:$W$303) -> 0.054388718 | D8: =SUMIF(Grid!$G$3:$G$303,3,Grid!$X$3:$X$303)/SUM(Grid!$X$3:$X$303) -> 0.04094262 | E8: =SUMIF(Grid!$G$3:$G$303,3,Grid!$Y$3:$Y$303)/SUM(Grid!$Y$3:$Y$303) -> 0.035340726
A9: Top 1% (cumulative) | B9: =SUMIF(Grid!$G$3:$G$303,"<=3",Grid!$V$3:$V$303)/SUM(Grid!$V$3:$V$303) -> 0.20003932 | C9: =SUMIF(Grid!$G$3:$G$303,"<=3",Grid!$W$3:$W$303)/SUM(Grid!$W$3:$W$303) -> 0.065984302 | D9: =SUMIF(Grid!$G$3:$G$303,"<=3",Grid!$X$3:$X$303)/SUM(Grid!$X$3:$X$303) -> 0.047346766 | E9: =SUMIF(Grid!$G$3:$G$303,"<=3",Grid!$Y$3:$Y$303)/SUM(Grid!$Y$3:$Y$303) -> 0.040202203
A10: Rest of top 10% | B10: =SUMIF(Grid!$G$3:$G$303,4,Grid!$V$3:$V$303)/SUM(Grid!$V$3:$V$303) -> 0.2481851 | C10: =SUMIF(Grid!$G$3:$G$303,4,Grid!$W$3:$W$303)/SUM(Grid!$W$3:$W$303) -> 0.25617378 | D10: =SUMIF(Grid!$G$3:$G$303,4,Grid!$X$3:$X$303)/SUM(Grid!$X$3:$X$303) -> 0.24980142 | E10: =SUMIF(Grid!$G$3:$G$303,4,Grid!$Y$3:$Y$303)/SUM(Grid!$Y$3:$Y$303) -> 0.25271705
A11: Bottom 90% | B11: =SUMIF(Grid!$G$3:$G$303,5,Grid!$V$3:$V$303)/SUM(Grid!$V$3:$V$303) -> 0.55177559 | C11: =SUMIF(Grid!$G$3:$G$303,5,Grid!$W$3:$W$303)/SUM(Grid!$W$3:$W$303) -> 0.67784192 | D11: =SUMIF(Grid!$G$3:$G$303,5,Grid!$X$3:$X$303)/SUM(Grid!$X$3:$X$303) -> 0.70285181 | E11: =SUMIF(Grid!$G$3:$G$303,5,Grid!$Y$3:$Y$303)/SUM(Grid!$Y$3:$Y$303) -> 0.70708074
A13: FITTED PARAMETERS AND IMPLIED MOMENTS
A14: parameter 1 | B14: ="alpha = "&TEXT(Fit!B9,"0.000") -> alpha = 1.531 | C14: ="sigma = "&TEXT(Fit!B15,"0.000") -> sigma = 0.820 | D14: ="kappa = "&TEXT(Fit!B21,"0.000") -> kappa = 1.142 | E14: ="sd = "&TEXT(Fit!B27,"0.00") -> sd = 62.42
A15: parameter 2 | B15: ="x_min = "&TEXT(Fit!B10,"0.00") -> x_min = 27.35 | C15: ="mu = "&TEXT(Fit!B16,"0.000") -> mu = 3.761 | D15: ="lambda = "&TEXT(Fit!B22,"0.00") -> lambda = 59.27 | E15: ="mean = "&TEXT(Fit!B28,"0.00") -> mean = 43.00
A16: theoretical mean (bp/mo) | B16: =Fit!B11 -> 78.809571 | C16: =Fit!B17 -> 60.187925 | D16: =Fit!B23 -> 56.516024 | E16: =Fit!B29 -> 43
A17: theoretical median (bp/mo) | B17: =Fit!B12 -> 43 | C17: =Fit!B18 -> 43 | D17: =Fit!B24 -> 43 | E17: =Fit!B30 -> 43
A19: Compare each theoretical mean against the target mean on the Inputs sheet. A large gap means that distribution cannot reproduce the source's reported mean.

Sheet Fit
A1: Distribution fitting — two upper-tail quantiles, closed form
A2: p = upper-tail probability, so p=0.5 is the median and p=0.1 the 90th percentile. Every parameter is derived.
A4: Standard normal deviates
A5: z1 = -NORMSINV(p1) | B5: =-NORMSINV(Inputs!B9) -> 0
A6: z2 = -NORMSINV(p2) | B6: =-NORMSINV(Inputs!B11) -> 1.2815516
A8: PARETO
A9: alpha | B9: =LN(Inputs!B9/Inputs!B11)/LN(Inputs!B12/Inputs!B10) -> 1.5313626
A10: x_min (bp/mo) | B10: =Inputs!B10*Inputs!B9^(1/B9) -> 27.345879
A11: theoretical mean | B11: =IF(B9>1,B9*B10/(B9-1),-1) -> 78.809571 | C11: -1 means the mean is divergent (alpha <= 1).
A12: theoretical median | B12: =B10*2^(1/B9) -> 43
A14: LOGNORMAL
A15: sigma | B15: =(LN(Inputs!B12)-LN(Inputs!B10))/(B6-B5) -> 0.82008736
A16: mu | B16: =LN(Inputs!B10)-B15*B5 -> 3.7612001
A17: theoretical mean | B17: =EXP(B16+B15^2/2) -> 60.187925
A18: theoretical median | B18: =EXP(B16) -> 43
A20: WEIBULL
A21: kappa (shape) | B21: =LN(LN(1/Inputs!B11)/LN(1/Inputs!B9))/LN(Inputs!B12/Inputs!B10) -> 1.1423058
A22: lambda (scale) | B22: =Inputs!B10/LN(1/Inputs!B9)^(1/B21) -> 59.267063
A23: theoretical mean | B23: =B22*EXP(GAMMALN(1+1/B21)) -> 56.516024
A24: theoretical median | B24: =B22*LN(2)^(1/B21) -> 43
A26: NORMAL
A27: s (standard deviation) | B27: =(Inputs!B12-Inputs!B10)/(B6-B5) -> 62.424332
A28: m (mean) | B28: =Inputs!B10-B27*B5 -> 43 | C28: Quantiles are floored at zero: a normal fitted to these anchors goes negative in the lower tail.
A29: theoretical mean | B29: =B28 -> 43
A30: theoretical median | B30: =B28 -> 43
A32: ACTIVE DISTRIBUTION
A33: name | B33: =CHOOSE(Inputs!B5,"Pareto","Lognormal","Weibull","Normal") -> Pareto
A34: theoretical mean (bp/mo) | B34: =CHOOSE(Inputs!B5,B11,B17,B23,B29) -> 78.809571
A35: theoretical median (bp/mo) | B35: =CHOOSE(Inputs!B5,B12,B18,B24,B30) -> 43
A37: QUANTILE SPOT-CHECKS (active distribution)
B38: u (upper-tail p) | C38: bp/month | D38: % per year
A39: anchor 1 — should equal the input | B39: =Inputs!B9 -> 0.5 | C39: =CHOOSE(Inputs!$B$5,$B$10*B39^(-1/$B$9),EXP($B$16+$B$15*-NORMSINV(B39)),$B$22*LN(1/B39)^(1/$B$21),MAX(0,$B$28+$B$27*-NORMSINV(B39))) -> 43 | D39: =C39*12/100 -> 5.16
A40: anchor 2 — should equal the input | B40: =Inputs!B11 -> 0.1 | C40: =CHOOSE(Inputs!$B$5,$B$10*B40^(-1/$B$9),EXP($B$16+$B$15*-NORMSINV(B40)),$B$22*LN(1/B40)^(1/$B$21),MAX(0,$B$28+$B$27*-NORMSINV(B40))) -> 123 | D40: =C40*12/100 -> 14.76
A41: 99th percentile | B41: 0.01 | C41: =CHOOSE(Inputs!$B$5,$B$10*B41^(-1/$B$9),EXP($B$16+$B$15*-NORMSINV(B41)),$B$22*LN(1/B41)^(1/$B$21),MAX(0,$B$28+$B$27*-NORMSINV(B41))) -> 553.24607 | D41: =C41*12/100 -> 66.389528
A42: 99.9th percentile | B42: 0.001 | C42: =CHOOSE(Inputs!$B$5,$B$10*B42^(-1/$B$9),EXP($B$16+$B$15*-NORMSINV(B42)),$B$22*LN(1/B42)^(1/$B$21),MAX(0,$B$28+$B$27*-NORMSINV(B42))) -> 2488.4651 | D42: =C42*12/100 -> 298.61582
A43: 99.99th percentile | B43: 0.0001 | C43: =CHOOSE(Inputs!$B$5,$B$10*B43^(-1/$B$9),EXP($B$16+$B$15*-NORMSINV(B43)),$B$22*LN(1/B43)^(1/$B$21),MAX(0,$B$28+$B$27*-NORMSINV(B43))) -> 11192.956 | D43: =C43*12/100 -> 1343.1547
A45: PARETO FEASIBILITY CHECK
A46: required mean / anchor-2 value | B46: =Inputs!B13/Inputs!B12 -> 0.34146341
A47: minimum ratio any Pareto can attain | B47: 0.6259
A48: feasible? | B48: =IF(B46>=B47,"yes","NO - no Pareto matches this mean with this 90th percentile") -> NO - no Pareto matches this mean with this 90th percentile
A49: smallest attainable Pareto mean (bp/mo) | B49: =B47*Inputs!B12 -> 76.9857
A50: Minimum of [a/(a-1)]*10^(-1/a) over a, which occurs at a = 1.77. Valid only when anchor 2 is the 90th percentile; recompute the constant if anchor 2 changes.

Sheet Grid
A1: Numerical grid — 301 population bands (row 3 is rank 1; 60 log-spaced bands per tier) | AA1: T = SUM(w*du) | AB1: =SUM(O3:O303) -> 78.580248
A2: j | B2: u_lo | C2: u_hi | D2: u_mid | E2: du | F2: people | G2: tier | H2: x Pareto | I2: x Lognorm | J2: x Weibull | K2: x Normal | L2: x active | M2: x*du | N2: w = x^pwr | O2: w*du | P2: V per person | Q2: ppl*SQRT(V) | R2: A* | S2: S | T2: ppl*A* | U2: ppl*V | V2: contrib Par | W2: contrib Logn | X2: contrib Weib | Y2: contrib Norm | AA2: Mean of x, finite population | AB2: =SUM(M3:M303) -> 78.580248
A3: 1 | B3: 0 | C3: =1/Inputs!$B$16 -> 4.4161809e-07 | D3: =Inputs!$B$17/Inputs!$B$16 -> 2.2080904e-07 | E3: =C3-B3 -> 4.4161809e-07 | F3: =Inputs!$B$16*E3 -> 1 | G3: =IF(D3<=Inputs!$B$21,1,IF(D3<=Inputs!$B$22,2,IF(D3<=Inputs!$B$23,3,IF(D3<=Inputs!$B$24,4,5)))) -> 1 | H3: =Fit!$B$10*D3^(-1/Fit!$B$9) -> 607207.18 | I3: =EXP(Fit!$B$16+Fit!$B$15*-NORMSINV(D3)) -> 2704.6002 | J3: =Fit!$B$22*LN(1/D3)^(1/Fit!$B$21) -> 646.49248 | K3: =MAX(0,Fit!$B$28+Fit!$B$27*-NORMSINV(D3)) -> 358.24806 | L3: =INDEX(H3:K3,1,Inputs!$B$5) -> 607207.18 | M3: =L3*E3 -> 0.26815367 | N3: =L3^$AB$7 -> 607207.18 | O3: =N3*E3 -> 0.26815367 | P3: =N3*$AB$3/($AB$4*$AB$1) -> 4.0949783e+09 | Q3: =IF(G3<=3,F3*SQRT(P3),0) -> 63992.017 | R3: =SQRT(P3/$AB$6) -> 2.9566732e+10 | S3: =2*$AB$6*R3 -> 0.27699904 | T3: =IF(G3<=3,F3*R3,0) -> 2.9566732e+10 | U3: =F3*P3 -> 4.0949783e+09 | V3: =H3^$AB$7*E3 -> 0.26815367 | W3: =I3^$AB$7*E3 -> 0.0011944004 | X3: =J3^$AB$7*E3 -> 0.00028550277 | Y3: =K3^$AB$7*E3 -> 0.00015820882 | AA3: Pool 1 ($) | AB3: =Inputs!$B$28 -> 1200000000000
A4: 2 | B4: =C3 -> 4.4161809e-07 | C4: =(1/Inputs!$B$16)*(Inputs!$B$21/(1/Inputs!$B$16))^(1/60) -> 4.8338823e-07 | D4: =(B4+C4)/2 -> 4.6250316e-07 | E4: =C4-B4 -> 4.1770143e-08 | F4: =Inputs!$B$16*E4 -> 0.094584311 | G4: =IF(D4<=Inputs!$B$21,1,IF(D4<=Inputs!$B$22,2,IF(D4<=Inputs!$B$23,3,IF(D4<=Inputs!$B$24,4,5)))) -> 1 | H4: =Fit!$B$10*D4^(-1/Fit!$B$9) -> 374675.9 | I4: =EXP(Fit!$B$16+Fit!$B$15*-NORMSINV(D4)) -> 2405.0668 | J4: =Fit!$B$22*LN(1/D4)^(1/Fit!$B$21) -> 619.10617 | K4: =MAX(0,Fit!$B$28+Fit!$B$27*-NORMSINV(D4)) -> 349.31347 | L4: =INDEX(H4:K4,1,Inputs!$B$5) -> 374675.9 | M4: =L4*E4 -> 0.015650266 | N4: =L4^$AB$7 -> 374675.9 | O4: =N4*E4 -> 0.015650266 | P4: =N4*$AB$3/($AB$4*$AB$1) -> 2.5267976e+09 | Q4: =IF(G4<=3,F4*SQRT(P4),0) -> 4754.4944 | R4: =SQRT(P4/$AB$6) -> 2.3225376e+10 | S4: =2*$AB$6*R4 -> 0.21758938 | T4: =IF(G4<=3,F4*R4,0) -> 2.1967562e+09 | U4: =F4*P4 -> 2.3899541e+08 | V4: =H4^$AB$7*E4 -> 0.015650266 | W4: =I4^$AB$7*E4 -> 0.00010045998 | X4: =J4^$AB$7*E4 -> 2.5860153e-05 | Y4: =K4^$AB$7*E4 -> 1.4590873e-05 | AA4: N | AB4: =Inputs!$B$16 -> 2264400
A5: 3 | B5: =C4 -> 4.8338823e-07 | C5: =(1/Inputs!$B$16)*(Inputs!$B$21/(1/Inputs!$B$16))^(2/60) -> 5.2910917e-07 | D5: =(B5+C5)/2 -> 5.062487e-07 | E5: =C5-B5 -> 4.5720943e-08 | F5: =Inputs!$B$16*E5 -> 0.1035305 | G5: =IF(D5<=Inputs!$B$21,1,IF(D5<=Inputs!$B$22,2,IF(D5<=Inputs!$B$23,3,IF(D5<=Inputs!$B$24,4,5)))) -> 1 | H5: =Fit!$B$10*D5^(-1/Fit!$B$9) -> 353203.91 | I5: =EXP(Fit!$B$16+Fit!$B$15*-NORMSINV(D5)) -> 2370.2867 | J5: =Fit!$B$22*LN(1/D5)^(1/Fit!$B$21) -> 615.74692 | K5: =MAX(0,Fit!$B$28+Fit!$B$27*-NORMSINV(D5)) -> 348.20466 | L5: =INDEX(H5:K5,1,Inputs!$B$5) -> 353203.91 | M5: =L5*E5 -> 0.016148816 | N5: =L5^$AB$7 -> 353203.91 | O5: =N5*E5 -> 0.016148816 | P5: =N5*$AB$3/($AB$4*$AB$1) -> 2.3819915e+09 | Q5: =IF(G5<=3,F5*SQRT(P5),0) -> 5052.8735 | R5: =SQRT(P5/$AB$6) -> 2.2550056e+10 | S5: =2*$AB$6*R5 -> 0.21126257 | T5: =IF(G5<=3,F5*R5,0) -> 2.3346187e+09 | U5: =F5*P5 -> 2.4660878e+08 | V5: =H5^$AB$7*E5 -> 0.016148816 | W5: =I5^$AB$7*E5 -> 0.00010837174 | X5: =J5^$AB$7*E5 -> 2.815253e-05 | Y5: =K5^$AB$7*E5 -> 1.5920245e-05 | AA5: SUM people*SQRT(V), top 1% | AB5: =SUM(Q3:Q303) -> 64929749
A6: 4 | B6: =C5 -> 5.2910917e-07 | C6: =(1/Inputs!$B$16)*(Inputs!$B$21/(1/Inputs!$B$16))^(3/60) -> 5.791546e-07 | D6: =(B6+C6)/2 -> 5.5413189e-07 | E6: =C6-B6 -> 5.0045427e-08 | F6: =Inputs!$B$16*E6 -> 0.11332286 | G6: =IF(D6<=Inputs!$B$21,1,IF(D6<=Inputs!$B$22,2,IF(D6<=Inputs!$B$23,3,IF(D6<=Inputs!$B$24,4,5)))) -> 1 | H6: =Fit!$B$10*D6^(-1/Fit!$B$9) -> 332962.43 | I6: =EXP(Fit!$B$16+Fit!$B$15*-NORMSINV(D6)) -> 2335.8943 | J6: =Fit!$B$22*LN(1/D6)^(1/Fit!$B$21) -> 612.38505 | K6: =MAX(0,Fit!$B$28+Fit!$B$27*-NORMSINV(D6)) -> 347.09209 | L6: =INDEX(H6:K6,1,Inputs!$B$5) -> 332962.43 | M6: =L6*E6 -> 0.016663247 | N6: =L6^$AB$7 -> 332962.43 | O6: =N6*E6 -> 0.016663247 | P6: =N6*$AB$3/($AB$4*$AB$1) -> 2.2454839e+09 | Q6: =IF(G6<=3,F6*SQRT(P6),0) -> 5369.9781 | R6: =SQRT(P6/$AB$6) -> 2.1894372e+10 | S6: =2*$AB$6*R6 -> 0.20511973 | T6: =IF(G6<=3,F6*R6,0) -> 2.481133e+09 | U6: =F6*P6 -> 2.5446467e+08 | V6: =H6^$AB$7*E6 -> 0.016663247 | W6: =I6^$AB$7*E6 -> 0.00011690083 | X6: =J6^$AB$7*E6 -> 3.0647071e-05 | Y6: =K6^$AB$7*E6 -> 1.7370372e-05 | AA6: b (per $ of AUM) | AB6: =($AB$5/Inputs!$B$35)^2 -> 4.6843026e-12
A7: 5 | B7: =C6 -> 5.791546e-07 | C7: =(1/Inputs!$B$16)*(Inputs!$B$21/(1/Inputs!$B$16))^(4/60) -> 6.3393354e-07 | D7: =(B7+C7)/2 -> 6.0654407e-07 | E7: =C7-B7 -> 5.4778939e-08 | F7: =Inputs!$B$16*E7 -> 0.12404143 | G7: =IF(D7<=Inputs!$B$21,1,IF(D7<=Inputs!$B$22,2,IF(D7<=Inputs!$B$23,3,IF(D7<=Inputs!$B$24,4,5)))) -> 1 | H7: =Fit!$B$10*D7^(-1/Fit!$B$9) -> 313880.97 | I7: =EXP(Fit!$B$16+Fit!$B$15*-NORMSINV(D7)) -> 2301.8861 | J7: =Fit!$B$22*LN(1/D7)^(1/Fit!$B$21) -> 609.02056 | K7: =MAX(0,Fit!$B$28+Fit!$B$27*-NORMSINV(D7)) -> 345.97573 | L7: =INDEX(H7:K7,1,Inputs!$B$5) -> 313880.97 | M7: =L7*E7 -> 0.017194066 | N7: =L7^$AB$7 -> 313880.97 | O7: =N7*E7 -> 0.017194066 | P7: =N7*$AB$3/($AB$4*$AB$1) -> 2.1167993e+09 | Q7: =IF(G7<=3,F7*SQRT(P7),0) -> 5706.9833 | R7: =SQRT(P7/$AB$6) -> 2.1257754e+10 | S7: =2*$AB$6*R7 -> 0.1991555 | T7: =IF(G7<=3,F7*R7,0) -> 2.6368422e+09 | U7: =F7*P7 -> 2.6257081e+08 | V7: =H7^$AB$7*E7 -> 0.017194066 | W7: =I7^$AB$7*E7 -> 0.00012609488 | X7: =J7^$AB$7*E7 -> 3.33615e-05 | Y7: =K7^$AB$7*E7 -> 1.8952184e-05 | AA7: power | AB7: =Inputs!$B$6 -> 1
A8: 6 | B8: =C7 -> 6.3393354e-07 | C8: =(1/Inputs!$B$16)*(Inputs!$B$21/(1/Inputs!$B$16))^(5/60) -> 6.9389371e-07 | D8: =(B8+C8)/2 -> 6.6391362e-07 | E8: =C8-B8 -> 5.9960167e-08 | F8: =Inputs!$B$16*E8 -> 0.1357738 | G8: =IF(D8<=Inputs!$B$21,1,IF(D8<=Inputs!$B$22,2,IF(D8<=Inputs!$B$23,3,IF(D8<=Inputs!$B$24,4,5)))) -> 1 | H8: =Fit!$B$10*D8^(-1/Fit!$B$9) -> 295893.02 | I8: =EXP(Fit!$B$16+Fit!$B$15*-NORMSINV(D8)) -> 2268.2587 | J8: =Fit!$B$22*LN(1/D8)^(1/Fit!$B$21) -> 605.65342 | K8: =MAX(0,Fit!$B$28+Fit!$B$27*-NORMSINV(D8)) -> 344.85553 | L8: =INDEX(H8:K8,1,Inputs!$B$5) -> 295893.02 | M8: =L8*E8 -> 0.017741795 | N8: =L8^$AB$7 -> 295893.02 | O8: =N8*E8 -> 0.017741795 | P8: =N8*$AB$3/($AB$4*$AB$1) -> 1.9954894e+09 | Q8: =IF(G8<=3,F8*SQRT(P8),0) -> 6065.1381 | R8: =SQRT(P8/$AB$6) -> 2.0639646e+10 | S8: =2*$AB$6*R8 -> 0.19336469 | T8: =IF(G8<=3,F8*R8,0) -> 2.8023232e+09 | U8: =F8*P8 -> 2.7093518e+08 | V8: =H8^$AB$7*E8 -> 0.017741795 | W8: =I8^$AB$7*E8 -> 0.00013600517 | X8: =J8^$AB$7*E8 -> 3.631508e-05 | Y8: =K8^$AB$7*E8 -> 2.0677596e-05 | AA8: Total A* of the top 1% ($) | AB8: =SUM(T3:T303) -> 30000000000000
A9: 7 | B9: =C8 -> 6.9389371e-07 | C9: =(1/Inputs!$B$16)*(Inputs!$B$21/(1/Inputs!$B$16))^(6/60) -> 7.5952517e-07 | D9: =(B9+C9)/2 -> 7.2670944e-07 | E9: =C9-B9 -> 6.5631458e-08 | F9: =Inputs!$B$16*E9 -> 0.14861587 | G9: =IF(D9<=Inputs!$B$21,1,IF(D9<=Inputs!$B$22,2,IF(D9<=Inputs!$B$23,3,IF(D9<=Inputs!$B$24,4,5)))) -> 1 | H9: =Fit!$B$10*D9^(-1/Fit!$B$9) -> 278935.93 | I9: =EXP(Fit!$B$16+Fit!$B$15*-NORMSINV(D9)) -> 2235.0089 | J9: =Fit!$B$22*LN(1/D9)^(1/Fit!$B$21) -> 602.28361 | K9: =MAX(0,Fit!$B$28+Fit!$B$27*-NORMSINV(D9)) -> 343.73146 | L9: =INDEX(H9:K9,1,Inputs!$B$5) -> 278935.93 | M9: =L9*E9 -> 0.018306972 | N9: =L9^$AB$7 -> 278935.93 | O9: =N9*E9 -> 0.018306972 | P9: =N9*$AB$3/($AB$4*$AB$1) -> 1.8811315e+09 | Q9: =IF(G9<=3,F9*SQRT(P9),0) -> 6445.7697 | R9: =SQRT(P9/$AB$6) -> 2.0039511e+10 | S9: =2*$AB$6*R9 -> 0.18774226 | T9: =IF(G9<=3,F9*R9,0) -> 2.9781894e+09 | U9: =F9*P9 -> 2.7956601e+08 | V9: =H9^$AB$7*E9 -> 0.018306972 | W9: =I9^$AB$7*E9 -> 0.00014668689 | X9: =J9^$AB$7*E9 -> 3.9528752e-05 | Y9: =K9^$AB$7*E9 -> 2.2559597e-05
A10: 8 | B10: =C9 -> 7.5952517e-07 | C10: =(1/Inputs!$B$16)*(Inputs!$B$21/(1/Inputs!$B$16))^(7/60) -> 8.3136433e-07 | D10: =(B10+C10)/2 -> 7.9544475e-07 | E10: =C10-B10 -> 7.1839165e-08 | F10: =Inputs!$B$16*E10 -> 0.1626726 | G10: =IF(D10<=Inputs!$B$21,1,IF(D10<=Inputs!$B$22,2,IF(D10<=Inputs!$B$23,3,IF(D10<=Inputs!$B$24,4,5)))) -> 1 | H10: =Fit!$B$10*D10^(-1/Fit!$B$9) -> 262950.62 | I10: =EXP(Fit!$B$16+Fit!$B$15*-NORMSINV(D10)) -> 2202.1332 | J10: =Fit!$B$22*LN(1/D10)^(1/Fit!$B$21) -> 598.91112 | K10: =MAX(0,Fit!$B$28+Fit!$B$27*-NORMSINV(D10)) -> 342.60348 | L10: =INDEX(H10:K10,1,Inputs!$B$5) -> 262950.62 | M10: =L10*E10 -> 0.018890153 | N10: =L10^$AB$7 -> 262950.62 | O10: =N10*E10 -> 0.018890153 | P10: =N10*$AB$3/($AB$4*$AB$1) -> 1.7733273e+09 | Q10: =IF(G10<=3,F10*SQRT(P10),0) -> 6850.2887 | R10: =SQRT(P10/$AB$6) -> 1.9456825e+10 | S10: =2*$AB$6*R10 -> 0.18228332 | T10: =IF(G10<=3,F10*R10,0) -> 3.1650925e+09 | U10: =F10*P10 -> 2.8847177e+08 | V10: =H10^$AB$7*E10 -> 0.018890153 | W10: =I10^$AB$7*E10 -> 0.00015819941 | X10: =J10^$AB$7*E10 -> 4.3025274e-05 | Y10: =K10^$AB$7*E10 -> 2.4612348e-05
A11: 9 | B11: =C10 -> 8.3136433e-07 | C11: =(1/Inputs!$B$16)*(Inputs!$B$21/(1/Inputs!$B$16))^(8/60) -> 9.0999835e-07 | D11: =(B11+C11)/2 -> 8.7068134e-07 | E11: =C11-B11 -> 7.8634023e-08 | F11: =Inputs!$B$16*E11 -> 0.17805888 | G11: =IF(D11<=Inputs!$B$21,1,IF(D11<=Inputs!$B$22,2,IF(D11<=Inputs!$B$23,3,IF(D11<=Inputs!$B$24,4,5)))) -> 1 | H11: =Fit!$B$10*D11^(-1/Fit!$B$9) -> 247881.4 | I11: =EXP(Fit!$B$16+Fit!$B$15*-NORMSINV(D11)) -> 2169.6285 | J11: =Fit!$B$22*LN(1/D11)^(1/Fit!$B$21) -> 595.53592 | K11: =MAX(0,Fit!$B$28+Fit!$B$27*-NORMSINV(D11)) -> 341.47154 | L11: =INDEX(H11:K11,1,Inputs!$B$5) -> 247881.4 | M11: =L11*E11 -> 0.019491912 | N11: =L11^$AB$7 -> 247881.4 | O11: =N11*E11 -> 0.019491912 | P11: =N11*$AB$3/($AB$4*$AB$1) -> 1.6717012e+09 | Q11: =IF(G11<=3,F11*SQRT(P11),0) -> 7280.1942 | R11: =SQRT(P11/$AB$6) -> 1.8891083e+10 | S11: =2*$AB$6*R11 -> 0.1769831 | T11: =IF(G11<=3,F11*R11,0) -> 3.3637251e+09 | U11: =F11*P11 -> 2.9766124e+08 | V11: =H11^$AB$7*E11 -> 0.019491912 | W11: =I11^$AB$7*E11 -> 0.00017060661 | X11: =J11^$AB$7*E11 -> 4.6829385e-05 | Y11: =K11^$AB$7*E11 -> 2.6851281e-05
A12: 10 | B12: =C11 -> 9.0999835e-07 | C12: =(1/Inputs!$B$16)*(Inputs!$B$21/(1/Inputs!$B$16))^(9/60) -> 9.9606992e-07 | D12: =(B12+C12)/2 -> 9.5303414e-07 | E12: =C12-B12 -> 8.6071568e-08 | F12: =Inputs!$B$16*E12 -> 0.19490046 | G12: =IF(D12<=Inputs!$B$21,1,IF(D12<=Inputs!$B$22,2,IF(D12<=Inputs!$B$23,3,IF(D12<=Inputs!$B$24,4,5)))) -> 1 | H12: =Fit!$B$10*D12^(-1/Fit!$B$9) -> 233675.77 | I12: =EXP(Fit!$B$16+Fit!$B$15*-NORMSINV(D12)) -> 2137.4913 | J12: =Fit!$B$22*LN(1/D12)^(1/Fit!$B$21) -> 592.158 | K12: =MAX(0,Fit!$B$28+Fit!$B$27*-NORMSINV(D12)) -> 340.33561 | L12: =INDEX(H12:K12,1,Inputs!$B$5) -> 233675.77 | M12: =L12*E12 -> 0.02011284 | N12: =L12^$AB$7 -> 233675.77 | O12: =N12*E12 -> 0.02011284 | P12: =N12*$AB$3/($AB$4*$AB$1) -> 1.575899e+09 | Q12: =IF(G12<=3,F12*SQRT(P12),0) -> 7737.0794 | R12: =SQRT(P12/$AB$6) -> 1.834179e+10 | S12: =2*$AB$6*R12 -> 0.17183699 | T12: =IF(G12<=3,F12*R12,0) -> 3.5748233e+09 | U12: =F12*P12 -> 3.0714344e+08 | V12: =H12^$AB$7*E12 -> 0.02011284 | W12: =I12^$AB$7*E12 -> 0.00018397723 | X12: =J12^$AB$7*E12 -> 5.0967967e-05 | Y12: =K12^$AB$7*E12 -> 2.929322e-05
A13: 11 | B13: =C12 -> 9.9606992e-07 | C13: =(1/Inputs!$B$16)*(Inputs!$B$21/(1/Inputs!$B$16))^(10/60) -> 1.0902825e-06 | D13: =(B13+C13)/2 -> 1.0431762e-06 | E13: =C13-B13 -> 9.4212588e-08 | F13: =Inputs!$B$16*E13 -> 0.21333498 | G13: =IF(D13<=Inputs!$B$21,1,IF(D13<=Inputs!$B$22,2,IF(D13<=Inputs!$B$23,3,IF(D13<=Inputs!$B$24,4,5)))) -> 1 | H13: =Fit!$B$10*D13^(-1/Fit!$B$9) -> 220284.24 | I13: =EXP(Fit!$B$16+Fit!$B$15*-NORMSINV(D13)) -> 2105.7185 | J13: =Fit!$B$22*LN(1/D13)^(1/Fit!$B$21) -> 588.77733 | K13: =MAX(0,Fit!$B$28+Fit!$B$27*-NORMSINV(D13)) -> 339.19564 | L13: =INDEX(H13:K13,1,Inputs!$B$5) -> 220284.24 | M13: =L13*E13 -> 0.020753548 | N13: =L13^$AB$7 -> 220284.24 | O13: =N13*E13 -> 0.020753548 | P13: =N13*$AB$3/($AB$4*$AB$1) -> 1.4855871e+09 | Q13: =IF(G13<=3,F13*SQRT(P13),0) -> 8222.6375 | R13: =SQRT(P13/$AB$6) -> 1.7808469e+10 | S13: =2*$AB$6*R13 -> 0.16684052 | T13: =IF(G13<=3,F13*R13,0) -> 3.7991695e+09 | U13: =F13*P13 -> 3.1692771e+08 | V13: =H13^$AB$7*E13 -> 0.020753548 | W13: =I13^$AB$7*E13 -> 0.00019838519 | X13: =J13^$AB$7*E13 -> 5.5470236e-05 | Y13: =K13^$AB$7*E13 -> 3.1956499e-05
A14: 12 | B14: =C13 -> 1.0902825e-06 | C14: =(1/Inputs!$B$16)*(Inputs!$B$21/(1/Inputs!$B$16))^(11/60) -> 1.1934061e-06 | D14: =(B14+C14)/2 -> 1.1418443e-06 | E14: =C14-B14 -> 1.0312362e-07 | F14: =Inputs!$B$16*E14 -> 0.23351313 | G14: =IF(D14<=Inputs!$B$21,1,IF(D14<=Inputs!$B$22,2,IF(D14<=Inputs!$B$23,3,IF(D14<=Inputs!$B$24,4,5)))) -> 1 | H14: =Fit!$B$10*D14^(-1/Fit!$B$9) -> 207660.15 | I14: =EXP(Fit!$B$16+Fit!$B$15*-NORMSINV(D14)) -> 2074.3069 | J14: =Fit!$B$22*LN(1/D14)^(1/Fit!$B$21) -> 585.3939 | K14: =MAX(0,Fit!$B$28+Fit!$B$27*-NORMSINV(D14)) -> 338.0516 | L14: =INDEX(H14:K14,1,Inputs!$B$5) -> 207660.15 | M14: =L14*E14 -> 0.021414667 | N14: =L14^$AB$7 -> 207660.15 | O14: =N14*E14 -> 0.021414667 | P14: =N14*$AB$3/($AB$4*$AB$1) -> 1.4004508e+09 | Q14: =IF(G14<=3,F14*SQRT(P14),0) -> 8738.6678 | R14: =SQRT(P14/$AB$6) -> 1.7290656e+10 | S14: =2*$AB$6*R14 -> 0.16198933 | T14: =IF(G14<=3,F14*R14,0) -> 4.0375951e+09 | U14: =F14*P14 -> 3.2702365e+08 | V14: =H14^$AB$7*E14 -> 0.021414667 | W14: =I14^$AB$7*E14 -> 0.00021391004 | X14: =J14^$AB$7*E14 -> 6.0367939e-05 | Y14: =K14^$AB$7*E14 -> 3.4861105e-05
A15: 13 | B15: =C14 -> 1.1934061e-06 | C15: =(1/Inputs!$B$16)*(Inputs!$B$21/(1/Inputs!$B$16))^(12/60) -> 1.3062836e-06 | D15: =(B15+C15)/2 -> 1.2498449e-06 | E15: =C15-B15 -> 1.128775e-07 | F15: =Inputs!$B$16*E15 -> 0.2555998 | G15: =IF(D15<=Inputs!$B$21,1,IF(D15<=Inputs!$B$22,2,IF(D15<=Inputs!$B$23,3,IF(D15<=Inputs!$B$24,4,5)))) -> 1 | H15: =Fit!$B$10*D15^(-1/Fit!$B$9) -> 195759.53 | I15: =EXP(Fit!$B$16+Fit!$B$15*-NORMSINV(D15)) -> 2043.2532 | J15: =Fit!$B$22*LN(1/D15)^(1/Fit!$B$21) -> 582.00769 | K15: =MAX(0,Fit!$B$28+Fit!$B$27*-NORMSINV(D15)) -> 336.90343 | L15: =INDEX(H15:K15,1,Inputs!$B$5) -> 195759.53 | M15: =L15*E15 -> 0.022096845 | N15: =L15^$AB$7 -> 195759.53 | O15: =N15*E15 -> 0.022096845 | P15: =N15*$AB$3/($AB$4*$AB$1) -> 1.3201936e+09 | Q15: =IF(G15<=3,F15*SQRT(P15),0) -> 9287.0829 | R15: =SQRT(P15/$AB$6) -> 1.6787899e+10 | S15: =2*$AB$6*R15 -> 0.15727919 | T15: =IF(G15<=3,F15*R15,0) -> 4.2909836e+09 | U15: =F15*P15 -> 3.3744122e+08 | V15: =H15^$AB$7*E15 -> 0.022096845 | W15: =I15^$AB$7*E15 -> 0.00023063731 | X15: =J15^$AB$7*E15 -> 6.5695571e-05 | Y15: =K15^$AB$7*E15 -> 3.8028816e-05
A16: 14 | B16: =C15 -> 1.3062836e-06 | C16: =(1/Inputs!$B$16)*(Inputs!$B$21/(1/Inputs!$B$16))^(13/60) -> 1.4298376e-06 | D16: =(B16+C16)/2 -> 1.3680606e-06 | E16: =C16-B16 -> 1.2355394e-07 | F16: =Inputs!$B$16*E16 -> 0.27977554 | G16: =IF(D16<=Inputs!$B$21,1,IF(D16<=Inputs!$B$22,2,IF(D16<=Inputs!$B$23,3,IF(D16<=Inputs!$B$24,4,5)))) -> 1 | H16: =Fit!$B$10*D16^(-1/Fit!$B$9) -> 184540.91 | I16: =EXP(Fit!$B$16+Fit!$B$15*-NORMSINV(D16)) -> 2012.5543 | J16: =Fit!$B$22*LN(1/D16)^(1/Fit!$B$21) -> 578.61867 | K16: =MAX(0,Fit!$B$28+Fit!$B$27*-NORMSINV(D16)) -> 335.7511 | L16: =INDEX(H16:K16,1,Inputs!$B$5) -> 184540.91 | M16: =L16*E16 -> 0.022800755 | N16: =L16^$AB$7 -> 184540.91 | O16: =N16*E16 -> 0.022800755 | P16: =N16*$AB$3/($AB$4*$AB$1) -> 1.2445357e+09 | Q16: =IF(G16<=3,F16*SQRT(P16),0) -> 9869.915 | R16: =SQRT(P16/$AB$6) -> 1.629976e+10 | S16: =2*$AB$6*R16 -> 0.15270601 | T16: =IF(G16<=3,F16*R16,0) -> 4.560274e+09 | U16: =F16*P16 -> 3.4819064e+08 | V16: =H16^$AB$7*E16 -> 0.022800755 | W16: =I16^$AB$7*E16 -> 0.00024865901 | X16: =J16^$AB$7*E16 -> 7.1490615e-05 | Y16: =K16^$AB$7*E16 -> 4.148337e-05
A17: 15 | B17: =C16 -> 1.4298376e-06 | C17: =(1/Inputs!$B$16)*(Inputs!$B$21/(1/Inputs!$B$16))^(14/60) -> 1.5650778e-06 | D17: =(B17+C17)/2 -> 1.4974577e-06 | E17: =C17-B17 -> 1.352402e-07 | F17: =Inputs!$B$16*E17 -> 0.30623791 | G17: =IF(D17<=Inputs!$B$21,1,IF(D17<=Inputs!$B$22,2,IF(D17<=Inputs!$B$23,3,IF(D17<=Inputs!$B$24,4,5)))) -> 1 | H17: =Fit!$B$10*D17^(-1/Fit!$B$9) -> 173965.2 | I17: =EXP(Fit!$B$16+Fit!$B$15*-NORMSINV(D17)) -> 1982.207 | J17: =Fit!$B$22*LN(1/D17)^(1/Fit!$B$21) -> 575.22682 | K17: =MAX(0,Fit!$B$28+Fit!$B$27*-NORMSINV(D17)) -> 334.59455 | L17: =INDEX(H17:K17,1,Inputs!$B$5) -> 173965.2 | M17: =L17*E17 -> 0.023527089 | N17: =L17^$AB$7 -> 173965.2 | O17: =N17*E17 -> 0.023527089 | P17: =N17*$AB$3/($AB$4*$AB$1) -> 1.1732136e+09 | Q17: =IF(G17<=3,F17*SQRT(P17),0) -> 10489.324 | R17: =SQRT(P17/$AB$6) -> 1.5825815e+10 | S17: =2*$AB$6*R17 -> 0.14826581 | T17: =IF(G17<=3,F17*R17,0) -> 4.8464644e+09 | U17: =F17*P17 -> 3.5928249e+08 | V17: =H17^$AB$7*E17 -> 0.023527089 | W17: =I17^$AB$7*E17 -> 0.00026807407 | X17: =J17^$AB$7*E17 -> 7.7793791e-05 | Y17: =K17^$AB$7*E17 -> 4.5250635e-05
A18: 16 | B18: =C17 -> 1.5650778e-06 | C18: =(1/Inputs!$B$16)*(Inputs!$B$21/(1/Inputs!$B$16))^(15/60) -> 1.7131096e-06 | D18: =(B18+C18)/2 -> 1.6390937e-06 | E18: =C18-B18 -> 1.480318e-07 | F18: =Inputs!$B$16*E18 -> 0.33520321 | G18: =IF(D18<=Inputs!$B$21,1,IF(D18<=Inputs!$B$22,2,IF(D18<=Inputs!$B$23,3,IF(D18<=Inputs!$B$24,4,5)))) -> 1 | H18: =Fit!$B$10*D18^(-1/Fit!$B$9) -> 163995.57 | I18: =EXP(Fit!$B$16+Fit!$B$15*-NORMSINV(D18)) -> 1952.2081 | J18: =Fit!$B$22*LN(1/D18)^(1/Fit!$B$21) -> 571.83212 | K18: =MAX(0,Fit!$B$28+Fit!$B$27*-NORMSINV(D18)) -> 333.43376 | L18: =INDEX(H18:K18,1,Inputs!$B$5) -> 163995.57 | M18: =L18*E18 -> 0.024276561 | N18: =L18^$AB$7 -> 163995.57 | O18: =N18*E18 -> 0.024276561 | P18: =N18*$AB$3/($AB$4*$AB$1) -> 1.1059789e+09 | Q18: =IF(G18<=3,F18*SQRT(P18),0) -> 11147.605 | R18: =SQRT(P18/$AB$6) -> 1.536565e+10 | S18: =2*$AB$6*R18 -> 0.14395471 | T18: =IF(G18<=3,F18*R18,0) -> 5.1506154e+09 | U18: =F18*P18 -> 3.7072767e+08 | V18: =H18^$AB$7*E18 -> 0.024276561 | W18: =I18^$AB$7*E18 -> 0.00028898888 | X18: =J18^$AB$7*E18 -> 8.464934e-05 | Y18: =K18^$AB$7*E18 -> 4.93588e-05
A19: 17 | B19: =C18 -> 1.7131096e-06 | C19: =(1/Inputs!$B$16)*(Inputs!$B$21/(1/Inputs!$B$16))^(16/60) -> 1.8751429e-06 | D19: =(B19+C19)/2 -> 1.7941262e-06 | E19: =C19-B19 -> 1.6203329e-07 | F19: =Inputs!$B$16*E19 -> 0.36690818 | G19: =IF(D19<=Inputs!$B$21,1,IF(D19<=Inputs!$B$22,2,IF(D19<=Inputs!$B$23,3,IF(D19<=Inputs!$B$24,4,5)))) -> 1 | H19: =Fit!$B$10*D19^(-1/Fit!$B$9) -> 154597.29 | I19: =EXP(Fit!$B$16+Fit!$B$15*-NORMSINV(D19)) -> 1922.5546 | J19: =Fit!$B$22*LN(1/D19)^(1/Fit!$B$21) -> 568.43456 | K19: =MAX(0,Fit!$B$28+Fit!$B$27*-NORMSINV(D19)) -> 332.26866 | L19: =INDEX(H19:K19,1,Inputs!$B$5) -> 154597.29 | M19: =L19*E19 -> 0.025049907 | N19: =L19^$AB$7 -> 154597.29 | O19: =N19*E19 -> 0.025049907 | P19: =N19*$AB$3/($AB$4*$AB$1) -> 1.0425972e+09 | Q19: =IF(G19<=3,F19*SQRT(P19),0) -> 11847.199 | R19: =SQRT(P19/$AB$6) -> 1.4918866e+10 | S19: =2*$AB$6*R19 -> 0.13976897 | T19: =IF(G19<=3,F19*R19,0) -> 5.473854e+09 | U19: =F19*P19 -> 3.8253746e+08 | V19: =H19^$AB$7*E19 -> 0.025049907 | W19: =I19^$AB$7*E19 -> 0.00031151784 | X19: =J19^$AB$7*E19 -> 9.210532e-05 | Y19: =K19^$AB$7*E19 -> 5.3838583e-05
A20: 18 | B20: =C19 -> 1.8751429e-06 | C20: =(1/Inputs!$B$16)*(Inputs!$B$21/(1/Inputs!$B$16))^(17/60) -> 2.052502e-06 | D20: =(B20+C20)/2 -> 1.9638224e-06 | E20: =C20-B20 -> 1.773591e-07 | F20: =Inputs!$B$16*E20 -> 0.40161194 | G20: =IF(D20<=Inputs!$B$21,1,IF(D20<=Inputs!$B$22,2,IF(D20<=Inputs!$B$23,3,IF(D20<=Inputs!$B$24,4,5)))) -> 1 | H20: =Fit!$B$10*D20^(-1/Fit!$B$9) -> 145737.6 | I20: =EXP(Fit!$B$16+Fit!$B$15*-NORMSINV(D20)) -> 1893.2433 | J20: =Fit!$B$22*LN(1/D20)^(1/Fit!$B$21) -> 565.0341 | K20: =MAX(0,Fit!$B$28+Fit!$B$27*-NORMSINV(D20)) -> 331.09921 | L20: =INDEX(H20:K20,1,Inputs!$B$5) -> 145737.6 | M20: =L20*E20 -> 0.025847889 | N20: =L20^$AB$7 -> 145737.6 | O20: =N20*E20 -> 0.025847889 | P20: =N20*$AB$3/($AB$4*$AB$1) -> 9.828479e+08 | Q20: =IF(G20<=3,F20*SQRT(P20),0) -> 12590.697 | R20: =SQRT(P20/$AB$6) -> 1.4485073e+10 | S20: =2*$AB$6*R20 -> 0.13570493 | T20: =IF(G20<=3,F20*R20,0) -> 5.8173782e+09 | U20: =F20*P20 -> 3.9472345e+08 | V20: =H20^$AB$7*E20 -> 0.025847889 | W20: =I20^$AB$7*E20 -> 0.00033578392 | X20: =J20^$AB$7*E20 -> 0.00010021394 | Y20: =K20^$AB$7*E20 -> 5.8723456e-05
A21: 19 | B21: =C20 -> 2.052502e-06 | C21: =(1/Inputs!$B$16)*(Inputs!$B$21/(1/Inputs!$B$16))^(18/60) -> 2.2466364e-06 | D21: =(B21+C21)/2 -> 2.1495692e-06 | E21: =C21-B21 -> 1.9413448e-07 | F21: =Inputs!$B$16*E21 -> 0.43959812 | G21: =IF(D21<=Inputs!$B$21,1,IF(D21<=Inputs!$B$22,2,IF(D21<=Inputs!$B$23,3,IF(D21<=Inputs!$B$24,4,5)))) -> 1 | H21: =Fit!$B$10*D21^(-1/Fit!$B$9) -> 137385.64 | I21: =EXP(Fit!$B$16+Fit!$B$15*-NORMSINV(D21)) -> 1864.2713 | J21: =Fit!$B$22*LN(1/D21)^(1/Fit!$B$21) -> 561.63072 | K21: =MAX(0,Fit!$B$28+Fit!$B$27*-NORMSINV(D21)) -> 329.92536 | L21: =INDEX(H21:K21,1,Inputs!$B$5) -> 137385.64 | M21: =L21*E21 -> 0.026671291 | N21: =L21^$AB$7 -> 137385.64 | O21: =N21*E21 -> 0.026671291 | P21: =N21*$AB$3/($AB$4*$AB$1) -> 9.2652268e+08 | Q21: =IF(G21<=3,F21*SQRT(P21),0) -> 13380.855 | R21: =SQRT(P21/$AB$6) -> 1.4063893e+10 | S21: =2*$AB$6*R21 -> 0.13175906 | T21: =IF(G21<=3,F21*R21,0) -> 6.1824611e+09 | U21: =F21*P21 -> 4.0729763e+08 | V21: =H21^$AB$7*E21 -> 0.026671291 | W21: =I21^$AB$7*E21 -> 0.00036191934 | X21: =J21^$AB$7*E21 -> 0.00010903189 | Y21: =K21^$AB$7*E21 -> 6.4049889e-05
A22: 20 | B22: =C21 -> 2.2466364e-06 | C22: =(1/Inputs!$B$16)*(Inputs!$B$21/(1/Inputs!$B$16))^(19/60) -> 2.459133e-06 | D22: =(B22+C22)/2 -> 2.3528847e-06 | E22: =C22-B22 -> 2.1249656e-07 | F22: =Inputs!$B$16*E22 -> 0.48117721 | G22: =IF(D22<=Inputs!$B$21,1,IF(D22<=Inputs!$B$22,2,IF(D22<=Inputs!$B$23,3,IF(D22<=Inputs!$B$24,4,5)))) -> 1 | H22: =Fit!$B$10*D22^(-1/Fit!$B$9) -> 129512.32 | I22: =EXP(Fit!$B$16+Fit!$B$15*-NORMSINV(D22)) -> 1835.6353 | J22: =Fit!$B$22*LN(1/D22)^(1/Fit!$B$21) -> 558.22441 | K22: =MAX(0,Fit!$B$28+Fit!$B$27*-NORMSINV(D22)) -> 328.74707 | L22: =INDEX(H22:K22,1,Inputs!$B$5) -> 129512.32 | M22: =L22*E22 -> 0.027520923 | N22: =L22^$AB$7 -> 129512.32 | O22: =N22*E22 -> 0.027520923 | P22: =N22*$AB$3/($AB$4*$AB$1) -> 8.7342536e+08 | Q22: =IF(G22<=3,F22*SQRT(P22),0) -> 14220.601 | R22: =SQRT(P22/$AB$6) -> 1.365496e+10 | S22: =2*$AB$6*R22 -> 0.12792793 | T22: =IF(G22<=3,F22*R22,0) -> 6.5704555e+09 | U22: =F22*P22 -> 4.2027238e+08 | V22: =H22^$AB$7*E22 -> 0.027520923 | W22: =I22^$AB$7*E22 -> 0.0003900662 | X22: =J22^$AB$7*E22 -> 0.00011862077 | Y22: =K22^$AB$7*E22 -> 6.9857621e-05
A23: 21 | B23: =C22 -> 2.459133e-06 | C23: =(1/Inputs!$B$16)*(Inputs!$B$21/(1/Inputs!$B$16))^(20/60) -> 2.6917284e-06 | D23: =(B23+C23)/2 -> 2.5754307e-06 | E23: =C23-B23 -> 2.325954e-07 | F23: =Inputs!$B$16*E23 -> 0.52668903 | G23: =IF(D23<=Inputs!$B$21,1,IF(D23<=Inputs!$B$22,2,IF(D23<=Inputs!$B$23,3,IF(D23<=Inputs!$B$24,4,5)))) -> 1 | H23: =Fit!$B$10*D23^(-1/Fit!$B$9) -> 122090.21 | I23: =EXP(Fit!$B$16+Fit!$B$15*-NORMSINV(D23)) -> 1807.3325 | J23: =Fit!$B$22*LN(1/D23)^(1/Fit!$B$21) -> 554.81514 | K23: =MAX(0,Fit!$B$28+Fit!$B$27*-NORMSINV(D23)) -> 327.56428 | L23: =INDEX(H23:K23,1,Inputs!$B$5) -> 122090.21 | M23: =L23*E23 -> 0.028397621 | N23: =L23^$AB$7 -> 122090.21 | O23: =N23*E23 -> 0.028397621 | P23: =N23*$AB$3/($AB$4*$AB$1) -> 8.2337095e+08 | Q23: =IF(G23<=3,F23*SQRT(P23),0) -> 15113.047 | R23: =SQRT(P23/$AB$6) -> 1.3257917e+10 | S23: =2*$AB$6*R23 -> 0.12420819 | T23: =IF(G23<=3,F23*R23,0) -> 6.9827994e+09 | U23: =F23*P23 -> 4.3366044e+08 | V23: =H23^$AB$7*E23 -> 0.028397621 | W23: =I23^$AB$7*E23 -> 0.00042037724 | X23: =J23^$AB$7*E23 -> 0.00012904745 | Y23: =K23^$AB$7*E23 -> 7.6189945e-05
A24: 22 | B24: =C23 -> 2.6917284e-06 | C24: =(1/Inputs!$B$16)*(Inputs!$B$21/(1/Inputs!$B$16))^(21/60) -> 2.9463237e-06 | D24: =(B24+C24)/2 -> 2.819026e-06 | E24: =C24-B24 -> 2.5459528e-07 | F24: =Inputs!$B$16*E24 -> 0.57650554 | G24: =IF(D24<=Inputs!$B$21,1,IF(D24<=Inputs!$B$22,2,IF(D24<=Inputs!$B$23,3,IF(D24<=Inputs!$B$24,4,5)))) -> 1 | H24: =Fit!$B$10*D24^(-1/Fit!$B$9) -> 115093.44 | I24: =EXP(Fit!$B$16+Fit!$B$15*-NORMSINV(D24)) -> 1779.3599 | J24: =Fit!$B$22*LN(1/D24)^(1/Fit!$B$21) -> 551.40288 | K24: =MAX(0,Fit!$B$28+Fit!$B$27*-NORMSINV(D24)) -> 326.37695 | L24: =INDEX(H24:K24,1,Inputs!$B$5) -> 115093.44 | M24: =L24*E24 -> 0.029302246 | N24: =L24^$AB$7 -> 115093.44 | O24: =N24*E24 -> 0.029302246 | P24: =N24*$AB$3/($AB$4*$AB$1) -> 7.7618506e+08 | Q24: =IF(G24<=3,F24*SQRT(P24),0) -> 16061.501 | R24: =SQRT(P24/$AB$6) -> 1.2872419e+10 | S24: =2*$AB$6*R24 -> 0.12059661 | T24: =IF(G24<=3,F24*R24,0) -> 7.421021e+09 | U24: =F24*P24 -> 4.4747499e+08 | V24: =H24^$AB$7*E24 -> 0.029302246 | W24: =I24^$AB$7*E24 -> 0.00045301662 | X24: =J24^$AB$7*E24 -> 0.00014038457 | Y24: =K24^$AB$7*E24 -> 8.3094029e-05
A25: 23 | B25: =C24 -> 2.9463237e-06 | C25: =(1/Inputs!$B$16)*(Inputs!$B$21/(1/Inputs!$B$16))^(22/60) -> 3.2249997e-06 | D25: =(B25+C25)/2 -> 3.0856617e-06 | E25: =C25-B25 -> 2.78676e-07 | F25: =Inputs!$B$16*E25 -> 0.63103392 | G25: =IF(D25<=Inputs!$B$21,1,IF(D25<=Inputs!$B$22,2,IF(D25<=Inputs!$B$23,3,IF(D25<=Inputs!$B$24,4,5)))) -> 1 | H25: =Fit!$B$10*D25^(-1/Fit!$B$9) -> 108497.65 | I25: =EXP(Fit!$B$16+Fit!$B$15*-NORMSINV(D25)) -> 1751.7143 | J25: =Fit!$B$22*LN(1/D25)^(1/Fit!$B$21) -> 547.98762 | K25: =MAX(0,Fit!$B$28+Fit!$B$27*-NORMSINV(D25)) -> 325.18502 | L25: =INDEX(H25:K25,1,Inputs!$B$5) -> 108497.65 | M25: =L25*E25 -> 0.030235689 | N25: =L25^$AB$7 -> 108497.65 | O25: =N25*E25 -> 0.030235689 | P25: =N25*$AB$3/($AB$4*$AB$1) -> 7.3170331e+08 | Q25: =IF(G25<=3,F25*SQRT(P25),0) -> 17069.477 | R25: =SQRT(P25/$AB$6) -> 1.249813e+10 | S25: =2*$AB$6*R25 -> 0.11709005 | T25: =IF(G25<=3,F25*R25,0) -> 7.8867441e+09 | U25: =F25*P25 -> 4.6172961e+08 | V25: =H25^$AB$7*E25 -> 0.030235689 | W25: =I25^$AB$7*E25 -> 0.00048816073 | X25: =J25^$AB$7*E25 -> 0.000152711 | Y25: =K25^$AB$7*E25 -> 9.0621259e-05
A26: 24 | B26: =C25 -> 3.2249997e-06 | C26: =(1/Inputs!$B$16)*(Inputs!$B$21/(1/Inputs!$B$16))^(23/60) -> 3.530034e-06 | D26: =(B26+C26)/2 -> 3.3775169e-06 | E26: =C26-B26 -> 3.0503437e-07 | F26: =Inputs!$B$16*E26 -> 0.69071983 | G26: =IF(D26<=Inputs!$B$21,1,IF(D26<=Inputs!$B$22,2,IF(D26<=Inputs!$B$23,3,IF(D26<=Inputs!$B$24,4,5)))) -> 1 | H26: =Fit!$B$10*D26^(-1/Fit!$B$9) -> 102279.84 | I26: =EXP(Fit!$B$16+Fit!$B$15*-NORMSINV(D26)) -> 1724.3929 | J26: =Fit!$B$22*LN(1/D26)^(1/Fit!$B$21) -> 544.56932 | K26: =MAX(0,Fit!$B$28+Fit!$B$27*-NORMSINV(D26)) -> 323.98844 | L26: =INDEX(H26:K26,1,Inputs!$B$5) -> 102279.84 | M26: =L26*E26 -> 0.031198868 | N26: =L26^$AB$7 -> 102279.84 | O26: =N26*E26 -> 0.031198868 | P26: =N26*$AB$3/($AB$4*$AB$1) -> 6.8977073e+08 | Q26: =IF(G26<=3,F26*SQRT(P26),0) -> 18140.711 | R26: =SQRT(P26/$AB$6) -> 1.2134724e+10 | S26: =2*$AB$6*R26 -> 0.11368544 | T26: =IF(G26<=3,F26*R26,0) -> 8.3816947e+09 | U26: =F26*P26 -> 4.7643832e+08 | V26: =H26^$AB$7*E26 -> 0.031198868 | W26: =I26^$AB$7*E26 -> 0.00052599912 | X26: =J26^$AB$7*E26 -> 0.00016611236 | Y26: =K26^$AB$7*E26 -> 9.882761e-05
A27: 25 | B27: =C26 -> 3.530034e-06 | C27: =(1/Inputs!$B$16)*(Inputs!$B$21/(1/Inputs!$B$16))^(24/60) -> 3.8639199e-06 | D27: =(B27+C27)/2 -> 3.696977e-06 | E27: =C27-B27 -> 3.3388584e-07 | F27: =Inputs!$B$16*E27 -> 0.75605109 | G27: =IF(D27<=Inputs!$B$21,1,IF(D27<=Inputs!$B$22,2,IF(D27<=Inputs!$B$23,3,IF(D27<=Inputs!$B$24,4,5)))) -> 1 | H27: =Fit!$B$10*D27^(-1/Fit!$B$9) -> 96418.373 | I27: =EXP(Fit!$B$16+Fit!$B$15*-NORMSINV(D27)) -> 1697.3928 | J27: =Fit!$B$22*LN(1/D27)^(1/Fit!$B$21) -> 541.14797 | K27: =MAX(0,Fit!$B$28+Fit!$B$27*-NORMSINV(D27)) -> 322.78715 | L27: =INDEX(H27:K27,1,Inputs!$B$5) -> 96418.373 | M27: =L27*E27 -> 0.032192729 | N27: =L27^$AB$7 -> 96418.373 | O27: =N27*E27 -> 0.032192729 | P27: =N27*$AB$3/($AB$4*$AB$1) -> 6.5024123e+08 | Q27: =IF(G27<=3,F27*SQRT(P27),0) -> 19279.173 | R27: =SQRT(P27/$AB$6) -> 1.1781885e+10 | S27: =2*$AB$6*R27 -> 0.11037983 | T27: =IF(G27<=3,F27*R27,0) -> 8.9077071e+09 | U27: =F27*P27 -> 4.9161559e+08 | V27: =H27^$AB$7*E27 -> 0.032192729 | W27: =I27^$AB$7*E27 -> 0.00056673542 | X27: =J27^$AB$7*E27 -> 0.00018068164 | Y27: =K27^$AB$7*E27 -> 0.00010777406
A28: 26 | B28: =C27 -> 3.8639199e-06 | C28: =(1/Inputs!$B$16)*(Inputs!$B$21/(1/Inputs!$B$16))^(25/60) -> 4.2293861e-06 | D28: =(B28+C28)/2 -> 4.046653e-06 | E28: =C28-B28 -> 3.654662e-07 | F28: =Inputs!$B$16*E28 -> 0.82756166 | G28: =IF(D28<=Inputs!$B$21,1,IF(D28<=Inputs!$B$22,2,IF(D28<=Inputs!$B$23,3,IF(D28<=Inputs!$B$24,4,5)))) -> 1 | H28: =Fit!$B$10*D28^(-1/Fit!$B$9) -> 90892.812 | I28: =EXP(Fit!$B$16+Fit!$B$15*-NORMSINV(D28)) -> 1670.711 | J28: =Fit!$B$22*LN(1/D28)^(1/Fit!$B$21) -> 537.72354 | K28: =MAX(0,Fit!$B$28+Fit!$B$27*-NORMSINV(D28)) -> 321.58111 | L28: =INDEX(H28:K28,1,Inputs!$B$5) -> 90892.812 | M28: =L28*E28 -> 0.033218251 | N28: =L28^$AB$7 -> 90892.812 | O28: =N28*E28 -> 0.033218251 | P28: =N28*$AB$3/($AB$4*$AB$1) -> 6.1297709e+08 | Q28: =IF(G28<=3,F28*SQRT(P28),0) -> 20489.081 | R28: =SQRT(P28/$AB$6) -> 1.1439305e+10 | S28: =2*$AB$6*R28 -> 0.10717033 | T28: =IF(G28<=3,F28*R28,0) -> 9.4667305e+09 | U28: =F28*P28 -> 5.0727634e+08 | V28: =H28^$AB$7*E28 -> 0.033218251 | W28: =I28^$AB$7*E28 -> 0.0006105884 | X28: =J28^$AB$7*E28 -> 0.00019651978 | Y28: =K28^$AB$7*E28 -> 0.00011752703
A29: 27 | B29: =C28 -> 4.2293861e-06 | C29: =(1/Inputs!$B$16)*(Inputs!$B$21/(1/Inputs!$B$16))^(26/60) -> 4.6294196e-06 | D29: =(B29+C29)/2 -> 4.4294029e-06 | E29: =C29-B29 -> 4.0003357e-07 | F29: =Inputs!$B$16*E29 -> 0.90583601 | G29: =IF(D29<=Inputs!$B$21,1,IF(D29<=Inputs!$B$22,2,IF(D29<=Inputs!$B$23,3,IF(D29<=Inputs!$B$24,4,5)))) -> 1 | H29: =Fit!$B$10*D29^(-1/Fit!$B$9) -> 85683.911 | I29: =EXP(Fit!$B$16+Fit!$B$15*-NORMSINV(D29)) -> 1644.3446 | J29: =Fit!$B$22*LN(1/D29)^(1/Fit!$B$21) -> 534.296 | K29: =MAX(0,Fit!$B$28+Fit!$B$27*-NORMSINV(D29)) -> 320.37025 | L29: =INDEX(H29:K29,1,Inputs!$B$5) -> 85683.911 | M29: =L29*E29 -> 0.034276441 | N29: =L29^$AB$7 -> 85683.911 | O29: =N29*E29 -> 0.034276441 | P29: =N29*$AB$3/($AB$4*$AB$1) -> 5.7784849e+08 | Q29: =IF(G29<=3,F29*SQRT(P29),0) -> 21774.92 | R29: =SQRT(P29/$AB$6) -> 1.1106687e+10 | S29: =2*$AB$6*R29 -> 0.10405416 | T29: =IF(G29<=3,F29*R29,0) -> 1.0060837e+10 | U29: =F29*P29 -> 5.2343597e+08 | V29: =H29^$AB$7*E29 -> 0.034276441 | W29: =I29^$AB$7*E29 -> 0.00065779304 | X29: =J29^$AB$7*E29 -> 0.00021373634 | Y29: =K29^$AB$7*E29 -> 0.00012815886
A30: 28 | B30: =C29 -> 4.6294196e-06 | C30: =(1/Inputs!$B$16)*(Inputs!$B$21/(1/Inputs!$B$16))^(27/60) -> 5.0672901e-06 | D30: =(B30+C30)/2 -> 4.8483549e-06 | E30: =C30-B30 -> 4.3787047e-07 | F30: =Inputs!$B$16*E30 -> 0.99151389 | G30: =IF(D30<=Inputs!$B$21,1,IF(D30<=Inputs!$B$22,2,IF(D30<=Inputs!$B$23,3,IF(D30<=Inputs!$B$24,4,5)))) -> 1 | H30: =Fit!$B$10*D30^(-1/Fit!$B$9) -> 80773.522 | I30: =EXP(Fit!$B$16+Fit!$B$15*-NORMSINV(D30)) -> 1618.2908 | J30: =Fit!$B$22*LN(1/D30)^(1/Fit!$B$21) -> 530.86533 | K30: =MAX(0,Fit!$B$28+Fit!$B$27*-NORMSINV(D30)) -> 319.15452 | L30: =INDEX(H30:K30,1,Inputs!$B$5) -> 80773.522 | M30: =L30*E30 -> 0.03536834 | N30: =L30^$AB$7 -> 80773.522 | O30: =N30*E30 -> 0.03536834 | P30: =N30*$AB$3/($AB$4*$AB$1) -> 5.4473305e+08 | Q30: =IF(G30<=3,F30*SQRT(P30),0) -> 23141.455 | R30: =SQRT(P30/$AB$6) -> 1.078374e+10 | S30: =2*$AB$6*R30 -> 0.1010286 | T30: =IF(G30<=3,F30*R30,0) -> 1.0692228e+10 | U30: =F30*P30 -> 5.4011038e+08 | V30: =H30^$AB$7*E30 -> 0.03536834 | W30: =I30^$AB$7*E30 -> 0.00070860173 | X30: =J30^$AB$7*E30 -> 0.00023245025 | Y30: =K30^$AB$7*E30 -> 0.00013974834
A31: 29 | B31: =C30 -> 5.0672901e-06 | C31: =(1/Inputs!$B$16)*(Inputs!$B$21/(1/Inputs!$B$16))^(28/60) -> 5.5465763e-06 | D31: =(B31+C31)/2 -> 5.3069332e-06 | E31: =C31-B31 -> 4.7928615e-07 | F31: =Inputs!$B$16*E31 -> 1.0852955 | G31: =IF(D31<=Inputs!$B$21,1,IF(D31<=Inputs!$B$22,2,IF(D31<=Inputs!$B$23,3,IF(D31<=Inputs!$B$24,4,5)))) -> 1 | H31: =Fit!$B$10*D31^(-1/Fit!$B$9) -> 76144.539 | I31: =EXP(Fit!$B$16+Fit!$B$15*-NORMSINV(D31)) -> 1592.5466 | J31: =Fit!$B$22*LN(1/D31)^(1/Fit!$B$21) -> 527.4315 | K31: =MAX(0,Fit!$B$28+Fit!$B$27*-NORMSINV(D31)) -> 317.93387 | L31: =INDEX(H31:K31,1,Inputs!$B$5) -> 76144.539 | M31: =L31*E31 -> 0.036495023 | N31: =L31^$AB$7 -> 76144.539 | O31: =N31*E31 -> 0.036495023 | P31: =N31*$AB$3/($AB$4*$AB$1) -> 5.1351539e+08 | Q31: =IF(G31<=3,F31*SQRT(P31),0) -> 24593.75 | R31: =SQRT(P31/$AB$6) -> 1.0470183e+10 | S31: =2*$AB$6*R31 -> 0.098091008 | T31: =IF(G31<=3,F31*R31,0) -> 1.1363243e+10 | U31: =F31*P31 -> 5.5731597e+08 | V31: =H31^$AB$7*E31 -> 0.036495023 | W31: =I31^$AB$7*E31 -> 0.00076328553 | X31: =J31^$AB$7*E31 -> 0.00025279061 | Y31: =K31^$AB$7*E31 -> 0.0001523813
A32: 30 | B32: =C31 -> 5.5465763e-06 | C32: =(1/Inputs!$B$16)*(Inputs!$B$21/(1/Inputs!$B$16))^(29/60) -> 6.0711954e-06 | D32: =(B32+C32)/2 -> 5.8088858e-06 | E32: =C32-B32 -> 5.246191e-07 | F32: =Inputs!$B$16*E32 -> 1.1879475 | G32: =IF(D32<=Inputs!$B$21,1,IF(D32<=Inputs!$B$22,2,IF(D32<=Inputs!$B$23,3,IF(D32<=Inputs!$B$24,4,5)))) -> 1 | H32: =Fit!$B$10*D32^(-1/Fit!$B$9) -> 71780.834 | I32: =EXP(Fit!$B$16+Fit!$B$15*-NORMSINV(D32)) -> 1567.1093 | J32: =Fit!$B$22*LN(1/D32)^(1/Fit!$B$21) -> 523.99449 | K32: =MAX(0,Fit!$B$28+Fit!$B$27*-NORMSINV(D32)) -> 316.70823 | L32: =INDEX(H32:K32,1,Inputs!$B$5) -> 71780.834 | M32: =L32*E32 -> 0.037657596 | N32: =L32^$AB$7 -> 71780.834 | O32: =N32*E32 -> 0.037657596 | P32: =N32*$AB$3/($AB$4*$AB$1) -> 4.8408676e+08 | Q32: =IF(G32<=3,F32*SQRT(P32),0) -> 26137.187 | R32: =SQRT(P32/$AB$6) -> 1.0165743e+10 | S32: =2*$AB$6*R32 -> 0.095238834 | T32: =IF(G32<=3,F32*R32,0) -> 1.2076369e+10 | U32: =F32*P32 -> 5.7506965e+08 | V32: =H32^$AB$7*E32 -> 0.037657596 | W32: =I32^$AB$7*E32 -> 0.00082213547 | X32: =J32^$AB$7*E32 -> 0.00027489752 | Y32: =K32^$AB$7*E32 -> 0.00016615118
A33: 31 | B33: =C32 -> 6.0711954e-06 | C33: =(1/Inputs!$B$16)*(Inputs!$B$21/(1/Inputs!$B$16))^(30/60) -> 6.6454352e-06 | D33: =(B33+C33)/2 -> 6.3583153e-06 | E33: =C33-B33 -> 5.7423983e-07 | F33: =Inputs!$B$16*E33 -> 1.3003087 | G33: =IF(D33<=Inputs!$B$21,1,IF(D33<=Inputs!$B$22,2,IF(D33<=Inputs!$B$23,3,IF(D33<=Inputs!$B$24,4,5)))) -> 1 | H33: =Fit!$B$10*D33^(-1/Fit!$B$9) -> 67667.206 | I33: =EXP(Fit!$B$16+Fit!$B$15*-NORMSINV(D33)) -> 1541.9761 | J33: =Fit!$B$22*LN(1/D33)^(1/Fit!$B$21) -> 520.55426 | K33: =MAX(0,Fit!$B$28+Fit!$B$27*-NORMSINV(D33)) -> 315.47753 | L33: =INDEX(H33:K33,1,Inputs!$B$5) -> 67667.206 | M33: =L33*E33 -> 0.038857205 | N33: =L33^$AB$7 -> 67667.206 | O33: =N33*E33 -> 0.038857205 | P33: =N33*$AB$3/($AB$4*$AB$1) -> 4.5634463e+08 | Q33: =IF(G33<=3,F33*SQRT(P33),0) -> 27777.486 | R33: =SQRT(P33/$AB$6) -> 9.8701557e+09 | S33: =2*$AB$6*R33 -> 0.092469591 | T33: =IF(G33<=3,F33*R33,0) -> 1.2834249e+10 | U33: =F33*P33 -> 5.9338888e+08 | V33: =H33^$AB$7*E33 -> 0.038857205 | W33: =I33^$AB$7*E33 -> 0.00088546408 | X33: =J33^$AB$7*E33 -> 0.00029892299 | Y33: =K33^$AB$7*E33 -> 0.00018115977
A34: 32 | B34: =C33 -> 6.6454352e-06 | C34: =(1/Inputs!$B$16)*(Inputs!$B$21/(1/Inputs!$B$16))^(31/60) -> 7.2739891e-06 | D34: =(B34+C34)/2 -> 6.9597121e-06 | E34: =C34-B34 -> 6.2855391e-07 | F34: =Inputs!$B$16*E34 -> 1.4232975 | G34: =IF(D34<=Inputs!$B$21,1,IF(D34<=Inputs!$B$22,2,IF(D34<=Inputs!$B$23,3,IF(D34<=Inputs!$B$24,4,5)))) -> 1 | H34: =Fit!$B$10*D34^(-1/Fit!$B$9) -> 63789.322 | I34: =EXP(Fit!$B$16+Fit!$B$15*-NORMSINV(D34)) -> 1517.1441 | J34: =Fit!$B$22*LN(1/D34)^(1/Fit!$B$21) -> 517.1108 | K34: =MAX(0,Fit!$B$28+Fit!$B$27*-NORMSINV(D34)) -> 314.24173 | L34: =INDEX(H34:K34,1,Inputs!$B$5) -> 63789.322 | M34: =L34*E34 -> 0.040095028 | N34: =L34^$AB$7 -> 63789.322 | O34: =N34*E34 -> 0.040095028 | P34: =N34*$AB$3/($AB$4*$AB$1) -> 4.3019235e+08 | Q34: =IF(G34<=3,F34*SQRT(P34),0) -> 29520.725 | R34: =SQRT(P34/$AB$6) -> 9.583163e+09 | S34: =2*$AB$6*R34 -> 0.08978087 | T34: =IF(G34<=3,F34*R34,0) -> 1.3639692e+10 | U34: =F34*P34 -> 6.1229169e+08 | V34: =H34^$AB$7*E34 -> 0.040095028 | W34: =I34^$AB$7*E34 -> 0.00095360686 | X34: =J34^$AB$7*E34 -> 0.00032503202 | Y34: =K34^$AB$7*E34 -> 0.00019751787
A35: 33 | B35: =C34 -> 7.2739891e-06 | C35: =(1/Inputs!$B$16)*(Inputs!$B$21/(1/Inputs!$B$16))^(32/60) -> 7.9619944e-06 | D35: =(B35+C35)/2 -> 7.6179917e-06 | E35: =C35-B35 -> 6.8800525e-07 | F35: =Inputs!$B$16*E35 -> 1.5579191 | G35: =IF(D35<=Inputs!$B$21,1,IF(D35<=Inputs!$B$22,2,IF(D35<=Inputs!$B$23,3,IF(D35<=Inputs!$B$24,4,5)))) -> 1 | H35: =Fit!$B$10*D35^(-1/Fit!$B$9) -> 60133.672 | I35: =EXP(Fit!$B$16+Fit!$B$15*-NORMSINV(D35)) -> 1492.6106 | J35: =Fit!$B$22*LN(1/D35)^(1/Fit!$B$21) -> 513.66407 | K35: =MAX(0,Fit!$B$28+Fit!$B$27*-NORMSINV(D35)) -> 313.00076 | L35: =INDEX(H35:K35,1,Inputs!$B$5) -> 60133.672 | M35: =L35*E35 -> 0.041372282 | N35: =L35^$AB$7 -> 60133.672 | O35: =N35*E35 -> 0.041372282 | P35: =N35*$AB$3/($AB$4*$AB$1) -> 4.0553882e+08 | Q35: =IF(G35<=3,F35*SQRT(P35),0) -> 31373.366 | R35: =SQRT(P35/$AB$6) -> 9.3045151e+09 | S35: =2*$AB$6*R35 -> 0.087170328 | T35: =IF(G35<=3,F35*R35,0) -> 1.4495682e+10 | U35: =F35*P35 -> 6.3179666e+08 | V35: =H35^$AB$7*E35 -> 0.041372282 | W35: =I35^$AB$7*E35 -> 0.0010269239 | X35: =J35^$AB$7*E35 -> 0.00035340358 | Y35: =K35^$AB$7*E35 -> 0.00021534617
A36: 34 | B36: =C35 -> 7.9619944e-06 | C36: =(1/Inputs!$B$16)*(Inputs!$B$21/(1/Inputs!$B$16))^(33/60) -> 8.7150741e-06 | D36: =(B36+C36)/2 -> 8.3385342e-06 | E36: =C36-B36 -> 7.5307975e-07 | F36: =Inputs!$B$16*E36 -> 1.7052738 | G36: =IF(D36<=Inputs!$B$21,1,IF(D36<=Inputs!$B$22,2,IF(D36<=Inputs!$B$23,3,IF(D36<=Inputs!$B$24,4,5)))) -> 1 | H36: =Fit!$B$10*D36^(-1/Fit!$B$9) -> 56687.521 | I36: =EXP(Fit!$B$16+Fit!$B$15*-NORMSINV(D36)) -> 1468.3728 | J36: =Fit!$B$22*LN(1/D36)^(1/Fit!$B$21) -> 510.21405 | K36: =MAX(0,Fit!$B$28+Fit!$B$27*-NORMSINV(D36)) -> 311.75456 | L36: =INDEX(H36:K36,1,Inputs!$B$5) -> 56687.521 | M36: =L36*E36 -> 0.042690224 | N36: =L36^$AB$7 -> 56687.521 | O36: =N36*E36 -> 0.042690224 | P36: =N36*$AB$3/($AB$4*$AB$1) -> 3.8229813e+08 | Q36: =IF(G36<=3,F36*SQRT(P36),0) -> 33342.273 | R36: =SQRT(P36/$AB$6) -> 9.0339694e+09 | S36: =2*$AB$6*R36 -> 0.084635692 | T36: =IF(G36<=3,F36*R36,0) -> 1.5405391e+10 | U36: =F36*P36 -> 6.5192298e+08 | V36: =H36^$AB$7*E36 -> 0.042690224 | W36: =I36^$AB$7*E36 -> 0.0011058018 | X36: =J36^$AB$7*E36 -> 0.00038423187 | Y36: =K36^$AB$7*E36 -> 0.00023477604
A37: 35 | B37: =C36 -> 8.7150741e-06 | C37: =(1/Inputs!$B$16)*(Inputs!$B$21/(1/Inputs!$B$16))^(34/60) -> 9.5393834e-06 | D37: =(B37+C37)/2 -> 9.1272287e-06 | E37: =C37-B37 -> 8.2430928e-07 | F37: =Inputs!$B$16*E37 -> 1.8665659 | G37: =IF(D37<=Inputs!$B$21,1,IF(D37<=Inputs!$B$22,2,IF(D37<=Inputs!$B$23,3,IF(D37<=Inputs!$B$24,4,5)))) -> 1 | H37: =Fit!$B$10*D37^(-1/Fit!$B$9) -> 53438.863 | I37: =EXP(Fit!$B$16+Fit!$B$15*-NORMSINV(D37)) -> 1444.4281 | J37: =Fit!$B$22*LN(1/D37)^(1/Fit!$B$21) -> 506.7607 | K37: =MAX(0,Fit!$B$28+Fit!$B$27*-NORMSINV(D37)) -> 310.50305 | L37: =INDEX(H37:K37,1,Inputs!$B$5) -> 53438.863 | M37: =L37*E37 -> 0.044050151 | N37: =L37^$AB$7 -> 53438.863 | O37: =N37*E37 -> 0.044050151 | P37: =N37*$AB$3/($AB$4*$AB$1) -> 3.6038932e+08 | Q37: =IF(G37<=3,F37*SQRT(P37),0) -> 35434.743 | R37: =SQRT(P37/$AB$6) -> 8.7712903e+09 | S37: =2*$AB$6*R37 -> 0.082174755 | T37: =IF(G37<=3,F37*R37,0) -> 1.6372192e+10 | U37: =F37*P37 -> 6.7269043e+08 | V37: =H37^$AB$7*E37 -> 0.044050151 | W37: =I37^$AB$7*E37 -> 0.0011906555 | X37: =J37^$AB$7*E37 -> 0.00041772755 | Y37: =K37^$AB$7*E37 -> 0.00025595055
A38: 36 | B38: =C37 -> 9.5393834e-06 | C38: =(1/Inputs!$B$16)*(Inputs!$B$21/(1/Inputs!$B$16))^(35/60) -> 1.0441659e-05 | D38: =(B38+C38)/2 -> 9.9905214e-06 | E38: =C38-B38 -> 9.0227601e-07 | F38: =Inputs!$B$16*E38 -> 2.0431138 | G38: =IF(D38<=Inputs!$B$21,1,IF(D38<=Inputs!$B$22,2,IF(D38<=Inputs!$B$23,3,IF(D38<=Inputs!$B$24,4,5)))) -> 1 | H38: =Fit!$B$10*D38^(-1/Fit!$B$9) -> 50376.379 | I38: =EXP(Fit!$B$16+Fit!$B$15*-NORMSINV(D38)) -> 1420.7736 | J38: =Fit!$B$22*LN(1/D38)^(1/Fit!$B$21) -> 503.30401 | K38: =MAX(0,Fit!$B$28+Fit!$B$27*-NORMSINV(D38)) -> 309.24617 | L38: =INDEX(H38:K38,1,Inputs!$B$5) -> 50376.379 | M38: =L38*E38 -> 0.045453398 | N38: =L38^$AB$7 -> 50376.379 | O38: =N38*E38 -> 0.045453398 | P38: =N38*$AB$3/($AB$4*$AB$1) -> 3.3973606e+08 | Q38: =IF(G38<=3,F38*SQRT(P38),0) -> 37658.532 | R38: =SQRT(P38/$AB$6) -> 8.5162491e+09 | S38: =2*$AB$6*R38 -> 0.079785375 | T38: =IF(G38<=3,F38*R38,0) -> 1.7399666e+10 | U38: =F38*P38 -> 6.9411944e+08 | V38: =H38^$AB$7*E38 -> 0.045453398 | W38: =I38^$AB$7*E38 -> 0.0012819299 | X38: =J38^$AB$7*E38 -> 0.00045411913 | Y38: =K38^$AB$7*E38 -> 0.0002790254
A39: 37 | B39: =C38 -> 1.0441659e-05 | C39: =(1/Inputs!$B$16)*(Inputs!$B$21/(1/Inputs!$B$16))^(36/60) -> 1.1429277e-05 | D39: =(B39+C39)/2 -> 1.0935468e-05 | E39: =C39-B39 -> 9.8761716e-07 | F39: =Inputs!$B$16*E39 -> 2.2363603 | G39: =IF(D39<=Inputs!$B$21,1,IF(D39<=Inputs!$B$22,2,IF(D39<=Inputs!$B$23,3,IF(D39<=Inputs!$B$24,4,5)))) -> 1 | H39: =Fit!$B$10*D39^(-1/Fit!$B$9) -> 47489.401 | I39: =EXP(Fit!$B$16+Fit!$B$15*-NORMSINV(D39)) -> 1397.4067 | J39: =Fit!$B$22*LN(1/D39)^(1/Fit!$B$21) -> 499.84393 | K39: =MAX(0,Fit!$B$28+Fit!$B$27*-NORMSINV(D39)) -> 307.98387 | L39: =INDEX(H39:K39,1,Inputs!$B$5) -> 47489.401 | M39: =L39*E39 -> 0.046901347 | N39: =L39^$AB$7 -> 47489.401 | O39: =N39*E39 -> 0.046901347 | P39: =N39*$AB$3/($AB$4*$AB$1) -> 3.2026641e+08 | Q39: =IF(G39<=3,F39*SQRT(P39),0) -> 40021.879 | R39: =SQRT(P39/$AB$6) -> 8.2686237e+09 | S39: =2*$AB$6*R39 -> 0.07746547 | T39: =IF(G39<=3,F39*R39,0) -> 1.8491622e+10 | U39: =F39*P39 -> 7.1623109e+08 | V39: =H39^$AB$7*E39 -> 0.046901347 | W39: =I39^$AB$7*E39 -> 0.0013801029 | X39: =J39^$AB$7*E39 -> 0.00049365444 | Y39: =K39^$AB$7*E39 -> 0.00030417015
A40: 38 | B40: =C39 -> 1.1429277e-05 | C40: =(1/Inputs!$B$16)*(Inputs!$B$21/(1/Inputs!$B$16))^(37/60) -> 1.2510307e-05 | D40: =(B40+C40)/2 -> 1.1969792e-05 | E40: =C40-B40 -> 1.0810303e-06 | F40: =Inputs!$B$16*E40 -> 2.4478849 | G40: =IF(D40<=Inputs!$B$21,1,IF(D40<=Inputs!$B$22,2,IF(D40<=Inputs!$B$23,3,IF(D40<=Inputs!$B$24,4,5)))) -> 1 | H40: =Fit!$B$10*D40^(-1/Fit!$B$9) -> 44767.87 | I40: =EXP(Fit!$B$16+Fit!$B$15*-NORMSINV(D40)) -> 1374.3248 | J40: =Fit!$B$22*LN(1/D40)^(1/Fit!$B$21) -> 496.38043 | K40: =MAX(0,Fit!$B$28+Fit!$B$27*-NORMSINV(D40)) -> 306.71605 | L40: =INDEX(H40:K40,1,Inputs!$B$5) -> 44767.87 | M40: =L40*E40 -> 0.048395422 | N40: =L40^$AB$7 -> 44767.87 | O40: =N40*E40 -> 0.048395422 | P40: =N40*$AB$3/($AB$4*$AB$1) -> 3.0191253e+08 | Q40: =IF(G40<=3,F40*SQRT(P40),0) -> 42533.543 | R40: =SQRT(P40/$AB$6) -> 8.0281984e+09 | S40: =2*$AB$6*R40 -> 0.075213021 | T40: =IF(G40<=3,F40*R40,0) -> 1.9652106e+10 | U40: =F40*P40 -> 7.3904712e+08 | V40: =H40^$AB$7*E40 -> 0.048395422 | W40: =I40^$AB$7*E40 -> 0.0014856866 | X40: =J40^$AB$7*E40 -> 0.00053660226 | Y40: =K40^$AB$7*E40 -> 0.00033156933
A41: 39 | B41: =C40 -> 1.2510307e-05 | C41: =(1/Inputs!$B$16)*(Inputs!$B$21/(1/Inputs!$B$16))^(38/60) -> 1.3693586e-05 | D41: =(B41+C41)/2 -> 1.3101946e-05 | E41: =C41-B41 -> 1.1832788e-06 | F41: =Inputs!$B$16*E41 -> 2.6794164 | G41: =IF(D41<=Inputs!$B$21,1,IF(D41<=Inputs!$B$22,2,IF(D41<=Inputs!$B$23,3,IF(D41<=Inputs!$B$24,4,5)))) -> 1 | H41: =Fit!$B$10*D41^(-1/Fit!$B$9) -> 42202.305 | I41: =EXP(Fit!$B$16+Fit!$B$15*-NORMSINV(D41)) -> 1351.5251 | J41: =Fit!$B$22*LN(1/D41)^(1/Fit!$B$21) -> 492.9135 | K41: =MAX(0,Fit!$B$28+Fit!$B$27*-NORMSINV(D41)) -> 305.44267 | L41: =INDEX(H41:K41,1,Inputs!$B$5) -> 42202.305 | M41: =L41*E41 -> 0.049937091 | N41: =L41^$AB$7 -> 42202.305 | O41: =N41*E41 -> 0.049937091 | P41: =N41*$AB$3/($AB$4*$AB$1) -> 2.8461047e+08 | Q41: =IF(G41<=3,F41*SQRT(P41),0) -> 45202.833 | R41: =SQRT(P41/$AB$6) -> 7.7947639e+09 | S41: =2*$AB$6*R41 -> 0.073026065 | T41: =IF(G41<=3,F41*R41,0) -> 2.0885418e+10 | U41: =F41*P41 -> 7.6258997e+08 | V41: =H41^$AB$7*E41 -> 0.049937091 | W41: =I41^$AB$7*E41 -> 0.0015992309 | X41: =J41^$AB$7*E41 -> 0.00058325407 | Y41: =K41^$AB$7*E41 -> 0.00036142382
A42: 40 | B42: =C41 -> 1.3693586e-05 | C42: =(1/Inputs!$B$16)*(Inputs!$B$21/(1/Inputs!$B$16))^(39/60) -> 1.4988784e-05 | D42: =(B42+C42)/2 -> 1.4341185e-05 | E42: =C42-B42 -> 1.2951984e-06 | F42: =Inputs!$B$16*E42 -> 2.9328472 | G42: =IF(D42<=Inputs!$B$21,1,IF(D42<=Inputs!$B$22,2,IF(D42<=Inputs!$B$23,3,IF(D42<=Inputs!$B$24,4,5)))) -> 1 | H42: =Fit!$B$10*D42^(-1/Fit!$B$9) -> 39783.768 | I42: =EXP(Fit!$B$16+Fit!$B$15*-NORMSINV(D42)) -> 1329.005 | J42: =Fit!$B$22*LN(1/D42)^(1/Fit!$B$21) -> 489.44309 | K42: =MAX(0,Fit!$B$28+Fit!$B$27*-NORMSINV(D42)) -> 304.16363 | L42: =INDEX(H42:K42,1,Inputs!$B$5) -> 39783.768 | M42: =L42*E42 -> 0.051527871 | N42: =L42^$AB$7 -> 39783.768 | O42: =N42*E42 -> 0.051527871 | P42: =N42*$AB$3/($AB$4*$AB$1) -> 2.6829996e+08 | Q42: =IF(G42<=3,F42*SQRT(P42),0) -> 48039.639 | R42: =SQRT(P42/$AB$6) -> 7.568117e+09 | S42: =2*$AB$6*R42 -> 0.0709027 | T42: =IF(G42<=3,F42*R42,0) -> 2.2196131e+10 | U42: =F42*P42 -> 7.8688279e+08 | V42: =H42^$AB$7*E42 -> 0.051527871 | W42: =I42^$AB$7*E42 -> 0.0017213252 | X42: =J42^$AB$7*E42 -> 0.00063392589 | Y42: =K42^$AB$7*E42 -> 0.00039395223
A43: 41 | B43: =C42 -> 1.4988784e-05 | C43: =(1/Inputs!$B$16)*(Inputs!$B$21/(1/Inputs!$B$16))^(40/60) -> 1.6406488e-05 | D43: =(B43+C43)/2 -> 1.5697636e-05 | E43: =C43-B43 -> 1.4177038e-06 | F43: =Inputs!$B$16*E43 -> 3.2102485 | G43: =IF(D43<=Inputs!$B$21,1,IF(D43<=Inputs!$B$22,2,IF(D43<=Inputs!$B$23,3,IF(D43<=Inputs!$B$24,4,5)))) -> 1 | H43: =Fit!$B$10*D43^(-1/Fit!$B$9) -> 37503.833 | I43: =EXP(Fit!$B$16+Fit!$B$15*-NORMSINV(D43)) -> 1306.762 | J43: =Fit!$B$22*LN(1/D43)^(1/Fit!$B$21) -> 485.96918 | K43: =MAX(0,Fit!$B$28+Fit!$B$27*-NORMSINV(D43)) -> 302.87887 | L43: =INDEX(H43:K43,1,Inputs!$B$5) -> 37503.833 | M43: =L43*E43 -> 0.053169326 | N43: =L43^$AB$7 -> 37503.833 | O43: =N43*E43 -> 0.053169326 | P43: =N43*$AB$3/($AB$4*$AB$1) -> 2.5292418e+08 | Q43: =IF(G43<=3,F43*SQRT(P43),0) -> 51054.477 | R43: =SQRT(P43/$AB$6) -> 7.3480602e+09 | S43: =2*$AB$6*R43 -> 0.068841075 | T43: =IF(G43<=3,F43*R43,0) -> 2.3589099e+10 | U43: =F43*P43 -> 8.1194948e+08 | V43: =H43^$AB$7*E43 -> 0.053169326 | W43: =I43^$AB$7*E43 -> 0.0018526015 | X43: =J43^$AB$7*E43 -> 0.00068896035 | Y43: =K43^$AB$7*E43 -> 0.00042939253
A44: 42 | B44: =C43 -> 1.6406488e-05 | C44: =(1/Inputs!$B$16)*(Inputs!$B$21/(1/Inputs!$B$16))^(41/60) -> 1.7958284e-05 | D44: =(B44+C44)/2 -> 1.7182386e-05 | E44: =C44-B44 -> 1.5517963e-06 | F44: =Inputs!$B$16*E44 -> 3.5138876 | G44: =IF(D44<=Inputs!$B$21,1,IF(D44<=Inputs!$B$22,2,IF(D44<=Inputs!$B$23,3,IF(D44<=Inputs!$B$24,4,5)))) -> 1 | H44: =Fit!$B$10*D44^(-1/Fit!$B$9) -> 35354.556 | I44: =EXP(Fit!$B$16+Fit!$B$15*-NORMSINV(D44)) -> 1284.7935 | J44: =Fit!$B$22*LN(1/D44)^(1/Fit!$B$21) -> 482.49173 | K44: =MAX(0,Fit!$B$28+Fit!$B$27*-NORMSINV(D44)) -> 301.58832 | L44: =INDEX(H44:K44,1,Inputs!$B$5) -> 35354.556 | M44: =L44*E44 -> 0.054863071 | N44: =L44^$AB$7 -> 35354.556 | O44: =N44*E44 -> 0.054863071 | P44: =N44*$AB$3/($AB$4*$AB$1) -> 2.3842956e+08 | Q44: =IF(G44<=3,F44*SQRT(P44),0) -> 54258.517 | R44: =SQRT(P44/$AB$6) -> 7.134402e+09 | S44: =2*$AB$6*R44 -> 0.066839396 | T44: =IF(G44<=3,F44*R44,0) -> 2.5069487e+10 | U44: =F44*P44 -> 8.3781468e+08 | V44: =H44^$AB$7*E44 -> 0.054863071 | W44: =I44^$AB$7*E44 -> 0.0019937378 | X44: =J44^$AB$7*E44 -> 0.0007487289 | Y44: =K44^$AB$7*E44 -> 0.00046800366
A45: 43 | B45: =C44 -> 1.7958284e-05 | C45: =(1/Inputs!$B$16)*(Inputs!$B$21/(1/Inputs!$B$16))^(42/60) -> 1.9656856e-05 | D45: =(B45+C45)/2 -> 1.880757e-05 | E45: =C45-B45 -> 1.6985719e-06 | F45: =Inputs!$B$16*E45 -> 3.8462463 | G45: =IF(D45<=Inputs!$B$21,1,IF(D45<=Inputs!$B$22,2,IF(D45<=Inputs!$B$23,3,IF(D45<=Inputs!$B$24,4,5)))) -> 1 | H45: =Fit!$B$10*D45^(-1/Fit!$B$9) -> 33328.451 | I45: =EXP(Fit!$B$16+Fit!$B$15*-NORMSINV(D45)) -> 1263.0968 | J45: =Fit!$B$22*LN(1/D45)^(1/Fit!$B$21) -> 479.0107 | K45: =MAX(0,Fit!$B$28+Fit!$B$27*-NORMSINV(D45)) -> 300.2919 | L45: =INDEX(H45:K45,1,Inputs!$B$5) -> 33328.451 | M45: =L45*E45 -> 0.056610772 | N45: =L45^$AB$7 -> 33328.451 | O45: =N45*E45 -> 0.056610772 | P45: =N45*$AB$3/($AB$4*$AB$1) -> 2.247656e+08 | Q45: =IF(G45<=3,F45*SQRT(P45),0) -> 57663.634 | R45: =SQRT(P45/$AB$6) -> 6.9269563e+09 | S45: =2*$AB$6*R45 -> 0.064895919 | T45: =IF(G45<=3,F45*R45,0) -> 2.664278e+10 | U45: =F45*P45 -> 8.6450384e+08 | V45: =H45^$AB$7*E45 -> 0.056610772 | W45: =I45^$AB$7*E45 -> 0.0021454607 | X45: =J45^$AB$7*E45 -> 0.00081363414 | Y45: =K45^$AB$7*E45 -> 0.00051006739
A46: 44 | B46: =C45 -> 1.9656856e-05 | C46: =(1/Inputs!$B$16)*(Inputs!$B$21/(1/Inputs!$B$16))^(43/60) -> 2.1516086e-05 | D46: =(B46+C46)/2 -> 2.0586471e-05 | E46: =C46-B46 -> 1.8592302e-06 | F46: =Inputs!$B$16*E46 -> 4.2100408 | G46: =IF(D46<=Inputs!$B$21,1,IF(D46<=Inputs!$B$22,2,IF(D46<=Inputs!$B$23,3,IF(D46<=Inputs!$B$24,4,5)))) -> 1 | H46: =Fit!$B$10*D46^(-1/Fit!$B$9) -> 31418.459 | I46: =EXP(Fit!$B$16+Fit!$B$15*-NORMSINV(D46)) -> 1241.6693 | J46: =Fit!$B$22*LN(1/D46)^(1/Fit!$B$21) -> 475.52608 | K46: =MAX(0,Fit!$B$28+Fit!$B$27*-NORMSINV(D46)) -> 298.98952 | L46: =INDEX(H46:K46,1,Inputs!$B$5) -> 31418.459 | M46: =L46*E46 -> 0.058414147 | N46: =L46^$AB$7 -> 31418.459 | O46: =N46*E46 -> 0.058414147 | P46: =N46*$AB$3/($AB$4*$AB$1) -> 2.1188469e+08 | Q46: =IF(G46<=3,F46*SQRT(P46),0) -> 61282.447 | R46: =SQRT(P46/$AB$6) -> 6.7255425e+09 | S46: =2*$AB$6*R46 -> 0.063008952 | T46: =IF(G46<=3,F46*R46,0) -> 2.8314808e+10 | U46: =F46*P46 -> 8.920432e+08 | V46: =H46^$AB$7*E46 -> 0.058414147 | W46: =I46^$AB$7*E46 -> 0.0023085491 | X46: =J46^$AB$7*E46 -> 0.00088411244 | Y46: =K46^$AB$7*E46 -> 0.00055589034
A47: 45 | B47: =C46 -> 2.1516086e-05 | C47: =(1/Inputs!$B$16)*(Inputs!$B$21/(1/Inputs!$B$16))^(44/60) -> 2.355117e-05 | D47: =(B47+C47)/2 -> 2.2533628e-05 | E47: =C47-B47 -> 2.0350842e-06 | F47: =Inputs!$B$16*E47 -> 4.6082446 | G47: =IF(D47<=Inputs!$B$21,1,IF(D47<=Inputs!$B$22,2,IF(D47<=Inputs!$B$23,3,IF(D47<=Inputs!$B$24,4,5)))) -> 1 | H47: =Fit!$B$10*D47^(-1/Fit!$B$9) -> 29617.924 | I47: =EXP(Fit!$B$16+Fit!$B$15*-NORMSINV(D47)) -> 1220.5087 | J47: =Fit!$B$22*LN(1/D47)^(1/Fit!$B$21) -> 472.03782 | K47: =MAX(0,Fit!$B$28+Fit!$B$27*-NORMSINV(D47)) -> 297.68111 | L47: =INDEX(H47:K47,1,Inputs!$B$5) -> 29617.924 | M47: =L47*E47 -> 0.060274969 | N47: =L47^$AB$7 -> 29617.924 | O47: =N47*E47 -> 0.060274969 | P47: =N47*$AB$3/($AB$4*$AB$1) -> 1.9974197e+08 | Q47: =IF(G47<=3,F47*SQRT(P47),0) -> 65128.367 | R47: =SQRT(P47/$AB$6) -> 6.5299851e+09 | S47: =2*$AB$6*R47 -> 0.061176852 | T47: =IF(G47<=3,F47*R47,0) -> 3.0091769e+10 | U47: =F47*P47 -> 9.2045984e+08 | V47: =H47^$AB$7*E47 -> 0.060274969 | W47: =I47^$AB$7*E47 -> 0.002483838 | X47: =J47^$AB$7*E47 -> 0.0009606367 | Y47: =K47^$AB$7*E47 -> 0.00060580612
A48: 46 | B48: =C47 -> 2.355117e-05 | C48: =(1/Inputs!$B$16)*(Inputs!$B$21/(1/Inputs!$B$16))^(45/60) -> 2.5778742e-05 | D48: =(B48+C48)/2 -> 2.4664956e-05 | E48: =C48-B48 -> 2.2275712e-06 | F48: =Inputs!$B$16*E48 -> 5.0441123 | G48: =IF(D48<=Inputs!$B$21,1,IF(D48<=Inputs!$B$22,2,IF(D48<=Inputs!$B$23,3,IF(D48<=Inputs!$B$24,4,5)))) -> 1 | H48: =Fit!$B$10*D48^(-1/Fit!$B$9) -> 27920.575 | I48: =EXP(Fit!$B$16+Fit!$B$15*-NORMSINV(D48)) -> 1199.6123 | J48: =Fit!$B$22*LN(1/D48)^(1/Fit!$B$21) -> 468.54588 | K48: =MAX(0,Fit!$B$28+Fit!$B$27*-NORMSINV(D48)) -> 296.36658 | L48: =INDEX(H48:K48,1,Inputs!$B$5) -> 27920.575 | M48: =L48*E48 -> 0.062195069 | N48: =L48^$AB$7 -> 27920.575 | O48: =N48*E48 -> 0.062195069 | P48: =N48*$AB$3/($AB$4*$AB$1) -> 1.8829512e+08 | Q48: =IF(G48<=3,F48*SQRT(P48),0) -> 69215.646 | R48: =SQRT(P48/$AB$6) -> 6.3401139e+09 | S48: =2*$AB$6*R48 -> 0.059398024 | T48: =IF(G48<=3,F48*R48,0) -> 3.1980247e+10 | U48: =F48*P48 -> 9.4978172e+08 | V48: =H48^$AB$7*E48 -> 0.062195069 | W48: =I48^$AB$7*E48 -> 0.0026722218 | X48: =J48^$AB$7*E48 -> 0.0010437193 | Y48: =K48^$AB$7*E48 -> 0.00066017768
A49: 47 | B49: =C48 -> 2.5778742e-05 | C49: =(1/Inputs!$B$16)*(Inputs!$B$21/(1/Inputs!$B$16))^(46/60) -> 2.8217006e-05 | D49: =(B49+C49)/2 -> 2.6997874e-05 | E49: =C49-B49 -> 2.4382645e-06 | F49: =Inputs!$B$16*E49 -> 5.5212062 | G49: =IF(D49<=Inputs!$B$21,1,IF(D49<=Inputs!$B$22,2,IF(D49<=Inputs!$B$23,3,IF(D49<=Inputs!$B$24,4,5)))) -> 1 | H49: =Fit!$B$10*D49^(-1/Fit!$B$9) -> 26320.498 | I49: =EXP(Fit!$B$16+Fit!$B$15*-NORMSINV(D49)) -> 1178.9777 | J49: =Fit!$B$22*LN(1/D49)^(1/Fit!$B$21) -> 465.05024 | K49: =MAX(0,Fit!$B$28+Fit!$B$27*-NORMSINV(D49)) -> 295.04586 | L49: =INDEX(H49:K49,1,Inputs!$B$5) -> 26320.498 | M49: =L49*E49 -> 0.064176336 | N49: =L49^$AB$7 -> 26320.498 | O49: =N49*E49 -> 0.064176336 | P49: =N49*$AB$3/($AB$4*$AB$1) -> 1.7750427e+08 | Q49: =IF(G49<=3,F49*SQRT(P49),0) -> 73559.432 | R49: =SQRT(P49/$AB$6) -> 6.1557636e+09 | S49: =2*$AB$6*R49 -> 0.057670918 | T49: =IF(G49<=3,F49*R49,0) -> 3.398724e+10 | U49: =F49*P49 -> 9.8003766e+08 | V49: =H49^$AB$7*E49 -> 0.064176336 | W49: =I49^$AB$7*E49 -> 0.0028746594 | X49: =J49^$AB$7*E49 -> 0.0011339155 | Y49: =K49^$AB$7*E49 -> 0.00071939985
A50: 48 | B50: =C49 -> 2.8217006e-05 | C50: =(1/Inputs!$B$16)*(Inputs!$B$21/(1/Inputs!$B$16))^(47/60) -> 3.0885892e-05 | D50: =(B50+C50)/2 -> 2.9551449e-05 | E50: =C50-B50 -> 2.6688861e-06 | F50: =Inputs!$B$16*E50 -> 6.0434257 | G50: =IF(D50<=Inputs!$B$21,1,IF(D50<=Inputs!$B$22,2,IF(D50<=Inputs!$B$23,3,IF(D50<=Inputs!$B$24,4,5)))) -> 1 | H50: =Fit!$B$10*D50^(-1/Fit!$B$9) -> 24812.118 | I50: =EXP(Fit!$B$16+Fit!$B$15*-NORMSINV(D50)) -> 1158.6023 | J50: =Fit!$B$22*LN(1/D50)^(1/Fit!$B$21) -> 461.55085 | K50: =MAX(0,Fit!$B$28+Fit!$B$27*-NORMSINV(D50)) -> 293.71885 | L50: =INDEX(H50:K50,1,Inputs!$B$5) -> 24812.118 | M50: =L50*E50 -> 0.066220717 | N50: =L50^$AB$7 -> 24812.118 | O50: =N50*E50 -> 0.066220717 | P50: =N50*$AB$3/($AB$4*$AB$1) -> 1.6733182e+08 | Q50: =IF(G50<=3,F50*SQRT(P50),0) -> 78175.822 | R50: =SQRT(P50/$AB$6) -> 5.9767735e+09 | S50: =2*$AB$6*R50 -> 0.055994031 | T50: =IF(G50<=3,F50*R50,0) -> 3.6120187e+10 | U50: =F50*P50 -> 1.0112574e+09 | V50: =H50^$AB$7*E50 -> 0.066220717 | W50: =I50^$AB$7*E50 -> 0.0030921775 | X50: =J50^$AB$7*E50 -> 0.0012318267 | Y50: =K50^$AB$7*E50 -> 0.00078390215
A51: 49 | B51: =C50 -> 3.0885892e-05 | C51: =(1/Inputs!$B$16)*(Inputs!$B$21/(1/Inputs!$B$16))^(48/60) -> 3.3807213e-05 | D51: =(B51+C51)/2 -> 3.2346553e-05 | E51: =C51-B51 -> 2.9213208e-06 | F51: =Inputs!$B$16*E51 -> 6.6150389 | G51: =IF(D51<=Inputs!$B$21,1,IF(D51<=Inputs!$B$22,2,IF(D51<=Inputs!$B$23,3,IF(D51<=Inputs!$B$24,4,5)))) -> 1 | H51: =Fit!$B$10*D51^(-1/Fit!$B$9) -> 23390.181 | I51: =EXP(Fit!$B$16+Fit!$B$15*-NORMSINV(D51)) -> 1138.4837 | J51: =Fit!$B$22*LN(1/D51)^(1/Fit!$B$21) -> 458.04769 | K51: =MAX(0,Fit!$B$28+Fit!$B$27*-NORMSINV(D51)) -> 292.38547 | L51: =INDEX(H51:K51,1,Inputs!$B$5) -> 23390.181 | M51: =L51*E51 -> 0.068330223 | N51: =L51^$AB$7 -> 23390.181 | O51: =N51*E51 -> 0.068330223 | P51: =N51*$AB$3/($AB$4*$AB$1) -> 1.5774234e+08 | Q51: =IF(G51<=3,F51*SQRT(P51),0) -> 83081.924 | R51: =SQRT(P51/$AB$6) -> 5.802988e+09 | S51: =2*$AB$6*R51 -> 0.054365903 | T51: =IF(G51<=3,F51*R51,0) -> 3.8386991e+10 | U51: =F51*P51 -> 1.0434717e+09 | V51: =H51^$AB$7*E51 -> 0.068330223 | W51: =I51^$AB$7*E51 -> 0.0033258762 | X51: =J51^$AB$7*E51 -> 0.0013381043 | Y51: =K51^$AB$7*E51 -> 0.00085415176
A52: 50 | B52: =C51 -> 3.3807213e-05 | C52: =(1/Inputs!$B$16)*(Inputs!$B$21/(1/Inputs!$B$16))^(49/60) -> 3.7004845e-05 | D52: =(B52+C52)/2 -> 3.5406029e-05 | E52: =C52-B52 -> 3.197632e-06 | F52: =Inputs!$B$16*E52 -> 7.2407178 | G52: =IF(D52<=Inputs!$B$21,1,IF(D52<=Inputs!$B$22,2,IF(D52<=Inputs!$B$23,3,IF(D52<=Inputs!$B$24,4,5)))) -> 1 | H52: =Fit!$B$10*D52^(-1/Fit!$B$9) -> 22049.732 | I52: =EXP(Fit!$B$16+Fit!$B$15*-NORMSINV(D52)) -> 1118.6195 | J52: =Fit!$B$22*LN(1/D52)^(1/Fit!$B$21) -> 454.54071 | K52: =MAX(0,Fit!$B$28+Fit!$B$27*-NORMSINV(D52)) -> 291.04562 | L52: =INDEX(H52:K52,1,Inputs!$B$5) -> 22049.732 | M52: =L52*E52 -> 0.070506929 | N52: =L52^$AB$7 -> 22049.732 | O52: =N52*E52 -> 0.070506929 | P52: =N52*$AB$3/($AB$4*$AB$1) -> 1.4870242e+08 | Q52: =IF(G52<=3,F52*SQRT(P52),0) -> 88295.92 | R52: =SQRT(P52/$AB$6) -> 5.6342556e+09 | S52: =2*$AB$6*R52 -> 0.052785116 | T52: =IF(G52<=3,F52*R52,0) -> 4.0796055e+10 | U52: =F52*P52 -> 1.0767122e+09 | V52: =H52^$AB$7*E52 -> 0.070506929 | W52: =I52^$AB$7*E52 -> 0.0035769334 | X52: =J52^$AB$7*E52 -> 0.0014534539 | Y52: =K52^$AB$7*E52 -> 0.00093065678
A53: 51 | B53: =C52 -> 3.7004845e-05 | C53: =(1/Inputs!$B$16)*(Inputs!$B$21/(1/Inputs!$B$16))^(50/60) -> 4.0504923e-05 | D53: =(B53+C53)/2 -> 3.8754884e-05 | E53: =C53-B53 -> 3.5000778e-06 | F53: =Inputs!$B$16*E53 -> 7.9255761 | G53: =IF(D53<=Inputs!$B$21,1,IF(D53<=Inputs!$B$22,2,IF(D53<=Inputs!$B$23,3,IF(D53<=Inputs!$B$24,4,5)))) -> 1 | H53: =Fit!$B$10*D53^(-1/Fit!$B$9) -> 20786.102 | I53: =EXP(Fit!$B$16+Fit!$B$15*-NORMSINV(D53)) -> 1099.0072 | J53: =Fit!$B$22*LN(1/D53)^(1/Fit!$B$21) -> 451.02987 | K53: =MAX(0,Fit!$B$28+Fit!$B$27*-NORMSINV(D53)) -> 289.69922 | L53: =INDEX(H53:K53,1,Inputs!$B$5) -> 20786.102 | M53: =L53*E53 -> 0.072752975 | N53: =L53^$AB$7 -> 20786.102 | O53: =N53*E53 -> 0.072752975 | P53: =N53*$AB$3/($AB$4*$AB$1) -> 1.4018055e+08 | Q53: =IF(G53<=3,F53*SQRT(P53),0) -> 93837.132 | R53: =SQRT(P53/$AB$6) -> 5.4704293e+09 | S53: =2*$AB$6*R53 -> 0.051250292 | T53: =IF(G53<=3,F53*R53,0) -> 4.3356304e+10 | U53: =F53*P53 -> 1.1110116e+09 | V53: =H53^$AB$7*E53 -> 0.072752975 | W53: =I53^$AB$7*E53 -> 0.0038466107 | X53: =J53^$AB$7*E53 -> 0.0015786396 | Y53: =K53^$AB$7*E53 -> 0.0010139698
A54: 52 | B54: =C53 -> 4.0504923e-05 | C54: =(1/Inputs!$B$16)*(Inputs!$B$21/(1/Inputs!$B$16))^(51/60) -> 4.4336053e-05 | D54: =(B54+C54)/2 -> 4.2420488e-05 | E54: =C54-B54 -> 3.8311302e-06 | F54: =Inputs!$B$16*E54 -> 8.6752113 | G54: =IF(D54<=Inputs!$B$21,1,IF(D54<=Inputs!$B$22,2,IF(D54<=Inputs!$B$23,3,IF(D54<=Inputs!$B$24,4,5)))) -> 1 | H54: =Fit!$B$10*D54^(-1/Fit!$B$9) -> 19594.889 | I54: =EXP(Fit!$B$16+Fit!$B$15*-NORMSINV(D54)) -> 1079.6445 | J54: =Fit!$B$22*LN(1/D54)^(1/Fit!$B$21) -> 447.51514 | K54: =MAX(0,Fit!$B$28+Fit!$B$27*-NORMSINV(D54)) -> 288.34617 | L54: =INDEX(H54:K54,1,Inputs!$B$5) -> 19594.889 | M54: =L54*E54 -> 0.075070571 | N54: =L54^$AB$7 -> 19594.889 | O54: =N54*E54 -> 0.075070571 | P54: =N54*$AB$3/($AB$4*$AB$1) -> 1.3214706e+08 | Q54: =IF(G54<=3,F54*SQRT(P54),0) -> 99726.095 | R54: =SQRT(P54/$AB$6) -> 5.3113667e+09 | S54: =2*$AB$6*R54 -> 0.049760097 | T54: =IF(G54<=3,F54*R54,0) -> 4.6077228e+10 | U54: =F54*P54 -> 1.1464037e+09 | V54: =H54^$AB$7*E54 -> 0.075070571 | W54: =I54^$AB$7*E54 -> 0.0041362585 | X54: =J54^$AB$7*E54 -> 0.0017144888 | Y54: =K54^$AB$7*E54 -> 0.0011046917
A55: 53 | B55: =C54 -> 4.4336053e-05 | C55: =(1/Inputs!$B$16)*(Inputs!$B$21/(1/Inputs!$B$16))^(52/60) -> 4.8529548e-05 | D55: =(B55+C55)/2 -> 4.6432801e-05 | E55: =C55-B55 -> 4.193495e-06 | F55: =Inputs!$B$16*E55 -> 9.4957502 | G55: =IF(D55<=Inputs!$B$21,1,IF(D55<=Inputs!$B$22,2,IF(D55<=Inputs!$B$23,3,IF(D55<=Inputs!$B$24,4,5)))) -> 1 | H55: =Fit!$B$10*D55^(-1/Fit!$B$9) -> 18471.941 | I55: =EXP(Fit!$B$16+Fit!$B$15*-NORMSINV(D55)) -> 1060.5288 | J55: =Fit!$B$22*LN(1/D55)^(1/Fit!$B$21) -> 443.99648 | K55: =MAX(0,Fit!$B$28+Fit!$B$27*-NORMSINV(D55)) -> 286.98637 | L55: =INDEX(H55:K55,1,Inputs!$B$5) -> 18471.941 | M55: =L55*E55 -> 0.077461995 | N55: =L55^$AB$7 -> 18471.941 | O55: =N55*E55 -> 0.077461995 | P55: =N55*$AB$3/($AB$4*$AB$1) -> 1.2457395e+08 | Q55: =IF(G55<=3,F55*SQRT(P55),0) -> 105984.63 | R55: =SQRT(P55/$AB$6) -> 5.156929e+09 | S55: =2*$AB$6*R55 -> 0.048313232 | T55: =IF(G55<=3,F55*R55,0) -> 4.896891e+10 | U55: =F55*P55 -> 1.1829231e+09 | V55: =H55^$AB$7*E55 -> 0.077461995 | W55: =I55^$AB$7*E55 -> 0.0044473224 | X55: =J55^$AB$7*E55 -> 0.001861897 | Y55: =K55^$AB$7*E55 -> 0.0012034759
A56: 54 | B56: =C55 -> 4.8529548e-05 | C56: =(1/Inputs!$B$16)*(Inputs!$B$21/(1/Inputs!$B$16))^(53/60) -> 5.3119682e-05 | D56: =(B56+C56)/2 -> 5.0824615e-05 | E56: =C56-B56 -> 4.5901339e-06 | F56: =Inputs!$B$16*E56 -> 10.393899 | G56: =IF(D56<=Inputs!$B$21,1,IF(D56<=Inputs!$B$22,2,IF(D56<=Inputs!$B$23,3,IF(D56<=Inputs!$B$24,4,5)))) -> 1 | H56: =Fit!$B$10*D56^(-1/Fit!$B$9) -> 17413.348 | I56: =EXP(Fit!$B$16+Fit!$B$15*-NORMSINV(D56)) -> 1041.658 | J56: =Fit!$B$22*LN(1/D56)^(1/Fit!$B$21) -> 440.47384 | K56: =MAX(0,Fit!$B$28+Fit!$B$27*-NORMSINV(D56)) -> 285.61972 | L56: =INDEX(H56:K56,1,Inputs!$B$5) -> 17413.348 | M56: =L56*E56 -> 0.0799296 | N56: =L56^$AB$7 -> 17413.348 | O56: =N56*E56 -> 0.0799296 | P56: =N56*$AB$3/($AB$4*$AB$1) -> 1.1743485e+08 | Q56: =IF(G56<=3,F56*SQRT(P56),0) -> 112635.94 | R56: =SQRT(P56/$AB$6) -> 5.0069819e+09 | S56: =2*$AB$6*R56 -> 0.046908437 | T56: =IF(G56<=3,F56*R56,0) -> 5.2042065e+10 | U56: =F56*P56 -> 1.220606e+09 | V56: =H56^$AB$7*E56 -> 0.0799296 | W56: =I56^$AB$7*E56 -> 0.0047813497 | X56: =J56^$AB$7*E56 -> 0.0020218339 | Y56: =K56^$AB$7*E56 -> 0.0013110328
A57: 55 | B57: =C56 -> 5.3119682e-05 | C57: =(1/Inputs!$B$16)*(Inputs!$B$21/(1/Inputs!$B$16))^(54/60) -> 5.8143971e-05 | D57: =(B57+C57)/2 -> 5.5631826e-05 | E57: =C57-B57 -> 5.0242885e-06 | F57: =Inputs!$B$16*E57 -> 11.376999 | G57: =IF(D57<=Inputs!$B$21,1,IF(D57<=Inputs!$B$22,2,IF(D57<=Inputs!$B$23,3,IF(D57<=Inputs!$B$24,4,5)))) -> 1 | H57: =Fit!$B$10*D57^(-1/Fit!$B$9) -> 16415.421 | I57: =EXP(Fit!$B$16+Fit!$B$15*-NORMSINV(D57)) -> 1023.0296 | J57: =Fit!$B$22*LN(1/D57)^(1/Fit!$B$21) -> 436.94719 | K57: =MAX(0,Fit!$B$28+Fit!$B$27*-NORMSINV(D57)) -> 284.24613 | L57: =INDEX(H57:K57,1,Inputs!$B$5) -> 16415.421 | M57: =L57*E57 -> 0.082475811 | N57: =L57^$AB$7 -> 16415.421 | O57: =N57*E57 -> 0.082475811 | P57: =N57*$AB$3/($AB$4*$AB$1) -> 1.1070487e+08 | Q57: =IF(G57<=3,F57*SQRT(P57),0) -> 119704.67 | R57: =SQRT(P57/$AB$6) -> 4.8613948e+09 | S57: =2*$AB$6*R57 -> 0.045544489 | T57: =IF(G57<=3,F57*R57,0) -> 5.5308084e+10 | U57: =F57*P57 -> 1.2594892e+09 | V57: =H57^$AB$7*E57 -> 0.082475811 | W57: =I57^$AB$7*E57 -> 0.0051399957 | X57: =J57^$AB$7*E57 -> 0.0021953488 | Y57: =K57^$AB$7*E57 -> 0.0014281346
A58: 56 | B58: =C57 -> 5.8143971e-05 | C58: =(1/Inputs!$B$16)*(Inputs!$B$21/(1/Inputs!$B$16))^(55/60) -> 6.3643478e-05 | D58: =(B58+C58)/2 -> 6.0893724e-05 | E58: =C58-B58 -> 5.4995074e-06 | F58: =Inputs!$B$16*E58 -> 12.453085 | G58: =IF(D58<=Inputs!$B$21,1,IF(D58<=Inputs!$B$22,2,IF(D58<=Inputs!$B$23,3,IF(D58<=Inputs!$B$24,4,5)))) -> 1 | H58: =Fit!$B$10*D58^(-1/Fit!$B$9) -> 15474.683 | I58: =EXP(Fit!$B$16+Fit!$B$15*-NORMSINV(D58)) -> 1004.6412 | J58: =Fit!$B$22*LN(1/D58)^(1/Fit!$B$21) -> 433.41649 | K58: =MAX(0,Fit!$B$28+Fit!$B$27*-NORMSINV(D58)) -> 282.86549 | L58: =INDEX(H58:K58,1,Inputs!$B$5) -> 15474.683 | M58: =L58*E58 -> 0.085103135 | N58: =L58^$AB$7 -> 15474.683 | O58: =N58*E58 -> 0.085103135 | P58: =N58*$AB$3/($AB$4*$AB$1) -> 1.0436058e+08 | Q58: =IF(G58<=3,F58*SQRT(P58),0) -> 127217.01 | R58: =SQRT(P58/$AB$6) -> 4.7200409e+09 | S58: =2*$AB$6*R58 -> 0.0442202 | T58: =IF(G58<=3,F58*R58,0) -> 5.8779069e+10 | U58: =F58*P58 -> 1.2996111e+09 | V58: =H58^$AB$7*E58 -> 0.085103135 | W58: =I58^$AB$7*E58 -> 0.0055250317 | X58: =J58^$AB$7*E58 -> 0.0023835772 | Y58: =K58^$AB$7*E58 -> 0.0015556209
A59: 57 | B59: =C58 -> 6.3643478e-05 | C59: =(1/Inputs!$B$16)*(Inputs!$B$21/(1/Inputs!$B$16))^(56/60) -> 6.9663152e-05 | D59: =(B59+C59)/2 -> 6.6653315e-05 | E59: =C59-B59 -> 6.0196745e-06 | F59: =Inputs!$B$16*E59 -> 13.630951 | G59: =IF(D59<=Inputs!$B$21,1,IF(D59<=Inputs!$B$22,2,IF(D59<=Inputs!$B$23,3,IF(D59<=Inputs!$B$24,4,5)))) -> 1 | H59: =Fit!$B$10*D59^(-1/Fit!$B$9) -> 14587.857 | I59: =EXP(Fit!$B$16+Fit!$B$15*-NORMSINV(D59)) -> 986.49059 | J59: =Fit!$B$22*LN(1/D59)^(1/Fit!$B$21) -> 429.88169 | K59: =MAX(0,Fit!$B$28+Fit!$B$27*-NORMSINV(D59)) -> 281.47769 | L59: =INDEX(H59:K59,1,Inputs!$B$5) -> 14587.857 | M59: =L59*E59 -> 0.087814153 | N59: =L59^$AB$7 -> 14587.857 | O59: =N59*E59 -> 0.087814153 | P59: =N59*$AB$3/($AB$4*$AB$1) -> 98379862 | Q59: =IF(G59<=3,F59*SQRT(P59),0) -> 135200.8 | R59: =SQRT(P59/$AB$6) -> 4.5827972e+09 | S59: =2*$AB$6*R59 -> 0.042934417 | T59: =IF(G59<=3,F59*R59,0) -> 6.2467884e+10 | U59: =F59*P59 -> 1.3410111e+09 | V59: =H59^$AB$7*E59 -> 0.087814153 | W59: =I59^$AB$7*E59 -> 0.0059383523 | X59: =J59^$AB$7*E59 -> 0.0025877478 | Y59: =K59^$AB$7*E59 -> 0.0016944041
A60: 58 | B60: =C59 -> 6.9663152e-05 | C60: =(1/Inputs!$B$16)*(Inputs!$B$21/(1/Inputs!$B$16))^(57/60) -> 7.6252194e-05 | D60: =(B60+C60)/2 -> 7.2957673e-05 | E60: =C60-B60 -> 6.5890413e-06 | F60: =Inputs!$B$16*E60 -> 14.920225 | G60: =IF(D60<=Inputs!$B$21,1,IF(D60<=Inputs!$B$22,2,IF(D60<=Inputs!$B$23,3,IF(D60<=Inputs!$B$24,4,5)))) -> 1 | H60: =Fit!$B$10*D60^(-1/Fit!$B$9) -> 13751.854 | I60: =EXP(Fit!$B$16+Fit!$B$15*-NORMSINV(D60)) -> 968.57544 | J60: =Fit!$B$22*LN(1/D60)^(1/Fit!$B$21) -> 426.34274 | K60: =MAX(0,Fit!$B$28+Fit!$B$27*-NORMSINV(D60)) -> 280.08262 | L60: =INDEX(H60:K60,1,Inputs!$B$5) -> 13751.854 | M60: =L60*E60 -> 0.090611533 | N60: =L60^$AB$7 -> 13751.854 | O60: =N60*E60 -> 0.090611533 | P60: =N60*$AB$3/($AB$4*$AB$1) -> 92741892 | Q60: =IF(G60<=3,F60*SQRT(P60),0) -> 143685.63 | R60: =SQRT(P60/$AB$6) -> 4.449544e+09 | S60: =2*$AB$6*R60 -> 0.041686021 | T60: =IF(G60<=3,F60*R60,0) -> 6.6388198e+10 | U60: =F60*P60 -> 1.3837299e+09 | V60: =H60^$AB$7*E60 -> 0.090611533 | W60: =I60^$AB$7*E60 -> 0.0063819836 | X60: =J60^$AB$7*E60 -> 0.0028091899 | Y60: =K60^$AB$7*E60 -> 0.001845476
A61: 59 | B61: =C60 -> 7.6252194e-05 | C61: =(1/Inputs!$B$16)*(Inputs!$B$21/(1/Inputs!$B$16))^(58/60) -> 8.3464455e-05 | D61: =(B61+C61)/2 -> 7.9858324e-05 | E61: =C61-B61 -> 7.2122612e-06 | F61: =Inputs!$B$16*E61 -> 16.331444 | G61: =IF(D61<=Inputs!$B$21,1,IF(D61<=Inputs!$B$22,2,IF(D61<=Inputs!$B$23,3,IF(D61<=Inputs!$B$24,4,5)))) -> 1 | H61: =Fit!$B$10*D61^(-1/Fit!$B$9) -> 12963.76 | I61: =EXP(Fit!$B$16+Fit!$B$15*-NORMSINV(D61)) -> 950.89346 | J61: =Fit!$B$22*LN(1/D61)^(1/Fit!$B$21) -> 422.79961 | K61: =MAX(0,Fit!$B$28+Fit!$B$27*-NORMSINV(D61)) -> 278.68018 | L61: =INDEX(H61:K61,1,Inputs!$B$5) -> 12963.76 | M61: =L61*E61 -> 0.093498025 | N61: =L61^$AB$7 -> 12963.76 | O61: =N61*E61 -> 0.093498025 | P61: =N61*$AB$3/($AB$4*$AB$1) -> 87427023 | Q61: =IF(G61<=3,F61*SQRT(P61),0) -> 152702.95 | R61: =SQRT(P61/$AB$6) -> 4.3201654e+09 | S61: =2*$AB$6*R61 -> 0.040473924 | T61: =IF(G61<=3,F61*R61,0) -> 7.0554541e+10 | U61: =F61*P61 -> 1.4278096e+09 | V61: =H61^$AB$7*E61 -> 0.093498025 | W61: =I61^$AB$7*E61 -> 0.006858092 | X61: =J61^$AB$7*E61 -> 0.0030493413 | Y61: =K61^$AB$7*E61 -> 0.0020099142
A62: 60 | B62: =C61 -> 8.3464455e-05 | C62: =(1/Inputs!$B$16)*(Inputs!$B$21/(1/Inputs!$B$16))^(59/60) -> 9.1358883e-05 | D62: =(B62+C62)/2 -> 8.7411669e-05 | E62: =C62-B62 -> 7.894428e-06 | F62: =Inputs!$B$16*E62 -> 17.876143 | G62: =IF(D62<=Inputs!$B$21,1,IF(D62<=Inputs!$B$22,2,IF(D62<=Inputs!$B$23,3,IF(D62<=Inputs!$B$24,4,5)))) -> 1 | H62: =Fit!$B$10*D62^(-1/Fit!$B$9) -> 12220.831 | I62: =EXP(Fit!$B$16+Fit!$B$15*-NORMSINV(D62)) -> 933.44238 | J62: =Fit!$B$22*LN(1/D62)^(1/Fit!$B$21) -> 419.25225 | K62: =MAX(0,Fit!$B$28+Fit!$B$27*-NORMSINV(D62)) -> 277.27024 | L62: =INDEX(H62:K62,1,Inputs!$B$5) -> 12220.831 | M62: =L62*E62 -> 0.096476468 | N62: =L62^$AB$7 -> 12220.831 | O62: =N62*E62 -> 0.096476468 | P62: =N62*$AB$3/($AB$4*$AB$1) -> 82416740 | Q62: =IF(G62<=3,F62*SQRT(P62),0) -> 162286.18 | R62: =SQRT(P62/$AB$6) -> 4.1945488e+09 | S62: =2*$AB$6*R62 -> 0.039297071 | T62: =IF(G62<=3,F62*R62,0) -> 7.4982352e+10 | U62: =F62*P62 -> 1.4732934e+09 | V62: =H62^$AB$7*E62 -> 0.096476468 | W62: =I62^$AB$7*E62 -> 0.0073689936 | X62: =J62^$AB$7*E62 -> 0.0033097567 | Y62: =K62^$AB$7*E62 -> 0.0021888899
A63: 61 | B63: =C62 -> 9.1358883e-05 | C63: =(1/Inputs!$B$16)*(Inputs!$B$21/(1/Inputs!$B$16))^(60/60) -> 0.0001 | D63: =(B63+C63)/2 -> 9.5679441e-05 | E63: =C63-B63 -> 8.641117e-06 | F63: =Inputs!$B$16*E63 -> 19.566945 | G63: =IF(D63<=Inputs!$B$21,1,IF(D63<=Inputs!$B$22,2,IF(D63<=Inputs!$B$23,3,IF(D63<=Inputs!$B$24,4,5)))) -> 1 | H63: =Fit!$B$10*D63^(-1/Fit!$B$9) -> 11520.477 | I63: =EXP(Fit!$B$16+Fit!$B$15*-NORMSINV(D63)) -> 916.21995 | J63: =Fit!$B$22*LN(1/D63)^(1/Fit!$B$21) -> 415.70062 | K63: =MAX(0,Fit!$B$28+Fit!$B$27*-NORMSINV(D63)) -> 275.85269 | L63: =INDEX(H63:K63,1,Inputs!$B$5) -> 11520.477 | M63: =L63*E63 -> 0.099549792 | N63: =L63^$AB$7 -> 11520.477 | O63: =N63*E63 -> 0.099549792 | P63: =N63*$AB$3/($AB$4*$AB$1) -> 77693587 | Q63: =IF(G63<=3,F63*SQRT(P63),0) -> 172470.82 | R63: =SQRT(P63/$AB$6) -> 4.0725846e+09 | S63: =2*$AB$6*R63 -> 0.038154437 | T63: =IF(G63<=3,F63*R63,0) -> 7.9688041e+10 | U63: =F63*P63 -> 1.5202262e+09 | V63: =H63^$AB$7*E63 -> 0.099549792 | W63: =I63^$AB$7*E63 -> 0.0079171638 | X63: =J63^$AB$7*E63 -> 0.0035921177 | Y63: =K63^$AB$7*E63 -> 0.0023836754
A64: 62 | B64: =C63 -> 0.0001 | C64: =Inputs!$B$21*(Inputs!$B$22/Inputs!$B$21)^(1/60) -> 0.00010391223 | D64: =(B64+C64)/2 -> 0.00010195612 | E64: =C64-B64 -> 3.9122304e-06 | F64: =Inputs!$B$16*E64 -> 8.8588545 | G64: =IF(D64<=Inputs!$B$21,1,IF(D64<=Inputs!$B$22,2,IF(D64<=Inputs!$B$23,3,IF(D64<=Inputs!$B$24,4,5)))) -> 2 | H64: =Fit!$B$10*D64^(-1/Fit!$B$9) -> 11052.253 | I64: =EXP(Fit!$B$16+Fit!$B$15*-NORMSINV(D64)) -> 904.2472 | J64: =Fit!$B$22*LN(1/D64)^(1/Fit!$B$21) -> 413.20101 | K64: =MAX(0,Fit!$B$28+Fit!$B$27*-NORMSINV(D64)) -> 274.85144 | L64: =INDEX(H64:K64,1,Inputs!$B$5) -> 11052.253 | M64: =L64*E64 -> 0.043238958 | N64: =L64^$AB$7 -> 11052.253 | O64: =N64*E64 -> 0.043238958 | P64: =N64*$AB$3/($AB$4*$AB$1) -> 74535901 | Q64: =IF(G64<=3,F64*SQRT(P64),0) -> 76482.191 | R64: =SQRT(P64/$AB$6) -> 3.9889655e+09 | S64: =2*$AB$6*R64 -> 0.037371043 | T64: =IF(G64<=3,F64*R64,0) -> 3.5337665e+10 | U64: =F64*P64 -> 6.603027e+08 | V64: =H64^$AB$7*E64 -> 0.043238958 | W64: =I64^$AB$7*E64 -> 0.0035376234 | X64: =J64^$AB$7*E64 -> 0.0016165375 | Y64: =K64^$AB$7*E64 -> 0.0010752822
A65: 63 | B65: =C64 -> 0.00010391223 | C65: =Inputs!$B$21*(Inputs!$B$22/Inputs!$B$21)^(2/60) -> 0.00010797752 | D65: =(B65+C65)/2 -> 0.00010594487 | E65: =C65-B65 -> 4.0652858e-06 | F65: =Inputs!$B$16*E65 -> 9.2054333 | G65: =IF(D65<=Inputs!$B$21,1,IF(D65<=Inputs!$B$22,2,IF(D65<=Inputs!$B$23,3,IF(D65<=Inputs!$B$24,4,5)))) -> 2 | H65: =Fit!$B$10*D65^(-1/Fit!$B$9) -> 10778.721 | I65: =EXP(Fit!$B$16+Fit!$B$15*-NORMSINV(D65)) -> 897.06976 | J65: =Fit!$B$22*LN(1/D65)^(1/Fit!$B$21) -> 411.69025 | K65: =MAX(0,Fit!$B$28+Fit!$B$27*-NORMSINV(D65)) -> 274.24484 | L65: =INDEX(H65:K65,1,Inputs!$B$5) -> 10778.721 | M65: =L65*E65 -> 0.043818584 | N65: =L65^$AB$7 -> 10778.721 | O65: =N65*E65 -> 0.043818584 | P65: =N65*$AB$3/($AB$4*$AB$1) -> 72691219 | Q65: =IF(G65<=3,F65*SQRT(P65),0) -> 78484.737 | R65: =SQRT(P65/$AB$6) -> 3.939295e+09 | S65: =2*$AB$6*R65 -> 0.036905699 | T65: =IF(G65<=3,F65*R65,0) -> 3.6262917e+10 | U65: =F65*P65 -> 6.6915416e+08 | V65: =H65^$AB$7*E65 -> 0.043818584 | W65: =I65^$AB$7*E65 -> 0.003646845 | X65: =J65^$AB$7*E65 -> 0.0016736386 | Y65: =K65^$AB$7*E65 -> 0.0011148837
A66: 64 | B66: =C65 -> 0.00010797752 | C66: =Inputs!$B$21*(Inputs!$B$22/Inputs!$B$21)^(3/60) -> 0.00011220185 | D66: =(B66+C66)/2 -> 0.00011008968 | E66: =C66-B66 -> 4.2243292e-06 | F66: =Inputs!$B$16*E66 -> 9.565571 | G66: =IF(D66<=Inputs!$B$21,1,IF(D66<=Inputs!$B$22,2,IF(D66<=Inputs!$B$23,3,IF(D66<=Inputs!$B$24,4,5)))) -> 2 | H66: =Fit!$B$10*D66^(-1/Fit!$B$9) -> 10511.96 | I66: =EXP(Fit!$B$16+Fit!$B$15*-NORMSINV(D66)) -> 889.93269 | J66: =Fit!$B$22*LN(1/D66)^(1/Fit!$B$21) -> 410.1787 | K66: =MAX(0,Fit!$B$28+Fit!$B$27*-NORMSINV(D66)) -> 273.63681 | L66: =INDEX(H66:K66,1,Inputs!$B$5) -> 10511.96 | M66: =L66*E66 -> 0.044405979 | N66: =L66^$AB$7 -> 10511.96 | O66: =N66*E66 -> 0.044405979 | P66: =N66*$AB$3/($AB$4*$AB$1) -> 70892191 | Q66: =IF(G66<=3,F66*SQRT(P66),0) -> 80539.717 | R66: =SQRT(P66/$AB$6) -> 3.890243e+09 | S66: =2*$AB$6*R66 -> 0.03644615 | T66: =IF(G66<=3,F66*R66,0) -> 3.7212396e+10 | U66: =F66*P66 -> 6.7812428e+08 | V66: =H66^$AB$7*E66 -> 0.044405979 | W66: =I66^$AB$7*E66 -> 0.0037593687 | X66: =J66^$AB$7*E66 -> 0.0017327299 | Y66: =K66^$AB$7*E66 -> 0.001155932
A67: 65 | B67: =C66 -> 0.00011220185 | C67: =Inputs!$B$21*(Inputs!$B$22/Inputs!$B$21)^(4/60) -> 0.00011659144 | D67: =(B67+C67)/2 -> 0.00011439664 | E67: =C67-B67 -> 4.3895947e-06 | F67: =Inputs!$B$16*E67 -> 9.9397982 | G67: =IF(D67<=Inputs!$B$21,1,IF(D67<=Inputs!$B$22,2,IF(D67<=Inputs!$B$23,3,IF(D67<=Inputs!$B$24,4,5)))) -> 2 | H67: =Fit!$B$10*D67^(-1/Fit!$B$9) -> 10251.8 | I67: =EXP(Fit!$B$16+Fit!$B$15*-NORMSINV(D67)) -> 882.83583 | J67: =Fit!$B$22*LN(1/D67)^(1/Fit!$B$21) -> 408.66636 | K67: =MAX(0,Fit!$B$28+Fit!$B$27*-NORMSINV(D67)) -> 273.02736 | L67: =INDEX(H67:K67,1,Inputs!$B$5) -> 10251.8 | M67: =L67*E67 -> 0.045001248 | N67: =L67^$AB$7 -> 10251.8 | O67: =N67*E67 -> 0.045001248 | P67: =N67*$AB$3/($AB$4*$AB$1) -> 69137686 | Q67: =IF(G67<=3,F67*SQRT(P67),0) -> 82648.503 | R67: =SQRT(P67/$AB$6) -> 3.8418018e+09 | S67: =2*$AB$6*R67 -> 0.035992324 | T67: =IF(G67<=3,F67*R67,0) -> 3.8186734e+10 | U67: =F67*P67 -> 6.8721465e+08 | V67: =H67^$AB$7*E67 -> 0.045001248 | W67: =I67^$AB$7*E67 -> 0.0038752915 | X67: =J67^$AB$7*E67 -> 0.0017938797 | Y67: =K67^$AB$7*E67 -> 0.0011984795
A68: 66 | B68: =C67 -> 0.00011659144 | C68: =Inputs!$B$21*(Inputs!$B$22/Inputs!$B$21)^(5/60) -> 0.00012115277 | D68: =(B68+C68)/2 -> 0.0001188721 | E68: =C68-B68 -> 4.5613257e-06 | F68: =Inputs!$B$16*E68 -> 10.328666 | G68: =IF(D68<=Inputs!$B$21,1,IF(D68<=Inputs!$B$22,2,IF(D68<=Inputs!$B$23,3,IF(D68<=Inputs!$B$24,4,5)))) -> 2 | H68: =Fit!$B$10*D68^(-1/Fit!$B$9) -> 9998.0795 | I68: =EXP(Fit!$B$16+Fit!$B$15*-NORMSINV(D68)) -> 875.77902 | J68: =Fit!$B$22*LN(1/D68)^(1/Fit!$B$21) -> 407.15322 | K68: =MAX(0,Fit!$B$28+Fit!$B$27*-NORMSINV(D68)) -> 272.41647 | L68: =INDEX(H68:K68,1,Inputs!$B$5) -> 9998.0795 | M68: =L68*E68 -> 0.045604497 | N68: =L68^$AB$7 -> 9998.0795 | O68: =N68*E68 -> 0.045604497 | P68: =N68*$AB$3/($AB$4*$AB$1) -> 67426604 | Q68: =IF(G68<=3,F68*SQRT(P68),0) -> 84812.503 | R68: =SQRT(P68/$AB$6) -> 3.7939637e+09 | S68: =2*$AB$6*R68 -> 0.035544148 | T68: =IF(G68<=3,F68*R68,0) -> 3.9186584e+10 | U68: =F68*P68 -> 6.9642688e+08 | V68: =H68^$AB$7*E68 -> 0.045604497 | W68: =I68^$AB$7*E68 -> 0.0039947134 | X68: =J68^$AB$7*E68 -> 0.0018571585 | Y68: =K68^$AB$7*E68 -> 0.0012425803
A69: 67 | B69: =C68 -> 0.00012115277 | C69: =Inputs!$B$21*(Inputs!$B$22/Inputs!$B$21)^(6/60) -> 0.00012589254 | D69: =(B69+C69)/2 -> 0.00012352265 | E69: =C69-B69 -> 4.7397753e-06 | F69: =Inputs!$B$16*E69 -> 10.732747 | G69: =IF(D69<=Inputs!$B$21,1,IF(D69<=Inputs!$B$22,2,IF(D69<=Inputs!$B$23,3,IF(D69<=Inputs!$B$24,4,5)))) -> 2 | H69: =Fit!$B$10*D69^(-1/Fit!$B$9) -> 9750.638 | I69: =EXP(Fit!$B$16+Fit!$B$15*-NORMSINV(D69)) -> 868.76207 | J69: =Fit!$B$22*LN(1/D69)^(1/Fit!$B$21) -> 405.63928 | K69: =MAX(0,Fit!$B$28+Fit!$B$27*-NORMSINV(D69)) -> 271.80413 | L69: =INDEX(H69:K69,1,Inputs!$B$5) -> 9750.638 | M69: =L69*E69 -> 0.046215833 | N69: =L69^$AB$7 -> 9750.638 | O69: =N69*E69 -> 0.046215833 | P69: =N69*$AB$3/($AB$4*$AB$1) -> 65757870 | Q69: =IF(G69<=3,F69*SQRT(P69),0) -> 87033.163 | R69: =SQRT(P69/$AB$6) -> 3.7467214e+09 | S69: =2*$AB$6*R69 -> 0.035101553 | T69: =IF(G69<=3,F69*R69,0) -> 4.0212613e+10 | U69: =F69*P69 -> 7.0576259e+08 | V69: =H69^$AB$7*E69 -> 0.046215833 | W69: =I69^$AB$7*E69 -> 0.004117737 | X69: =J69^$AB$7*E69 -> 0.0019226391 | Y69: =K69^$AB$7*E69 -> 0.0012882905
A70: 68 | B70: =C69 -> 0.00012589254 | C70: =Inputs!$B$21*(Inputs!$B$22/Inputs!$B$21)^(7/60) -> 0.00013081775 | D70: =(B70+C70)/2 -> 0.00012835514 | E70: =C70-B70 -> 4.9252062e-06 | F70: =Inputs!$B$16*E70 -> 11.152637 | G70: =IF(D70<=Inputs!$B$21,1,IF(D70<=Inputs!$B$22,2,IF(D70<=Inputs!$B$23,3,IF(D70<=Inputs!$B$24,4,5)))) -> 2 | H70: =Fit!$B$10*D70^(-1/Fit!$B$9) -> 9509.3203 | I70: =EXP(Fit!$B$16+Fit!$B$15*-NORMSINV(D70)) -> 861.78483 | J70: =Fit!$B$22*LN(1/D70)^(1/Fit!$B$21) -> 404.12454 | K70: =MAX(0,Fit!$B$28+Fit!$B$27*-NORMSINV(D70)) -> 271.19033 | L70: =INDEX(H70:K70,1,Inputs!$B$5) -> 9509.3203 | M70: =L70*E70 -> 0.046835364 | N70: =L70^$AB$7 -> 9509.3203 | O70: =N70*E70 -> 0.046835364 | P70: =N70*$AB$3/($AB$4*$AB$1) -> 64130434 | Q70: =IF(G70<=3,F70*SQRT(P70),0) -> 89311.968 | R70: =SQRT(P70/$AB$6) -> 3.7000673e+09 | S70: =2*$AB$6*R70 -> 0.034664469 | T70: =IF(G70<=3,F70*R70,0) -> 4.1265507e+10 | U70: =F70*P70 -> 7.1522346e+08 | V70: =H70^$AB$7*E70 -> 0.046835364 | W70: =I70^$AB$7*E70 -> 0.004244468 | X70: =J70^$AB$7*E70 -> 0.0019903967 | Y70: =K70^$AB$7*E70 -> 0.0013356683
A71: 69 | B71: =C70 -> 0.00013081775 | C71: =Inputs!$B$21*(Inputs!$B$22/Inputs!$B$21)^(8/60) -> 0.00013593564 | D71: =(B71+C71)/2 -> 0.00013337669 | E71: =C71-B71 -> 5.1178917e-06 | F71: =Inputs!$B$16*E71 -> 11.588954 | G71: =IF(D71<=Inputs!$B$21,1,IF(D71<=Inputs!$B$22,2,IF(D71<=Inputs!$B$23,3,IF(D71<=Inputs!$B$24,4,5)))) -> 2 | H71: =Fit!$B$10*D71^(-1/Fit!$B$9) -> 9273.9751 | I71: =EXP(Fit!$B$16+Fit!$B$15*-NORMSINV(D71)) -> 854.84713 | J71: =Fit!$B$22*LN(1/D71)^(1/Fit!$B$21) -> 402.60899 | K71: =MAX(0,Fit!$B$28+Fit!$B$27*-NORMSINV(D71)) -> 270.57506 | L71: =INDEX(H71:K71,1,Inputs!$B$5) -> 9273.9751 | M71: =L71*E71 -> 0.0474632 | N71: =L71^$AB$7 -> 9273.9751 | O71: =N71*E71 -> 0.0474632 | P71: =N71*$AB$3/($AB$4*$AB$1) -> 62543276 | Q71: =IF(G71<=3,F71*SQRT(P71),0) -> 91650.439 | R71: =SQRT(P71/$AB$6) -> 3.6539941e+09 | S71: =2*$AB$6*R71 -> 0.034232828 | T71: =IF(G71<=3,F71*R71,0) -> 4.2345969e+10 | U71: =F71*P71 -> 7.2481114e+08 | V71: =H71^$AB$7*E71 -> 0.0474632 | W71: =I71^$AB$7*E71 -> 0.004375015 | X71: =J71^$AB$7*E71 -> 0.0020605092 | Y71: =K71^$AB$7*E71 -> 0.0013847739
A72: 70 | B72: =C71 -> 0.00013593564 | C72: =Inputs!$B$21*(Inputs!$B$22/Inputs!$B$21)^(9/60) -> 0.00014125375 | D72: =(B72+C72)/2 -> 0.0001385947 | E72: =C72-B72 -> 5.3181154e-06 | F72: =Inputs!$B$16*E72 -> 12.04234 | G72: =IF(D72<=Inputs!$B$21,1,IF(D72<=Inputs!$B$22,2,IF(D72<=Inputs!$B$23,3,IF(D72<=Inputs!$B$24,4,5)))) -> 2 | H72: =Fit!$B$10*D72^(-1/Fit!$B$9) -> 9044.4543 | I72: =EXP(Fit!$B$16+Fit!$B$15*-NORMSINV(D72)) -> 847.9488 | J72: =Fit!$B$22*LN(1/D72)^(1/Fit!$B$21) -> 401.09262 | K72: =MAX(0,Fit!$B$28+Fit!$B$27*-NORMSINV(D72)) -> 269.95831 | L72: =INDEX(H72:K72,1,Inputs!$B$5) -> 9044.4543 | M72: =L72*E72 -> 0.048099452 | N72: =L72^$AB$7 -> 9044.4543 | O72: =N72*E72 -> 0.048099452 | P72: =N72*$AB$3/($AB$4*$AB$1) -> 60995399 | Q72: =IF(G72<=3,F72*SQRT(P72),0) -> 94050.138 | R72: =SQRT(P72/$AB$6) -> 3.6084947e+09 | S72: =2*$AB$6*R72 -> 0.033806562 | T72: =IF(G72<=3,F72*R72,0) -> 4.3454721e+10 | U72: =F72*P72 -> 7.3452736e+08 | V72: =H72^$AB$7*E72 -> 0.048099452 | W72: =I72^$AB$7*E72 -> 0.0045094896 | X72: =J72^$AB$7*E72 -> 0.0021330568 | Y72: =K72^$AB$7*E72 -> 0.0014356695
A73: 71 | B73: =C72 -> 0.00014125375 | C73: =Inputs!$B$21*(Inputs!$B$22/Inputs!$B$21)^(10/60) -> 0.00014677993 | D73: =(B73+C73)/2 -> 0.00014401684 | E73: =C73-B73 -> 5.5261723e-06 | F73: =Inputs!$B$16*E73 -> 12.513465 | G73: =IF(D73<=Inputs!$B$21,1,IF(D73<=Inputs!$B$22,2,IF(D73<=Inputs!$B$23,3,IF(D73<=Inputs!$B$24,4,5)))) -> 2 | H73: =Fit!$B$10*D73^(-1/Fit!$B$9) -> 8820.614 | I73: =EXP(Fit!$B$16+Fit!$B$15*-NORMSINV(D73)) -> 841.08968 | J73: =Fit!$B$22*LN(1/D73)^(1/Fit!$B$21) -> 399.57544 | K73: =MAX(0,Fit!$B$28+Fit!$B$27*-NORMSINV(D73)) -> 269.34008 | L73: =INDEX(H73:K73,1,Inputs!$B$5) -> 8820.614 | M73: =L73*E73 -> 0.048744233 | N73: =L73^$AB$7 -> 8820.614 | O73: =N73*E73 -> 0.048744233 | P73: =N73*$AB$3/($AB$4*$AB$1) -> 59485829 | Q73: =IF(G73<=3,F73*SQRT(P73),0) -> 96512.669 | R73: =SQRT(P73/$AB$6) -> 3.5635618e+09 | S73: =2*$AB$6*R73 -> 0.033385603 | T73: =IF(G73<=3,F73*R73,0) -> 4.4592504e+10 | U73: =F73*P73 -> 7.4437382e+08 | V73: =H73^$AB$7*E73 -> 0.048744233 | W73: =I73^$AB$7*E73 -> 0.0046480065 | X73: =J73^$AB$7*E73 -> 0.0022081227 | Y73: =K73^$AB$7*E73 -> 0.0014884197
A74: 72 | B74: =C73 -> 0.00014677993 | C74: =Inputs!$B$21*(Inputs!$B$22/Inputs!$B$21)^(11/60) -> 0.0001525223 | D74: =(B74+C74)/2 -> 0.00014965111 | E74: =C74-B74 -> 5.7423689e-06 | F74: =Inputs!$B$16*E74 -> 13.00302 | G74: =IF(D74<=Inputs!$B$21,1,IF(D74<=Inputs!$B$22,2,IF(D74<=Inputs!$B$23,3,IF(D74<=Inputs!$B$24,4,5)))) -> 2 | H74: =Fit!$B$10*D74^(-1/Fit!$B$9) -> 8602.3134 | I74: =EXP(Fit!$B$16+Fit!$B$15*-NORMSINV(D74)) -> 834.2696 | J74: =Fit!$B$22*LN(1/D74)^(1/Fit!$B$21) -> 398.05744 | K74: =MAX(0,Fit!$B$28+Fit!$B$27*-NORMSINV(D74)) -> 268.72034 | L74: =INDEX(H74:K74,1,Inputs!$B$5) -> 8602.3134 | M74: =L74*E74 -> 0.049397657 | N74: =L74^$AB$7 -> 8602.3134 | O74: =N74*E74 -> 0.049397657 | P74: =N74*$AB$3/($AB$4*$AB$1) -> 58013620 | Q74: =IF(G74<=3,F74*SQRT(P74),0) -> 99039.678 | R74: =SQRT(P74/$AB$6) -> 3.5191884e+09 | S74: =2*$AB$6*R74 -> 0.032969886 | T74: =IF(G74<=3,F74*R74,0) -> 4.5760077e+10 | U74: =F74*P74 -> 7.5435227e+08 | V74: =H74^$AB$7*E74 -> 0.049397657 | W74: =I74^$AB$7*E74 -> 0.0047906838 | X74: =J74^$AB$7*E74 -> 0.0022857927 | Y74: =K74^$AB$7*E74 -> 0.0015430913
A75: 73 | B75: =C74 -> 0.0001525223 | C75: =Inputs!$B$21*(Inputs!$B$22/Inputs!$B$21)^(12/60) -> 0.00015848932 | D75: =(B75+C75)/2 -> 0.00015550581 | E75: =C75-B75 -> 5.9670236e-06 | F75: =Inputs!$B$16*E75 -> 13.511728 | G75: =IF(D75<=Inputs!$B$21,1,IF(D75<=Inputs!$B$22,2,IF(D75<=Inputs!$B$23,3,IF(D75<=Inputs!$B$24,4,5)))) -> 2 | H75: =Fit!$B$10*D75^(-1/Fit!$B$9) -> 8389.4156 | I75: =EXP(Fit!$B$16+Fit!$B$15*-NORMSINV(D75)) -> 827.4884 | J75: =Fit!$B$22*LN(1/D75)^(1/Fit!$B$21) -> 396.53862 | K75: =MAX(0,Fit!$B$28+Fit!$B$27*-NORMSINV(D75)) -> 268.09909 | L75: =INDEX(H75:K75,1,Inputs!$B$5) -> 8389.4156 | M75: =L75*E75 -> 0.050059841 | N75: =L75^$AB$7 -> 8389.4156 | O75: =N75*E75 -> 0.050059841 | P75: =N75*$AB$3/($AB$4*$AB$1) -> 56577846 | Q75: =IF(G75<=3,F75*SQRT(P75),0) -> 101632.85 | R75: =SQRT(P75/$AB$6) -> 3.4753675e+09 | S75: =2*$AB$6*R75 -> 0.032559346 | T75: =IF(G75<=3,F75*R75,0) -> 4.6958221e+10 | U75: =F75*P75 -> 7.6446448e+08 | V75: =H75^$AB$7*E75 -> 0.050059841 | W75: =I75^$AB$7*E75 -> 0.0049376428 | X75: =J75^$AB$7*E75 -> 0.0023661553 | Y75: =K75^$AB$7*E75 -> 0.0015997536
A76: 74 | B76: =C75 -> 0.00015848932 | C76: =Inputs!$B$21*(Inputs!$B$22/Inputs!$B$21)^(13/60) -> 0.00016468979 | D76: =(B76+C76)/2 -> 0.00016158955 | E76: =C76-B76 -> 6.2004673e-06 | F76: =Inputs!$B$16*E76 -> 14.040338 | G76: =IF(D76<=Inputs!$B$21,1,IF(D76<=Inputs!$B$22,2,IF(D76<=Inputs!$B$23,3,IF(D76<=Inputs!$B$24,4,5)))) -> 2 | H76: =Fit!$B$10*D76^(-1/Fit!$B$9) -> 8181.7867 | I76: =EXP(Fit!$B$16+Fit!$B$15*-NORMSINV(D76)) -> 820.74592 | J76: =Fit!$B$22*LN(1/D76)^(1/Fit!$B$21) -> 395.01896 | K76: =MAX(0,Fit!$B$28+Fit!$B$27*-NORMSINV(D76)) -> 267.47632 | L76: =INDEX(H76:K76,1,Inputs!$B$5) -> 8181.7867 | M76: =L76*E76 -> 0.050730901 | N76: =L76^$AB$7 -> 8181.7867 | O76: =N76*E76 -> 0.050730901 | P76: =N76*$AB$3/($AB$4*$AB$1) -> 55177607 | Q76: =IF(G76<=3,F76*SQRT(P76),0) -> 104293.92 | R76: =SQRT(P76/$AB$6) -> 3.4320923e+09 | S76: =2*$AB$6*R76 -> 0.032153918 | T76: =IF(G76<=3,F76*R76,0) -> 4.8187737e+10 | U76: =F76*P76 -> 7.7471226e+08 | V76: =H76^$AB$7*E76 -> 0.050730901 | W76: =I76^$AB$7*E76 -> 0.0050890082 | X76: =J76^$AB$7*E76 -> 0.0024493022 | Y76: =K76^$AB$7*E76 -> 0.0016584782
A77: 75 | B77: =C76 -> 0.00016468979 | C77: =Inputs!$B$21*(Inputs!$B$22/Inputs!$B$21)^(14/60) -> 0.00017113283 | D77: =(B77+C77)/2 -> 0.00016791131 | E77: =C77-B77 -> 6.4430439e-06 | F77: =Inputs!$B$16*E77 -> 14.589629 | G77: =IF(D77<=Inputs!$B$21,1,IF(D77<=Inputs!$B$22,2,IF(D77<=Inputs!$B$23,3,IF(D77<=Inputs!$B$24,4,5)))) -> 2 | H77: =Fit!$B$10*D77^(-1/Fit!$B$9) -> 7979.2965 | I77: =EXP(Fit!$B$16+Fit!$B$15*-NORMSINV(D77)) -> 814.04198 | J77: =Fit!$B$22*LN(1/D77)^(1/Fit!$B$21) -> 393.49848 | K77: =MAX(0,Fit!$B$28+Fit!$B$27*-NORMSINV(D77)) -> 266.85202 | L77: =INDEX(H77:K77,1,Inputs!$B$5) -> 7979.2965 | M77: =L77*E77 -> 0.051410957 | N77: =L77^$AB$7 -> 7979.2965 | O77: =N77*E77 -> 0.051410957 | P77: =N77*$AB$3/($AB$4*$AB$1) -> 53812021 | Q77: =IF(G77<=3,F77*SQRT(P77),0) -> 107024.67 | R77: =SQRT(P77/$AB$6) -> 3.389356e+09 | S77: =2*$AB$6*R77 -> 0.031753538 | T77: =IF(G77<=3,F77*R77,0) -> 4.9449445e+10 | U77: =F77*P77 -> 7.850974e+08 | V77: =H77^$AB$7*E77 -> 0.051410957 | W77: =I77^$AB$7*E77 -> 0.0052449082 | X77: =J77^$AB$7*E77 -> 0.0025353279 | Y77: =K77^$AB$7*E77 -> 0.0017193393
A78: 76 | B78: =C77 -> 0.00017113283 | C78: =Inputs!$B$21*(Inputs!$B$22/Inputs!$B$21)^(15/60) -> 0.00017782794 | D78: =(B78+C78)/2 -> 0.00017448039 | E78: =C78-B78 -> 6.6951106e-06 | F78: =Inputs!$B$16*E78 -> 15.160408 | G78: =IF(D78<=Inputs!$B$21,1,IF(D78<=Inputs!$B$22,2,IF(D78<=Inputs!$B$23,3,IF(D78<=Inputs!$B$24,4,5)))) -> 2 | H78: =Fit!$B$10*D78^(-1/Fit!$B$9) -> 7781.8176 | I78: =EXP(Fit!$B$16+Fit!$B$15*-NORMSINV(D78)) -> 807.37643 | J78: =Fit!$B$22*LN(1/D78)^(1/Fit!$B$21) -> 391.97715 | K78: =MAX(0,Fit!$B$28+Fit!$B$27*-NORMSINV(D78)) -> 266.22618 | L78: =INDEX(H78:K78,1,Inputs!$B$5) -> 7781.8176 | M78: =L78*E78 -> 0.05210013 | N78: =L78^$AB$7 -> 7781.8176 | O78: =N78*E78 -> 0.05210013 | P78: =N78*$AB$3/($AB$4*$AB$1) -> 52480233 | Q78: =IF(G78<=3,F78*SQRT(P78),0) -> 109826.91 | R78: =SQRT(P78/$AB$6) -> 3.3471518e+09 | S78: =2*$AB$6*R78 -> 0.031358143 | T78: =IF(G78<=3,F78*R78,0) -> 5.0744188e+10 | U78: =F78*P78 -> 7.9562176e+08 | V78: =H78^$AB$7*E78 -> 0.05210013 | W78: =I78^$AB$7*E78 -> 0.0054054745 | X78: =J78^$AB$7*E78 -> 0.0026243304 | Y78: =K78^$AB$7*E78 -> 0.0017824137
A79: 77 | B79: =C78 -> 0.00017782794 | C79: =Inputs!$B$21*(Inputs!$B$22/Inputs!$B$21)^(16/60) -> 0.00018478498 | D79: =(B79+C79)/2 -> 0.00018130646 | E79: =C79-B79 -> 6.9570387e-06 | F79: =Inputs!$B$16*E79 -> 15.753519 | G79: =IF(D79<=Inputs!$B$21,1,IF(D79<=Inputs!$B$22,2,IF(D79<=Inputs!$B$23,3,IF(D79<=Inputs!$B$24,4,5)))) -> 2 | H79: =Fit!$B$10*D79^(-1/Fit!$B$9) -> 7589.2261 | I79: =EXP(Fit!$B$16+Fit!$B$15*-NORMSINV(D79)) -> 800.74911 | J79: =Fit!$B$22*LN(1/D79)^(1/Fit!$B$21) -> 390.45499 | K79: =MAX(0,Fit!$B$28+Fit!$B$27*-NORMSINV(D79)) -> 265.59878 | L79: =INDEX(H79:K79,1,Inputs!$B$5) -> 7589.2261 | M79: =L79*E79 -> 0.05279854 | N79: =L79^$AB$7 -> 7589.2261 | O79: =N79*E79 -> 0.05279854 | P79: =N79*$AB$3/($AB$4*$AB$1) -> 51181404 | Q79: =IF(G79<=3,F79*SQRT(P79),0) -> 112702.53 | R79: =SQRT(P79/$AB$6) -> 3.3054731e+09 | S79: =2*$AB$6*R79 -> 0.030967672 | T79: =IF(G79<=3,F79*R79,0) -> 5.2072832e+10 | U79: =F79*P79 -> 8.062872e+08 | V79: =H79^$AB$7*E79 -> 0.05279854 | W79: =I79^$AB$7*E79 -> 0.0055708426 | X79: =J79^$AB$7*E79 -> 0.0027164105 | Y79: =K79^$AB$7*E79 -> 0.001847781
A80: 78 | B80: =C79 -> 0.00018478498 | C80: =Inputs!$B$21*(Inputs!$B$22/Inputs!$B$21)^(17/60) -> 0.00019201419 | D80: =(B80+C80)/2 -> 0.00018839959 | E80: =C80-B80 -> 7.2292141e-06 | F80: =Inputs!$B$16*E80 -> 16.369832 | G80: =IF(D80<=Inputs!$B$21,1,IF(D80<=Inputs!$B$22,2,IF(D80<=Inputs!$B$23,3,IF(D80<=Inputs!$B$24,4,5)))) -> 2 | H80: =Fit!$B$10*D80^(-1/Fit!$B$9) -> 7401.4011 | I80: =EXP(Fit!$B$16+Fit!$B$15*-NORMSINV(D80)) -> 794.15985 | J80: =Fit!$B$22*LN(1/D80)^(1/Fit!$B$21) -> 388.93198 | K80: =MAX(0,Fit!$B$28+Fit!$B$27*-NORMSINV(D80)) -> 264.96981 | L80: =INDEX(H80:K80,1,Inputs!$B$5) -> 7401.4011 | M80: =L80*E80 -> 0.053506313 | N80: =L80^$AB$7 -> 7401.4011 | O80: =N80*E80 -> 0.053506313 | P80: =N80*$AB$3/($AB$4*$AB$1) -> 49914721 | Q80: =IF(G80<=3,F80*SQRT(P80),0) -> 115653.44 | R80: =SQRT(P80/$AB$6) -> 3.2643134e+09 | S80: =2*$AB$6*R80 -> 0.030582064 | T80: =IF(G80<=3,F80*R80,0) -> 5.3436264e+10 | U80: =F80*P80 -> 8.1709561e+08 | V80: =H80^$AB$7*E80 -> 0.053506313 | W80: =I80^$AB$7*E80 -> 0.0057411516 | X80: =J80^$AB$7*E80 -> 0.0028116726 | Y80: =K80^$AB$7*E80 -> 0.0019155235
A81: 79 | B81: =C80 -> 0.00019201419 | C81: =Inputs!$B$21*(Inputs!$B$22/Inputs!$B$21)^(18/60) -> 0.00019952623 | D81: =(B81+C81)/2 -> 0.00019577021 | E81: =C81-B81 -> 7.5120376e-06 | F81: =Inputs!$B$16*E81 -> 17.010258 | G81: =IF(D81<=Inputs!$B$21,1,IF(D81<=Inputs!$B$22,2,IF(D81<=Inputs!$B$23,3,IF(D81<=Inputs!$B$24,4,5)))) -> 2 | H81: =Fit!$B$10*D81^(-1/Fit!$B$9) -> 7218.2245 | I81: =EXP(Fit!$B$16+Fit!$B$15*-NORMSINV(D81)) -> 787.6085 | J81: =Fit!$B$22*LN(1/D81)^(1/Fit!$B$21) -> 387.40812 | K81: =MAX(0,Fit!$B$28+Fit!$B$27*-NORMSINV(D81)) -> 264.33927 | L81: =INDEX(H81:K81,1,Inputs!$B$5) -> 7218.2245 | M81: =L81*E81 -> 0.054223574 | N81: =L81^$AB$7 -> 7218.2245 | O81: =N81*E81 -> 0.054223574 | P81: =N81*$AB$3/($AB$4*$AB$1) -> 48679386 | Q81: =IF(G81<=3,F81*SQRT(P81),0) -> 118681.61 | R81: =SQRT(P81/$AB$6) -> 3.2236663e+09 | S81: =2*$AB$6*R81 -> 0.030201256 | T81: =IF(G81<=3,F81*R81,0) -> 5.4835395e+10 | U81: =F81*P81 -> 8.2804891e+08 | V81: =H81^$AB$7*E81 -> 0.054223574 | W81: =I81^$AB$7*E81 -> 0.0059165447 | X81: =J81^$AB$7*E81 -> 0.0029102244 | Y81: =K81^$AB$7*E81 -> 0.0019857265
A82: 80 | B82: =C81 -> 0.00019952623 | C82: =Inputs!$B$21*(Inputs!$B$22/Inputs!$B$21)^(19/60) -> 0.00020733216 | D82: =(B82+C82)/2 -> 0.00020342919 | E82: =C82-B82 -> 7.8059259e-06 | F82: =Inputs!$B$16*E82 -> 17.675738 | G82: =IF(D82<=Inputs!$B$21,1,IF(D82<=Inputs!$B$22,2,IF(D82<=Inputs!$B$23,3,IF(D82<=Inputs!$B$24,4,5)))) -> 2 | H82: =Fit!$B$10*D82^(-1/Fit!$B$9) -> 7039.5814 | I82: =EXP(Fit!$B$16+Fit!$B$15*-NORMSINV(D82)) -> 781.09489 | J82: =Fit!$B$22*LN(1/D82)^(1/Fit!$B$21) -> 385.88341 | K82: =MAX(0,Fit!$B$28+Fit!$B$27*-NORMSINV(D82)) -> 263.70714 | L82: =INDEX(H82:K82,1,Inputs!$B$5) -> 7039.5814 | M82: =L82*E82 -> 0.05495045 | N82: =L82^$AB$7 -> 7039.5814 | O82: =N82*E82 -> 0.05495045 | P82: =N82*$AB$3/($AB$4*$AB$1) -> 47474624 | Q82: =IF(G82<=3,F82*SQRT(P82),0) -> 121789.08 | R82: =SQRT(P82/$AB$6) -> 3.1835252e+09 | S82: =2*$AB$6*R82 -> 0.029825191 | T82: =IF(G82<=3,F82*R82,0) -> 5.627116e+10 | U82: =F82*P82 -> 8.3914904e+08 | V82: =H82^$AB$7*E82 -> 0.05495045 | W82: =I82^$AB$7*E82 -> 0.0060971688 | X82: =J82^$AB$7*E82 -> 0.0030121773 | Y82: =K82^$AB$7*E82 -> 0.0020584784
A83: 81 | B83: =C82 -> 0.00020733216 | C83: =Inputs!$B$21*(Inputs!$B$22/Inputs!$B$21)^(20/60) -> 0.00021544347 | D83: =(B83+C83)/2 -> 0.00021138781 | E83: =C83-B83 -> 8.1113117e-06 | F83: =Inputs!$B$16*E83 -> 18.367254 | G83: =IF(D83<=Inputs!$B$21,1,IF(D83<=Inputs!$B$22,2,IF(D83<=Inputs!$B$23,3,IF(D83<=Inputs!$B$24,4,5)))) -> 2 | H83: =Fit!$B$10*D83^(-1/Fit!$B$9) -> 6865.3594 | I83: =EXP(Fit!$B$16+Fit!$B$15*-NORMSINV(D83)) -> 774.61886 | J83: =Fit!$B$22*LN(1/D83)^(1/Fit!$B$21) -> 384.35785 | K83: =MAX(0,Fit!$B$28+Fit!$B$27*-NORMSINV(D83)) -> 263.0734 | L83: =INDEX(H83:K83,1,Inputs!$B$5) -> 6865.3594 | M83: =L83*E83 -> 0.05568707 | N83: =L83^$AB$7 -> 6865.3594 | O83: =N83*E83 -> 0.05568707 | P83: =N83*$AB$3/($AB$4*$AB$1) -> 46299679 | Q83: =IF(G83<=3,F83*SQRT(P83),0) -> 124977.9 | R83: =SQRT(P83/$AB$6) -> 3.1438841e+09 | S83: =2*$AB$6*R83 -> 0.029453808 | T83: =IF(G83<=3,F83*R83,0) -> 5.7744517e+10 | U83: =F83*P83 -> 8.5039798e+08 | V83: =H83^$AB$7*E83 -> 0.05568707 | W83: =I83^$AB$7*E83 -> 0.006283175 | X83: =J83^$AB$7*E83 -> 0.0031176463 | Y83: =K83^$AB$7*E83 -> 0.0021338704
A84: 82 | B84: =C83 -> 0.00021544347 | C84: =Inputs!$B$21*(Inputs!$B$22/Inputs!$B$21)^(21/60) -> 0.00022387211 | D84: =(B84+C84)/2 -> 0.00021965779 | E84: =C84-B84 -> 8.4286449e-06 | F84: =Inputs!$B$16*E84 -> 19.085823 | G84: =IF(D84<=Inputs!$B$21,1,IF(D84<=Inputs!$B$22,2,IF(D84<=Inputs!$B$23,3,IF(D84<=Inputs!$B$24,4,5)))) -> 2 | H84: =Fit!$B$10*D84^(-1/Fit!$B$9) -> 6695.4493 | I84: =EXP(Fit!$B$16+Fit!$B$15*-NORMSINV(D84)) -> 768.18025 | J84: =Fit!$B$22*LN(1/D84)^(1/Fit!$B$21) -> 382.83141 | K84: =MAX(0,Fit!$B$28+Fit!$B$27*-NORMSINV(D84)) -> 262.43806 | L84: =INDEX(H84:K84,1,Inputs!$B$5) -> 6695.4493 | M84: =L84*E84 -> 0.056433564 | N84: =L84^$AB$7 -> 6695.4493 | O84: =N84*E84 -> 0.056433564 | P84: =N84*$AB$3/($AB$4*$AB$1) -> 45153813 | Q84: =IF(G84<=3,F84*SQRT(P84),0) -> 128250.22 | R84: =SQRT(P84/$AB$6) -> 3.1047365e+09 | S84: =2*$AB$6*R84 -> 0.02908705 | T84: =IF(G84<=3,F84*R84,0) -> 5.9256452e+10 | U84: =F84*P84 -> 8.617977e+08 | V84: =H84^$AB$7*E84 -> 0.056433564 | W84: =I84^$AB$7*E84 -> 0.0064747185 | X84: =J84^$AB$7*E84 -> 0.00322675 | Y84: =K84^$AB$7*E84 -> 0.0022119972
A85: 83 | B85: =C84 -> 0.00022387211 | C85: =Inputs!$B$21*(Inputs!$B$22/Inputs!$B$21)^(22/60) -> 0.00023263051 | D85: =(B85+C85)/2 -> 0.00022825131 | E85: =C85-B85 -> 8.7583929e-06 | F85: =Inputs!$B$16*E85 -> 19.832505 | G85: =IF(D85<=Inputs!$B$21,1,IF(D85<=Inputs!$B$22,2,IF(D85<=Inputs!$B$23,3,IF(D85<=Inputs!$B$24,4,5)))) -> 2 | H85: =Fit!$B$10*D85^(-1/Fit!$B$9) -> 6529.7443 | I85: =EXP(Fit!$B$16+Fit!$B$15*-NORMSINV(D85)) -> 761.77891 | J85: =Fit!$B$22*LN(1/D85)^(1/Fit!$B$21) -> 381.30412 | K85: =MAX(0,Fit!$B$28+Fit!$B$27*-NORMSINV(D85)) -> 261.80109 | L85: =INDEX(H85:K85,1,Inputs!$B$5) -> 6529.7443 | M85: =L85*E85 -> 0.057190065 | N85: =L85^$AB$7 -> 6529.7443 | O85: =N85*E85 -> 0.057190065 | P85: =N85*$AB$3/($AB$4*$AB$1) -> 44036305 | Q85: =IF(G85<=3,F85*SQRT(P85),0) -> 131608.22 | R85: =SQRT(P85/$AB$6) -> 3.0660764e+09 | S85: =2*$AB$6*R85 -> 0.028724859 | T85: =IF(G85<=3,F85*R85,0) -> 6.0807974e+10 | U85: =F85*P85 -> 8.7335024e+08 | V85: =H85^$AB$7*E85 -> 0.057190065 | W85: =I85^$AB$7*E85 -> 0.0066719589 | X85: =J85^$AB$7*E85 -> 0.0033396113 | Y85: =K85^$AB$7*E85 -> 0.0022929568
A86: 84 | B86: =C85 -> 0.00023263051 | C86: =Inputs!$B$21*(Inputs!$B$22/Inputs!$B$21)^(23/60) -> 0.00024173155 | D86: =(B86+C86)/2 -> 0.00023718103 | E86: =C86-B86 -> 9.1010414e-06 | F86: =Inputs!$B$16*E86 -> 20.608398 | G86: =IF(D86<=Inputs!$B$21,1,IF(D86<=Inputs!$B$22,2,IF(D86<=Inputs!$B$23,3,IF(D86<=Inputs!$B$24,4,5)))) -> 2 | H86: =Fit!$B$10*D86^(-1/Fit!$B$9) -> 6368.1402 | I86: =EXP(Fit!$B$16+Fit!$B$15*-NORMSINV(D86)) -> 755.41467 | J86: =Fit!$B$22*LN(1/D86)^(1/Fit!$B$21) -> 379.77595 | K86: =MAX(0,Fit!$B$28+Fit!$B$27*-NORMSINV(D86)) -> 261.16249 | L86: =INDEX(H86:K86,1,Inputs!$B$5) -> 6368.1402 | M86: =L86*E86 -> 0.057956708 | N86: =L86^$AB$7 -> 6368.1402 | O86: =N86*E86 -> 0.057956708 | P86: =N86*$AB$3/($AB$4*$AB$1) -> 42946455 | Q86: =IF(G86<=3,F86*SQRT(P86),0) -> 135054.14 | R86: =SQRT(P86/$AB$6) -> 3.0278977e+09 | S86: =2*$AB$6*R86 -> 0.028367178 | T86: =IF(G86<=3,F86*R86,0) -> 6.240012e+10 | U86: =F86*P86 -> 8.8505764e+08 | V86: =H86^$AB$7*E86 -> 0.057956708 | W86: =I86^$AB$7*E86 -> 0.0068750601 | X86: =J86^$AB$7*E86 -> 0.0034563566 | Y86: =K86^$AB$7*E86 -> 0.0023768506
A87: 85 | B87: =C86 -> 0.00024173155 | C87: =Inputs!$B$21*(Inputs!$B$22/Inputs!$B$21)^(24/60) -> 0.00025118864 | D87: =(B87+C87)/2 -> 0.0002464601 | E87: =C87-B87 -> 9.4570951e-06 | F87: =Inputs!$B$16*E87 -> 21.414646 | G87: =IF(D87<=Inputs!$B$21,1,IF(D87<=Inputs!$B$22,2,IF(D87<=Inputs!$B$23,3,IF(D87<=Inputs!$B$24,4,5)))) -> 2 | H87: =Fit!$B$10*D87^(-1/Fit!$B$9) -> 6210.5357 | I87: =EXP(Fit!$B$16+Fit!$B$15*-NORMSINV(D87)) -> 749.08737 | J87: =Fit!$B$22*LN(1/D87)^(1/Fit!$B$21) -> 378.2469 | K87: =MAX(0,Fit!$B$28+Fit!$B$27*-NORMSINV(D87)) -> 260.52224 | L87: =INDEX(H87:K87,1,Inputs!$B$5) -> 6210.5357 | M87: =L87*E87 -> 0.058733627 | N87: =L87^$AB$7 -> 6210.5357 | O87: =N87*E87 -> 0.058733627 | P87: =N87*$AB$3/($AB$4*$AB$1) -> 41883577 | Q87: =IF(G87<=3,F87*SQRT(P87),0) -> 138590.28 | R87: =SQRT(P87/$AB$6) -> 2.9901943e+09 | S87: =2*$AB$6*R87 -> 0.02801395 | T87: =IF(G87<=3,F87*R87,0) -> 6.4033953e+10 | U87: =F87*P87 -> 8.9692198e+08 | V87: =H87^$AB$7*E87 -> 0.058733627 | W87: =I87^$AB$7*E87 -> 0.0070841905 | X87: =J87^$AB$7*E87 -> 0.0035771169 | Y87: =K87^$AB$7*E87 -> 0.0024637835
A88: 86 | B88: =C87 -> 0.00025118864 | C88: =Inputs!$B$21*(Inputs!$B$22/Inputs!$B$21)^(25/60) -> 0.00026101572 | D88: =(B88+C88)/2 -> 0.00025610218 | E88: =C88-B88 -> 9.8270784e-06 | F88: =Inputs!$B$16*E88 -> 22.252436 | G88: =IF(D88<=Inputs!$B$21,1,IF(D88<=Inputs!$B$22,2,IF(D88<=Inputs!$B$23,3,IF(D88<=Inputs!$B$24,4,5)))) -> 2 | H88: =Fit!$B$10*D88^(-1/Fit!$B$9) -> 6056.8318 | I88: =EXP(Fit!$B$16+Fit!$B$15*-NORMSINV(D88)) -> 742.79687 | J88: =Fit!$B$22*LN(1/D88)^(1/Fit!$B$21) -> 376.71698 | K88: =MAX(0,Fit!$B$28+Fit!$B$27*-NORMSINV(D88)) -> 259.88032 | L88: =INDEX(H88:K88,1,Inputs!$B$5) -> 6056.8318 | M88: =L88*E88 -> 0.059520961 | N88: =L88^$AB$7 -> 6056.8318 | O88: =N88*E88 -> 0.059520961 | P88: =N88*$AB$3/($AB$4*$AB$1) -> 40847005 | Q88: =IF(G88<=3,F88*SQRT(P88),0) -> 142219.02 | R88: =SQRT(P88/$AB$6) -> 2.9529605e+09 | S88: =2*$AB$6*R88 -> 0.027665121 | T88: =IF(G88<=3,F88*R88,0) -> 6.5710566e+10 | U88: =F88*P88 -> 9.0894537e+08 | V88: =H88^$AB$7*E88 -> 0.059520961 | W88: =I88^$AB$7*E88 -> 0.0072995231 | X88: =J88^$AB$7*E88 -> 0.0037020273 | Y88: =K88^$AB$7*E88 -> 0.0025538643
A89: 87 | B89: =C88 -> 0.00026101572 | C89: =Inputs!$B$21*(Inputs!$B$22/Inputs!$B$21)^(26/60) -> 0.00027122726 | D89: =(B89+C89)/2 -> 0.00026612149 | E89: =C89-B89 -> 1.0211536e-05 | F89: =Inputs!$B$16*E89 -> 23.123003 | G89: =IF(D89<=Inputs!$B$21,1,IF(D89<=Inputs!$B$22,2,IF(D89<=Inputs!$B$23,3,IF(D89<=Inputs!$B$24,4,5)))) -> 2 | H89: =Fit!$B$10*D89^(-1/Fit!$B$9) -> 5906.9318 | I89: =EXP(Fit!$B$16+Fit!$B$15*-NORMSINV(D89)) -> 736.543 | J89: =Fit!$B$22*LN(1/D89)^(1/Fit!$B$21) -> 375.18617 | K89: =MAX(0,Fit!$B$28+Fit!$B$27*-NORMSINV(D89)) -> 259.23673 | L89: =INDEX(H89:K89,1,Inputs!$B$5) -> 5906.9318 | M89: =L89*E89 -> 0.060318849 | N89: =L89^$AB$7 -> 5906.9318 | O89: =N89*E89 -> 0.060318849 | P89: =N89*$AB$3/($AB$4*$AB$1) -> 39836086 | Q89: =IF(G89<=3,F89*SQRT(P89),0) -> 145942.76 | R89: =SQRT(P89/$AB$6) -> 2.9161903e+09 | S89: =2*$AB$6*R89 -> 0.027320635 | T89: =IF(G89<=3,F89*R89,0) -> 6.7431077e+10 | U89: =F89*P89 -> 9.2112993e+08 | V89: =H89^$AB$7*E89 -> 0.060318849 | W89: =I89^$AB$7*E89 -> 0.0075212356 | X89: =J89^$AB$7*E89 -> 0.0038312272 | Y89: =K89^$AB$7*E89 -> 0.0026472053
A90: 88 | B90: =C89 -> 0.00027122726 | C90: =Inputs!$B$21*(Inputs!$B$22/Inputs!$B$21)^(27/60) -> 0.00028183829 | D90: =(B90+C90)/2 -> 0.00027653278 | E90: =C90-B90 -> 1.0611035e-05 | F90: =Inputs!$B$16*E90 -> 24.027628 | G90: =IF(D90<=Inputs!$B$21,1,IF(D90<=Inputs!$B$22,2,IF(D90<=Inputs!$B$23,3,IF(D90<=Inputs!$B$24,4,5)))) -> 2 | H90: =Fit!$B$10*D90^(-1/Fit!$B$9) -> 5760.7417 | I90: =EXP(Fit!$B$16+Fit!$B$15*-NORMSINV(D90)) -> 730.3256 | J90: =Fit!$B$22*LN(1/D90)^(1/Fit!$B$21) -> 373.65447 | K90: =MAX(0,Fit!$B$28+Fit!$B$27*-NORMSINV(D90)) -> 258.59146 | L90: =INDEX(H90:K90,1,Inputs!$B$5) -> 5760.7417 | M90: =L90*E90 -> 0.061127433 | N90: =L90^$AB$7 -> 5760.7417 | O90: =N90*E90 -> 0.061127433 | P90: =N90*$AB$3/($AB$4*$AB$1) -> 38850186 | Q90: =IF(G90<=3,F90*SQRT(P90),0) -> 149764.01 | R90: =SQRT(P90/$AB$6) -> 2.879878e+09 | S90: =2*$AB$6*R90 -> 0.026980439 | T90: =IF(G90<=3,F90*R90,0) -> 6.9196637e+10 | U90: =F90*P90 -> 9.3347783e+08 | V90: =H90^$AB$7*E90 -> 0.061127433 | W90: =I90^$AB$7*E90 -> 0.0077495106 | X90: =J90^$AB$7*E90 -> 0.0039648608 | Y90: =K90^$AB$7*E90 -> 0.0027439231
A91: 89 | B91: =C90 -> 0.00028183829 | C91: =Inputs!$B$21*(Inputs!$B$22/Inputs!$B$21)^(28/60) -> 0.00029286446 | D91: =(B91+C91)/2 -> 0.00028735137 | E91: =C91-B91 -> 1.1026163e-05 | F91: =Inputs!$B$16*E91 -> 24.967644 | G91: =IF(D91<=Inputs!$B$21,1,IF(D91<=Inputs!$B$22,2,IF(D91<=Inputs!$B$23,3,IF(D91<=Inputs!$B$24,4,5)))) -> 2 | H91: =Fit!$B$10*D91^(-1/Fit!$B$9) -> 5618.1697 | I91: =EXP(Fit!$B$16+Fit!$B$15*-NORMSINV(D91)) -> 724.14452 | J91: =Fit!$B$22*LN(1/D91)^(1/Fit!$B$21) -> 372.12188 | K91: =MAX(0,Fit!$B$28+Fit!$B$27*-NORMSINV(D91)) -> 257.94449 | L91: =INDEX(H91:K91,1,Inputs!$B$5) -> 5618.1697 | M91: =L91*E91 -> 0.061946856 | N91: =L91^$AB$7 -> 5618.1697 | O91: =N91*E91 -> 0.061946856 | P91: =N91*$AB$3/($AB$4*$AB$1) -> 37888687 | Q91: =IF(G91<=3,F91*SQRT(P91),0) -> 153685.31 | R91: =SQRT(P91/$AB$6) -> 2.8440178e+09 | S91: =2*$AB$6*R91 -> 0.02664448 | T91: =IF(G91<=3,F91*R91,0) -> 7.1008424e+10 | U91: =F91*P91 -> 9.4599125e+08 | V91: =H91^$AB$7*E91 -> 0.061946856 | W91: =I91^$AB$7*E91 -> 0.0079845358 | X91: =J91^$AB$7*E91 -> 0.0041030766 | Y91: =K91^$AB$7*E91 -> 0.0028441381
A92: 90 | B92: =C91 -> 0.00029286446 | C92: =Inputs!$B$21*(Inputs!$B$22/Inputs!$B$21)^(29/60) -> 0.00030432199 | D92: =(B92+C92)/2 -> 0.00029859322 | E92: =C92-B92 -> 1.1457532e-05 | F92: =Inputs!$B$16*E92 -> 25.944436 | G92: =IF(D92<=Inputs!$B$21,1,IF(D92<=Inputs!$B$22,2,IF(D92<=Inputs!$B$23,3,IF(D92<=Inputs!$B$24,4,5)))) -> 2 | H92: =Fit!$B$10*D92^(-1/Fit!$B$9) -> 5479.1261 | I92: =EXP(Fit!$B$16+Fit!$B$15*-NORMSINV(D92)) -> 717.99961 | J92: =Fit!$B$22*LN(1/D92)^(1/Fit!$B$21) -> 370.58839 | K92: =MAX(0,Fit!$B$28+Fit!$B$27*-NORMSINV(D92)) -> 257.2958 | L92: =INDEX(H92:K92,1,Inputs!$B$5) -> 5479.1261 | M92: =L92*E92 -> 0.062777264 | N92: =L92^$AB$7 -> 5479.1261 | O92: =N92*E92 -> 0.062777264 | P92: =N92*$AB$3/($AB$4*$AB$1) -> 36950983 | Q92: =IF(G92<=3,F92*SQRT(P92),0) -> 157709.27 | R92: =SQRT(P92/$AB$6) -> 2.8086041e+09 | S92: =2*$AB$6*R92 -> 0.026312703 | T92: =IF(G92<=3,F92*R92,0) -> 7.286765e+10 | U92: =F92*P92 -> 9.5867242e+08 | V92: =H92^$AB$7*E92 -> 0.062777264 | W92: =I92^$AB$7*E92 -> 0.0082265037 | X92: =J92^$AB$7*E92 -> 0.0042460284 | Y92: =K92^$AB$7*E92 -> 0.002947975
A93: 91 | B93: =C92 -> 0.00030432199 | C93: =Inputs!$B$21*(Inputs!$B$22/Inputs!$B$21)^(30/60) -> 0.00031622777 | D93: =(B93+C93)/2 -> 0.00031027488 | E93: =C93-B93 -> 1.1905777e-05 | F93: =Inputs!$B$16*E93 -> 26.959442 | G93: =IF(D93<=Inputs!$B$21,1,IF(D93<=Inputs!$B$22,2,IF(D93<=Inputs!$B$23,3,IF(D93<=Inputs!$B$24,4,5)))) -> 2 | H93: =Fit!$B$10*D93^(-1/Fit!$B$9) -> 5343.5237 | I93: =EXP(Fit!$B$16+Fit!$B$15*-NORMSINV(D93)) -> 711.8907 | J93: =Fit!$B$22*LN(1/D93)^(1/Fit!$B$21) -> 369.054 | K93: =MAX(0,Fit!$B$28+Fit!$B$27*-NORMSINV(D93)) -> 256.64539 | L93: =INDEX(H93:K93,1,Inputs!$B$5) -> 5343.5237 | M93: =L93*E93 -> 0.063618804 | N93: =L93^$AB$7 -> 5343.5237 | O93: =N93*E93 -> 0.063618804 | P93: =N93*$AB$3/($AB$4*$AB$1) -> 36036487 | Q93: =IF(G93<=3,F93*SQRT(P93),0) -> 161838.6 | R93: =SQRT(P93/$AB$6) -> 2.7736315e+09 | S93: =2*$AB$6*R93 -> 0.025985058 | T93: =IF(G93<=3,F93*R93,0) -> 7.4775557e+10 | U93: =F93*P93 -> 9.7152358e+08 | V93: =H93^$AB$7*E93 -> 0.063618804 | W93: =I93^$AB$7*E93 -> 0.0084756122 | X93: =J93^$AB$7*E93 -> 0.0043938747 | Y93: =K93^$AB$7*E93 -> 0.0030555629
A94: 92 | B94: =C93 -> 0.00031622777 | C94: =Inputs!$B$21*(Inputs!$B$22/Inputs!$B$21)^(31/60) -> 0.00032859932 | D94: =(B94+C94)/2 -> 0.00032241355 | E94: =C94-B94 -> 1.2371559e-05 | F94: =Inputs!$B$16*E94 -> 28.014158 | G94: =IF(D94<=Inputs!$B$21,1,IF(D94<=Inputs!$B$22,2,IF(D94<=Inputs!$B$23,3,IF(D94<=Inputs!$B$24,4,5)))) -> 2 | H94: =Fit!$B$10*D94^(-1/Fit!$B$9) -> 5211.2774 | I94: =EXP(Fit!$B$16+Fit!$B$15*-NORMSINV(D94)) -> 705.81765 | J94: =Fit!$B$22*LN(1/D94)^(1/Fit!$B$21) -> 367.51869 | K94: =MAX(0,Fit!$B$28+Fit!$B$27*-NORMSINV(D94)) -> 255.99325 | L94: =INDEX(H94:K94,1,Inputs!$B$5) -> 5211.2774 | M94: =L94*E94 -> 0.064471624 | N94: =L94^$AB$7 -> 5211.2774 | O94: =N94*E94 -> 0.064471624 | P94: =N94*$AB$3/($AB$4*$AB$1) -> 35144623 | Q94: =IF(G94<=3,F94*SQRT(P94),0) -> 166076.05 | R94: =SQRT(P94/$AB$6) -> 2.7390943e+09 | S94: =2*$AB$6*R94 -> 0.025661492 | T94: =IF(G94<=3,F94*R94,0) -> 7.6733418e+10 | U94: =F94*P94 -> 9.8454702e+08 | V94: =H94^$AB$7*E94 -> 0.064471624 | W94: =I94^$AB$7*E94 -> 0.0087320645 | X94: =J94^$AB$7*E94 -> 0.0045467791 | Y94: =K94^$AB$7*E94 -> 0.0031670355
A95: 93 | B95: =C94 -> 0.00032859932 | C95: =Inputs!$B$21*(Inputs!$B$22/Inputs!$B$21)^(32/60) -> 0.00034145489 | D95: =(B95+C95)/2 -> 0.00033502711 | E95: =C95-B95 -> 1.2855563e-05 | F95: =Inputs!$B$16*E95 -> 29.110136 | G95: =IF(D95<=Inputs!$B$21,1,IF(D95<=Inputs!$B$22,2,IF(D95<=Inputs!$B$23,3,IF(D95<=Inputs!$B$24,4,5)))) -> 2 | H95: =Fit!$B$10*D95^(-1/Fit!$B$9) -> 5082.3039 | I95: =EXP(Fit!$B$16+Fit!$B$15*-NORMSINV(D95)) -> 699.7803 | J95: =Fit!$B$22*LN(1/D95)^(1/Fit!$B$21) -> 365.98248 | K95: =MAX(0,Fit!$B$28+Fit!$B$27*-NORMSINV(D95)) -> 255.33935 | L95: =INDEX(H95:K95,1,Inputs!$B$5) -> 5082.3039 | M95: =L95*E95 -> 0.065335877 | N95: =L95^$AB$7 -> 5082.3039 | O95: =N95*E95 -> 0.065335877 | P95: =N95*$AB$3/($AB$4*$AB$1) -> 34274832 | Q95: =IF(G95<=3,F95*SQRT(P95),0) -> 170424.45 | R95: =SQRT(P95/$AB$6) -> 2.7049871e+09 | S95: =2*$AB$6*R95 -> 0.025341956 | T95: =IF(G95<=3,F95*R95,0) -> 7.8742543e+10 | U95: =F95*P95 -> 9.9774503e+08 | V95: =H95^$AB$7*E95 -> 0.065335877 | W95: =I95^$AB$7*E95 -> 0.0089960695 | X95: =J95^$AB$7*E95 -> 0.0047049107 | Y95: =K95^$AB$7*E95 -> 0.0032825309
A96: 94 | B96: =C95 -> 0.00034145489 | C96: =Inputs!$B$21*(Inputs!$B$22/Inputs!$B$21)^(33/60) -> 0.00035481339 | D96: =(B96+C96)/2 -> 0.00034813414 | E96: =C96-B96 -> 1.3358502e-05 | F96: =Inputs!$B$16*E96 -> 30.248992 | G96: =IF(D96<=Inputs!$B$21,1,IF(D96<=Inputs!$B$22,2,IF(D96<=Inputs!$B$23,3,IF(D96<=Inputs!$B$24,4,5)))) -> 2 | H96: =Fit!$B$10*D96^(-1/Fit!$B$9) -> 4956.5225 | I96: =EXP(Fit!$B$16+Fit!$B$15*-NORMSINV(D96)) -> 693.7785 | J96: =Fit!$B$22*LN(1/D96)^(1/Fit!$B$21) -> 364.44534 | K96: =MAX(0,Fit!$B$28+Fit!$B$27*-NORMSINV(D96)) -> 254.68368 | L96: =INDEX(H96:K96,1,Inputs!$B$5) -> 4956.5225 | M96: =L96*E96 -> 0.066211715 | N96: =L96^$AB$7 -> 4956.5225 | O96: =N96*E96 -> 0.066211715 | P96: =N96*$AB$3/($AB$4*$AB$1) -> 33426568 | Q96: =IF(G96<=3,F96*SQRT(P96),0) -> 174886.7 | R96: =SQRT(P96/$AB$6) -> 2.6713047e+09 | S96: =2*$AB$6*R96 -> 0.025026399 | T96: =IF(G96<=3,F96*R96,0) -> 8.0804272e+10 | U96: =F96*P96 -> 1.01112e+09 | V96: =H96^$AB$7*E96 -> 0.066211715 | W96: =I96^$AB$7*E96 -> 0.0092678413 | X96: =J96^$AB$7*E96 -> 0.0048684438 | Y96: =K96^$AB$7*E96 -> 0.0034021924
A97: 95 | B97: =C96 -> 0.00035481339 | C97: =Inputs!$B$21*(Inputs!$B$22/Inputs!$B$21)^(34/60) -> 0.00036869451 | D97: =(B97+C97)/2 -> 0.00036175395 | E97: =C97-B97 -> 1.3881117e-05 | F97: =Inputs!$B$16*E97 -> 31.432402 | G97: =IF(D97<=Inputs!$B$21,1,IF(D97<=Inputs!$B$22,2,IF(D97<=Inputs!$B$23,3,IF(D97<=Inputs!$B$24,4,5)))) -> 2 | H97: =Fit!$B$10*D97^(-1/Fit!$B$9) -> 4833.854 | I97: =EXP(Fit!$B$16+Fit!$B$15*-NORMSINV(D97)) -> 687.81209 | J97: =Fit!$B$22*LN(1/D97)^(1/Fit!$B$21) -> 362.90729 | K97: =MAX(0,Fit!$B$28+Fit!$B$27*-NORMSINV(D97)) -> 254.02623 | L97: =INDEX(H97:K97,1,Inputs!$B$5) -> 4833.854 | M97: =L97*E97 -> 0.067099294 | N97: =L97^$AB$7 -> 4833.854 | O97: =N97*E97 -> 0.067099294 | P97: =N97*$AB$3/($AB$4*$AB$1) -> 32599297 | Q97: =IF(G97<=3,F97*SQRT(P97),0) -> 179465.79 | R97: =SQRT(P97/$AB$6) -> 2.6380416e+09 | S97: =2*$AB$6*R97 -> 0.02471477 | T97: =IF(G97<=3,F97*R97,0) -> 8.2919985e+10 | U97: =F97*P97 -> 1.0246742e+09 | V97: =H97^$AB$7*E97 -> 0.067099294 | W97: =I97^$AB$7*E97 -> 0.0095476002 | X97: =J97^$AB$7*E97 -> 0.0050375586 | Y97: =K97^$AB$7*E97 -> 0.0035261679
A98: 96 | B98: =C97 -> 0.00036869451 | C98: =Inputs!$B$21*(Inputs!$B$22/Inputs!$B$21)^(35/60) -> 0.00038311868 | D98: =(B98+C98)/2 -> 0.0003759066 | E98: =C98-B98 -> 1.4424179e-05 | F98: =Inputs!$B$16*E98 -> 32.66211 | G98: =IF(D98<=Inputs!$B$21,1,IF(D98<=Inputs!$B$22,2,IF(D98<=Inputs!$B$23,3,IF(D98<=Inputs!$B$24,4,5)))) -> 2 | H98: =Fit!$B$10*D98^(-1/Fit!$B$9) -> 4714.2214 | I98: =EXP(Fit!$B$16+Fit!$B$15*-NORMSINV(D98)) -> 681.88092 | J98: =Fit!$B$22*LN(1/D98)^(1/Fit!$B$21) -> 361.3683 | K98: =MAX(0,Fit!$B$28+Fit!$B$27*-NORMSINV(D98)) -> 253.36699 | L98: =INDEX(H98:K98,1,Inputs!$B$5) -> 4714.2214 | M98: =L98*E98 -> 0.067998771 | N98: =L98^$AB$7 -> 4714.2214 | O98: =N98*E98 -> 0.067998771 | P98: =N98*$AB$3/($AB$4*$AB$1) -> 31792500 | Q98: =IF(G98<=3,F98*SQRT(P98),0) -> 184164.78 | R98: =SQRT(P98/$AB$6) -> 2.6051928e+09 | S98: =2*$AB$6*R98 -> 0.024407023 | T98: =IF(G98<=3,F98*R98,0) -> 8.5091093e+10 | U98: =F98*P98 -> 1.0384101e+09 | V98: =H98^$AB$7*E98 -> 0.067998771 | W98: =I98^$AB$7*E98 -> 0.009835572 | X98: =J98^$AB$7*E98 -> 0.0052124409 | Y98: =K98^$AB$7*E98 -> 0.0036546107
A99: 97 | B99: =C98 -> 0.00038311868 | C99: =Inputs!$B$21*(Inputs!$B$22/Inputs!$B$21)^(36/60) -> 0.00039810717 | D99: =(B99+C99)/2 -> 0.00039061293 | E99: =C99-B99 -> 1.4988486e-05 | F99: =Inputs!$B$16*E99 -> 33.939927 | G99: =IF(D99<=Inputs!$B$21,1,IF(D99<=Inputs!$B$22,2,IF(D99<=Inputs!$B$23,3,IF(D99<=Inputs!$B$24,4,5)))) -> 2 | H99: =Fit!$B$10*D99^(-1/Fit!$B$9) -> 4597.5496 | I99: =EXP(Fit!$B$16+Fit!$B$15*-NORMSINV(D99)) -> 675.98483 | J99: =Fit!$B$22*LN(1/D99)^(1/Fit!$B$21) -> 359.82838 | K99: =MAX(0,Fit!$B$28+Fit!$B$27*-NORMSINV(D99)) -> 252.70594 | L99: =INDEX(H99:K99,1,Inputs!$B$5) -> 4597.5496 | M99: =L99*E99 -> 0.068910305 | N99: =L99^$AB$7 -> 4597.5496 | O99: =N99*E99 -> 0.068910305 | P99: =N99*$AB$3/($AB$4*$AB$1) -> 31005670 | Q99: =IF(G99<=3,F99*SQRT(P99),0) -> 188986.8 | R99: =SQRT(P99/$AB$6) -> 2.572753e+09 | S99: =2*$AB$6*R99 -> 0.024103107 | T99: =IF(G99<=3,F99*R99,0) -> 8.7319048e+10 | U99: =F99*P99 -> 1.0523302e+09 | V99: =H99^$AB$7*E99 -> 0.068910305 | W99: =I99^$AB$7*E99 -> 0.010131989 | X99: =J99^$AB$7*E99 -> 0.0053932825 | Y99: =K99^$AB$7*E99 -> 0.0037876794
A100: 98 | B100: =C99 -> 0.00039810717 | C100: =Inputs!$B$21*(Inputs!$B$22/Inputs!$B$21)^(37/60) -> 0.00041368204 | D100: =(B100+C100)/2 -> 0.00040589461 | E100: =C100-B100 -> 1.557487e-05 | F100: =Inputs!$B$16*E100 -> 35.267735 | G100: =IF(D100<=Inputs!$B$21,1,IF(D100<=Inputs!$B$22,2,IF(D100<=Inputs!$B$23,3,IF(D100<=Inputs!$B$24,4,5)))) -> 2 | H100: =Fit!$B$10*D100^(-1/Fit!$B$9) -> 4483.7652 | I100: =EXP(Fit!$B$16+Fit!$B$15*-NORMSINV(D100)) -> 670.12369 | J100: =Fit!$B$22*LN(1/D100)^(1/Fit!$B$21) -> 358.28752 | K100: =MAX(0,Fit!$B$28+Fit!$B$27*-NORMSINV(D100)) -> 252.04307 | L100: =INDEX(H100:K100,1,Inputs!$B$5) -> 4483.7652 | M100: =L100*E100 -> 0.069834059 | N100: =L100^$AB$7 -> 4483.7652 | O100: =N100*E100 -> 0.069834059 | P100: =N100*$AB$3/($AB$4*$AB$1) -> 30238314 | Q100: =IF(G100<=3,F100*SQRT(P100),0) -> 193935.07 | R100: =SQRT(P100/$AB$6) -> 2.5407171e+09 | S100: =2*$AB$6*R100 -> 0.023802976 | T100: =IF(G100<=3,F100*R100,0) -> 8.9605338e+10 | U100: =F100*P100 -> 1.0664368e+09 | V100: =H100^$AB$7*E100 -> 0.069834059 | W100: =I100^$AB$7*E100 -> 0.010437089 | X100: =J100^$AB$7*E100 -> 0.0055802815 | Y100: =K100^$AB$7*E100 -> 0.003925538
...

Sheet Notes
A1: Method, sources and limitations
A3: THE MODEL
A4: Berk, J.B. and van Binsbergen, J.H. (2015), "Measuring Skill in the Mutual Fund Industry", Journal of Financial Economics 118(1), Section 4, equations 14-16.
A5: Alpha declines linearly with the size of the book: alpha(A) = S - b*A. Dollar value added is V = A*(S - b*A).
A6: Maximising over A gives the optimal book A* = S/(2b) and the value at that book V* = S^2/(4b). Two identities follow and are used here: the alpha earned at the optimum is S/2, and A* = SQRT(V*/b).
A8: STEP BY STEP
A9: 1. Fit the chosen distribution to two upper-tail quantiles (Inputs B9:B12). Every distribution has a closed form for this, shown on the Fit sheet.
A10: 2. Decide whether the fitted shape describes value added V or skill S (Inputs B6). If S, then V is proportional to S^2, which for a Pareto halves the effective exponent. An effective exponent below 1 has no finite mean and the result is dominated by the single top person.
A11: 3. Build a grid of population bands in quantile space. Row 3 of the Grid sheet is rank 1 on its own, occupying u from 0 to 1/N and evaluated at the plotting position (Inputs B17). The rest is 60 log-spaced bands within each tier, so band edges land exactly on the tier boundaries.
A12: 4. For each band compute the quantile x(u_mid), the weight w = x^power, and the contribution w*du. The sum of contributions, T, normalises the shares.
A13: 5. Value per person at quantile u is V = w * Pool / (N * T). By construction the population total equals the pool exactly.
A14: 6. Restrict the book-running population to the top 1%. Solve b from the requirement that their optimal books sum to the capital input: b = (SUM over the top 1% of people*SQRT(V) / Capital)^2.
... A43: Blue text on yellow fill: input cells, safe to edit. Black: formulas. Grey fill: read-only.
