Workbook

Sheet README
A1: Graduate-recruitment ecosystem — graph dataset
A2: Source file | B2: graduate programs.md — 'Financial-Services Graduate/Campus Recruitment Target Lists — Five Regions'
A3: Purpose | B3: Node/edge tables ready to re-render as a network graph (geographic + organisational links, organisation size, yearly graduate intake).
A5: SHEETS
A6: Nodes | B6: One row per graph node. node_id is the primary key referenced by the Edges sheet.
A7: Edges | B7: One row per relationship. source_id and target_id both reference Nodes[node_id].
A8: Vocabulary | B8: Controlled value lists for node_type, edge_type, org_size_band, confirmation_status, data_confidence, geo_source.
A9: Summary | B9: Counts and coverage diagnostics, all formula-driven off Nodes and Edges.
A11: HOW TO RENDER
A12: Geography | B12: Hub → Country → Region form a PART_OF tree. Organisations attach to hubs via LOCATED_IN. A multinational has MULTIPLE LOCATED_IN edges, which is how cross-region presence is expressed (e.g. ORG_JPM sits in New York, Bengaluru, Hyderabad, Mumbai, São Paulo, Dublin and Luxembourg).
A13: Organisational links | B13: PARENT_OF (group → subsidiary), ABSORBED_BY (Credit Suisse → UBS), COMPETES_FOR_TALENT (undirected), IN_SECTOR (organisation → sector).
A14: Recruitment channel | B14: RECRUITS_VIA (organisation → Mechanism node) carries the entry mechanism; the Mechanism node holds cycle_timing and lead_time_months. RECRUITS_FROM / PARTNERS_WITH / RECRUITS_VIA_INTERMEDIARY point at TalentPool nodes.
A15: Node size | B15: Use annual_intake_low / annual_intake_high where populated; otherwise fall back to org_size_band (ordinal: Boutique < Mid < Large < Mega).
A16: Edge direction | B16: The 'directed' column is TRUE for all edge types except COMPETES_FOR_TALENT.
A18: DATA-QUALITY WARNINGS — READ BEFORE WEIGHTING NODES
A19: 1. Intake is almost entirely absent from the source. | B19: annual_intake_low / high / applications_per_cycle are populated for only 5 organisations (SBI, Evercore, Citadel Securities, ECB, Credit Suisse). Every other cell is deliberately blank — blank means UNKNOWN, not zero. Do not treat a blank as a small cohort.
A20: 2. org_size_band is INFERRED, not sourced. | B20: The source document contains no headcount or balance-sheet data. Bands are a coarse editorial judgement and every organisation row says so in size_basis. Replace them before using size quantitatively.
A21: 3. Confirmation status is a research artefact. | B21: [Note] means no formal scheme was confirmed in the research pass — NOT that no programme exists. The source flags China, LatAm and European insurers as especially under-verified.
A22: 4. Cohort/selectivity figures are secondary-sourced. | B22: US boutique and quant figures derive from career-advice sites and forums, not firm disclosures. Treat as indicative.
A23: 5. Grouped rows exist. | B23: A few nodes bundle several firms as the source did (ORG_BIG4, ORG_MBB, ORG_IN_LIFEINS, ORG_IN_AMC, ORG_LATAM_BIG4, ORG_LATAM_MBB). Split them if per-firm resolution matters.
A24: 6. Hub geography is partly inferred. | B24: geo_source = 'source' where the document names the city, 'inferred' where a well-known head-office location was used to place the node.
A25: 7. UK is out of scope. | B25: GEO_R_OTHER / GEO_C_UK / GEO_H_LON exist only so HSBC, Barclays and Standard Chartered resolve to a home base; the source covers five regions and excludes the UK.
A27: ENRICHMENT ORDER (from the source's own recommendations)
A28: Stage 1 | B28: Seed the graph with [C-Official] organisations only for a defensible core.
A29: Stage 2 | B29: Weight inflow by mechanism and scale, not firm size: mass channels (SBI/IBPS exams, Chinese Big Four quotas) are high-volume; boutiques and quant firms are low-volume/high-selectivity. Keep cohort size and selectivity as separate attributes.
A30: Stage 3 | B30: Treat the mechanism as an edge property with a lead-time parameter (already on the Mechanism nodes).
A31: Stage 4 | B31: Verify the [Note] tail on Chinese-language and Spanish/Portuguese careers pages before assigning any inflow weight.
A33: REGION 6 — UNITED KINGDOM (added by research, not in the source file)
A34: Why it exists | B34: The source document treats the UK list as its structural template and excludes it from the five regions it covers. The UK was originally a three-organisation placeholder (GEO_R_OTHER) so that HSBC, Barclays and Standard Chartered had a home base. It is now a full region, GEO_R_UK.
A35: Provenance | B35: Every UK organisation row carries geo_source = 'research'. Programme detail confirmed on a first-party careers site is marked [C-Official] and the exact URL is attached as a cell note on the programme_name, program_length_months and notes cells. Everything else is [Note] — a plausible UK graduate recruiter whose scheme was not verified in this pass.
A36: Confirmed to first-party sources | B36: Bank of England (Graduate Development Programme, 24 months to a permanent role, GBP 33,525, 2026 round opened for Leeds only), FCA (two-year rotational scheme with an external secondment, ~10 programme areas), Lloyds Banking Group (schemes across Data Science, Technology Engineering, Finance, Risk, Commercial Banking, Consumer Banking, Actuarial), NatWest Group (Engineering, Finance, Digital Transformation, NatWest Markets), Lloyd's of London (six two-year programmes, four six-month placements).
A37: Two UK mechanisms | B37: MECH_UK_SPRING is the Spring Week to summer internship to graduate scheme funnel the source contrasts the US against; its lead_time_months of 30 is the longest in the dataset. MECH_UK_SCHEME is direct autumn-to-September entry, used by retail banks, insurers, regulators and professional-services firms.
A38: London as a hub | B38: GEO_H_LON now carries 87 LOCATED_IN edges — every global bank, quant firm, custodian and data vendor already in the dataset that runs a London graduate intake, plus the UK-domiciled institutions. It is the densest node in the graph and will dominate any force-directed layout; consider collapsing it or weighting it down when rendering.
A39: Beware the name collision | B39: ORG_UK_LLOYDSBG (Lloyds Banking Group, a retail bank) and ORG_UK_LLOYDSMKT (Lloyd's of London, a specialist insurance market) are unrelated institutions.
A40: Intake is still unknown | B40: No UK organisation has a published cohort size in this pass, so annual_intake_low/high remain blank for all of them. The Bank of England salary figure is the only hard number the research produced.
A41: Grouped UK rows | B41: ORG_UK_BIG4, ORG_UK_MBB and ORG_UK_MIDTIER each bundle several firms, matching how the source groups them.
A43: INTAKE ESTIMATE (columns S and T on Nodes)
A44: Why it exists | B44: The source document supplies a cohort size for only five organisations, which makes the graph impossible to size by intake. Column S gives every organisation a central estimate so nodes can be scaled; column T records how each figure was arrived at.
A45: It is a formula, not typed numbers | B45: Every cell in S is a formula. Documented rows take the midpoint of annual_intake_low/high. Everything else is size-band base x sector factor x mechanism factor, with all three grids on the Assumptions sheet. Change a factor there and the whole column plus the Summary totals recalculate.
A46: Confidence | B46: 5 of 246 figures are sourced. The other 241 are order-of-magnitude judgements by Claude and carry no external authority. Use them to size nodes; do not quote them as intake statistics or aggregate them into a headline number you would defend.
A47: Zeros are meaningful here | B47: Unlike annual_intake_low/high, where blank means unknown, a zero in column S means 'no confirmed programme' or 'absorbed' - five organisations. Blank in column S means the row is not an organisation.
A48: Current shape | B48: Total modelled intake is about 52,500 a year: China 17,460, USA 10,579, Continental Europe 8,187, United Kingdom 7,268, India 5,837, Latin America 3,183. China dominates because the source describes its Big Four bank intake as quota-driven and in the thousands.
A49: First thing to retune | B49: The mechanism factors. MECH_CN_CYCLE at 3.0 and MECH_BR_TRAINEE at 0.25 are doing most of the work in the regional spread, and both are judgement calls rather than sourced ratios.
A51: CHANGE LOG — MECHANISM NODES REMOVED
A52: What was removed | B52: The 12 Mechanism nodes and the 324 edges that pointed at them (312 RECRUITS_VIA, 12 MECHANISM_OF), at the user's request. Node count 354 to 342; edge count 1,058 to 734.
A53: What survives | B53: Each organisation still names its channel in entry_mechanism_id (column I) as a plain text label, e.g. MECH_UK_SPRING. The intake estimate is unaffected: it looks the mechanism factor up on the Assumptions sheet by that text, not via the graph.
A54: What was lost | B54: cycle_timing (column L) and lead_time_months (column M) existed only on the mechanism rows and are now empty for every row. The source document's Stage 3 recommendation - model entry mechanism as an edge property with a lead-time parameter - can no longer be satisfied from this workbook. The reference values were: UK Spring Week 30 months, USA internship conversion 24, actuarial 24, India PGDBF 12, LatAm concurso 12, UK direct entry 12, India GCC 9, China cycle 9, Europe rotational 9, India exam 6, Brazil trainee 6, LatAm estagio 6.
A55: Also changed | B55: Summary rows 67 and 68 previously counted London RECRUITS_VIA edges, which included multinationals' London intakes (45 and 51). They now count UK-domiciled organisations by their primary mechanism (16 and 36). The multinational London-pipeline counts are no longer derivable.
A57: CHANGE LOG — TALENT POOL NODES REMOVED
A58: What was removed | B58: The 5 TalentPool nodes and the 55 edges attached to them (46 RECRUITS_FROM, 5 PART_OF, 3 PARTNERS_WITH, 1 RECRUITS_VIA_INTERMEDIARY), at the user's request. Node count 342 to 337; edge count 734 to 679.
A59: What was lost | B59: The supply side of the graph. The workbook no longer records where graduates are sourced from: the IIM/IIT elite-campus channel feeding 12 India GCCs, the Chinese-language 校园招聘 portal channel feeding 34 Chinese firms, Manipal Global / NIIT University as the hire-train academy partner behind the HDFC and Axis PGDBF diplomas, Cia de Talentos as BBVA Mexico's recruitment intermediary, and SENA as the training system behind Davivienda's Nativos scheme. Three edge types (RECRUITS_FROM, PARTNERS_WITH, RECRUITS_VIA_INTERMEDIARY) no longer occur anywhere.
A60: What survives | B60: Nothing depends on these nodes computationally - intake estimates, integrity checks and all remaining counts are unaffected. The graph is now purely organisations, geography and sectors.
A62: CHANGE LOG — CREDIT SUISSE REMOVED
A63: What was removed | B63: ORG_CS and its 3 edges (LOCATED_IN Zurich, IN_SECTOR bulge bracket, ABSORBED_BY ORG_UBS), at the user's request. Node count 337 to 336; edge count 679 to 676. ABSORBED_BY was the only edge of its type, so that edge type no longer occurs.
A64: Note | B64: This departs from the source document, which recommended keeping the node and redirecting its edges to UBS so knowledge-transfer continuity was preserved. The 2023 acquisition is now recorded nowhere in the graph. Documented-intake coverage drops from 5 organisations to 4, since Credit Suisse carried an explicit zero.
A66: JSON EXPORT (sheet: JSON)
A67: What it is | B67: A ready-to-use JSON document containing only the nodes and edges: {"nodes":[...],"edges":[...]}. One JSON line per spreadsheet cell down column A, so the whole thing is valid JSON when the column is copied out.
A68: How to use it | B68: Select column A on the JSON sheet, copy, paste into a text editor, save with a .json extension. Nothing else is on that sheet, so the paste needs no cleaning up.
A69: Important | B69: It is a point-in-time snapshot, not a formula. It does NOT track changes to the Nodes and Edges tables - ask for it to be regenerated after any edit. Keys that were empty on every row (cycle_timing, lead_time_months, edge weight) are omitted.
A71: CHANGE LOG — ASIA-PACIFIC, MIDDLE EAST AND CANADA ADDED
A72: What was added | B72: Three regions beyond the source document (Asia-Pacific ex-China, Middle East, Canada), 5 countries, 8 hubs and 53 organisations, plus 85 site edges putting existing multinationals into the new hubs. Node count 336 to 405; edge count 676 to 880.
A73: The five hubs requested | B73: Singapore, Tokyo, Sydney, Dubai and Toronto. Three extra hubs were added out of necessity: Abu Dhabi (the UAE's largest graduate employers - FAB, ADIA, Mubadala, the central bank - are Abu Dhabi-based, so placing them in Dubai would be factually wrong), Other Australia (Macquarie, NAB, ANZ and Suncorp are Melbourne/Brisbane-based) and Other Canada (the Bank of Canada is in Ottawa).
A74: Confirmed to first-party sources | B74: DBS (Singapore), Nomura (Tokyo), Macquarie (Sydney), First Abu Dhabi Bank (Abu Dhabi) and RBC (Toronto). URLs are attached as cell notes on the programme, length and notes columns of those five rows. The remaining 48 are [Note] - plausible recruiters not verified to a primary source.
A75: New mechanisms | B75: Five entries added to the Assumptions mechanism grid: MECH_APAC_SCHEME (1.0), MECH_JP_SHINSOTSU (2.0), MECH_AU_GRAD (1.0), MECH_ME_NATIONAL (0.6), MECH_CA_ROTATIONAL (1.0). The estimate formula's lookup range was widened from B30:B42 to B30:B50 to reach them.
A76: Two structural features with no counterpart elsewhere | B76: Japanese shinsotsu (simultaneous mass recruitment of new graduates with an April start, cycle beginning about a year before March graduation) is weighted 2.0 and makes Japan the second-largest modelled intake after China. Emiratisation means UAE graduate schemes are nationality-restricted, so they are weighted 0.6 - FAB's Ethraa Programme is co-sponsored by the Central Bank of the UAE, a regulator directly underwriting a commercial bank's graduate scheme.
A77: Also new as institution types | B77: Sovereign wealth and state investment funds (GIC, Temasek, ADIA, Mubadala, Future Fund, GPIF, CPP Investments, Ontario Teachers') and Islamic banks (Dubai Islamic Bank, Abu Dhabi Islamic Bank). Neither appears anywhere in the original five regions.
A78: Still absent | B78: Hong Kong, Seoul, Mumbai's offshore rivals in Kuala Lumpur and Jakarta, Riyadh, Johannesburg and Sao Paulo's regional peers. Hong Kong is the most significant omission: it carries APAC graduate intake comparable to Singapore's for most global banks.

Sheet Nodes
A1: node_id | B1: label | C1: node_type | D1: region | E1: country | F1: hub_city | G1: sector | H1: subsector_tier | I1: entry_mechanism_id | J1: program_name | K1: program_length_months | L1: cycle_timing | M1: lead_time_months | N1: org_size_band | O1: size_basis | P1: annual_intake_low | Q1: annual_intake_high | R1: applications_per_cycle | S1: intake_estimate_central | T1: intake_estimate_basis | U1: confirmation_status | V1: data_confidence | W1: geo_source | X1: notes
A2: GEO_R_USA | B2: USA | C2: Region | D2: USA | S2: =IF($C2<>"Organisation","",IF(OR($P2<>"",$Q2<>""),IF($P2<>"",IF($Q2<>"",($P2+$Q2)/2,$P2),$Q2),ROUND(_xlfn.XLOOKUP($N2,Assumptions!$B$5:$B$9,Assumptions!$C$5:$C$9,0)*_xlfn.XLOOKUP($G2,Assumptions!$B$13:$B$26,Assumptions!$C$13:$C$26,0)*_xlfn.XLOOKUP($I2,Assumptions!$B$30:$B$50,Assumptions!$C$30:$C$50,0),0))) | T2: =IF($C2<>"Organisation","",IF(OR($P2<>"",$Q2<>""),"Documented in source - midpoint of annual_intake_low/high",IF($I2="","No confirmed programme - modelled as zero",$N2&" base x "&TEXT(_xlfn.XLOOKUP($G2,Assumptions!$B$13:$B$26,Assumptions!$C$13:$C$26,0),"0.0#")&" sector x "&TEXT(_xlfn.XLOOKUP($I2,Assumptions!$B$30:$B$50,Assumptions!$C$30:$C$50,0),"0.0#")&" mechanism"))) | X2: Source region
A3: GEO_R_INDIA | B3: India | C3: Region | D3: India | S3: =IF($C3<>"Organisation","",IF(OR($P3<>"",$Q3<>""),IF($P3<>"",IF($Q3<>"",($P3+$Q3)/2,$P3),$Q3),ROUND(_xlfn.XLOOKUP($N3,Assumptions!$B$5:$B$9,Assumptions!$C$5:$C$9,0)*_xlfn.XLOOKUP($G3,Assumptions!$B$13:$B$26,Assumptions!$C$13:$C$26,0)*_xlfn.XLOOKUP($I3,Assumptions!$B$30:$B$50,Assumptions!$C$30:$C$50,0),0))) | T3: =IF($C3<>"Organisation","",IF(OR($P3<>"",$Q3<>""),"Documented in source - midpoint of annual_intake_low/high",IF($I3="","No confirmed programme - modelled as zero",$N3&" base x "&TEXT(_xlfn.XLOOKUP($G3,Assumptions!$B$13:$B$26,Assumptions!$C$13:$C$26,0),"0.0#")&" sector x "&TEXT(_xlfn.XLOOKUP($I3,Assumptions!$B$30:$B$50,Assumptions!$C$30:$C$50,0),"0.0#")&" mechanism"))) | X3: Source region
A4: GEO_R_CHINA | B4: China | C4: Region | D4: China | S4: =IF($C4<>"Organisation","",IF(OR($P4<>"",$Q4<>""),IF($P4<>"",IF($Q4<>"",($P4+$Q4)/2,$P4),$Q4),ROUND(_xlfn.XLOOKUP($N4,Assumptions!$B$5:$B$9,Assumptions!$C$5:$C$9,0)*_xlfn.XLOOKUP($G4,Assumptions!$B$13:$B$26,Assumptions!$C$13:$C$26,0)*_xlfn.XLOOKUP($I4,Assumptions!$B$30:$B$50,Assumptions!$C$30:$C$50,0),0))) | T4: =IF($C4<>"Organisation","",IF(OR($P4<>"",$Q4<>""),"Documented in source - midpoint of annual_intake_low/high",IF($I4="","No confirmed programme - modelled as zero",$N4&" base x "&TEXT(_xlfn.XLOOKUP($G4,Assumptions!$B$13:$B$26,Assumptions!$C$13:$C$26,0),"0.0#")&" sector x "&TEXT(_xlfn.XLOOKUP($I4,Assumptions!$B$30:$B$50,Assumptions!$C$30:$C$50,0),"0.0#")&" mechanism"))) | X4: Source region
A5: GEO_R_LATAM | B5: Latin America | C5: Region | D5: Latin America | S5: =IF($C5<>"Organisation","",IF(OR($P5<>"",$Q5<>""),IF($P5<>"",IF($Q5<>"",($P5+$Q5)/2,$P5),$Q5),ROUND(_xlfn.XLOOKUP($N5,Assumptions!$B$5:$B$9,Assumptions!$C$5:$C$9,0)*_xlfn.XLOOKUP($G5,Assumptions!$B$13:$B$26,Assumptions!$C$13:$C$26,0)*_xlfn.XLOOKUP($I5,Assumptions!$B$30:$B$50,Assumptions!$C$30:$C$50,0),0))) | T5: =IF($C5<>"Organisation","",IF(OR($P5<>"",$Q5<>""),"Documented in source - midpoint of annual_intake_low/high",IF($I5="","No confirmed programme - modelled as zero",$N5&" base x "&TEXT(_xlfn.XLOOKUP($G5,Assumptions!$B$13:$B$26,Assumptions!$C$13:$C$26,0),"0.0#")&" sector x "&TEXT(_xlfn.XLOOKUP($I5,Assumptions!$B$30:$B$50,Assumptions!$C$30:$C$50,0),"0.0#")&" mechanism"))) | X5: Source region
A6: GEO_R_EUROPE | B6: Continental Europe | C6: Region | D6: Continental Europe | S6: =IF($C6<>"Organisation","",IF(OR($P6<>"",$Q6<>""),IF($P6<>"",IF($Q6<>"",($P6+$Q6)/2,$P6),$Q6),ROUND(_xlfn.XLOOKUP($N6,Assumptions!$B$5:$B$9,Assumptions!$C$5:$C$9,0)*_xlfn.XLOOKUP($G6,Assumptions!$B$13:$B$26,Assumptions!$C$13:$C$26,0)*_xlfn.XLOOKUP($I6,Assumptions!$B$30:$B$50,Assumptions!$C$30:$C$50,0),0))) | T6: =IF($C6<>"Organisation","",IF(OR($P6<>"",$Q6<>""),"Documented in source - midpoint of annual_intake_low/high",IF($I6="","No confirmed programme - modelled as zero",$N6&" base x "&TEXT(_xlfn.XLOOKUP($G6,Assumptions!$B$13:$B$26,Assumptions!$C$13:$C$26,0),"0.0#")&" sector x "&TEXT(_xlfn.XLOOKUP($I6,Assumptions!$B$30:$B$50,Assumptions!$C$30:$C$50,0),"0.0#")&" mechanism"))) | X6: Source region
A7: GEO_R_UK | B7: United Kingdom | C7: Region | D7: United Kingdom | S7: =IF($C7<>"Organisation","",IF(OR($P7<>"",$Q7<>""),IF($P7<>"",IF($Q7<>"",($P7+$Q7)/2,$P7),$Q7),ROUND(_xlfn.XLOOKUP($N7,Assumptions!$B$5:$B$9,Assumptions!$C$5:$C$9,0)*_xlfn.XLOOKUP($G7,Assumptions!$B$13:$B$26,Assumptions!$C$13:$C$26,0)*_xlfn.XLOOKUP($I7,Assumptions!$B$30:$B$50,Assumptions!$C$30:$C$50,0),0))) | T7: =IF($C7<>"Organisation","",IF(OR($P7<>"",$Q7<>""),"Documented in source - midpoint of annual_intake_low/high",IF($I7="","No confirmed programme - modelled as zero",$N7&" base x "&TEXT(_xlfn.XLOOKUP($G7,Assumptions!$B$13:$B$26,Assumptions!$C$13:$C$26,0),"0.0#")&" sector x "&TEXT(_xlfn.XLOOKUP($I7,Assumptions!$B$30:$B$50,Assumptions!$C$30:$C$50,0),"0.0#")&" mechanism"))) | X7: Source region 6 - added by research, not present in the source document (the source covers five regions and treats the UK list as its structural template only)
A8: GEO_C_US | B8: United States | C8: Country | D8: USA | E8: United States | S8: =IF($C8<>"Organisation","",IF(OR($P8<>"",$Q8<>""),IF($P8<>"",IF($Q8<>"",($P8+$Q8)/2,$P8),$Q8),ROUND(_xlfn.XLOOKUP($N8,Assumptions!$B$5:$B$9,Assumptions!$C$5:$C$9,0)*_xlfn.XLOOKUP($G8,Assumptions!$B$13:$B$26,Assumptions!$C$13:$C$26,0)*_xlfn.XLOOKUP($I8,Assumptions!$B$30:$B$50,Assumptions!$C$30:$C$50,0),0))) | T8: =IF($C8<>"Organisation","",IF(OR($P8<>"",$Q8<>""),"Documented in source - midpoint of annual_intake_low/high",IF($I8="","No confirmed programme - modelled as zero",$N8&" base x "&TEXT(_xlfn.XLOOKUP($G8,Assumptions!$B$13:$B$26,Assumptions!$C$13:$C$26,0),"0.0#")&" sector x "&TEXT(_xlfn.XLOOKUP($I8,Assumptions!$B$30:$B$50,Assumptions!$C$30:$C$50,0),"0.0#")&" mechanism")))
A9: GEO_C_IN | B9: India | C9: Country | D9: India | E9: India | S9: =IF($C9<>"Organisation","",IF(OR($P9<>"",$Q9<>""),IF($P9<>"",IF($Q9<>"",($P9+$Q9)/2,$P9),$Q9),ROUND(_xlfn.XLOOKUP($N9,Assumptions!$B$5:$B$9,Assumptions!$C$5:$C$9,0)*_xlfn.XLOOKUP($G9,Assumptions!$B$13:$B$26,Assumptions!$C$13:$C$26,0)*_xlfn.XLOOKUP($I9,Assumptions!$B$30:$B$50,Assumptions!$C$30:$C$50,0),0))) | T9: =IF($C9<>"Organisation","",IF(OR($P9<>"",$Q9<>""),"Documented in source - midpoint of annual_intake_low/high",IF($I9="","No confirmed programme - modelled as zero",$N9&" base x "&TEXT(_xlfn.XLOOKUP($G9,Assumptions!$B$13:$B$26,Assumptions!$C$13:$C$26,0),"0.0#")&" sector x "&TEXT(_xlfn.XLOOKUP($I9,Assumptions!$B$30:$B$50,Assumptions!$C$30:$C$50,0),"0.0#")&" mechanism")))
A10: GEO_C_CN | B10: China | C10: Country | D10: China | E10: China | S10: =IF($C10<>"Organisation","",IF(OR($P10<>"",$Q10<>""),IF($P10<>"",IF($Q10<>"",($P10+$Q10)/2,$P10),$Q10),ROUND(_xlfn.XLOOKUP($N10,Assumptions!$B$5:$B$9,Assumptions!$C$5:$C$9,0)*_xlfn.XLOOKUP($G10,Assumptions!$B$13:$B$26,Assumptions!$C$13:$C$26,0)*_xlfn.XLOOKUP($I10,Assumptions!$B$30:$B$50,Assumptions!$C$30:$C$50,0),0))) | T10: =IF($C10<>"Organisation","",IF(OR($P10<>"",$Q10<>""),"Documented in source - midpoint of annual_intake_low/high",IF($I10="","No confirmed programme - modelled as zero",$N10&" base x "&TEXT(_xlfn.XLOOKUP($G10,Assumptions!$B$13:$B$26,Assumptions!$C$13:$C$26,0),"0.0#")&" sector x "&TEXT(_xlfn.XLOOKUP($I10,Assumptions!$B$30:$B$50,Assumptions!$C$30:$C$50,0),"0.0#")&" mechanism")))
A11: GEO_C_BR | B11: Brazil | C11: Country | D11: Latin America | E11: Brazil | S11: =IF($C11<>"Organisation","",IF(OR($P11<>"",$Q11<>""),IF($P11<>"",IF($Q11<>"",($P11+$Q11)/2,$P11),$Q11),ROUND(_xlfn.XLOOKUP($N11,Assumptions!$B$5:$B$9,Assumptions!$C$5:$C$9,0)*_xlfn.XLOOKUP($G11,Assumptions!$B$13:$B$26,Assumptions!$C$13:$C$26,0)*_xlfn.XLOOKUP($I11,Assumptions!$B$30:$B$50,Assumptions!$C$30:$C$50,0),0))) | T11: =IF($C11<>"Organisation","",IF(OR($P11<>"",$Q11<>""),"Documented in source - midpoint of annual_intake_low/high",IF($I11="","No confirmed programme - modelled as zero",$N11&" base x "&TEXT(_xlfn.XLOOKUP($G11,Assumptions!$B$13:$B$26,Assumptions!$C$13:$C$26,0),"0.0#")&" sector x "&TEXT(_xlfn.XLOOKUP($I11,Assumptions!$B$30:$B$50,Assumptions!$C$30:$C$50,0),"0.0#")&" mechanism")))
A12: GEO_C_MX | B12: Mexico | C12: Country | D12: Latin America | E12: Mexico | S12: =IF($C12<>"Organisation","",IF(OR($P12<>"",$Q12<>""),IF($P12<>"",IF($Q12<>"",($P12+$Q12)/2,$P12),$Q12),ROUND(_xlfn.XLOOKUP($N12,Assumptions!$B$5:$B$9,Assumptions!$C$5:$C$9,0)*_xlfn.XLOOKUP($G12,Assumptions!$B$13:$B$26,Assumptions!$C$13:$C$26,0)*_xlfn.XLOOKUP($I12,Assumptions!$B$30:$B$50,Assumptions!$C$30:$C$50,0),0))) | T12: =IF($C12<>"Organisation","",IF(OR($P12<>"",$Q12<>""),"Documented in source - midpoint of annual_intake_low/high",IF($I12="","No confirmed programme - modelled as zero",$N12&" base x "&TEXT(_xlfn.XLOOKUP($G12,Assumptions!$B$13:$B$26,Assumptions!$C$13:$C$26,0),"0.0#")&" sector x "&TEXT(_xlfn.XLOOKUP($I12,Assumptions!$B$30:$B$50,Assumptions!$C$30:$C$50,0),"0.0#")&" mechanism")))
A13: GEO_C_CO | B13: Colombia | C13: Country | D13: Latin America | E13: Colombia | S13: =IF($C13<>"Organisation","",IF(OR($P13<>"",$Q13<>""),IF($P13<>"",IF($Q13<>"",($P13+$Q13)/2,$P13),$Q13),ROUND(_xlfn.XLOOKUP($N13,Assumptions!$B$5:$B$9,Assumptions!$C$5:$C$9,0)*_xlfn.XLOOKUP($G13,Assumptions!$B$13:$B$26,Assumptions!$C$13:$C$26,0)*_xlfn.XLOOKUP($I13,Assumptions!$B$30:$B$50,Assumptions!$C$30:$C$50,0),0))) | T13: =IF($C13<>"Organisation","",IF(OR($P13<>"",$Q13<>""),"Documented in source - midpoint of annual_intake_low/high",IF($I13="","No confirmed programme - modelled as zero",$N13&" base x "&TEXT(_xlfn.XLOOKUP($G13,Assumptions!$B$13:$B$26,Assumptions!$C$13:$C$26,0),"0.0#")&" sector x "&TEXT(_xlfn.XLOOKUP($I13,Assumptions!$B$30:$B$50,Assumptions!$C$30:$C$50,0),"0.0#")&" mechanism")))
A14: GEO_C_CL | B14: Chile | C14: Country | D14: Latin America | E14: Chile | S14: =IF($C14<>"Organisation","",IF(OR($P14<>"",$Q14<>""),IF($P14<>"",IF($Q14<>"",($P14+$Q14)/2,$P14),$Q14),ROUND(_xlfn.XLOOKUP($N14,Assumptions!$B$5:$B$9,Assumptions!$C$5:$C$9,0)*_xlfn.XLOOKUP($G14,Assumptions!$B$13:$B$26,Assumptions!$C$13:$C$26,0)*_xlfn.XLOOKUP($I14,Assumptions!$B$30:$B$50,Assumptions!$C$30:$C$50,0),0))) | T14: =IF($C14<>"Organisation","",IF(OR($P14<>"",$Q14<>""),"Documented in source - midpoint of annual_intake_low/high",IF($I14="","No confirmed programme - modelled as zero",$N14&" base x "&TEXT(_xlfn.XLOOKUP($G14,Assumptions!$B$13:$B$26,Assumptions!$C$13:$C$26,0),"0.0#")&" sector x "&TEXT(_xlfn.XLOOKUP($I14,Assumptions!$B$30:$B$50,Assumptions!$C$30:$C$50,0),"0.0#")&" mechanism")))
A15: GEO_C_PE | B15: Peru | C15: Country | D15: Latin America | E15: Peru | S15: =IF($C15<>"Organisation","",IF(OR($P15<>"",$Q15<>""),IF($P15<>"",IF($Q15<>"",($P15+$Q15)/2,$P15),$Q15),ROUND(_xlfn.XLOOKUP($N15,Assumptions!$B$5:$B$9,Assumptions!$C$5:$C$9,0)*_xlfn.XLOOKUP($G15,Assumptions!$B$13:$B$26,Assumptions!$C$13:$C$26,0)*_xlfn.XLOOKUP($I15,Assumptions!$B$30:$B$50,Assumptions!$C$30:$C$50,0),0))) | T15: =IF($C15<>"Organisation","",IF(OR($P15<>"",$Q15<>""),"Documented in source - midpoint of annual_intake_low/high",IF($I15="","No confirmed programme - modelled as zero",$N15&" base x "&TEXT(_xlfn.XLOOKUP($G15,Assumptions!$B$13:$B$26,Assumptions!$C$13:$C$26,0),"0.0#")&" sector x "&TEXT(_xlfn.XLOOKUP($I15,Assumptions!$B$30:$B$50,Assumptions!$C$30:$C$50,0),"0.0#")&" mechanism")))
A16: GEO_C_AR | B16: Argentina | C16: Country | D16: Latin America | E16: Argentina | S16: =IF($C16<>"Organisation","",IF(OR($P16<>"",$Q16<>""),IF($P16<>"",IF($Q16<>"",($P16+$Q16)/2,$P16),$Q16),ROUND(_xlfn.XLOOKUP($N16,Assumptions!$B$5:$B$9,Assumptions!$C$5:$C$9,0)*_xlfn.XLOOKUP($G16,Assumptions!$B$13:$B$26,Assumptions!$C$13:$C$26,0)*_xlfn.XLOOKUP($I16,Assumptions!$B$30:$B$50,Assumptions!$C$30:$C$50,0),0))) | T16: =IF($C16<>"Organisation","",IF(OR($P16<>"",$Q16<>""),"Documented in source - midpoint of annual_intake_low/high",IF($I16="","No confirmed programme - modelled as zero",$N16&" base x "&TEXT(_xlfn.XLOOKUP($G16,Assumptions!$B$13:$B$26,Assumptions!$C$13:$C$26,0),"0.0#")&" sector x "&TEXT(_xlfn.XLOOKUP($I16,Assumptions!$B$30:$B$50,Assumptions!$C$30:$C$50,0),"0.0#")&" mechanism")))
A17: GEO_C_DE | B17: Germany | C17: Country | D17: Continental Europe | E17: Germany | S17: =IF($C17<>"Organisation","",IF(OR($P17<>"",$Q17<>""),IF($P17<>"",IF($Q17<>"",($P17+$Q17)/2,$P17),$Q17),ROUND(_xlfn.XLOOKUP($N17,Assumptions!$B$5:$B$9,Assumptions!$C$5:$C$9,0)*_xlfn.XLOOKUP($G17,Assumptions!$B$13:$B$26,Assumptions!$C$13:$C$26,0)*_xlfn.XLOOKUP($I17,Assumptions!$B$30:$B$50,Assumptions!$C$30:$C$50,0),0))) | T17: =IF($C17<>"Organisation","",IF(OR($P17<>"",$Q17<>""),"Documented in source - midpoint of annual_intake_low/high",IF($I17="","No confirmed programme - modelled as zero",$N17&" base x "&TEXT(_xlfn.XLOOKUP($G17,Assumptions!$B$13:$B$26,Assumptions!$C$13:$C$26,0),"0.0#")&" sector x "&TEXT(_xlfn.XLOOKUP($I17,Assumptions!$B$30:$B$50,Assumptions!$C$30:$C$50,0),"0.0#")&" mechanism")))
A18: GEO_C_FR | B18: France | C18: Country | D18: Continental Europe | E18: France | S18: =IF($C18<>"Organisation","",IF(OR($P18<>"",$Q18<>""),IF($P18<>"",IF($Q18<>"",($P18+$Q18)/2,$P18),$Q18),ROUND(_xlfn.XLOOKUP($N18,Assumptions!$B$5:$B$9,Assumptions!$C$5:$C$9,0)*_xlfn.XLOOKUP($G18,Assumptions!$B$13:$B$26,Assumptions!$C$13:$C$26,0)*_xlfn.XLOOKUP($I18,Assumptions!$B$30:$B$50,Assumptions!$C$30:$C$50,0),0))) | T18: =IF($C18<>"Organisation","",IF(OR($P18<>"",$Q18<>""),"Documented in source - midpoint of annual_intake_low/high",IF($I18="","No confirmed programme - modelled as zero",$N18&" base x "&TEXT(_xlfn.XLOOKUP($G18,Assumptions!$B$13:$B$26,Assumptions!$C$13:$C$26,0),"0.0#")&" sector x "&TEXT(_xlfn.XLOOKUP($I18,Assumptions!$B$30:$B$50,Assumptions!$C$30:$C$50,0),"0.0#")&" mechanism")))
A19: GEO_C_CH | B19: Switzerland | C19: Country | D19: Continental Europe | E19: Switzerland | S19: =IF($C19<>"Organisation","",IF(OR($P19<>"",$Q19<>""),IF($P19<>"",IF($Q19<>"",($P19+$Q19)/2,$P19),$Q19),ROUND(_xlfn.XLOOKUP($N19,Assumptions!$B$5:$B$9,Assumptions!$C$5:$C$9,0)*_xlfn.XLOOKUP($G19,Assumptions!$B$13:$B$26,Assumptions!$C$13:$C$26,0)*_xlfn.XLOOKUP($I19,Assumptions!$B$30:$B$50,Assumptions!$C$30:$C$50,0),0))) | T19: =IF($C19<>"Organisation","",IF(OR($P19<>"",$Q19<>""),"Documented in source - midpoint of annual_intake_low/high",IF($I19="","No confirmed programme - modelled as zero",$N19&" base x "&TEXT(_xlfn.XLOOKUP($G19,Assumptions!$B$13:$B$26,Assumptions!$C$13:$C$26,0),"0.0#")&" sector x "&TEXT(_xlfn.XLOOKUP($I19,Assumptions!$B$30:$B$50,Assumptions!$C$30:$C$50,0),"0.0#")&" mechanism")))
... A28: GEO_C_LU | B28: Luxembourg | C28: Country | D28: Continental Europe | E28: Luxembourg | S28: =IF($C28<>"Organisation","",IF(OR($P28<>"",$Q28<>""),IF($P28<>"",IF($Q28<>"",($P28+$Q28)/2,$P28),$Q28),ROUND(_xlfn.XLOOKUP($N28,Assumptions!$B$5:$B$9,Assumptions!$C$5:$C$9,0)*_xlfn.XLOOKUP($G28,Assumptions!$B$13:$B$26,Assumptions!$C$13:$C$26,0)*_xlfn.XLOOKUP($I28,Assumptions!$B$30:$B$50,Assumptions!$C$30:$C$50,0),0))) | T28: =IF($C28<>"Organisation","",IF(OR($P28<>"",$Q28<>""),"Documented in source - midpoint of annual_intake_low/high",IF($I28="","No confirmed programme - modelled as zero",$N28&" base x "&TEXT(_xlfn.XLOOKUP($G28,Assumptions!$B$13:$B$26,Assumptions!$C$13:$C$26,0),"0.0#")&" sector x "&TEXT(_xlfn.XLOOKUP($I28,Assumptions!$B$30:$B$50,Assumptions!$C$30:$C$50,0),"0.0#")&" mechanism")))
A29: GEO_C_UK | B29: United Kingdom | C29: Country | D29: United Kingdom | E29: United Kingdom | S29: =IF($C29<>"Organisation","",IF(OR($P29<>"",$Q29<>""),IF($P29<>"",IF($Q29<>"",($P29+$Q29)/2,$P29),$Q29),ROUND(_xlfn.XLOOKUP($N29,Assumptions!$B$5:$B$9,Assumptions!$C$5:$C$9,0)*_xlfn.XLOOKUP($G29,Assumptions!$B$13:$B$26,Assumptions!$C$13:$C$26,0)*_xlfn.XLOOKUP($I29,Assumptions!$B$30:$B$50,Assumptions!$C$30:$C$50,0),0))) | T29: =IF($C29<>"Organisation","",IF(OR($P29<>"",$Q29<>""),"Documented in source - midpoint of annual_intake_low/high",IF($I29="","No confirmed programme - modelled as zero",$N29&" base x "&TEXT(_xlfn.XLOOKUP($G29,Assumptions!$B$13:$B$26,Assumptions!$C$13:$C$26,0),"0.0#")&" sector x "&TEXT(_xlfn.XLOOKUP($I29,Assumptions!$B$30:$B$50,Assumptions!$C$30:$C$50,0),"0.0#")&" mechanism"))) | X29: Promoted from out-of-scope placeholder to a full region
A30: GEO_H_NYC | B30: New York | C30: Hub | D30: USA | E30: United States | F30: New York | S30: =IF($C30<>"Organisation","",IF(OR($P30<>"",$Q30<>""),IF($P30<>"",IF($Q30<>"",($P30+$Q30)/2,$P30),$Q30),ROUND(_xlfn.XLOOKUP($N30,Assumptions!$B$5:$B$9,Assumptions!$C$5:$C$9,0)*_xlfn.XLOOKUP($G30,Assumptions!$B$13:$B$26,Assumptions!$C$13:$C$26,0)*_xlfn.XLOOKUP($I30,Assumptions!$B$30:$B$50,Assumptions!$C$30:$C$50,0),0))) | T30: =IF($C30<>"Organisation","",IF(OR($P30<>"",$Q30<>""),"Documented in source - midpoint of annual_intake_low/high",IF($I30="","No confirmed programme - modelled as zero",$N30&" base x "&TEXT(_xlfn.XLOOKUP($G30,Assumptions!$B$13:$B$26,Assumptions!$C$13:$C$26,0),"0.0#")&" sector x "&TEXT(_xlfn.XLOOKUP($I30,Assumptions!$B$30:$B$50,Assumptions!$C$30:$C$50,0),"0.0#")&" mechanism"))) | W30: inferred
A31: GEO_H_CHI | B31: Chicago | C31: Hub | D31: USA | E31: United States | F31: Chicago | S31: =IF($C31<>"Organisation","",IF(OR($P31<>"",$Q31<>""),IF($P31<>"",IF($Q31<>"",($P31+$Q31)/2,$P31),$Q31),ROUND(_xlfn.XLOOKUP($N31,Assumptions!$B$5:$B$9,Assumptions!$C$5:$C$9,0)*_xlfn.XLOOKUP($G31,Assumptions!$B$13:$B$26,Assumptions!$C$13:$C$26,0)*_xlfn.XLOOKUP($I31,Assumptions!$B$30:$B$50,Assumptions!$C$30:$C$50,0),0))) | T31: =IF($C31<>"Organisation","",IF(OR($P31<>"",$Q31<>""),"Documented in source - midpoint of annual_intake_low/high",IF($I31="","No confirmed programme - modelled as zero",$N31&" base x "&TEXT(_xlfn.XLOOKUP($G31,Assumptions!$B$13:$B$26,Assumptions!$C$13:$C$26,0),"0.0#")&" sector x "&TEXT(_xlfn.XLOOKUP($I31,Assumptions!$B$30:$B$50,Assumptions!$C$30:$C$50,0),"0.0#")&" mechanism"))) | W31: inferred
A32: GEO_H_BOS | B32: Boston | C32: Hub | D32: USA | E32: United States | F32: Boston | S32: =IF($C32<>"Organisation","",IF(OR($P32<>"",$Q32<>""),IF($P32<>"",IF($Q32<>"",($P32+$Q32)/2,$P32),$Q32),ROUND(_xlfn.XLOOKUP($N32,Assumptions!$B$5:$B$9,Assumptions!$C$5:$C$9,0)*_xlfn.XLOOKUP($G32,Assumptions!$B$13:$B$26,Assumptions!$C$13:$C$26,0)*_xlfn.XLOOKUP($I32,Assumptions!$B$30:$B$50,Assumptions!$C$30:$C$50,0),0))) | T32: =IF($C32<>"Organisation","",IF(OR($P32<>"",$Q32<>""),"Documented in source - midpoint of annual_intake_low/high",IF($I32="","No confirmed programme - modelled as zero",$N32&" base x "&TEXT(_xlfn.XLOOKUP($G32,Assumptions!$B$13:$B$26,Assumptions!$C$13:$C$26,0),"0.0#")&" sector x "&TEXT(_xlfn.XLOOKUP($I32,Assumptions!$B$30:$B$50,Assumptions!$C$30:$C$50,0),"0.0#")&" mechanism"))) | W32: inferred
A33: GEO_H_CLT | B33: Charlotte | C33: Hub | D33: USA | E33: United States | F33: Charlotte | S33: =IF($C33<>"Organisation","",IF(OR($P33<>"",$Q33<>""),IF($P33<>"",IF($Q33<>"",($P33+$Q33)/2,$P33),$Q33),ROUND(_xlfn.XLOOKUP($N33,Assumptions!$B$5:$B$9,Assumptions!$C$5:$C$9,0)*_xlfn.XLOOKUP($G33,Assumptions!$B$13:$B$26,Assumptions!$C$13:$C$26,0)*_xlfn.XLOOKUP($I33,Assumptions!$B$30:$B$50,Assumptions!$C$30:$C$50,0),0))) | T33: =IF($C33<>"Organisation","",IF(OR($P33<>"",$Q33<>""),"Documented in source - midpoint of annual_intake_low/high",IF($I33="","No confirmed programme - modelled as zero",$N33&" base x "&TEXT(_xlfn.XLOOKUP($G33,Assumptions!$B$13:$B$26,Assumptions!$C$13:$C$26,0),"0.0#")&" sector x "&TEXT(_xlfn.XLOOKUP($I33,Assumptions!$B$30:$B$50,Assumptions!$C$30:$C$50,0),"0.0#")&" mechanism"))) | W33: inferred
A34: GEO_H_SFO | B34: San Francisco Bay Area | C34: Hub | D34: USA | E34: United States | F34: San Francisco Bay Area | S34: =IF($C34<>"Organisation","",IF(OR($P34<>"",$Q34<>""),IF($P34<>"",IF($Q34<>"",($P34+$Q34)/2,$P34),$Q34),ROUND(_xlfn.XLOOKUP($N34,Assumptions!$B$5:$B$9,Assumptions!$C$5:$C$9,0)*_xlfn.XLOOKUP($G34,Assumptions!$B$13:$B$26,Assumptions!$C$13:$C$26,0)*_xlfn.XLOOKUP($I34,Assumptions!$B$30:$B$50,Assumptions!$C$30:$C$50,0),0))) | T34: =IF($C34<>"Organisation","",IF(OR($P34<>"",$Q34<>""),"Documented in source - midpoint of annual_intake_low/high",IF($I34="","No confirmed programme - modelled as zero",$N34&" base x "&TEXT(_xlfn.XLOOKUP($G34,Assumptions!$B$13:$B$26,Assumptions!$C$13:$C$26,0),"0.0#")&" sector x "&TEXT(_xlfn.XLOOKUP($I34,Assumptions!$B$30:$B$50,Assumptions!$C$30:$C$50,0),"0.0#")&" mechanism"))) | W34: inferred
A35: GEO_H_MIA | B35: Miami | C35: Hub | D35: USA | E35: United States | F35: Miami | S35: =IF($C35<>"Organisation","",IF(OR($P35<>"",$Q35<>""),IF($P35<>"",IF($Q35<>"",($P35+$Q35)/2,$P35),$Q35),ROUND(_xlfn.XLOOKUP($N35,Assumptions!$B$5:$B$9,Assumptions!$C$5:$C$9,0)*_xlfn.XLOOKUP($G35,Assumptions!$B$13:$B$26,Assumptions!$C$13:$C$26,0)*_xlfn.XLOOKUP($I35,Assumptions!$B$30:$B$50,Assumptions!$C$30:$C$50,0),0))) | T35: =IF($C35<>"Organisation","",IF(OR($P35<>"",$Q35<>""),"Documented in source - midpoint of annual_intake_low/high",IF($I35="","No confirmed programme - modelled as zero",$N35&" base x "&TEXT(_xlfn.XLOOKUP($G35,Assumptions!$B$13:$B$26,Assumptions!$C$13:$C$26,0),"0.0#")&" sector x "&TEXT(_xlfn.XLOOKUP($I35,Assumptions!$B$30:$B$50,Assumptions!$C$30:$C$50,0),"0.0#")&" mechanism"))) | W35: inferred
A36: GEO_H_LAX | B36: Los Angeles | C36: Hub | D36: USA | E36: United States | F36: Los Angeles | S36: =IF($C36<>"Organisation","",IF(OR($P36<>"",$Q36<>""),IF($P36<>"",IF($Q36<>"",($P36+$Q36)/2,$P36),$Q36),ROUND(_xlfn.XLOOKUP($N36,Assumptions!$B$5:$B$9,Assumptions!$C$5:$C$9,0)*_xlfn.XLOOKUP($G36,Assumptions!$B$13:$B$26,Assumptions!$C$13:$C$26,0)*_xlfn.XLOOKUP($I36,Assumptions!$B$30:$B$50,Assumptions!$C$30:$C$50,0),0))) | T36: =IF($C36<>"Organisation","",IF(OR($P36<>"",$Q36<>""),"Documented in source - midpoint of annual_intake_low/high",IF($I36="","No confirmed programme - modelled as zero",$N36&" base x "&TEXT(_xlfn.XLOOKUP($G36,Assumptions!$B$13:$B$26,Assumptions!$C$13:$C$26,0),"0.0#")&" sector x "&TEXT(_xlfn.XLOOKUP($I36,Assumptions!$B$30:$B$50,Assumptions!$C$30:$C$50,0),"0.0#")&" mechanism"))) | W36: inferred
A37: GEO_H_PHL | B37: Philadelphia area | C37: Hub | D37: USA | E37: United States | F37: Philadelphia area | S37: =IF($C37<>"Organisation","",IF(OR($P37<>"",$Q37<>""),IF($P37<>"",IF($Q37<>"",($P37+$Q37)/2,$P37),$Q37),ROUND(_xlfn.XLOOKUP($N37,Assumptions!$B$5:$B$9,Assumptions!$C$5:$C$9,0)*_xlfn.XLOOKUP($G37,Assumptions!$B$13:$B$26,Assumptions!$C$13:$C$26,0)*_xlfn.XLOOKUP($I37,Assumptions!$B$30:$B$50,Assumptions!$C$30:$C$50,0),0))) | T37: =IF($C37<>"Organisation","",IF(OR($P37<>"",$Q37<>""),"Documented in source - midpoint of annual_intake_low/high",IF($I37="","No confirmed programme - modelled as zero",$N37&" base x "&TEXT(_xlfn.XLOOKUP($G37,Assumptions!$B$13:$B$26,Assumptions!$C$13:$C$26,0),"0.0#")&" sector x "&TEXT(_xlfn.XLOOKUP($I37,Assumptions!$B$30:$B$50,Assumptions!$C$30:$C$50,0),"0.0#")&" mechanism"))) | W37: inferred
A38: GEO_H_USOTH | B38: Other US metro | C38: Hub | D38: USA | E38: United States | F38: Other US metro | S38: =IF($C38<>"Organisation","",IF(OR($P38<>"",$Q38<>""),IF($P38<>"",IF($Q38<>"",($P38+$Q38)/2,$P38),$Q38),ROUND(_xlfn.XLOOKUP($N38,Assumptions!$B$5:$B$9,Assumptions!$C$5:$C$9,0)*_xlfn.XLOOKUP($G38,Assumptions!$B$13:$B$26,Assumptions!$C$13:$C$26,0)*_xlfn.XLOOKUP($I38,Assumptions!$B$30:$B$50,Assumptions!$C$30:$C$50,0),0))) | T38: =IF($C38<>"Organisation","",IF(OR($P38<>"",$Q38<>""),"Documented in source - midpoint of annual_intake_low/high",IF($I38="","No confirmed programme - modelled as zero",$N38&" base x "&TEXT(_xlfn.XLOOKUP($G38,Assumptions!$B$13:$B$26,Assumptions!$C$13:$C$26,0),"0.0#")&" sector x "&TEXT(_xlfn.XLOOKUP($I38,Assumptions!$B$30:$B$50,Assumptions!$C$30:$C$50,0),"0.0#")&" mechanism"))) | W38: inferred
A39: GEO_H_MUM | B39: Mumbai | C39: Hub | D39: India | E39: India | F39: Mumbai | S39: =IF($C39<>"Organisation","",IF(OR($P39<>"",$Q39<>""),IF($P39<>"",IF($Q39<>"",($P39+$Q39)/2,$P39),$Q39),ROUND(_xlfn.XLOOKUP($N39,Assumptions!$B$5:$B$9,Assumptions!$C$5:$C$9,0)*_xlfn.XLOOKUP($G39,Assumptions!$B$13:$B$26,Assumptions!$C$13:$C$26,0)*_xlfn.XLOOKUP($I39,Assumptions!$B$30:$B$50,Assumptions!$C$30:$C$50,0),0))) | T39: =IF($C39<>"Organisation","",IF(OR($P39<>"",$Q39<>""),"Documented in source - midpoint of annual_intake_low/high",IF($I39="","No confirmed programme - modelled as zero",$N39&" base x "&TEXT(_xlfn.XLOOKUP($G39,Assumptions!$B$13:$B$26,Assumptions!$C$13:$C$26,0),"0.0#")&" sector x "&TEXT(_xlfn.XLOOKUP($I39,Assumptions!$B$30:$B$50,Assumptions!$C$30:$C$50,0),"0.0#")&" mechanism"))) | W39: source
A40: GEO_H_BLR | B40: Bengaluru | C40: Hub | D40: India | E40: India | F40: Bengaluru | S40: =IF($C40<>"Organisation","",IF(OR($P40<>"",$Q40<>""),IF($P40<>"",IF($Q40<>"",($P40+$Q40)/2,$P40),$Q40),ROUND(_xlfn.XLOOKUP($N40,Assumptions!$B$5:$B$9,Assumptions!$C$5:$C$9,0)*_xlfn.XLOOKUP($G40,Assumptions!$B$13:$B$26,Assumptions!$C$13:$C$26,0)*_xlfn.XLOOKUP($I40,Assumptions!$B$30:$B$50,Assumptions!$C$30:$C$50,0),0))) | T40: =IF($C40<>"Organisation","",IF(OR($P40<>"",$Q40<>""),"Documented in source - midpoint of annual_intake_low/high",IF($I40="","No confirmed programme - modelled as zero",$N40&" base x "&TEXT(_xlfn.XLOOKUP($G40,Assumptions!$B$13:$B$26,Assumptions!$C$13:$C$26,0),"0.0#")&" sector x "&TEXT(_xlfn.XLOOKUP($I40,Assumptions!$B$30:$B$50,Assumptions!$C$30:$C$50,0),"0.0#")&" mechanism"))) | W40: source
A41: GEO_H_HYD | B41: Hyderabad | C41: Hub | D41: India | E41: India | F41: Hyderabad | S41: =IF($C41<>"Organisation","",IF(OR($P41<>"",$Q41<>""),IF($P41<>"",IF($Q41<>"",($P41+$Q41)/2,$P41),$Q41),ROUND(_xlfn.XLOOKUP($N41,Assumptions!$B$5:$B$9,Assumptions!$C$5:$C$9,0)*_xlfn.XLOOKUP($G41,Assumptions!$B$13:$B$26,Assumptions!$C$13:$C$26,0)*_xlfn.XLOOKUP($I41,Assumptions!$B$30:$B$50,Assumptions!$C$30:$C$50,0),0))) | T41: =IF($C41<>"Organisation","",IF(OR($P41<>"",$Q41<>""),"Documented in source - midpoint of annual_intake_low/high",IF($I41="","No confirmed programme - modelled as zero",$N41&" base x "&TEXT(_xlfn.XLOOKUP($G41,Assumptions!$B$13:$B$26,Assumptions!$C$13:$C$26,0),"0.0#")&" sector x "&TEXT(_xlfn.XLOOKUP($I41,Assumptions!$B$30:$B$50,Assumptions!$C$30:$C$50,0),"0.0#")&" mechanism"))) | W41: source
... A70: GEO_H_LON | B70: London | C70: Hub | D70: United Kingdom | E70: United Kingdom | F70: London | S70: =IF($C70<>"Organisation","",IF(OR($P70<>"",$Q70<>""),IF($P70<>"",IF($Q70<>"",($P70+$Q70)/2,$P70),$Q70),ROUND(_xlfn.XLOOKUP($N70,Assumptions!$B$5:$B$9,Assumptions!$C$5:$C$9,0)*_xlfn.XLOOKUP($G70,Assumptions!$B$13:$B$26,Assumptions!$C$13:$C$26,0)*_xlfn.XLOOKUP($I70,Assumptions!$B$30:$B$50,Assumptions!$C$30:$C$50,0),0))) | T70: =IF($C70<>"Organisation","",IF(OR($P70<>"",$Q70<>""),"Documented in source - midpoint of annual_intake_low/high",IF($I70="","No confirmed programme - modelled as zero",$N70&" base x "&TEXT(_xlfn.XLOOKUP($G70,Assumptions!$B$13:$B$26,Assumptions!$C$13:$C$26,0),"0.0#")&" sector x "&TEXT(_xlfn.XLOOKUP($I70,Assumptions!$B$30:$B$50,Assumptions!$C$30:$C$50,0),"0.0#")&" mechanism"))) | W70: inferred
A71: SEC_IB_BB | B71: Investment Banking - Bulge Bracket | C71: Sector | S71: =IF($C71<>"Organisation","",IF(OR($P71<>"",$Q71<>""),IF($P71<>"",IF($Q71<>"",($P71+$Q71)/2,$P71),$Q71),ROUND(_xlfn.XLOOKUP($N71,Assumptions!$B$5:$B$9,Assumptions!$C$5:$C$9,0)*_xlfn.XLOOKUP($G71,Assumptions!$B$13:$B$26,Assumptions!$C$13:$C$26,0)*_xlfn.XLOOKUP($I71,Assumptions!$B$30:$B$50,Assumptions!$C$30:$C$50,0),0))) | T71: =IF($C71<>"Organisation","",IF(OR($P71<>"",$Q71<>""),"Documented in source - midpoint of annual_intake_low/high",IF($I71="","No confirmed programme - modelled as zero",$N71&" base x "&TEXT(_xlfn.XLOOKUP($G71,Assumptions!$B$13:$B$26,Assumptions!$C$13:$C$26,0),"0.0#")&" sector x "&TEXT(_xlfn.XLOOKUP($I71,Assumptions!$B$30:$B$50,Assumptions!$C$30:$C$50,0),"0.0#")&" mechanism")))
A72: SEC_IB_EB | B72: Investment Banking - Elite Boutique / Independent Advisory | C72: Sector | S72: =IF($C72<>"Organisation","",IF(OR($P72<>"",$Q72<>""),IF($P72<>"",IF($Q72<>"",($P72+$Q72)/2,$P72),$Q72),ROUND(_xlfn.XLOOKUP($N72,Assumptions!$B$5:$B$9,Assumptions!$C$5:$C$9,0)*_xlfn.XLOOKUP($G72,Assumptions!$B$13:$B$26,Assumptions!$C$13:$C$26,0)*_xlfn.XLOOKUP($I72,Assumptions!$B$30:$B$50,Assumptions!$C$30:$C$50,0),0))) | T72: =IF($C72<>"Organisation","",IF(OR($P72<>"",$Q72<>""),"Documented in source - midpoint of annual_intake_low/high",IF($I72="","No confirmed programme - modelled as zero",$N72&" base x "&TEXT(_xlfn.XLOOKUP($G72,Assumptions!$B$13:$B$26,Assumptions!$C$13:$C$26,0),"0.0#")&" sector x "&TEXT(_xlfn.XLOOKUP($I72,Assumptions!$B$30:$B$50,Assumptions!$C$30:$C$50,0),"0.0#")&" mechanism")))
A73: SEC_QUANT | B73: Proprietary Trading / Quant | C73: Sector | S73: =IF($C73<>"Organisation","",IF(OR($P73<>"",$Q73<>""),IF($P73<>"",IF($Q73<>"",($P73+$Q73)/2,$P73),$Q73),ROUND(_xlfn.XLOOKUP($N73,Assumptions!$B$5:$B$9,Assumptions!$C$5:$C$9,0)*_xlfn.XLOOKUP($G73,Assumptions!$B$13:$B$26,Assumptions!$C$13:$C$26,0)*_xlfn.XLOOKUP($I73,Assumptions!$B$30:$B$50,Assumptions!$C$30:$C$50,0),0))) | T73: =IF($C73<>"Organisation","",IF(OR($P73<>"",$Q73<>""),"Documented in source - midpoint of annual_intake_low/high",IF($I73="","No confirmed programme - modelled as zero",$N73&" base x "&TEXT(_xlfn.XLOOKUP($G73,Assumptions!$B$13:$B$26,Assumptions!$C$13:$C$26,0),"0.0#")&" sector x "&TEXT(_xlfn.XLOOKUP($I73,Assumptions!$B$30:$B$50,Assumptions!$C$30:$C$50,0),"0.0#")&" mechanism")))
A74: SEC_COMM | B74: Commercial / Retail Banking | C74: Sector | S74: =IF($C74<>"Organisation","",IF(OR($P74<>"",$Q74<>""),IF($P74<>"",IF($Q74<>"",($P74+$Q74)/2,$P74),$Q74),ROUND(_xlfn.XLOOKUP($N74,Assumptions!$B$5:$B$9,Assumptions!$C$5:$C$9,0)*_xlfn.XLOOKUP($G74,Assumptions!$B$13:$B$26,Assumptions!$C$13:$C$26,0)*_xlfn.XLOOKUP($I74,Assumptions!$B$30:$B$50,Assumptions!$C$30:$C$50,0),0))) | T74: =IF($C74<>"Organisation","",IF(OR($P74<>"",$Q74<>""),"Documented in source - midpoint of annual_intake_low/high",IF($I74="","No confirmed programme - modelled as zero",$N74&" base x "&TEXT(_xlfn.XLOOKUP($G74,Assumptions!$B$13:$B$26,Assumptions!$C$13:$C$26,0),"0.0#")&" sector x "&TEXT(_xlfn.XLOOKUP($I74,Assumptions!$B$30:$B$50,Assumptions!$C$30:$C$50,0),"0.0#")&" mechanism")))
A75: SEC_CUST | B75: Custodian / Asset Servicing / Fund Administration | C75: Sector | S75: =IF($C75<>"Organisation","",IF(OR($P75<>"",$Q75<>""),IF($P75<>"",IF($Q75<>"",($P75+$Q75)/2,$P75),$Q75),ROUND(_xlfn.XLOOKUP($N75,Assumptions!$B$5:$B$9,Assumptions!$C$5:$C$9,0)*_xlfn.XLOOKUP($G75,Assumptions!$B$13:$B$26,Assumptions!$C$13:$C$26,0)*_xlfn.XLOOKUP($I75,Assumptions!$B$30:$B$50,Assumptions!$C$30:$C$50,0),0))) | T75: =IF($C75<>"Organisation","",IF(OR($P75<>"",$Q75<>""),"Documented in source - midpoint of annual_intake_low/high",IF($I75="","No confirmed programme - modelled as zero",$N75&" base x "&TEXT(_xlfn.XLOOKUP($G75,Assumptions!$B$13:$B$26,Assumptions!$C$13:$C$26,0),"0.0#")&" sector x "&TEXT(_xlfn.XLOOKUP($I75,Assumptions!$B$30:$B$50,Assumptions!$C$30:$C$50,0),"0.0#")&" mechanism")))
A76: SEC_AM | B76: Investment / Asset Management | C76: Sector | S76: =IF($C76<>"Organisation","",IF(OR($P76<>"",$Q76<>""),IF($P76<>"",IF($Q76<>"",($P76+$Q76)/2,$P76),$Q76),ROUND(_xlfn.XLOOKUP($N76,Assumptions!$B$5:$B$9,Assumptions!$C$5:$C$9,0)*_xlfn.XLOOKUP($G76,Assumptions!$B$13:$B$26,Assumptions!$C$13:$C$26,0)*_xlfn.XLOOKUP($I76,Assumptions!$B$30:$B$50,Assumptions!$C$30:$C$50,0),0))) | T76: =IF($C76<>"Organisation","",IF(OR($P76<>"",$Q76<>""),"Documented in source - midpoint of annual_intake_low/high",IF($I76="","No confirmed programme - modelled as zero",$N76&" base x "&TEXT(_xlfn.XLOOKUP($G76,Assumptions!$B$13:$B$26,Assumptions!$C$13:$C$26,0),"0.0#")&" sector x "&TEXT(_xlfn.XLOOKUP($I76,Assumptions!$B$30:$B$50,Assumptions!$C$30:$C$50,0),"0.0#")&" mechanism")))
A77: SEC_INS | B77: Insurance | C77: Sector | S77: =IF($C77<>"Organisation","",IF(OR($P77<>"",$Q77<>""),IF($P77<>"",IF($Q77<>"",($P77+$Q77)/2,$P77),$Q77),ROUND(_xlfn.XLOOKUP($N77,Assumptions!$B$5:$B$9,Assumptions!$C$5:$C$9,0)*_xlfn.XLOOKUP($G77,Assumptions!$B$13:$B$26,Assumptions!$C$13:$C$26,0)*_xlfn.XLOOKUP($I77,Assumptions!$B$30:$B$50,Assumptions!$C$30:$C$50,0),0))) | T77: =IF($C77<>"Organisation","",IF(OR($P77<>"",$Q77<>""),"Documented in source - midpoint of annual_intake_low/high",IF($I77="","No confirmed programme - modelled as zero",$N77&" base x "&TEXT(_xlfn.XLOOKUP($G77,Assumptions!$B$13:$B$26,Assumptions!$C$13:$C$26,0),"0.0#")&" sector x "&TEXT(_xlfn.XLOOKUP($I77,Assumptions!$B$30:$B$50,Assumptions!$C$30:$C$50,0),"0.0#")&" mechanism")))
A78: SEC_DATA | B78: Ratings Agencies & Financial Data | C78: Sector | S78: =IF($C78<>"Organisation","",IF(OR($P78<>"",$Q78<>""),IF($P78<>"",IF($Q78<>"",($P78+$Q78)/2,$P78),$Q78),ROUND(_xlfn.XLOOKUP($N78,Assumptions!$B$5:$B$9,Assumptions!$C$5:$C$9,0)*_xlfn.XLOOKUP($G78,Assumptions!$B$13:$B$26,Assumptions!$C$13:$C$26,0)*_xlfn.XLOOKUP($I78,Assumptions!$B$30:$B$50,Assumptions!$C$30:$C$50,0),0))) | T78: =IF($C78<>"Organisation","",IF(OR($P78<>"",$Q78<>""),"Documented in source - midpoint of annual_intake_low/high",IF($I78="","No confirmed programme - modelled as zero",$N78&" base x "&TEXT(_xlfn.XLOOKUP($G78,Assumptions!$B$13:$B$26,Assumptions!$C$13:$C$26,0),"0.0#")&" sector x "&TEXT(_xlfn.XLOOKUP($I78,Assumptions!$B$30:$B$50,Assumptions!$C$30:$C$50,0),"0.0#")&" mechanism")))
A79: SEC_CONS | B79: Consulting / Professional Services | C79: Sector | S79: =IF($C79<>"Organisation","",IF(OR($P79<>"",$Q79<>""),IF($P79<>"",IF($Q79<>"",($P79+$Q79)/2,$P79),$Q79),ROUND(_xlfn.XLOOKUP($N79,Assumptions!$B$5:$B$9,Assumptions!$C$5:$C$9,0)*_xlfn.XLOOKUP($G79,Assumptions!$B$13:$B$26,Assumptions!$C$13:$C$26,0)*_xlfn.XLOOKUP($I79,Assumptions!$B$30:$B$50,Assumptions!$C$30:$C$50,0),0))) | T79: =IF($C79<>"Organisation","",IF(OR($P79<>"",$Q79<>""),"Documented in source - midpoint of annual_intake_low/high",IF($I79="","No confirmed programme - modelled as zero",$N79&" base x "&TEXT(_xlfn.XLOOKUP($G79,Assumptions!$B$13:$B$26,Assumptions!$C$13:$C$26,0),"0.0#")&" sector x "&TEXT(_xlfn.XLOOKUP($I79,Assumptions!$B$30:$B$50,Assumptions!$C$30:$C$50,0),"0.0#")&" mechanism")))
A80: SEC_FINTECH | B80: Fintech / Tech-Finance | C80: Sector | S80: =IF($C80<>"Organisation","",IF(OR($P80<>"",$Q80<>""),IF($P80<>"",IF($Q80<>"",($P80+$Q80)/2,$P80),$Q80),ROUND(_xlfn.XLOOKUP($N80,Assumptions!$B$5:$B$9,Assumptions!$C$5:$C$9,0)*_xlfn.XLOOKUP($G80,Assumptions!$B$13:$B$26,Assumptions!$C$13:$C$26,0)*_xlfn.XLOOKUP($I80,Assumptions!$B$30:$B$50,Assumptions!$C$30:$C$50,0),0))) | T80: =IF($C80<>"Organisation","",IF(OR($P80<>"",$Q80<>""),"Documented in source - midpoint of annual_intake_low/high",IF($I80="","No confirmed programme - modelled as zero",$N80&" base x "&TEXT(_xlfn.XLOOKUP($G80,Assumptions!$B$13:$B$26,Assumptions!$C$13:$C$26,0),"0.0#")&" sector x "&TEXT(_xlfn.XLOOKUP($I80,Assumptions!$B$30:$B$50,Assumptions!$C$30:$C$50,0),"0.0#")&" mechanism")))
A81: SEC_POLICY | B81: Policy / Development Bank | C81: Sector | S81: =IF($C81<>"Organisation","",IF(OR($P81<>"",$Q81<>""),IF($P81<>"",IF($Q81<>"",($P81+$Q81)/2,$P81),$Q81),ROUND(_xlfn.XLOOKUP($N81,Assumptions!$B$5:$B$9,Assumptions!$C$5:$C$9,0)*_xlfn.XLOOKUP($G81,Assumptions!$B$13:$B$26,Assumptions!$C$13:$C$26,0)*_xlfn.XLOOKUP($I81,Assumptions!$B$30:$B$50,Assumptions!$C$30:$C$50,0),0))) | T81: =IF($C81<>"Organisation","",IF(OR($P81<>"",$Q81<>""),"Documented in source - midpoint of annual_intake_low/high",IF($I81="","No confirmed programme - modelled as zero",$N81&" base x "&TEXT(_xlfn.XLOOKUP($G81,Assumptions!$B$13:$B$26,Assumptions!$C$13:$C$26,0),"0.0#")&" sector x "&TEXT(_xlfn.XLOOKUP($I81,Assumptions!$B$30:$B$50,Assumptions!$C$30:$C$50,0),"0.0#")&" mechanism")))
A82: SEC_CB | B82: Central Bank / Supervisor | C82: Sector | S82: =IF($C82<>"Organisation","",IF(OR($P82<>"",$Q82<>""),IF($P82<>"",IF($Q82<>"",($P82+$Q82)/2,$P82),$Q82),ROUND(_xlfn.XLOOKUP($N82,Assumptions!$B$5:$B$9,Assumptions!$C$5:$C$9,0)*_xlfn.XLOOKUP($G82,Assumptions!$B$13:$B$26,Assumptions!$C$13:$C$26,0)*_xlfn.XLOOKUP($I82,Assumptions!$B$30:$B$50,Assumptions!$C$30:$C$50,0),0))) | T82: =IF($C82<>"Organisation","",IF(OR($P82<>"",$Q82<>""),"Documented in source - midpoint of annual_intake_low/high",IF($I82="","No confirmed programme - modelled as zero",$N82&" base x "&TEXT(_xlfn.XLOOKUP($G82,Assumptions!$B$13:$B$26,Assumptions!$C$13:$C$26,0),"0.0#")&" sector x "&TEXT(_xlfn.XLOOKUP($I82,Assumptions!$B$30:$B$50,Assumptions!$C$30:$C$50,0),"0.0#")&" mechanism")))
... A84: SEC_NBFC | B84: NBFC / Diversified Financial | C84: Sector | S84: =IF($C84<>"Organisation","",IF(OR($P84<>"",$Q84<>""),IF($P84<>"",IF($Q84<>"",($P84+$Q84)/2,$P84),$Q84),ROUND(_xlfn.XLOOKUP($N84,Assumptions!$B$5:$B$9,Assumptions!$C$5:$C$9,0)*_xlfn.XLOOKUP($G84,Assumptions!$B$13:$B$26,Assumptions!$C$13:$C$26,0)*_xlfn.XLOOKUP($I84,Assumptions!$B$30:$B$50,Assumptions!$C$30:$C$50,0),0))) | T84: =IF($C84<>"Organisation","",IF(OR($P84<>"",$Q84<>""),"Documented in source - midpoint of annual_intake_low/high",IF($I84="","No confirmed programme - modelled as zero",$N84&" base x "&TEXT(_xlfn.XLOOKUP($G84,Assumptions!$B$13:$B$26,Assumptions!$C$13:$C$26,0),"0.0#")&" sector x "&TEXT(_xlfn.XLOOKUP($I84,Assumptions!$B$30:$B$50,Assumptions!$C$30:$C$50,0),"0.0#")&" mechanism")))
A85: ORG_GS | B85: Goldman Sachs | C85: Organisation | D85: USA | E85: United States | F85: New York | G85: Investment Banking - Bulge Bracket | H85: Tier 1 Bulge Bracket | I85: MECH_US_CONV | J85: Summer Analyst / New Analyst | N85: Large | O85: inferred - coarse band, verify | S85: =IF($C85<>"Organisation","",IF(OR($P85<>"",$Q85<>""),IF($P85<>"",IF($Q85<>"",($P85+$Q85)/2,$P85),$Q85),ROUND(_xlfn.XLOOKUP($N85,Assumptions!$B$5:$B$9,Assumptions!$C$5:$C$9,0)*_xlfn.XLOOKUP($G85,Assumptions!$B$13:$B$26,Assumptions!$C$13:$C$26,0)*_xlfn.XLOOKUP($I85,Assumptions!$B$30:$B$50,Assumptions!$C$30:$C$50,0),0))) -> 240 | T85: =IF($C85<>"Organisation","",IF(OR($P85<>"",$Q85<>""),"Documented in source - midpoint of annual_intake_low/high",IF($I85="","No confirmed programme - modelled as zero",$N85&" base x "&TEXT(_xlfn.XLOOKUP($G85,Assumptions!$B$13:$B$26,Assumptions!$C$13:$C$26,0),"0.0#")&" sector x "&TEXT(_xlfn.XLOOKUP($I85,Assumptions!$B$30:$B$50,Assumptions!$C$30:$C$50,0),"0.0#")&" mechanism"))) -> Large base x 2.0 sector x 1.0 mechanism | U85: [C-Official] | V85: High | W85: inferred
A86: ORG_MS | B86: Morgan Stanley | C86: Organisation | D86: USA | E86: United States | F86: New York | G86: Investment Banking - Bulge Bracket | H86: Tier 1 Bulge Bracket | I86: MECH_US_CONV | J86: Summer Analyst | N86: Large | O86: inferred - coarse band, verify | S86: =IF($C86<>"Organisation","",IF(OR($P86<>"",$Q86<>""),IF($P86<>"",IF($Q86<>"",($P86+$Q86)/2,$P86),$Q86),ROUND(_xlfn.XLOOKUP($N86,Assumptions!$B$5:$B$9,Assumptions!$C$5:$C$9,0)*_xlfn.XLOOKUP($G86,Assumptions!$B$13:$B$26,Assumptions!$C$13:$C$26,0)*_xlfn.XLOOKUP($I86,Assumptions!$B$30:$B$50,Assumptions!$C$30:$C$50,0),0))) -> 240 | T86: =IF($C86<>"Organisation","",IF(OR($P86<>"",$Q86<>""),"Documented in source - midpoint of annual_intake_low/high",IF($I86="","No confirmed programme - modelled as zero",$N86&" base x "&TEXT(_xlfn.XLOOKUP($G86,Assumptions!$B$13:$B$26,Assumptions!$C$13:$C$26,0),"0.0#")&" sector x "&TEXT(_xlfn.XLOOKUP($I86,Assumptions!$B$30:$B$50,Assumptions!$C$30:$C$50,0),"0.0#")&" mechanism"))) -> Large base x 2.0 sector x 1.0 mechanism | U86: [C-Official] | V86: High | W86: inferred
A87: ORG_JPM | B87: JPMorgan | C87: Organisation | D87: USA | E87: United States | F87: New York | G87: Investment Banking - Bulge Bracket | H87: Tier 1 Bulge Bracket | I87: MECH_US_CONV | J87: Corporate & Investment Bank Analyst | N87: Mega | O87: inferred - coarse band, verify | S87: =IF($C87<>"Organisation","",IF(OR($P87<>"",$Q87<>""),IF($P87<>"",IF($Q87<>"",($P87+$Q87)/2,$P87),$Q87),ROUND(_xlfn.XLOOKUP($N87,Assumptions!$B$5:$B$9,Assumptions!$C$5:$C$9,0)*_xlfn.XLOOKUP($G87,Assumptions!$B$13:$B$26,Assumptions!$C$13:$C$26,0)*_xlfn.XLOOKUP($I87,Assumptions!$B$30:$B$50,Assumptions!$C$30:$C$50,0),0))) -> 800 | T87: =IF($C87<>"Organisation","",IF(OR($P87<>"",$Q87<>""),"Documented in source - midpoint of annual_intake_low/high",IF($I87="","No confirmed programme - modelled as zero",$N87&" base x "&TEXT(_xlfn.XLOOKUP($G87,Assumptions!$B$13:$B$26,Assumptions!$C$13:$C$26,0),"0.0#")&" sector x "&TEXT(_xlfn.XLOOKUP($I87,Assumptions!$B$30:$B$50,Assumptions!$C$30:$C$50,0),"0.0#")&" mechanism"))) -> Mega base x 2.0 sector x 1.0 mechanism | U87: [C-Official] | V87: High | W87: inferred
A88: ORG_BAC | B88: Bank of America | C88: Organisation | D88: USA | E88: United States | F88: Charlotte | G88: Investment Banking - Bulge Bracket | H88: Tier 1 Bulge Bracket | I88: MECH_US_CONV | J88: Global Banking & Markets Analyst | N88: Mega | O88: inferred - coarse band, verify | S88: =IF($C88<>"Organisation","",IF(OR($P88<>"",$Q88<>""),IF($P88<>"",IF($Q88<>"",($P88+$Q88)/2,$P88),$Q88),ROUND(_xlfn.XLOOKUP($N88,Assumptions!$B$5:$B$9,Assumptions!$C$5:$C$9,0)*_xlfn.XLOOKUP($G88,Assumptions!$B$13:$B$26,Assumptions!$C$13:$C$26,0)*_xlfn.XLOOKUP($I88,Assumptions!$B$30:$B$50,Assumptions!$C$30:$C$50,0),0))) -> 800 | T88: =IF($C88<>"Organisation","",IF(OR($P88<>"",$Q88<>""),"Documented in source - midpoint of annual_intake_low/high",IF($I88="","No confirmed programme - modelled as zero",$N88&" base x "&TEXT(_xlfn.XLOOKUP($G88,Assumptions!$B$13:$B$26,Assumptions!$C$13:$C$26,0),"0.0#")&" sector x "&TEXT(_xlfn.XLOOKUP($I88,Assumptions!$B$30:$B$50,Assumptions!$C$30:$C$50,0),"0.0#")&" mechanism"))) -> Mega base x 2.0 sector x 1.0 mechanism | U88: [C-Press] | V88: Medium | W88: inferred
A89: ORG_CITI | B89: Citigroup | C89: Organisation | D89: USA | E89: United States | F89: New York | G89: Investment Banking - Bulge Bracket | H89: Tier 1 Bulge Bracket | I89: MECH_US_CONV | J89: Markets / Banking Full-Time Analyst | N89: Mega | O89: inferred - coarse band, verify | S89: =IF($C89<>"Organisation","",IF(OR($P89<>"",$Q89<>""),IF($P89<>"",IF($Q89<>"",($P89+$Q89)/2,$P89),$Q89),ROUND(_xlfn.XLOOKUP($N89,Assumptions!$B$5:$B$9,Assumptions!$C$5:$C$9,0)*_xlfn.XLOOKUP($G89,Assumptions!$B$13:$B$26,Assumptions!$C$13:$C$26,0)*_xlfn.XLOOKUP($I89,Assumptions!$B$30:$B$50,Assumptions!$C$30:$C$50,0),0))) -> 800 | T89: =IF($C89<>"Organisation","",IF(OR($P89<>"",$Q89<>""),"Documented in source - midpoint of annual_intake_low/high",IF($I89="","No confirmed programme - modelled as zero",$N89&" base x "&TEXT(_xlfn.XLOOKUP($G89,Assumptions!$B$13:$B$26,Assumptions!$C$13:$C$26,0),"0.0#")&" sector x "&TEXT(_xlfn.XLOOKUP($I89,Assumptions!$B$30:$B$50,Assumptions!$C$30:$C$50,0),"0.0#")&" mechanism"))) -> Mega base x 2.0 sector x 1.0 mechanism | U89: [C-Official] | V89: High | W89: inferred
A90: ORG_WFC | B90: Wells Fargo | C90: Organisation | D90: USA | E90: United States | F90: San Francisco Bay Area | G90: Investment Banking - Bulge Bracket | H90: Tier 1 Bulge Bracket | I90: MECH_US_CONV | J90: Analyst Program | N90: Mega | O90: inferred - coarse band, verify | S90: =IF($C90<>"Organisation","",IF(OR($P90<>"",$Q90<>""),IF($P90<>"",IF($Q90<>"",($P90+$Q90)/2,$P90),$Q90),ROUND(_xlfn.XLOOKUP($N90,Assumptions!$B$5:$B$9,Assumptions!$C$5:$C$9,0)*_xlfn.XLOOKUP($G90,Assumptions!$B$13:$B$26,Assumptions!$C$13:$C$26,0)*_xlfn.XLOOKUP($I90,Assumptions!$B$30:$B$50,Assumptions!$C$30:$C$50,0),0))) -> 800 | T90: =IF($C90<>"Organisation","",IF(OR($P90<>"",$Q90<>""),"Documented in source - midpoint of annual_intake_low/high",IF($I90="","No confirmed programme - modelled as zero",$N90&" base x "&TEXT(_xlfn.XLOOKUP($G90,Assumptions!$B$13:$B$26,Assumptions!$C$13:$C$26,0),"0.0#")&" sector x "&TEXT(_xlfn.XLOOKUP($I90,Assumptions!$B$30:$B$50,Assumptions!$C$30:$C$50,0),"0.0#")&" mechanism"))) -> Mega base x 2.0 sector x 1.0 mechanism | U90: [Note] | V90: Low | W90: inferred
A91: ORG_EVR | B91: Evercore | C91: Organisation | D91: USA | E91: United States | F91: New York | G91: Investment Banking - Elite Boutique / Independent Advisory | H91: Tier 1 prestige boutique | I91: MECH_US_CONV | J91: Analyst (First Round + Superday) | N91: Boutique | O91: inferred - coarse band, verify | P91: 80 | Q91: 100 | S91: =IF($C91<>"Organisation","",IF(OR($P91<>"",$Q91<>""),IF($P91<>"",IF($Q91<>"",($P91+$Q91)/2,$P91),$Q91),ROUND(_xlfn.XLOOKUP($N91,Assumptions!$B$5:$B$9,Assumptions!$C$5:$C$9,0)*_xlfn.XLOOKUP($G91,Assumptions!$B$13:$B$26,Assumptions!$C$13:$C$26,0)*_xlfn.XLOOKUP($I91,Assumptions!$B$30:$B$50,Assumptions!$C$30:$C$50,0),0))) -> 90 | T91: =IF($C91<>"Organisation","",IF(OR($P91<>"",$Q91<>""),"Documented in source - midpoint of annual_intake_low/high",IF($I91="","No confirmed programme - modelled as zero",$N91&" base x "&TEXT(_xlfn.XLOOKUP($G91,Assumptions!$B$13:$B$26,Assumptions!$C$13:$C$26,0),"0.0#")&" sector x "&TEXT(_xlfn.XLOOKUP($I91,Assumptions!$B$30:$B$50,Assumptions!$C$30:$C$50,0),"0.0#")&" mechanism"))) -> Documented in source - midpoint of annual_intake_low/high | U91: [C-Press] | V91: Medium | W91: inferred | X91: Largest independent IB by revenue; acceptance rate cited below 1%. Cohort size from career-advice sources - indicative only.
A92: ORG_CVP | B92: Centerview Partners | C92: Organisation | D92: USA | E92: United States | F92: New York | G92: Investment Banking - Elite Boutique / Independent Advisory | H92: Tier 1 prestige boutique | I92: MECH_US_CONV | J92: 3-year Analyst track | K92: 36 | N92: Boutique | O92: inferred - coarse band, verify | S92: =IF($C92<>"Organisation","",IF(OR($P92<>"",$Q92<>""),IF($P92<>"",IF($Q92<>"",($P92+$Q92)/2,$P92),$Q92),ROUND(_xlfn.XLOOKUP($N92,Assumptions!$B$5:$B$9,Assumptions!$C$5:$C$9,0)*_xlfn.XLOOKUP($G92,Assumptions!$B$13:$B$26,Assumptions!$C$13:$C$26,0)*_xlfn.XLOOKUP($I92,Assumptions!$B$30:$B$50,Assumptions!$C$30:$C$50,0),0))) -> 6 | T92: =IF($C92<>"Organisation","",IF(OR($P92<>"",$Q92<>""),"Documented in source - midpoint of annual_intake_low/high",IF($I92="","No confirmed programme - modelled as zero",$N92&" base x "&TEXT(_xlfn.XLOOKUP($G92,Assumptions!$B$13:$B$26,Assumptions!$C$13:$C$26,0),"0.0#")&" sector x "&TEXT(_xlfn.XLOOKUP($I92,Assumptions!$B$30:$B$50,Assumptions!$C$30:$C$50,0),"0.0#")&" mechanism"))) -> Boutique base x 0.8 sector x 1.0 mechanism | U92: [C-Press] | V92: Medium | W92: inferred
A93: ORG_LAZ | B93: Lazard | C93: Organisation | D93: USA | E93: United States | F93: New York | G93: Investment Banking - Elite Boutique / Independent Advisory | H93: Tier 1 prestige boutique | I93: MECH_US_CONV | J93: Analyst | N93: Mid | O93: inferred - coarse band, verify | S93: =IF($C93<>"Organisation","",IF(OR($P93<>"",$Q93<>""),IF($P93<>"",IF($Q93<>"",($P93+$Q93)/2,$P93),$Q93),ROUND(_xlfn.XLOOKUP($N93,Assumptions!$B$5:$B$9,Assumptions!$C$5:$C$9,0)*_xlfn.XLOOKUP($G93,Assumptions!$B$13:$B$26,Assumptions!$C$13:$C$26,0)*_xlfn.XLOOKUP($I93,Assumptions!$B$30:$B$50,Assumptions!$C$30:$C$50,0),0))) -> 24 | T93: =IF($C93<>"Organisation","",IF(OR($P93<>"",$Q93<>""),"Documented in source - midpoint of annual_intake_low/high",IF($I93="","No confirmed programme - modelled as zero",$N93&" base x "&TEXT(_xlfn.XLOOKUP($G93,Assumptions!$B$13:$B$26,Assumptions!$C$13:$C$26,0),"0.0#")&" sector x "&TEXT(_xlfn.XLOOKUP($I93,Assumptions!$B$30:$B$50,Assumptions!$C$30:$C$50,0),"0.0#")&" mechanism"))) -> Mid base x 0.8 sector x 1.0 mechanism | U93: [C-Press] | V93: Medium | W93: inferred
A94: ORG_MC | B94: Moelis & Company | C94: Organisation | D94: USA | E94: United States | F94: New York | G94: Investment Banking - Elite Boutique / Independent Advisory | H94: Tier 1 prestige boutique | I94: MECH_US_CONV | J94: Analyst | N94: Boutique | O94: inferred - coarse band, verify | S94: =IF($C94<>"Organisation","",IF(OR($P94<>"",$Q94<>""),IF($P94<>"",IF($Q94<>"",($P94+$Q94)/2,$P94),$Q94),ROUND(_xlfn.XLOOKUP($N94,Assumptions!$B$5:$B$9,Assumptions!$C$5:$C$9,0)*_xlfn.XLOOKUP($G94,Assumptions!$B$13:$B$26,Assumptions!$C$13:$C$26,0)*_xlfn.XLOOKUP($I94,Assumptions!$B$30:$B$50,Assumptions!$C$30:$C$50,0),0))) -> 6 | T94: =IF($C94<>"Organisation","",IF(OR($P94<>"",$Q94<>""),"Documented in source - midpoint of annual_intake_low/high",IF($I94="","No confirmed programme - modelled as zero",$N94&" base x "&TEXT(_xlfn.XLOOKUP($G94,Assumptions!$B$13:$B$26,Assumptions!$C$13:$C$26,0),"0.0#")&" sector x "&TEXT(_xlfn.XLOOKUP($I94,Assumptions!$B$30:$B$50,Assumptions!$C$30:$C$50,0),"0.0#")&" mechanism"))) -> Boutique base x 0.8 sector x 1.0 mechanism | U94: [C-Press] | V94: Medium | W94: inferred
A95: ORG_PJT | B95: PJT Partners | C95: Organisation | D95: USA | E95: United States | F95: New York | G95: Investment Banking - Elite Boutique / Independent Advisory | H95: Tier 1 prestige boutique | I95: MECH_US_CONV | J95: Summer Internship Program | N95: Boutique | O95: inferred - coarse band, verify | S95: =IF($C95<>"Organisation","",IF(OR($P95<>"",$Q95<>""),IF($P95<>"",IF($Q95<>"",($P95+$Q95)/2,$P95),$Q95),ROUND(_xlfn.XLOOKUP($N95,Assumptions!$B$5:$B$9,Assumptions!$C$5:$C$9,0)*_xlfn.XLOOKUP($G95,Assumptions!$B$13:$B$26,Assumptions!$C$13:$C$26,0)*_xlfn.XLOOKUP($I95,Assumptions!$B$30:$B$50,Assumptions!$C$30:$C$50,0),0))) -> 6 | T95: =IF($C95<>"Organisation","",IF(OR($P95<>"",$Q95<>""),"Documented in source - midpoint of annual_intake_low/high",IF($I95="","No confirmed programme - modelled as zero",$N95&" base x "&TEXT(_xlfn.XLOOKUP($G95,Assumptions!$B$13:$B$26,Assumptions!$C$13:$C$26,0),"0.0#")&" sector x "&TEXT(_xlfn.XLOOKUP($I95,Assumptions!$B$30:$B$50,Assumptions!$C$30:$C$50,0),"0.0#")&" mechanism"))) -> Boutique base x 0.8 sector x 1.0 mechanism | U95: [C-Official] | V95: High | W95: inferred
A96: ORG_PWP | B96: Perella Weinberg Partners | C96: Organisation | D96: USA | E96: United States | F96: New York | G96: Investment Banking - Elite Boutique / Independent Advisory | H96: Tier 1 prestige boutique | I96: MECH_US_CONV | J96: Analyst | N96: Boutique | O96: inferred - coarse band, verify | S96: =IF($C96<>"Organisation","",IF(OR($P96<>"",$Q96<>""),IF($P96<>"",IF($Q96<>"",($P96+$Q96)/2,$P96),$Q96),ROUND(_xlfn.XLOOKUP($N96,Assumptions!$B$5:$B$9,Assumptions!$C$5:$C$9,0)*_xlfn.XLOOKUP($G96,Assumptions!$B$13:$B$26,Assumptions!$C$13:$C$26,0)*_xlfn.XLOOKUP($I96,Assumptions!$B$30:$B$50,Assumptions!$C$30:$C$50,0),0))) -> 6 | T96: =IF($C96<>"Organisation","",IF(OR($P96<>"",$Q96<>""),"Documented in source - midpoint of annual_intake_low/high",IF($I96="","No confirmed programme - modelled as zero",$N96&" base x "&TEXT(_xlfn.XLOOKUP($G96,Assumptions!$B$13:$B$26,Assumptions!$C$13:$C$26,0),"0.0#")&" sector x "&TEXT(_xlfn.XLOOKUP($I96,Assumptions!$B$30:$B$50,Assumptions!$C$30:$C$50,0),"0.0#")&" mechanism"))) -> Boutique base x 0.8 sector x 1.0 mechanism | U96: [C-Press] | V96: Medium | W96: inferred
A97: ORG_HLI | B97: Houlihan Lokey | C97: Organisation | D97: USA | E97: United States | F97: Los Angeles | G97: Investment Banking - Elite Boutique / Independent Advisory | H97: Restructuring leader | I97: MECH_US_CONV | J97: Early Careers / Financial Analyst | N97: Mid | O97: inferred - coarse band, verify | S97: =IF($C97<>"Organisation","",IF(OR($P97<>"",$Q97<>""),IF($P97<>"",IF($Q97<>"",($P97+$Q97)/2,$P97),$Q97),ROUND(_xlfn.XLOOKUP($N97,Assumptions!$B$5:$B$9,Assumptions!$C$5:$C$9,0)*_xlfn.XLOOKUP($G97,Assumptions!$B$13:$B$26,Assumptions!$C$13:$C$26,0)*_xlfn.XLOOKUP($I97,Assumptions!$B$30:$B$50,Assumptions!$C$30:$C$50,0),0))) -> 24 | T97: =IF($C97<>"Organisation","",IF(OR($P97<>"",$Q97<>""),"Documented in source - midpoint of annual_intake_low/high",IF($I97="","No confirmed programme - modelled as zero",$N97&" base x "&TEXT(_xlfn.XLOOKUP($G97,Assumptions!$B$13:$B$26,Assumptions!$C$13:$C$26,0),"0.0#")&" sector x "&TEXT(_xlfn.XLOOKUP($I97,Assumptions!$B$30:$B$50,Assumptions!$C$30:$C$50,0),"0.0#")&" mechanism"))) -> Mid base x 0.8 sector x 1.0 mechanism | U97: [C-Official] | V97: High | W97: inferred
A98: ORG_GUGG | B98: Guggenheim Securities | C98: Organisation | D98: USA | E98: United States | F98: New York | G98: Investment Banking - Elite Boutique / Independent Advisory | H98: Boutique | I98: MECH_US_CONV | J98: Analyst | N98: Boutique | O98: inferred - coarse band, verify | S98: =IF($C98<>"Organisation","",IF(OR($P98<>"",$Q98<>""),IF($P98<>"",IF($Q98<>"",($P98+$Q98)/2,$P98),$Q98),ROUND(_xlfn.XLOOKUP($N98,Assumptions!$B$5:$B$9,Assumptions!$C$5:$C$9,0)*_xlfn.XLOOKUP($G98,Assumptions!$B$13:$B$26,Assumptions!$C$13:$C$26,0)*_xlfn.XLOOKUP($I98,Assumptions!$B$30:$B$50,Assumptions!$C$30:$C$50,0),0))) -> 6 | T98: =IF($C98<>"Organisation","",IF(OR($P98<>"",$Q98<>""),"Documented in source - midpoint of annual_intake_low/high",IF($I98="","No confirmed programme - modelled as zero",$N98&" base x "&TEXT(_xlfn.XLOOKUP($G98,Assumptions!$B$13:$B$26,Assumptions!$C$13:$C$26,0),"0.0#")&" sector x "&TEXT(_xlfn.XLOOKUP($I98,Assumptions!$B$30:$B$50,Assumptions!$C$30:$C$50,0),"0.0#")&" mechanism"))) -> Boutique base x 0.8 sector x 1.0 mechanism | U98: [C-Press] | V98: Medium | W98: inferred
A99: ORG_QTLY | B99: Qatalyst Partners | C99: Organisation | D99: USA | E99: United States | F99: San Francisco Bay Area | G99: Investment Banking - Elite Boutique / Independent Advisory | H99: Tech M&A micro-boutique | I99: MECH_US_CONV | J99: Analyst | N99: Boutique | O99: inferred - coarse band, verify | S99: =IF($C99<>"Organisation","",IF(OR($P99<>"",$Q99<>""),IF($P99<>"",IF($Q99<>"",($P99+$Q99)/2,$P99),$Q99),ROUND(_xlfn.XLOOKUP($N99,Assumptions!$B$5:$B$9,Assumptions!$C$5:$C$9,0)*_xlfn.XLOOKUP($G99,Assumptions!$B$13:$B$26,Assumptions!$C$13:$C$26,0)*_xlfn.XLOOKUP($I99,Assumptions!$B$30:$B$50,Assumptions!$C$30:$C$50,0),0))) -> 6 | T99: =IF($C99<>"Organisation","",IF(OR($P99<>"",$Q99<>""),"Documented in source - midpoint of annual_intake_low/high",IF($I99="","No confirmed programme - modelled as zero",$N99&" base x "&TEXT(_xlfn.XLOOKUP($G99,Assumptions!$B$13:$B$26,Assumptions!$C$13:$C$26,0),"0.0#")&" sector x "&TEXT(_xlfn.XLOOKUP($I99,Assumptions!$B$30:$B$50,Assumptions!$C$30:$C$50,0),"0.0#")&" mechanism"))) -> Boutique base x 0.8 sector x 1.0 mechanism | U99: [Note] | V99: Low | W99: inferred
A100: ORG_ROTH_US | B100: Rothschild & Co (US) | C100: Organisation | D100: USA | E100: United States | F100: New York | G100: Investment Banking - Elite Boutique / Independent Advisory | H100: Boutique | I100: MECH_US_CONV | J100: Analyst | N100: Mid | O100: inferred - coarse band, verify | S100: =IF($C100<>"Organisation","",IF(OR($P100<>"",$Q100<>""),IF($P100<>"",IF($Q100<>"",($P100+$Q100)/2,$P100),$Q100),ROUND(_xlfn.XLOOKUP($N100,Assumptions!$B$5:$B$9,Assumptions!$C$5:$C$9,0)*_xlfn.XLOOKUP($G100,Assumptions!$B$13:$B$26,Assumptions!$C$13:$C$26,0)*_xlfn.XLOOKUP($I100,Assumptions!$B$30:$B$50,Assumptions!$C$30:$C$50,0),0))) -> 24 | T100: =IF($C100<>"Organisation","",IF(OR($P100<>"",$Q100<>""),"Documented in source - midpoint of annual_intake_low/high",IF($I100="","No confirmed programme - modelled as zero",$N100&" base x "&TEXT(_xlfn.XLOOKUP($G100,Assumptions!$B$13:$B$26,Assumptions!$C$13:$C$26,0),"0.0#")&" sector x "&TEXT(_xlfn.XLOOKUP($I100,Assumptions!$B$30:$B$50,Assumptions!$C$30:$C$50,0),"0.0#")&" mechanism"))) -> Mid base x 0.8 sector x 1.0 mechanism | U100: [C-Press] | V100: Medium | W100: inferred
A101: ORG_WB | B101: William Blair | C101: Organisation | D101: USA | E101: United States | F101: Chicago | G101: Investment Banking - Elite Boutique / Independent Advisory | H101: Middle-market | I101: MECH_US_CONV | J101: Analyst | N101: Mid | O101: inferred - coarse band, verify | S101: =IF($C101<>"Organisation","",IF(OR($P101<>"",$Q101<>""),IF($P101<>"",IF($Q101<>"",($P101+$Q101)/2,$P101),$Q101),ROUND(_xlfn.XLOOKUP($N101,Assumptions!$B$5:$B$9,Assumptions!$C$5:$C$9,0)*_xlfn.XLOOKUP($G101,Assumptions!$B$13:$B$26,Assumptions!$C$13:$C$26,0)*_xlfn.XLOOKUP($I101,Assumptions!$B$30:$B$50,Assumptions!$C$30:$C$50,0),0))) -> 24 | T101: =IF($C101<>"Organisation","",IF(OR($P101<>"",$Q101<>""),"Documented in source - midpoint of annual_intake_low/high",IF($I101="","No confirmed programme - modelled as zero",$N101&" base x "&TEXT(_xlfn.XLOOKUP($G101,Assumptions!$B$13:$B$26,Assumptions!$C$13:$C$26,0),"0.0#")&" sector x "&TEXT(_xlfn.XLOOKUP($I101,Assumptions!$B$30:$B$50,Assumptions!$C$30:$C$50,0),"0.0#")&" mechanism"))) -> Mid base x 0.8 sector x 1.0 mechanism | U101: [C-Press] | V101: Medium | W101: inferred
A102: ORG_RWB | B102: Robert W. Baird | C102: Organisation | D102: USA | E102: United States | F102: Other US metro | G102: Investment Banking - Elite Boutique / Independent Advisory | H102: Middle-market | I102: MECH_US_CONV | J102: Analyst | N102: Mid | O102: inferred - coarse band, verify | S102: =IF($C102<>"Organisation","",IF(OR($P102<>"",$Q102<>""),IF($P102<>"",IF($Q102<>"",($P102+$Q102)/2,$P102),$Q102),ROUND(_xlfn.XLOOKUP($N102,Assumptions!$B$5:$B$9,Assumptions!$C$5:$C$9,0)*_xlfn.XLOOKUP($G102,Assumptions!$B$13:$B$26,Assumptions!$C$13:$C$26,0)*_xlfn.XLOOKUP($I102,Assumptions!$B$30:$B$50,Assumptions!$C$30:$C$50,0),0))) -> 24 | T102: =IF($C102<>"Organisation","",IF(OR($P102<>"",$Q102<>""),"Documented in source - midpoint of annual_intake_low/high",IF($I102="","No confirmed programme - modelled as zero",$N102&" base x "&TEXT(_xlfn.XLOOKUP($G102,Assumptions!$B$13:$B$26,Assumptions!$C$13:$C$26,0),"0.0#")&" sector x "&TEXT(_xlfn.XLOOKUP($I102,Assumptions!$B$30:$B$50,Assumptions!$C$30:$C$50,0),"0.0#")&" mechanism"))) -> Mid base x 0.8 sector x 1.0 mechanism | U102: [C-Press] | V102: Medium | W102: inferred
A103: ORG_JEF | B103: Jefferies | C103: Organisation | D103: USA | E103: United States | F103: New York | G103: Investment Banking - Elite Boutique / Independent Advisory | H103: Middle-market / full-service | I103: MECH_US_CONV | J103: Analyst | N103: Mid | O103: inferred - coarse band, verify | S103: =IF($C103<>"Organisation","",IF(OR($P103<>"",$Q103<>""),IF($P103<>"",IF($Q103<>"",($P103+$Q103)/2,$P103),$Q103),ROUND(_xlfn.XLOOKUP($N103,Assumptions!$B$5:$B$9,Assumptions!$C$5:$C$9,0)*_xlfn.XLOOKUP($G103,Assumptions!$B$13:$B$26,Assumptions!$C$13:$C$26,0)*_xlfn.XLOOKUP($I103,Assumptions!$B$30:$B$50,Assumptions!$C$30:$C$50,0),0))) -> 24 | T103: =IF($C103<>"Organisation","",IF(OR($P103<>"",$Q103<>""),"Documented in source - midpoint of annual_intake_low/high",IF($I103="","No confirmed programme - modelled as zero",$N103&" base x "&TEXT(_xlfn.XLOOKUP($G103,Assumptions!$B$13:$B$26,Assumptions!$C$13:$C$26,0),"0.0#")&" sector x "&TEXT(_xlfn.XLOOKUP($I103,Assumptions!$B$30:$B$50,Assumptions!$C$30:$C$50,0),"0.0#")&" mechanism"))) -> Mid base x 0.8 sector x 1.0 mechanism | U103: [C-Press] | V103: Medium | W103: inferred
A104: ORG_JS | B104: Jane Street | C104: Organisation | D104: USA | E104: United States | F104: New York | G104: Proprietary Trading / Quant | H104: Quant / prop | I104: MECH_US_CONV | J104: New-grad + intern roles | N104: Mid | O104: inferred - coarse band, verify | S104: =IF($C104<>"Organisation","",IF(OR($P104<>"",$Q104<>""),IF($P104<>"",IF($Q104<>"",($P104+$Q104)/2,$P104),$Q104),ROUND(_xlfn.XLOOKUP($N104,Assumptions!$B$5:$B$9,Assumptions!$C$5:$C$9,0)*_xlfn.XLOOKUP($G104,Assumptions!$B$13:$B$26,Assumptions!$C$13:$C$26,0)*_xlfn.XLOOKUP($I104,Assumptions!$B$30:$B$50,Assumptions!$C$30:$C$50,0),0))) -> 60 | T104: =IF($C104<>"Organisation","",IF(OR($P104<>"",$Q104<>""),"Documented in source - midpoint of annual_intake_low/high",IF($I104="","No confirmed programme - modelled as zero",$N104&" base x "&TEXT(_xlfn.XLOOKUP($G104,Assumptions!$B$13:$B$26,Assumptions!$C$13:$C$26,0),"0.0#")&" sector x "&TEXT(_xlfn.XLOOKUP($I104,Assumptions!$B$30:$B$50,Assumptions!$C$30:$C$50,0),"0.0#")&" mechanism"))) -> Mid base x 2.0 sector x 1.0 mechanism | U104: [C-Official] | V104: High | W104: inferred
A105: ORG_CITSEC | B105: Citadel Securities | C105: Organisation | D105: USA | E105: United States | F105: Miami | G105: Proprietary Trading / Quant | H105: Quant / prop | I105: MECH_US_CONV | J105: Intern / new-grad | N105: Mid | O105: inferred - coarse band, verify | Q105: 300 | R105: 108000 | S105: =IF($C105<>"Organisation","",IF(OR($P105<>"",$Q105<>""),IF($P105<>"",IF($Q105<>"",($P105+$Q105)/2,$P105),$Q105),ROUND(_xlfn.XLOOKUP($N105,Assumptions!$B$5:$B$9,Assumptions!$C$5:$C$9,0)*_xlfn.XLOOKUP($G105,Assumptions!$B$13:$B$26,Assumptions!$C$13:$C$26,0)*_xlfn.XLOOKUP($I105,Assumptions!$B$30:$B$50,Assumptions!$C$30:$C$50,0),0))) -> 300 | T105: =IF($C105<>"Organisation","",IF(OR($P105<>"",$Q105<>""),"Documented in source - midpoint of annual_intake_low/high",IF($I105="","No confirmed programme - modelled as zero",$N105&" base x "&TEXT(_xlfn.XLOOKUP($G105,Assumptions!$B$13:$B$26,Assumptions!$C$13:$C$26,0),"0.0#")&" sector x "&TEXT(_xlfn.XLOOKUP($I105,Assumptions!$B$30:$B$50,Assumptions!$C$30:$C$50,0),"0.0#")&" mechanism"))) -> Documented in source - midpoint of annual_intake_low/high | U105: [C-Press] | V105: Medium | W105: inferred | X105: ~0.4% intern acceptance (2025 cycle): >108,000 applications, fewer than 300 interns. Secondary sourcing.
A106: ORG_2SIG | B106: Two Sigma | C106: Organisation | D106: USA | E106: United States | F106: New York | G106: Proprietary Trading / Quant | H106: Quant / prop | I106: MECH_US_CONV | J106: Intern / new-grad | N106: Mid | O106: inferred - coarse band, verify | S106: =IF($C106<>"Organisation","",IF(OR($P106<>"",$Q106<>""),IF($P106<>"",IF($Q106<>"",($P106+$Q106)/2,$P106),$Q106),ROUND(_xlfn.XLOOKUP($N106,Assumptions!$B$5:$B$9,Assumptions!$C$5:$C$9,0)*_xlfn.XLOOKUP($G106,Assumptions!$B$13:$B$26,Assumptions!$C$13:$C$26,0)*_xlfn.XLOOKUP($I106,Assumptions!$B$30:$B$50,Assumptions!$C$30:$C$50,0),0))) -> 60 | T106: =IF($C106<>"Organisation","",IF(OR($P106<>"",$Q106<>""),"Documented in source - midpoint of annual_intake_low/high",IF($I106="","No confirmed programme - modelled as zero",$N106&" base x "&TEXT(_xlfn.XLOOKUP($G106,Assumptions!$B$13:$B$26,Assumptions!$C$13:$C$26,0),"0.0#")&" sector x "&TEXT(_xlfn.XLOOKUP($I106,Assumptions!$B$30:$B$50,Assumptions!$C$30:$C$50,0),"0.0#")&" mechanism"))) -> Mid base x 2.0 sector x 1.0 mechanism | U106: [C-Press] | V106: Medium | W106: inferred
A107: ORG_JUMP | B107: Jump Trading | C107: Organisation | D107: USA | E107: United States | F107: Chicago | G107: Proprietary Trading / Quant | H107: Quant / prop | I107: MECH_US_CONV | J107: Intern / new-grad | N107: Boutique | O107: inferred - coarse band, verify | S107: =IF($C107<>"Organisation","",IF(OR($P107<>"",$Q107<>""),IF($P107<>"",IF($Q107<>"",($P107+$Q107)/2,$P107),$Q107),ROUND(_xlfn.XLOOKUP($N107,Assumptions!$B$5:$B$9,Assumptions!$C$5:$C$9,0)*_xlfn.XLOOKUP($G107,Assumptions!$B$13:$B$26,Assumptions!$C$13:$C$26,0)*_xlfn.XLOOKUP($I107,Assumptions!$B$30:$B$50,Assumptions!$C$30:$C$50,0),0))) -> 16 | T107: =IF($C107<>"Organisation","",IF(OR($P107<>"",$Q107<>""),"Documented in source - midpoint of annual_intake_low/high",IF($I107="","No confirmed programme - modelled as zero",$N107&" base x "&TEXT(_xlfn.XLOOKUP($G107,Assumptions!$B$13:$B$26,Assumptions!$C$13:$C$26,0),"0.0#")&" sector x "&TEXT(_xlfn.XLOOKUP($I107,Assumptions!$B$30:$B$50,Assumptions!$C$30:$C$50,0),"0.0#")&" mechanism"))) -> Boutique base x 2.0 sector x 1.0 mechanism | U107: [C-Press] | V107: Medium | W107: inferred
A108: ORG_DES | B108: D. E. Shaw | C108: Organisation | D108: USA | E108: United States | F108: New York | G108: Proprietary Trading / Quant | H108: Quant / prop | I108: MECH_US_CONV | J108: Intern / new-grad | N108: Mid | O108: inferred - coarse band, verify | S108: =IF($C108<>"Organisation","",IF(OR($P108<>"",$Q108<>""),IF($P108<>"",IF($Q108<>"",($P108+$Q108)/2,$P108),$Q108),ROUND(_xlfn.XLOOKUP($N108,Assumptions!$B$5:$B$9,Assumptions!$C$5:$C$9,0)*_xlfn.XLOOKUP($G108,Assumptions!$B$13:$B$26,Assumptions!$C$13:$C$26,0)*_xlfn.XLOOKUP($I108,Assumptions!$B$30:$B$50,Assumptions!$C$30:$C$50,0),0))) -> 60 | T108: =IF($C108<>"Organisation","",IF(OR($P108<>"",$Q108<>""),"Documented in source - midpoint of annual_intake_low/high",IF($I108="","No confirmed programme - modelled as zero",$N108&" base x "&TEXT(_xlfn.XLOOKUP($G108,Assumptions!$B$13:$B$26,Assumptions!$C$13:$C$26,0),"0.0#")&" sector x "&TEXT(_xlfn.XLOOKUP($I108,Assumptions!$B$30:$B$50,Assumptions!$C$30:$C$50,0),"0.0#")&" mechanism"))) -> Mid base x 2.0 sector x 1.0 mechanism | U108: [C-Press] | V108: Medium | W108: inferred
A109: ORG_SIG | B109: Susquehanna (SIG) | C109: Organisation | D109: USA | E109: United States | F109: Philadelphia area | G109: Proprietary Trading / Quant | H109: Quant / prop | I109: MECH_US_CONV | J109: Intern / new-grad | N109: Mid | O109: inferred - coarse band, verify | S109: =IF($C109<>"Organisation","",IF(OR($P109<>"",$Q109<>""),IF($P109<>"",IF($Q109<>"",($P109+$Q109)/2,$P109),$Q109),ROUND(_xlfn.XLOOKUP($N109,Assumptions!$B$5:$B$9,Assumptions!$C$5:$C$9,0)*_xlfn.XLOOKUP($G109,Assumptions!$B$13:$B$26,Assumptions!$C$13:$C$26,0)*_xlfn.XLOOKUP($I109,Assumptions!$B$30:$B$50,Assumptions!$C$30:$C$50,0),0))) -> 60 | T109: =IF($C109<>"Organisation","",IF(OR($P109<>"",$Q109<>""),"Documented in source - midpoint of annual_intake_low/high",IF($I109="","No confirmed programme - modelled as zero",$N109&" base x "&TEXT(_xlfn.XLOOKUP($G109,Assumptions!$B$13:$B$26,Assumptions!$C$13:$C$26,0),"0.0#")&" sector x "&TEXT(_xlfn.XLOOKUP($I109,Assumptions!$B$30:$B$50,Assumptions!$C$30:$C$50,0),"0.0#")&" mechanism"))) -> Mid base x 2.0 sector x 1.0 mechanism | U109: [C-Press] | V109: Medium | W109: inferred
A110: ORG_USB | B110: US Bancorp | C110: Organisation | D110: USA | E110: United States | F110: Other US metro | G110: Commercial / Retail Banking | H110: Regional / super-regional | I110: MECH_US_CONV | N110: Large | O110: inferred - coarse band, verify | S110: =IF($C110<>"Organisation","",IF(OR($P110<>"",$Q110<>""),IF($P110<>"",IF($Q110<>"",($P110+$Q110)/2,$P110),$Q110),ROUND(_xlfn.XLOOKUP($N110,Assumptions!$B$5:$B$9,Assumptions!$C$5:$C$9,0)*_xlfn.XLOOKUP($G110,Assumptions!$B$13:$B$26,Assumptions!$C$13:$C$26,0)*_xlfn.XLOOKUP($I110,Assumptions!$B$30:$B$50,Assumptions!$C$30:$C$50,0),0))) -> 120 | T110: =IF($C110<>"Organisation","",IF(OR($P110<>"",$Q110<>""),"Documented in source - midpoint of annual_intake_low/high",IF($I110="","No confirmed programme - modelled as zero",$N110&" base x "&TEXT(_xlfn.XLOOKUP($G110,Assumptions!$B$13:$B$26,Assumptions!$C$13:$C$26,0),"0.0#")&" sector x "&TEXT(_xlfn.XLOOKUP($I110,Assumptions!$B$30:$B$50,Assumptions!$C$30:$C$50,0),"0.0#")&" mechanism"))) -> Large base x 1.0 sector x 1.0 mechanism | U110: [Note] | V110: Low | W110: inferred
A111: ORG_PNC | B111: PNC | C111: Organisation | D111: USA | E111: United States | F111: Other US metro | G111: Commercial / Retail Banking | H111: Regional / super-regional | I111: MECH_US_CONV | J111: Development Program | N111: Large | O111: inferred - coarse band, verify | S111: =IF($C111<>"Organisation","",IF(OR($P111<>"",$Q111<>""),IF($P111<>"",IF($Q111<>"",($P111+$Q111)/2,$P111),$Q111),ROUND(_xlfn.XLOOKUP($N111,Assumptions!$B$5:$B$9,Assumptions!$C$5:$C$9,0)*_xlfn.XLOOKUP($G111,Assumptions!$B$13:$B$26,Assumptions!$C$13:$C$26,0)*_xlfn.XLOOKUP($I111,Assumptions!$B$30:$B$50,Assumptions!$C$30:$C$50,0),0))) -> 120 | T111: =IF($C111<>"Organisation","",IF(OR($P111<>"",$Q111<>""),"Documented in source - midpoint of annual_intake_low/high",IF($I111="","No confirmed programme - modelled as zero",$N111&" base x "&TEXT(_xlfn.XLOOKUP($G111,Assumptions!$B$13:$B$26,Assumptions!$C$13:$C$26,0),"0.0#")&" sector x "&TEXT(_xlfn.XLOOKUP($I111,Assumptions!$B$30:$B$50,Assumptions!$C$30:$C$50,0),"0.0#")&" mechanism"))) -> Large base x 1.0 sector x 1.0 mechanism | U111: [Note] | V111: Low | W111: inferred
A112: ORG_TFC | B112: Truist | C112: Organisation | D112: USA | E112: United States | F112: Charlotte | G112: Commercial / Retail Banking | H112: Regional / super-regional | I112: MECH_US_CONV | J112: Leadership Development Program | N112: Large | O112: inferred - coarse band, verify | S112: =IF($C112<>"Organisation","",IF(OR($P112<>"",$Q112<>""),IF($P112<>"",IF($Q112<>"",($P112+$Q112)/2,$P112),$Q112),ROUND(_xlfn.XLOOKUP($N112,Assumptions!$B$5:$B$9,Assumptions!$C$5:$C$9,0)*_xlfn.XLOOKUP($G112,Assumptions!$B$13:$B$26,Assumptions!$C$13:$C$26,0)*_xlfn.XLOOKUP($I112,Assumptions!$B$30:$B$50,Assumptions!$C$30:$C$50,0),0))) -> 120 | T112: =IF($C112<>"Organisation","",IF(OR($P112<>"",$Q112<>""),"Documented in source - midpoint of annual_intake_low/high",IF($I112="","No confirmed programme - modelled as zero",$N112&" base x "&TEXT(_xlfn.XLOOKUP($G112,Assumptions!$B$13:$B$26,Assumptions!$C$13:$C$26,0),"0.0#")&" sector x "&TEXT(_xlfn.XLOOKUP($I112,Assumptions!$B$30:$B$50,Assumptions!$C$30:$C$50,0),"0.0#")&" mechanism"))) -> Large base x 1.0 sector x 1.0 mechanism | U112: [Note] | V112: Low | W112: inferred
A113: ORG_COF | B113: Capital One | C113: Organisation | D113: USA | E113: United States | F113: Other US metro | G113: Commercial / Retail Banking | H113: Regional / super-regional | I113: MECH_US_CONV | J113: Analyst / rotational | N113: Large | O113: inferred - coarse band, verify | S113: =IF($C113<>"Organisation","",IF(OR($P113<>"",$Q113<>""),IF($P113<>"",IF($Q113<>"",($P113+$Q113)/2,$P113),$Q113),ROUND(_xlfn.XLOOKUP($N113,Assumptions!$B$5:$B$9,Assumptions!$C$5:$C$9,0)*_xlfn.XLOOKUP($G113,Assumptions!$B$13:$B$26,Assumptions!$C$13:$C$26,0)*_xlfn.XLOOKUP($I113,Assumptions!$B$30:$B$50,Assumptions!$C$30:$C$50,0),0))) -> 120 | T113: =IF($C113<>"Organisation","",IF(OR($P113<>"",$Q113<>""),"Documented in source - midpoint of annual_intake_low/high",IF($I113="","No confirmed programme - modelled as zero",$N113&" base x "&TEXT(_xlfn.XLOOKUP($G113,Assumptions!$B$13:$B$26,Assumptions!$C$13:$C$26,0),"0.0#")&" sector x "&TEXT(_xlfn.XLOOKUP($I113,Assumptions!$B$30:$B$50,Assumptions!$C$30:$C$50,0),"0.0#")&" mechanism"))) -> Large base x 1.0 sector x 1.0 mechanism | U113: [Note] | V113: Low | W113: inferred
A114: ORG_FITB | B114: Fifth Third | C114: Organisation | D114: USA | E114: United States | F114: Other US metro | G114: Commercial / Retail Banking | H114: Regional / super-regional | I114: MECH_US_CONV | N114: Mid | O114: inferred - coarse band, verify | S114: =IF($C114<>"Organisation","",IF(OR($P114<>"",$Q114<>""),IF($P114<>"",IF($Q114<>"",($P114+$Q114)/2,$P114),$Q114),ROUND(_xlfn.XLOOKUP($N114,Assumptions!$B$5:$B$9,Assumptions!$C$5:$C$9,0)*_xlfn.XLOOKUP($G114,Assumptions!$B$13:$B$26,Assumptions!$C$13:$C$26,0)*_xlfn.XLOOKUP($I114,Assumptions!$B$30:$B$50,Assumptions!$C$30:$C$50,0),0))) -> 30 | T114: =IF($C114<>"Organisation","",IF(OR($P114<>"",$Q114<>""),"Documented in source - midpoint of annual_intake_low/high",IF($I114="","No confirmed programme - modelled as zero",$N114&" base x "&TEXT(_xlfn.XLOOKUP($G114,Assumptions!$B$13:$B$26,Assumptions!$C$13:$C$26,0),"0.0#")&" sector x "&TEXT(_xlfn.XLOOKUP($I114,Assumptions!$B$30:$B$50,Assumptions!$C$30:$C$50,0),"0.0#")&" mechanism"))) -> Mid base x 1.0 sector x 1.0 mechanism | U114: [Note] | V114: Low | W114: inferred
A115: ORG_MTB | B115: M&T Bank | C115: Organisation | D115: USA | E115: United States | F115: Other US metro | G115: Commercial / Retail Banking | H115: Regional / super-regional | I115: MECH_US_CONV | N115: Mid | O115: inferred - coarse band, verify | S115: =IF($C115<>"Organisation","",IF(OR($P115<>"",$Q115<>""),IF($P115<>"",IF($Q115<>"",($P115+$Q115)/2,$P115),$Q115),ROUND(_xlfn.XLOOKUP($N115,Assumptions!$B$5:$B$9,Assumptions!$C$5:$C$9,0)*_xlfn.XLOOKUP($G115,Assumptions!$B$13:$B$26,Assumptions!$C$13:$C$26,0)*_xlfn.XLOOKUP($I115,Assumptions!$B$30:$B$50,Assumptions!$C$30:$C$50,0),0))) -> 30 | T115: =IF($C115<>"Organisation","",IF(OR($P115<>"",$Q115<>""),"Documented in source - midpoint of annual_intake_low/high",IF($I115="","No confirmed programme - modelled as zero",$N115&" base x "&TEXT(_xlfn.XLOOKUP($G115,Assumptions!$B$13:$B$26,Assumptions!$C$13:$C$26,0),"0.0#")&" sector x "&TEXT(_xlfn.XLOOKUP($I115,Assumptions!$B$30:$B$50,Assumptions!$C$30:$C$50,0),"0.0#")&" mechanism"))) -> Mid base x 1.0 sector x 1.0 mechanism | U115: [Note] | V115: Low | W115: inferred
A116: ORG_RF | B116: Regions Financial | C116: Organisation | D116: USA | E116: United States | F116: Other US metro | G116: Commercial / Retail Banking | H116: Regional / super-regional | I116: MECH_US_CONV | N116: Mid | O116: inferred - coarse band, verify | S116: =IF($C116<>"Organisation","",IF(OR($P116<>"",$Q116<>""),IF($P116<>"",IF($Q116<>"",($P116+$Q116)/2,$P116),$Q116),ROUND(_xlfn.XLOOKUP($N116,Assumptions!$B$5:$B$9,Assumptions!$C$5:$C$9,0)*_xlfn.XLOOKUP($G116,Assumptions!$B$13:$B$26,Assumptions!$C$13:$C$26,0)*_xlfn.XLOOKUP($I116,Assumptions!$B$30:$B$50,Assumptions!$C$30:$C$50,0),0))) -> 30 | T116: =IF($C116<>"Organisation","",IF(OR($P116<>"",$Q116<>""),"Documented in source - midpoint of annual_intake_low/high",IF($I116="","No confirmed programme - modelled as zero",$N116&" base x "&TEXT(_xlfn.XLOOKUP($G116,Assumptions!$B$13:$B$26,Assumptions!$C$13:$C$26,0),"0.0#")&" sector x "&TEXT(_xlfn.XLOOKUP($I116,Assumptions!$B$30:$B$50,Assumptions!$C$30:$C$50,0),"0.0#")&" mechanism"))) -> Mid base x 1.0 sector x 1.0 mechanism | U116: [Note] | V116: Low | W116: inferred
A117: ORG_KEY | B117: KeyCorp | C117: Organisation | D117: USA | E117: United States | F117: Other US metro | G117: Commercial / Retail Banking | H117: Regional / super-regional | I117: MECH_US_CONV | N117: Mid | O117: inferred - coarse band, verify | S117: =IF($C117<>"Organisation","",IF(OR($P117<>"",$Q117<>""),IF($P117<>"",IF($Q117<>"",($P117+$Q117)/2,$P117),$Q117),ROUND(_xlfn.XLOOKUP($N117,Assumptions!$B$5:$B$9,Assumptions!$C$5:$C$9,0)*_xlfn.XLOOKUP($G117,Assumptions!$B$13:$B$26,Assumptions!$C$13:$C$26,0)*_xlfn.XLOOKUP($I117,Assumptions!$B$30:$B$50,Assumptions!$C$30:$C$50,0),0))) -> 30 | T117: =IF($C117<>"Organisation","",IF(OR($P117<>"",$Q117<>""),"Documented in source - midpoint of annual_intake_low/high",IF($I117="","No confirmed programme - modelled as zero",$N117&" base x "&TEXT(_xlfn.XLOOKUP($G117,Assumptions!$B$13:$B$26,Assumptions!$C$13:$C$26,0),"0.0#")&" sector x "&TEXT(_xlfn.XLOOKUP($I117,Assumptions!$B$30:$B$50,Assumptions!$C$30:$C$50,0),"0.0#")&" mechanism"))) -> Mid base x 1.0 sector x 1.0 mechanism | U117: [Note] | V117: Low | W117: inferred
A118: ORG_CFG | B118: Citizens Financial | C118: Organisation | D118: USA | E118: United States | F118: Other US metro | G118: Commercial / Retail Banking | H118: Regional / super-regional | I118: MECH_US_CONV | N118: Mid | O118: inferred - coarse band, verify | S118: =IF($C118<>"Organisation","",IF(OR($P118<>"",$Q118<>""),IF($P118<>"",IF($Q118<>"",($P118+$Q118)/2,$P118),$Q118),ROUND(_xlfn.XLOOKUP($N118,Assumptions!$B$5:$B$9,Assumptions!$C$5:$C$9,0)*_xlfn.XLOOKUP($G118,Assumptions!$B$13:$B$26,Assumptions!$C$13:$C$26,0)*_xlfn.XLOOKUP($I118,Assumptions!$B$30:$B$50,Assumptions!$C$30:$C$50,0),0))) -> 30 | T118: =IF($C118<>"Organisation","",IF(OR($P118<>"",$Q118<>""),"Documented in source - midpoint of annual_intake_low/high",IF($I118="","No confirmed programme - modelled as zero",$N118&" base x "&TEXT(_xlfn.XLOOKUP($G118,Assumptions!$B$13:$B$26,Assumptions!$C$13:$C$26,0),"0.0#")&" sector x "&TEXT(_xlfn.XLOOKUP($I118,Assumptions!$B$30:$B$50,Assumptions!$C$30:$C$50,0),"0.0#")&" mechanism"))) -> Mid base x 1.0 sector x 1.0 mechanism | U118: [Note] | V118: Low | W118: inferred
A119: ORG_BNY | B119: BNY | C119: Organisation | D119: USA | E119: United States | F119: New York | G119: Custodian / Asset Servicing / Fund Administration | H119: Custodian | I119: MECH_US_CONV | J119: 24-month Analyst Program | K119: 24 | N119: Large | O119: inferred - coarse band, verify | S119: =IF($C119<>"Organisation","",IF(OR($P119<>"",$Q119<>""),IF($P119<>"",IF($Q119<>"",($P119+$Q119)/2,$P119),$Q119),ROUND(_xlfn.XLOOKUP($N119,Assumptions!$B$5:$B$9,Assumptions!$C$5:$C$9,0)*_xlfn.XLOOKUP($G119,Assumptions!$B$13:$B$26,Assumptions!$C$13:$C$26,0)*_xlfn.XLOOKUP($I119,Assumptions!$B$30:$B$50,Assumptions!$C$30:$C$50,0),0))) -> 180 | T119: =IF($C119<>"Organisation","",IF(OR($P119<>"",$Q119<>""),"Documented in source - midpoint of annual_intake_low/high",IF($I119="","No confirmed programme - modelled as zero",$N119&" base x "&TEXT(_xlfn.XLOOKUP($G119,Assumptions!$B$13:$B$26,Assumptions!$C$13:$C$26,0),"0.0#")&" sector x "&TEXT(_xlfn.XLOOKUP($I119,Assumptions!$B$30:$B$50,Assumptions!$C$30:$C$50,0),"0.0#")&" mechanism"))) -> Large base x 1.5 sector x 1.0 mechanism | U119: [C-Official] | V119: High | W119: inferred
A120: ORG_STT | B120: State Street | C120: Organisation | D120: USA | E120: United States | F120: Boston | G120: Custodian / Asset Servicing / Fund Administration | H120: Custodian | I120: MECH_US_CONV | J120: Professional Development Program (PDP) + Summer Analyst | N120: Large | O120: inferred - coarse band, verify | S120: =IF($C120<>"Organisation","",IF(OR($P120<>"",$Q120<>""),IF($P120<>"",IF($Q120<>"",($P120+$Q120)/2,$P120),$Q120),ROUND(_xlfn.XLOOKUP($N120,Assumptions!$B$5:$B$9,Assumptions!$C$5:$C$9,0)*_xlfn.XLOOKUP($G120,Assumptions!$B$13:$B$26,Assumptions!$C$13:$C$26,0)*_xlfn.XLOOKUP($I120,Assumptions!$B$30:$B$50,Assumptions!$C$30:$C$50,0),0))) -> 180 | T120: =IF($C120<>"Organisation","",IF(OR($P120<>"",$Q120<>""),"Documented in source - midpoint of annual_intake_low/high",IF($I120="","No confirmed programme - modelled as zero",$N120&" base x "&TEXT(_xlfn.XLOOKUP($G120,Assumptions!$B$13:$B$26,Assumptions!$C$13:$C$26,0),"0.0#")&" sector x "&TEXT(_xlfn.XLOOKUP($I120,Assumptions!$B$30:$B$50,Assumptions!$C$30:$C$50,0),"0.0#")&" mechanism"))) -> Large base x 1.5 sector x 1.0 mechanism | U120: [C-Official] | V120: High | W120: inferred
A121: ORG_NTRS | B121: Northern Trust | C121: Organisation | D121: USA | E121: United States | F121: Chicago | G121: Custodian / Asset Servicing / Fund Administration | H121: Custodian | I121: MECH_US_CONV | J121: Analyst Development Program | K121: 12-27 | N121: Large | O121: inferred - coarse band, verify | S121: =IF($C121<>"Organisation","",IF(OR($P121<>"",$Q121<>""),IF($P121<>"",IF($Q121<>"",($P121+$Q121)/2,$P121),$Q121),ROUND(_xlfn.XLOOKUP($N121,Assumptions!$B$5:$B$9,Assumptions!$C$5:$C$9,0)*_xlfn.XLOOKUP($G121,Assumptions!$B$13:$B$26,Assumptions!$C$13:$C$26,0)*_xlfn.XLOOKUP($I121,Assumptions!$B$30:$B$50,Assumptions!$C$30:$C$50,0),0))) -> 180 | T121: =IF($C121<>"Organisation","",IF(OR($P121<>"",$Q121<>""),"Documented in source - midpoint of annual_intake_low/high",IF($I121="","No confirmed programme - modelled as zero",$N121&" base x "&TEXT(_xlfn.XLOOKUP($G121,Assumptions!$B$13:$B$26,Assumptions!$C$13:$C$26,0),"0.0#")&" sector x "&TEXT(_xlfn.XLOOKUP($I121,Assumptions!$B$30:$B$50,Assumptions!$C$30:$C$50,0),"0.0#")&" mechanism"))) -> Large base x 1.5 sector x 1.0 mechanism | U121: [C-Official] | V121: High | W121: inferred
A122: ORG_BLK | B122: BlackRock | C122: Organisation | D122: USA | E122: United States | F122: New York | G122: Investment / Asset Management | H122: Tier 1 | I122: MECH_US_CONV | J122: 2-year Analyst / Rotational | K122: 24 | N122: Large | O122: inferred - coarse band, verify | S122: =IF($C122<>"Organisation","",IF(OR($P122<>"",$Q122<>""),IF($P122<>"",IF($Q122<>"",($P122+$Q122)/2,$P122),$Q122),ROUND(_xlfn.XLOOKUP($N122,Assumptions!$B$5:$B$9,Assumptions!$C$5:$C$9,0)*_xlfn.XLOOKUP($G122,Assumptions!$B$13:$B$26,Assumptions!$C$13:$C$26,0)*_xlfn.XLOOKUP($I122,Assumptions!$B$30:$B$50,Assumptions!$C$30:$C$50,0),0))) -> 96 | T122: =IF($C122<>"Organisation","",IF(OR($P122<>"",$Q122<>""),"Documented in source - midpoint of annual_intake_low/high",IF($I122="","No confirmed programme - modelled as zero",$N122&" base x "&TEXT(_xlfn.XLOOKUP($G122,Assumptions!$B$13:$B$26,Assumptions!$C$13:$C$26,0),"0.0#")&" sector x "&TEXT(_xlfn.XLOOKUP($I122,Assumptions!$B$30:$B$50,Assumptions!$C$30:$C$50,0),"0.0#")&" mechanism"))) -> Large base x 0.8 sector x 1.0 mechanism | U122: [C-Official] | V122: High | W122: inferred
A123: ORG_VAN | B123: Vanguard | C123: Organisation | D123: USA | E123: United States | F123: Philadelphia area | G123: Investment / Asset Management | H123: Tier 1 | I123: MECH_US_CONV | J123: College to Corporate Internship / development programs | N123: Large | O123: inferred - coarse band, verify | S123: =IF($C123<>"Organisation","",IF(OR($P123<>"",$Q123<>""),IF($P123<>"",IF($Q123<>"",($P123+$Q123)/2,$P123),$Q123),ROUND(_xlfn.XLOOKUP($N123,Assumptions!$B$5:$B$9,Assumptions!$C$5:$C$9,0)*_xlfn.XLOOKUP($G123,Assumptions!$B$13:$B$26,Assumptions!$C$13:$C$26,0)*_xlfn.XLOOKUP($I123,Assumptions!$B$30:$B$50,Assumptions!$C$30:$C$50,0),0))) -> 96 | T123: =IF($C123<>"Organisation","",IF(OR($P123<>"",$Q123<>""),"Documented in source - midpoint of annual_intake_low/high",IF($I123="","No confirmed programme - modelled as zero",$N123&" base x "&TEXT(_xlfn.XLOOKUP($G123,Assumptions!$B$13:$B$26,Assumptions!$C$13:$C$26,0),"0.0#")&" sector x "&TEXT(_xlfn.XLOOKUP($I123,Assumptions!$B$30:$B$50,Assumptions!$C$30:$C$50,0),"0.0#")&" mechanism"))) -> Large base x 0.8 sector x 1.0 mechanism | U123: [C-Press] | V123: Medium | W123: inferred
A124: ORG_FID | B124: Fidelity Investments | C124: Organisation | D124: USA | E124: United States | F124: Boston | G124: Investment / Asset Management | H124: Tier 1 | I124: MECH_US_CONV | J124: Summer Analyst | N124: Large | O124: inferred - coarse band, verify | S124: =IF($C124<>"Organisation","",IF(OR($P124<>"",$Q124<>""),IF($P124<>"",IF($Q124<>"",($P124+$Q124)/2,$P124),$Q124),ROUND(_xlfn.XLOOKUP($N124,Assumptions!$B$5:$B$9,Assumptions!$C$5:$C$9,0)*_xlfn.XLOOKUP($G124,Assumptions!$B$13:$B$26,Assumptions!$C$13:$C$26,0)*_xlfn.XLOOKUP($I124,Assumptions!$B$30:$B$50,Assumptions!$C$30:$C$50,0),0))) -> 96 | T124: =IF($C124<>"Organisation","",IF(OR($P124<>"",$Q124<>""),"Documented in source - midpoint of annual_intake_low/high",IF($I124="","No confirmed programme - modelled as zero",$N124&" base x "&TEXT(_xlfn.XLOOKUP($G124,Assumptions!$B$13:$B$26,Assumptions!$C$13:$C$26,0),"0.0#")&" sector x "&TEXT(_xlfn.XLOOKUP($I124,Assumptions!$B$30:$B$50,Assumptions!$C$30:$C$50,0),"0.0#")&" mechanism"))) -> Large base x 0.8 sector x 1.0 mechanism | U124: [C-Press] | V124: Medium | W124: inferred
A125: ORG_TROW | B125: T. Rowe Price | C125: Organisation | D125: USA | E125: United States | F125: Other US metro | G125: Investment / Asset Management | H125: Tier 1 | I125: MECH_US_CONV | J125: Summer Analyst; INPAC Rotational | N125: Large | O125: inferred - coarse band, verify | S125: =IF($C125<>"Organisation","",IF(OR($P125<>"",$Q125<>""),IF($P125<>"",IF($Q125<>"",($P125+$Q125)/2,$P125),$Q125),ROUND(_xlfn.XLOOKUP($N125,Assumptions!$B$5:$B$9,Assumptions!$C$5:$C$9,0)*_xlfn.XLOOKUP($G125,Assumptions!$B$13:$B$26,Assumptions!$C$13:$C$26,0)*_xlfn.XLOOKUP($I125,Assumptions!$B$30:$B$50,Assumptions!$C$30:$C$50,0),0))) -> 96 | T125: =IF($C125<>"Organisation","",IF(OR($P125<>"",$Q125<>""),"Documented in source - midpoint of annual_intake_low/high",IF($I125="","No confirmed programme - modelled as zero",$N125&" base x "&TEXT(_xlfn.XLOOKUP($G125,Assumptions!$B$13:$B$26,Assumptions!$C$13:$C$26,0),"0.0#")&" sector x "&TEXT(_xlfn.XLOOKUP($I125,Assumptions!$B$30:$B$50,Assumptions!$C$30:$C$50,0),"0.0#")&" mechanism"))) -> Large base x 0.8 sector x 1.0 mechanism | U125: [C-Official] | V125: High | W125: inferred
A126: ORG_PIMCO | B126: PIMCO | C126: Organisation | D126: USA | E126: United States | F126: Los Angeles | G126: Investment / Asset Management | H126: Tier 2 | I126: MECH_US_CONV | J126: Analyst | N126: Mid | O126: inferred - coarse band, verify | S126: =IF($C126<>"Organisation","",IF(OR($P126<>"",$Q126<>""),IF($P126<>"",IF($Q126<>"",($P126+$Q126)/2,$P126),$Q126),ROUND(_xlfn.XLOOKUP($N126,Assumptions!$B$5:$B$9,Assumptions!$C$5:$C$9,0)*_xlfn.XLOOKUP($G126,Assumptions!$B$13:$B$26,Assumptions!$C$13:$C$26,0)*_xlfn.XLOOKUP($I126,Assumptions!$B$30:$B$50,Assumptions!$C$30:$C$50,0),0))) -> 24 | T126: =IF($C126<>"Organisation","",IF(OR($P126<>"",$Q126<>""),"Documented in source - midpoint of annual_intake_low/high",IF($I126="","No confirmed programme - modelled as zero",$N126&" base x "&TEXT(_xlfn.XLOOKUP($G126,Assumptions!$B$13:$B$26,Assumptions!$C$13:$C$26,0),"0.0#")&" sector x "&TEXT(_xlfn.XLOOKUP($I126,Assumptions!$B$30:$B$50,Assumptions!$C$30:$C$50,0),"0.0#")&" mechanism"))) -> Mid base x 0.8 sector x 1.0 mechanism | U126: [Note] | V126: Low | W126: inferred
A127: ORG_CG | B127: Capital Group | C127: Organisation | D127: USA | E127: United States | F127: Los Angeles | G127: Investment / Asset Management | H127: Tier 2 | I127: MECH_US_CONV | J127: Associate program | N127: Mid | O127: inferred - coarse band, verify | S127: =IF($C127<>"Organisation","",IF(OR($P127<>"",$Q127<>""),IF($P127<>"",IF($Q127<>"",($P127+$Q127)/2,$P127),$Q127),ROUND(_xlfn.XLOOKUP($N127,Assumptions!$B$5:$B$9,Assumptions!$C$5:$C$9,0)*_xlfn.XLOOKUP($G127,Assumptions!$B$13:$B$26,Assumptions!$C$13:$C$26,0)*_xlfn.XLOOKUP($I127,Assumptions!$B$30:$B$50,Assumptions!$C$30:$C$50,0),0))) -> 24 | T127: =IF($C127<>"Organisation","",IF(OR($P127<>"",$Q127<>""),"Documented in source - midpoint of annual_intake_low/high",IF($I127="","No confirmed programme - modelled as zero",$N127&" base x "&TEXT(_xlfn.XLOOKUP($G127,Assumptions!$B$13:$B$26,Assumptions!$C$13:$C$26,0),"0.0#")&" sector x "&TEXT(_xlfn.XLOOKUP($I127,Assumptions!$B$30:$B$50,Assumptions!$C$30:$C$50,0),"0.0#")&" mechanism"))) -> Mid base x 0.8 sector x 1.0 mechanism | U127: [Note] | V127: Low | W127: inferred
A128: ORG_WELL | B128: Wellington Management | C128: Organisation | D128: USA | E128: United States | F128: Boston | G128: Investment / Asset Management | H128: Tier 2 | I128: MECH_US_CONV | N128: Mid | O128: inferred - coarse band, verify | S128: =IF($C128<>"Organisation","",IF(OR($P128<>"",$Q128<>""),IF($P128<>"",IF($Q128<>"",($P128+$Q128)/2,$P128),$Q128),ROUND(_xlfn.XLOOKUP($N128,Assumptions!$B$5:$B$9,Assumptions!$C$5:$C$9,0)*_xlfn.XLOOKUP($G128,Assumptions!$B$13:$B$26,Assumptions!$C$13:$C$26,0)*_xlfn.XLOOKUP($I128,Assumptions!$B$30:$B$50,Assumptions!$C$30:$C$50,0),0))) -> 24 | T128: =IF($C128<>"Organisation","",IF(OR($P128<>"",$Q128<>""),"Documented in source - midpoint of annual_intake_low/high",IF($I128="","No confirmed programme - modelled as zero",$N128&" base x "&TEXT(_xlfn.XLOOKUP($G128,Assumptions!$B$13:$B$26,Assumptions!$C$13:$C$26,0),"0.0#")&" sector x "&TEXT(_xlfn.XLOOKUP($I128,Assumptions!$B$30:$B$50,Assumptions!$C$30:$C$50,0),"0.0#")&" mechanism"))) -> Mid base x 0.8 sector x 1.0 mechanism | U128: [Note] | V128: Low | W128: inferred
A129: ORG_IVZ | B129: Invesco | C129: Organisation | D129: USA | E129: United States | F129: Other US metro | G129: Investment / Asset Management | H129: Tier 2 | I129: MECH_US_CONV | N129: Mid | O129: inferred - coarse band, verify | S129: =IF($C129<>"Organisation","",IF(OR($P129<>"",$Q129<>""),IF($P129<>"",IF($Q129<>"",($P129+$Q129)/2,$P129),$Q129),ROUND(_xlfn.XLOOKUP($N129,Assumptions!$B$5:$B$9,Assumptions!$C$5:$C$9,0)*_xlfn.XLOOKUP($G129,Assumptions!$B$13:$B$26,Assumptions!$C$13:$C$26,0)*_xlfn.XLOOKUP($I129,Assumptions!$B$30:$B$50,Assumptions!$C$30:$C$50,0),0))) -> 24 | T129: =IF($C129<>"Organisation","",IF(OR($P129<>"",$Q129<>""),"Documented in source - midpoint of annual_intake_low/high",IF($I129="","No confirmed programme - modelled as zero",$N129&" base x "&TEXT(_xlfn.XLOOKUP($G129,Assumptions!$B$13:$B$26,Assumptions!$C$13:$C$26,0),"0.0#")&" sector x "&TEXT(_xlfn.XLOOKUP($I129,Assumptions!$B$30:$B$50,Assumptions!$C$30:$C$50,0),"0.0#")&" mechanism"))) -> Mid base x 0.8 sector x 1.0 mechanism | U129: [Note] | V129: Low | W129: inferred
A130: ORG_BEN | B130: Franklin Templeton | C130: Organisation | D130: USA | E130: United States | F130: San Francisco Bay Area | G130: Investment / Asset Management | H130: Tier 2 | I130: MECH_US_CONV | N130: Mid | O130: inferred - coarse band, verify | S130: =IF($C130<>"Organisation","",IF(OR($P130<>"",$Q130<>""),IF($P130<>"",IF($Q130<>"",($P130+$Q130)/2,$P130),$Q130),ROUND(_xlfn.XLOOKUP($N130,Assumptions!$B$5:$B$9,Assumptions!$C$5:$C$9,0)*_xlfn.XLOOKUP($G130,Assumptions!$B$13:$B$26,Assumptions!$C$13:$C$26,0)*_xlfn.XLOOKUP($I130,Assumptions!$B$30:$B$50,Assumptions!$C$30:$C$50,0),0))) -> 24 | T130: =IF($C130<>"Organisation","",IF(OR($P130<>"",$Q130<>""),"Documented in source - midpoint of annual_intake_low/high",IF($I130="","No confirmed programme - modelled as zero",$N130&" base x "&TEXT(_xlfn.XLOOKUP($G130,Assumptions!$B$13:$B$26,Assumptions!$C$13:$C$26,0),"0.0#")&" sector x "&TEXT(_xlfn.XLOOKUP($I130,Assumptions!$B$30:$B$50,Assumptions!$C$30:$C$50,0),"0.0#")&" mechanism"))) -> Mid base x 0.8 sector x 1.0 mechanism | U130: [Note] | V130: Low | W130: inferred
A131: ORG_JHG | B131: Janus Henderson | C131: Organisation | D131: USA | E131: United States | F131: Other US metro | G131: Investment / Asset Management | H131: Tier 3 | I131: MECH_US_CONV | N131: Mid | O131: inferred - coarse band, verify | S131: =IF($C131<>"Organisation","",IF(OR($P131<>"",$Q131<>""),IF($P131<>"",IF($Q131<>"",($P131+$Q131)/2,$P131),$Q131),ROUND(_xlfn.XLOOKUP($N131,Assumptions!$B$5:$B$9,Assumptions!$C$5:$C$9,0)*_xlfn.XLOOKUP($G131,Assumptions!$B$13:$B$26,Assumptions!$C$13:$C$26,0)*_xlfn.XLOOKUP($I131,Assumptions!$B$30:$B$50,Assumptions!$C$30:$C$50,0),0))) -> 24 | T131: =IF($C131<>"Organisation","",IF(OR($P131<>"",$Q131<>""),"Documented in source - midpoint of annual_intake_low/high",IF($I131="","No confirmed programme - modelled as zero",$N131&" base x "&TEXT(_xlfn.XLOOKUP($G131,Assumptions!$B$13:$B$26,Assumptions!$C$13:$C$26,0),"0.0#")&" sector x "&TEXT(_xlfn.XLOOKUP($I131,Assumptions!$B$30:$B$50,Assumptions!$C$30:$C$50,0),"0.0#")&" mechanism"))) -> Mid base x 0.8 sector x 1.0 mechanism | U131: [Note] | V131: Low | W131: inferred
A132: ORG_MET | B132: MetLife | C132: Organisation | D132: USA | E132: United States | F132: New York | G132: Insurance | H132: Insurance - actuarial/finance track | I132: MECH_ACTUARIAL | J132: US Actuarial Development Program (ADP); early-career internships | N132: Large | O132: inferred - coarse band, verify | S132: =IF($C132<>"Organisation","",IF(OR($P132<>"",$Q132<>""),IF($P132<>"",IF($Q132<>"",($P132+$Q132)/2,$P132),$Q132),ROUND(_xlfn.XLOOKUP($N132,Assumptions!$B$5:$B$9,Assumptions!$C$5:$C$9,0)*_xlfn.XLOOKUP($G132,Assumptions!$B$13:$B$26,Assumptions!$C$13:$C$26,0)*_xlfn.XLOOKUP($I132,Assumptions!$B$30:$B$50,Assumptions!$C$30:$C$50,0),0))) -> 60 | T132: =IF($C132<>"Organisation","",IF(OR($P132<>"",$Q132<>""),"Documented in source - midpoint of annual_intake_low/high",IF($I132="","No confirmed programme - modelled as zero",$N132&" base x "&TEXT(_xlfn.XLOOKUP($G132,Assumptions!$B$13:$B$26,Assumptions!$C$13:$C$26,0),"0.0#")&" sector x "&TEXT(_xlfn.XLOOKUP($I132,Assumptions!$B$30:$B$50,Assumptions!$C$30:$C$50,0),"0.0#")&" mechanism"))) -> Large base x 1.0 sector x 0.5 mechanism | U132: [C-Official] | V132: High | W132: inferred
A133: ORG_PRU | B133: Prudential Financial | C133: Organisation | D133: USA | E133: United States | F133: Other US metro | G133: Insurance | H133: Insurance - actuarial/finance track | I133: MECH_ACTUARIAL | J133: Actuarial / finance programs | N133: Large | O133: inferred - coarse band, verify | S133: =IF($C133<>"Organisation","",IF(OR($P133<>"",$Q133<>""),IF($P133<>"",IF($Q133<>"",($P133+$Q133)/2,$P133),$Q133),ROUND(_xlfn.XLOOKUP($N133,Assumptions!$B$5:$B$9,Assumptions!$C$5:$C$9,0)*_xlfn.XLOOKUP($G133,Assumptions!$B$13:$B$26,Assumptions!$C$13:$C$26,0)*_xlfn.XLOOKUP($I133,Assumptions!$B$30:$B$50,Assumptions!$C$30:$C$50,0),0))) -> 60 | T133: =IF($C133<>"Organisation","",IF(OR($P133<>"",$Q133<>""),"Documented in source - midpoint of annual_intake_low/high",IF($I133="","No confirmed programme - modelled as zero",$N133&" base x "&TEXT(_xlfn.XLOOKUP($G133,Assumptions!$B$13:$B$26,Assumptions!$C$13:$C$26,0),"0.0#")&" sector x "&TEXT(_xlfn.XLOOKUP($I133,Assumptions!$B$30:$B$50,Assumptions!$C$30:$C$50,0),"0.0#")&" mechanism"))) -> Large base x 1.0 sector x 0.5 mechanism | U133: [C-Press] | V133: Medium | W133: inferred
A134: ORG_AIG | B134: AIG | C134: Organisation | D134: USA | E134: United States | F134: New York | G134: Insurance | H134: Insurance - actuarial/finance track | I134: MECH_ACTUARIAL | J134: Early Career Analyst / actuarial | N134: Large | O134: inferred - coarse band, verify | S134: =IF($C134<>"Organisation","",IF(OR($P134<>"",$Q134<>""),IF($P134<>"",IF($Q134<>"",($P134+$Q134)/2,$P134),$Q134),ROUND(_xlfn.XLOOKUP($N134,Assumptions!$B$5:$B$9,Assumptions!$C$5:$C$9,0)*_xlfn.XLOOKUP($G134,Assumptions!$B$13:$B$26,Assumptions!$C$13:$C$26,0)*_xlfn.XLOOKUP($I134,Assumptions!$B$30:$B$50,Assumptions!$C$30:$C$50,0),0))) -> 60 | T134: =IF($C134<>"Organisation","",IF(OR($P134<>"",$Q134<>""),"Documented in source - midpoint of annual_intake_low/high",IF($I134="","No confirmed programme - modelled as zero",$N134&" base x "&TEXT(_xlfn.XLOOKUP($G134,Assumptions!$B$13:$B$26,Assumptions!$C$13:$C$26,0),"0.0#")&" sector x "&TEXT(_xlfn.XLOOKUP($I134,Assumptions!$B$30:$B$50,Assumptions!$C$30:$C$50,0),"0.0#")&" mechanism"))) -> Large base x 1.0 sector x 0.5 mechanism | U134: [C-Official] | V134: High | W134: inferred
A135: ORG_CB | B135: Chubb | C135: Organisation | D135: USA | E135: United States | F135: Philadelphia area | G135: Insurance | H135: Insurance - actuarial/finance track | I135: MECH_ACTUARIAL | J135: Actuarial / underwriting | N135: Large | O135: inferred - coarse band, verify | S135: =IF($C135<>"Organisation","",IF(OR($P135<>"",$Q135<>""),IF($P135<>"",IF($Q135<>"",($P135+$Q135)/2,$P135),$Q135),ROUND(_xlfn.XLOOKUP($N135,Assumptions!$B$5:$B$9,Assumptions!$C$5:$C$9,0)*_xlfn.XLOOKUP($G135,Assumptions!$B$13:$B$26,Assumptions!$C$13:$C$26,0)*_xlfn.XLOOKUP($I135,Assumptions!$B$30:$B$50,Assumptions!$C$30:$C$50,0),0))) -> 60 | T135: =IF($C135<>"Organisation","",IF(OR($P135<>"",$Q135<>""),"Documented in source - midpoint of annual_intake_low/high",IF($I135="","No confirmed programme - modelled as zero",$N135&" base x "&TEXT(_xlfn.XLOOKUP($G135,Assumptions!$B$13:$B$26,Assumptions!$C$13:$C$26,0),"0.0#")&" sector x "&TEXT(_xlfn.XLOOKUP($I135,Assumptions!$B$30:$B$50,Assumptions!$C$30:$C$50,0),"0.0#")&" mechanism"))) -> Large base x 1.0 sector x 0.5 mechanism | U135: [C-Press] | V135: Medium | W135: inferred
A136: ORG_TRV | B136: Travelers | C136: Organisation | D136: USA | E136: United States | F136: Other US metro | G136: Insurance | H136: Insurance - actuarial/finance track | I136: MECH_ACTUARIAL | J136: Actuarial / analyst | N136: Large | O136: inferred - coarse band, verify | S136: =IF($C136<>"Organisation","",IF(OR($P136<>"",$Q136<>""),IF($P136<>"",IF($Q136<>"",($P136+$Q136)/2,$P136),$Q136),ROUND(_xlfn.XLOOKUP($N136,Assumptions!$B$5:$B$9,Assumptions!$C$5:$C$9,0)*_xlfn.XLOOKUP($G136,Assumptions!$B$13:$B$26,Assumptions!$C$13:$C$26,0)*_xlfn.XLOOKUP($I136,Assumptions!$B$30:$B$50,Assumptions!$C$30:$C$50,0),0))) -> 60 | T136: =IF($C136<>"Organisation","",IF(OR($P136<>"",$Q136<>""),"Documented in source - midpoint of annual_intake_low/high",IF($I136="","No confirmed programme - modelled as zero",$N136&" base x "&TEXT(_xlfn.XLOOKUP($G136,Assumptions!$B$13:$B$26,Assumptions!$C$13:$C$26,0),"0.0#")&" sector x "&TEXT(_xlfn.XLOOKUP($I136,Assumptions!$B$30:$B$50,Assumptions!$C$30:$C$50,0),"0.0#")&" mechanism"))) -> Large base x 1.0 sector x 0.5 mechanism | U136: [C-Press] | V136: Medium | W136: inferred
A137: ORG_LMUT | B137: Liberty Mutual | C137: Organisation | D137: USA | E137: United States | F137: Boston | G137: Insurance | H137: Insurance - actuarial/finance track | I137: MECH_ACTUARIAL | J137: Actuarial / finance | N137: Large | O137: inferred - coarse band, verify | S137: =IF($C137<>"Organisation","",IF(OR($P137<>"",$Q137<>""),IF($P137<>"",IF($Q137<>"",($P137+$Q137)/2,$P137),$Q137),ROUND(_xlfn.XLOOKUP($N137,Assumptions!$B$5:$B$9,Assumptions!$C$5:$C$9,0)*_xlfn.XLOOKUP($G137,Assumptions!$B$13:$B$26,Assumptions!$C$13:$C$26,0)*_xlfn.XLOOKUP($I137,Assumptions!$B$30:$B$50,Assumptions!$C$30:$C$50,0),0))) -> 60 | T137: =IF($C137<>"Organisation","",IF(OR($P137<>"",$Q137<>""),"Documented in source - midpoint of annual_intake_low/high",IF($I137="","No confirmed programme - modelled as zero",$N137&" base x "&TEXT(_xlfn.XLOOKUP($G137,Assumptions!$B$13:$B$26,Assumptions!$C$13:$C$26,0),"0.0#")&" sector x "&TEXT(_xlfn.XLOOKUP($I137,Assumptions!$B$30:$B$50,Assumptions!$C$30:$C$50,0),"0.0#")&" mechanism"))) -> Large base x 1.0 sector x 0.5 mechanism | U137: [C-Press] | V137: Medium | W137: inferred
...

Sheet Edges
A1: edge_id | B1: source_id | C1: target_id | D1: edge_type | E1: directed | F1: weight | G1: notes
A2: E0001 | B2: GEO_C_US | C2: GEO_R_USA | D2: PART_OF | E2: TRUE
A3: E0002 | B3: GEO_C_IN | C3: GEO_R_INDIA | D3: PART_OF | E3: TRUE
A4: E0003 | B4: GEO_C_CN | C4: GEO_R_CHINA | D4: PART_OF | E4: TRUE
A5: E0004 | B5: GEO_C_BR | C5: GEO_R_LATAM | D5: PART_OF | E5: TRUE
A6: E0005 | B6: GEO_C_MX | C6: GEO_R_LATAM | D6: PART_OF | E6: TRUE
A7: E0006 | B7: GEO_C_CO | C7: GEO_R_LATAM | D7: PART_OF | E7: TRUE
A8: E0007 | B8: GEO_C_CL | C8: GEO_R_LATAM | D8: PART_OF | E8: TRUE
A9: E0008 | B9: GEO_C_PE | C9: GEO_R_LATAM | D9: PART_OF | E9: TRUE
A10: E0009 | B10: GEO_C_AR | C10: GEO_R_LATAM | D10: PART_OF | E10: TRUE
A11: E0010 | B11: GEO_C_DE | C11: GEO_R_EUROPE | D11: PART_OF | E11: TRUE
A12: E0011 | B12: GEO_C_FR | C12: GEO_R_EUROPE | D12: PART_OF | E12: TRUE
A13: E0012 | B13: GEO_C_CH | C13: GEO_R_EUROPE | D13: PART_OF | E13: TRUE
... A318: E0455 | B318: ORG_LUFAX | C318: SEC_FINTECH | D318: IN_SECTOR | E318: TRUE
A319: E0457 | B319: ORG_JPM | C319: GEO_H_BLR | D319: LOCATED_IN | E319: TRUE | G319: India GCC site (Channel c)
A320: E0458 | B320: ORG_JPM | C320: GEO_H_HYD | D320: LOCATED_IN | E320: TRUE | G320: India GCC site (Channel c)
A321: E0459 | B321: ORG_JPM | C321: GEO_H_MUM | D321: LOCATED_IN | E321: TRUE | G321: India GCC site (Channel c)
A322: E0460 | B322: ORG_GS | C322: GEO_H_BLR | D322: LOCATED_IN | E322: TRUE | G322: India GCC site (Channel c)
A323: E0461 | B323: ORG_GS | C323: GEO_H_HYD | D323: LOCATED_IN | E323: TRUE | G323: India GCC site (Channel c)
A324: E0462 | B324: ORG_MS | C324: GEO_H_MUM | D324: LOCATED_IN | E324: TRUE | G324: India GCC site (Channel c)
A325: E0463 | B325: ORG_CITI | C325: GEO_H_MUM | D325: LOCATED_IN | E325: TRUE | G325: India GCC site (Channel c)
A326: E0464 | B326: ORG_HSBC | C326: GEO_H_INOTH | D326: LOCATED_IN | E326: TRUE | G326: India GCC site (Channel c)
A327: E0465 | B327: ORG_BARC | C327: GEO_H_INOTH | D327: LOCATED_IN | E327: TRUE | G327: India GCC site (Channel c)
A328: E0466 | B328: ORG_STAN | C328: GEO_H_INOTH | D328: LOCATED_IN | E328: TRUE | G328: India GCC site (Channel c)
A329: E0467 | B329: ORG_STT | C329: GEO_H_INOTH | D329: LOCATED_IN | E329: TRUE | G329: India GCC site (Channel c)
A330: E0468 | B330: ORG_NTRS | C330: GEO_H_INOTH | D330: LOCATED_IN | E330: TRUE | G330: India GCC site (Channel c)
... A342: E0544 | B342: ORG_TENCENTFIT | C342: ORG_CCB | D342: COMPETES_FOR_TALENT | E342: FALSE | G342: Fintech giants compete head-to-head with Big Four state banks for the same talent
A343: E0545 | B343: ORG_ITAU | C343: GEO_H_SAO | D343: LOCATED_IN | E343: TRUE
A344: E0546 | B344: ORG_ITAU | C344: SEC_COMM | D344: IN_SECTOR | E344: TRUE
A345: E0548 | B345: ORG_BRADESCO | C345: GEO_H_SAO | D345: LOCATED_IN | E345: TRUE
A346: E0549 | B346: ORG_BRADESCO | C346: SEC_COMM | D346: IN_SECTOR | E346: TRUE
A347: E0551 | B347: ORG_BB | C347: GEO_H_SAO | D347: LOCATED_IN | E347: TRUE
A348: E0552 | B348: ORG_BB | C348: SEC_COMM | D348: IN_SECTOR | E348: TRUE
A349: E0554 | B349: ORG_SANBR | C349: GEO_H_SAO | D349: LOCATED_IN | E349: TRUE
A350: E0555 | B350: ORG_SANBR | C350: SEC_COMM | D350: IN_SECTOR | E350: TRUE
A351: E0557 | B351: ORG_BTG | C351: GEO_H_SAO | D351: LOCATED_IN | E351: TRUE
A352: E0558 | B352: ORG_BTG | C352: SEC_IB_EB | D352: IN_SECTOR | E352: TRUE
A353: E0560 | B353: ORG_ENFORCE | C353: GEO_H_SAO | D353: LOCATED_IN | E353: TRUE
A354: E0561 | B354: ORG_ENFORCE | C354: SEC_NBFC | D354: IN_SECTOR | E354: TRUE
... A480: E0748 | B480: ORG_EIB | C480: SEC_POLICY | D480: IN_SECTOR | E480: TRUE
A481: E0750 | B481: ORG_BTG | C481: ORG_ENFORCE | D481: PARENT_OF | E481: TRUE | G481: Trainee programme sits at the subsidiary
A482: E0754 | B482: ORG_SAN | C482: ORG_SANBR | D482: PARENT_OF | E482: TRUE
A483: E0755 | B483: ORG_SAN | C483: ORG_SANCL | D483: PARENT_OF | E483: TRUE
A484: E0756 | B484: ORG_SAN | C484: ORG_SANAR | D484: PARENT_OF | E484: TRUE
A485: E0757 | B485: ORG_BBVA | C485: ORG_BBVAMX | D485: PARENT_OF | E485: TRUE
A486: E0758 | B486: ORG_BBVA | C486: ORG_BBVAPE | D486: PARENT_OF | E486: TRUE
A487: E0759 | B487: ORG_BBVA | C487: ORG_BBVAAR | D487: PARENT_OF | E487: TRUE
A488: E0760 | B488: ORG_CITI | C488: ORG_CITIBANAMEX | D488: PARENT_OF | E488: TRUE
A489: E0761 | B489: ORG_ICICI | C489: ORG_ISEC | D489: PARENT_OF | E489: TRUE
A490: E0762 | B490: ORG_AXIS | C490: ORG_AXISCAP | D490: PARENT_OF | E490: TRUE
A491: E0763 | B491: ORG_KOTAK | C491: ORG_KOTAKIB | D491: PARENT_OF | E491: TRUE
A492: E0764 | B492: ORG_JPM | C492: GEO_H_SAO | D492: LOCATED_IN | E492: TRUE | G492: Mixed model - São Paulo local analyst/intern (Drive the Future - Brazil) AND NY-based Global Private Bank LatAm Program [C-Press]
A493: E0766 | B493: ORG_CITI | C493: GEO_H_SAO | D493: LOCATED_IN | E493: TRUE | G493: São Paulo Full-Time Analyst (Banking; Markets with 4-week training); LATAM Commercial Banking Analyst [C-Official]
A494: E0768 | B494: ORG_GS | C494: GEO_H_SAO | D494: LOCATED_IN | E494: TRUE | G494: São Paulo participates in Americas New Analyst/Summer Analyst programme; no distinct Brazil brand [C-Press]
A495: E0770 | B495: ORG_MS | C495: GEO_H_SAO | D495: LOCATED_IN | E495: TRUE | G495: São Paulo internship programme (recurring cycles); office since 1997 [C-Official]
A496: E0772 | B496: ORG_JPM | C496: GEO_H_NYC | D496: OFFSHORE_RECRUITS_FOR | E496: TRUE | G496: NY-based Global Private Bank LatAm Program recruits LatAm-focused analysts into a US programme
A497: E0774 | B497: ORG_SAN | C497: GEO_H_SAO | D497: PLACES_GRADUATES_IN | E497: TRUE | G497: Santander CIB International Graduate Programme LatAm placement [C-Official]
A498: E0775 | B498: ORG_SAN | C498: GEO_H_MEX | D498: PLACES_GRADUATES_IN | E498: TRUE | G498: Santander CIB International Graduate Programme LatAm placement [C-Official]
A499: E0776 | B499: ORG_SAN | C499: GEO_H_SCL | D499: PLACES_GRADUATES_IN | E499: TRUE | G499: Santander CIB International Graduate Programme LatAm placement [C-Official]
A500: E0777 | B500: ORG_SAN | C500: GEO_H_BOG | D500: PLACES_GRADUATES_IN | E500: TRUE | G500: Santander CIB International Graduate Programme LatAm placement [C-Official]
A501: E0778 | B501: ORG_DB | C501: GEO_H_INOTH | D501: LOCATED_IN | E501: TRUE | G501: India GCC analyst [Note]
A502: E0780 | B502: ORG_DB | C502: GEO_H_CNOTH | D502: LOCATED_IN | E502: TRUE | G502: China operations - limited intake [Note]
A503: E0782 | B503: ORG_STT | C503: GEO_H_DUB | D503: LOCATED_IN | E503: TRUE | G503: Dublin GCC - asset-servicing / fund-administration graduate & co-op programmes [C-Official]
... A510: E0792 | B510: ORG_JPM | C510: GEO_H_LUX | D510: LOCATED_IN | E510: TRUE | G510: Luxembourg fund-administration graduate / co-op programmes [Note]
A511: E0794 | B511: GEO_H_UKOTH | C511: GEO_C_UK | D511: PART_OF | E511: TRUE
A512: E0795 | B512: GEO_H_EDI | C512: GEO_C_UK | D512: PART_OF | E512: TRUE
A513: E0796 | B513: GEO_H_LDS | C513: GEO_C_UK | D513: PART_OF | E513: TRUE
A514: E0797 | B514: GEO_H_GLA | C514: GEO_C_UK | D514: PART_OF | E514: TRUE
A515: E0798 | B515: GEO_H_MAN | C515: GEO_C_UK | D515: PART_OF | E515: TRUE
A516: E0799 | B516: GEO_H_BHX | C516: GEO_C_UK | D516: PART_OF | E516: TRUE
A517: E0800 | B517: GEO_H_BRS | C517: GEO_C_UK | D517: PART_OF | E517: TRUE
A518: E0801 | B518: GEO_H_BFS | C518: GEO_C_UK | D518: PART_OF | E518: TRUE
A519: E0804 | B519: ORG_UK_BOE | C519: GEO_H_LON | D519: LOCATED_IN | E519: TRUE
A520: E0805 | B520: ORG_UK_BOE | C520: SEC_CB | D520: IN_SECTOR | E520: TRUE
A521: E0807 | B521: ORG_UK_BOE | C521: GEO_H_LDS | D521: LOCATED_IN | E521: TRUE | G521: Additional UK site for this programme
A522: E0808 | B522: ORG_UK_FCA | C522: GEO_H_LON | D522: LOCATED_IN | E522: TRUE
A523: E0809 | B523: ORG_UK_FCA | C523: SEC_CB | D523: IN_SECTOR | E523: TRUE
A524: E0811 | B524: ORG_UK_FCA | C524: GEO_H_LDS | D524: LOCATED_IN | E524: TRUE | G524: Additional UK site for this programme
A525: E0812 | B525: ORG_UK_FCA | C525: GEO_H_EDI | D525: LOCATED_IN | E525: TRUE | G525: Additional UK site for this programme
A526: E0813 | B526: ORG_UK_BBB | C526: GEO_H_UKOTH | D526: LOCATED_IN | E526: TRUE
A527: E0814 | B527: ORG_UK_BBB | C527: SEC_POLICY | D527: IN_SECTOR | E527: TRUE
A528: E0816 | B528: ORG_UK_LLOYDSBG | C528: GEO_H_LON | D528: LOCATED_IN | E528: TRUE
A529: E0817 | B529: ORG_UK_LLOYDSBG | C529: SEC_COMM | D529: IN_SECTOR | E529: TRUE
A530: E0819 | B530: ORG_UK_LLOYDSBG | C530: GEO_H_EDI | D530: LOCATED_IN | E530: TRUE | G530: Additional UK site for this programme
A531: E0820 | B531: ORG_UK_LLOYDSBG | C531: GEO_H_LDS | D531: LOCATED_IN | E531: TRUE | G531: Additional UK site for this programme
A532: E0821 | B532: ORG_UK_LLOYDSBG | C532: GEO_H_BRS | D532: LOCATED_IN | E532: TRUE | G532: Additional UK site for this programme
A533: E0822 | B533: ORG_UK_LLOYDSBG | C533: GEO_H_MAN | D533: LOCATED_IN | E533: TRUE | G533: Additional UK site for this programme
A534: E0823 | B534: ORG_UK_NATWEST | C534: GEO_H_EDI | D534: LOCATED_IN | E534: TRUE
A535: E0824 | B535: ORG_UK_NATWEST | C535: SEC_COMM | D535: IN_SECTOR | E535: TRUE
A536: E0826 | B536: ORG_UK_NATWEST | C536: GEO_H_LON | D536: LOCATED_IN | E536: TRUE | G536: Additional UK site for this programme
A537: E0827 | B537: ORG_UK_NATWEST | C537: GEO_H_MAN | D537: LOCATED_IN | E537: TRUE | G537: Additional UK site for this programme
A538: E0828 | B538: ORG_UK_SANUK | C538: GEO_H_LON | D538: LOCATED_IN | E538: TRUE
A539: E0829 | B539: ORG_UK_SANUK | C539: SEC_COMM | D539: IN_SECTOR | E539: TRUE
A540: E0831 | B540: ORG_UK_NATIONWIDE | C540: GEO_H_UKOTH | D540: LOCATED_IN | E540: TRUE
A541: E0832 | B541: ORG_UK_NATIONWIDE | C541: SEC_COMM | D541: IN_SECTOR | E541: TRUE
A542: E0834 | B542: ORG_UK_TSB | C542: GEO_H_EDI | D542: LOCATED_IN | E542: TRUE
A543: E0835 | B543: ORG_UK_TSB | C543: SEC_COMM | D543: IN_SECTOR | E543: TRUE
A544: E0837 | B544: ORG_UK_VMUK | C544: GEO_H_GLA | D544: LOCATED_IN | E544: TRUE
A545: E0838 | B545: ORG_UK_VMUK | C545: SEC_COMM | D545: IN_SECTOR | E545: TRUE
A546: E0840 | B546: ORG_UK_METRO | C546: GEO_H_LON | D546: LOCATED_IN | E546: TRUE
...

Sheet Vocabulary
A1: Field / vocabulary | B1: Allowed value | C1: Meaning
A2: node_type | B2: Region | C2: One of the five source regions (plus 'Other' for out-of-scope home markets)
A3: node_type | B3: Country | C3: National market; PART_OF a Region
A4: node_type | B4: Hub | C4: City / metro financial hub; PART_OF a Country
A5: node_type | B5: Organisation | C5: Employer node - the knowledge-inflow node in the simulator
A6: node_type | B6: Sector | C6: Sector taxonomy node
A7: node_type | B7: Mechanism | C7: Entry mechanism (carries cycle_timing and lead_time_months)
A8: node_type | B8: TalentPool | C8: Campus system or recruitment intermediary supplying graduates
A9: edge_type | B9: PART_OF | C9: Geographic hierarchy: Hub -> Country -> Region
A10: edge_type | B10: LOCATED_IN | C10: Organisation has a graduate-recruiting site in this hub (multiple per org = multinational)
A11: edge_type | B11: IN_SECTOR | C11: Organisation belongs to this sector
A12: edge_type | B12: RECRUITS_VIA | C12: Organisation uses this entry mechanism (inherit lead_time_months from the mechanism node)
... A41: intake_estimate_central | B41: Whole number, or blank for non-organisation rows | C41: Zero means no programme, NOT unknown

Sheet Summary
A1: Graph dataset summary
A2: All figures below are formulas over the Nodes and Edges sheets.
A4: NODES BY TYPE | B4: Count
A5: Region | B5: =COUNTIF(tblNodes[node_type],$A5) -> 9
A6: Country | B6: =COUNTIF(tblNodes[node_type],$A6) -> 27
A7: Hub | B7: =COUNTIF(tblNodes[node_type],$A7) -> 57
A8: Organisation | B8: =COUNTIF(tblNodes[node_type],$A8) -> 298
A9: Sector | B9: =COUNTIF(tblNodes[node_type],$A9) -> 14
A10: Mechanism (removed at user request) | B10: =COUNTIF(tblNodes[node_type],$A10) -> 0
A11: TalentPool (removed at user request) | B11: =COUNTIF(tblNodes[node_type],$A11) -> 0
A12: Total nodes | B12: =COUNTA(tblNodes[node_id]) -> 405
A14: ORGANISATIONS BY REGION | B14: Count | C14: Distinct hubs | D14: Est. annual intake
A15: USA | B15: =COUNTIFS(tblNodes[node_type],"Organisation",tblNodes[region],$A15) -> 67 | C15: =COUNTIFS(tblNodes[node_type],"Hub",tblNodes[region],$A15) -> 9 | D15: =SUMIFS(tblNodes[intake_estimate_central],tblNodes[node_type],"Organisation",tblNodes[region],$A15) -> 10579
A16: India | B16: =COUNTIFS(tblNodes[node_type],"Organisation",tblNodes[region],$A16) -> 23 | C16: =COUNTIFS(tblNodes[node_type],"Hub",tblNodes[region],$A16) -> 4 | D16: =SUMIFS(tblNodes[intake_estimate_central],tblNodes[node_type],"Organisation",tblNodes[region],$A16) -> 5837
A17: China | B17: =COUNTIFS(tblNodes[node_type],"Organisation",tblNodes[region],$A17) -> 34 | C17: =COUNTIFS(tblNodes[node_type],"Hub",tblNodes[region],$A17) -> 5 | D17: =SUMIFS(tblNodes[intake_estimate_central],tblNodes[node_type],"Organisation",tblNodes[region],$A17) -> 17460
A18: Latin America | B18: =COUNTIFS(tblNodes[node_type],"Organisation",tblNodes[region],$A18) -> 25 | C18: =COUNTIFS(tblNodes[node_type],"Hub",tblNodes[region],$A18) -> 7 | D18: =SUMIFS(tblNodes[intake_estimate_central],tblNodes[node_type],"Organisation",tblNodes[region],$A18) -> 3183
A19: Continental Europe | B19: =COUNTIFS(tblNodes[node_type],"Organisation",tblNodes[region],$A19) -> 44 | C19: =COUNTIFS(tblNodes[node_type],"Hub",tblNodes[region],$A19) -> 15 | D19: =SUMIFS(tblNodes[intake_estimate_central],tblNodes[node_type],"Organisation",tblNodes[region],$A19) -> 8187
A20: United Kingdom | B20: =COUNTIFS(tblNodes[node_type],"Organisation",tblNodes[region],$A20) -> 52 | C20: =COUNTIFS(tblNodes[node_type],"Hub",tblNodes[region],$A20) -> 9 | D20: =SUMIFS(tblNodes[intake_estimate_central],tblNodes[node_type],"Organisation",tblNodes[region],$A20) -> 7268
A21: Asia-Pacific (ex-China) | B21: =COUNTIFS(tblNodes[node_type],"Organisation",tblNodes[region],$A21) -> 31 | C21: =COUNTIFS(tblNodes[node_type],"Hub",tblNodes[region],$A21) -> 4 | D21: =SUMIFS(tblNodes[intake_estimate_central],tblNodes[node_type],"Organisation",tblNodes[region],$A21) -> 8612
A22: Middle East | B22: =COUNTIFS(tblNodes[node_type],"Organisation",tblNodes[region],$A22) -> 10 | C22: =COUNTIFS(tblNodes[node_type],"Hub",tblNodes[region],$A22) -> 2 | D22: =SUMIFS(tblNodes[intake_estimate_central],tblNodes[node_type],"Organisation",tblNodes[region],$A22) -> 841
A23: Canada | B23: =COUNTIFS(tblNodes[node_type],"Organisation",tblNodes[region],$A23) -> 12 | C23: =COUNTIFS(tblNodes[node_type],"Hub",tblNodes[region],$A23) -> 2 | D23: =SUMIFS(tblNodes[intake_estimate_central],tblNodes[node_type],"Organisation",tblNodes[region],$A23) -> 2739
A24: Total | B24: =SUM(B15:B23) -> 298 | D24: =SUM(D15:D23) -> 64706
A25: ORGANISATIONS BY SECTOR | B25: Count
A26: Investment Banking - Bulge Bracket | B26: =COUNTIFS(tblNodes[node_type],"Organisation",tblNodes[sector],$A26) -> 12
A27: Investment Banking - Elite Boutique / Independent Advisory | B27: =COUNTIFS(tblNodes[node_type],"Organisation",tblNodes[sector],$A27) -> 22
A28: Proprietary Trading / Quant | B28: =COUNTIFS(tblNodes[node_type],"Organisation",tblNodes[sector],$A28) -> 12
A29: Commercial / Retail Banking | B29: =COUNTIFS(tblNodes[node_type],"Organisation",tblNodes[sector],$A29) -> 106
A30: Custodian / Asset Servicing / Fund Administration | B30: =COUNTIFS(tblNodes[node_type],"Organisation",tblNodes[sector],$A30) -> 3
A31: Investment / Asset Management | B31: =COUNTIFS(tblNodes[node_type],"Organisation",tblNodes[sector],$A31) -> 37
A32: Insurance | B32: =COUNTIFS(tblNodes[node_type],"Organisation",tblNodes[sector],$A32) -> 42
A33: Ratings Agencies & Financial Data | B33: =COUNTIFS(tblNodes[node_type],"Organisation",tblNodes[sector],$A33) -> 14
A34: Consulting / Professional Services | B34: =COUNTIFS(tblNodes[node_type],"Organisation",tblNodes[sector],$A34) -> 9
A35: Fintech / Tech-Finance | B35: =COUNTIFS(tblNodes[node_type],"Organisation",tblNodes[sector],$A35) -> 8
A36: Policy / Development Bank | B36: =COUNTIFS(tblNodes[node_type],"Organisation",tblNodes[sector],$A36) -> 6
A37: Central Bank / Supervisor | B37: =COUNTIFS(tblNodes[node_type],"Organisation",tblNodes[sector],$A37) -> 13
... A39: NBFC / Diversified Financial | B39: =COUNTIFS(tblNodes[node_type],"Organisation",tblNodes[sector],$A39) -> 3
A41: EDGES BY TYPE | B41: Count
A42: PART_OF | B42: =COUNTIF(tblEdges[edge_type],$A42) -> 84
A43: LOCATED_IN | B43: =COUNTIF(tblEdges[edge_type],$A43) -> 472
A44: IN_SECTOR | B44: =COUNTIF(tblEdges[edge_type],$A44) -> 298
A45: RECRUITS_VIA (removed with mechanism nodes) | B45: =COUNTIF(tblEdges[edge_type],$A45) -> 0
A46: RECRUITS_FROM (removed with talent pools) | B46: =COUNTIF(tblEdges[edge_type],$A46) -> 0
A47: PARTNERS_WITH (removed with talent pools) | B47: =COUNTIF(tblEdges[edge_type],$A47) -> 0
A48: RECRUITS_VIA_INTERMEDIARY (removed with talent pools) | B48: =COUNTIF(tblEdges[edge_type],$A48) -> 0
A49: PARENT_OF | B49: =COUNTIF(tblEdges[edge_type],$A49) -> 14
A50: ABSORBED_BY (removed with Credit Suisse) | B50: =COUNTIF(tblEdges[edge_type],$A50) -> 0
A51: COMPETES_FOR_TALENT | B51: =COUNTIF(tblEdges[edge_type],$A51) -> 7
A52: PLACES_GRADUATES_IN | B52: =COUNTIF(tblEdges[edge_type],$A52) -> 4
A53: OFFSHORE_RECRUITS_FOR | B53: =COUNTIF(tblEdges[edge_type],$A53) -> 1
A54: MECHANISM_OF (removed with mechanism nodes) | B54: =COUNTIF(tblEdges[edge_type],$A54) -> 0
A55: Total edges | B55: =COUNTA(tblEdges[edge_id]) -> 880
A57: COVERAGE & INTEGRITY | B57: Value | C57: Note
A58: Organisations with a numeric annual intake | B58: {=SUMPRODUCT((tblNodes[node_type]="Organisation")*((tblNodes[annual_intake_low]<>"")+(tblNodes[annual_intake_high]<>"")>0))} -> 4 | C58: Blank intake = unknown, not zero
A59: Organisations with org_size_band = TBC | B59: =COUNTIFS(tblNodes[node_type],"Organisation",tblNodes[org_size_band],"TBC") -> 0 | C59: No size signal at all
A60: Organisations with an inferred size band | B60: =COUNTIFS(tblNodes[node_type],"Organisation",tblNodes[size_basis],"inferred - coarse band, verify") -> 298 | C60: size_basis flags these as editorial
A61: Confirmation [C-Official] (incl. Chinese portals) | B61: =COUNTIFS(tblNodes[node_type],"Organisation",tblNodes[confirmation_status],"[C-Official]")+COUNTIFS(tblNodes[node_type],"Organisation",tblNodes[confirmation_status],"[C-Official, Chinese]") -> 60 | C61: Highest-confidence core for Stage 1
A62: Confirmation [C-Press] | B62: =COUNTIFS(tblNodes[node_type],"Organisation",tblNodes[confirmation_status],"[C-Press]")+COUNTIFS(tblNodes[node_type],"Organisation",tblNodes[confirmation_status],"[C-Press, Chinese]") -> 50
A63: Confirmation [Note] | B63: =COUNTIFS(tblNodes[node_type],"Organisation",tblNodes[confirmation_status],"[Note]") -> 188 | C63: Unverified tail - verify before weighting
A64: Organisations present in more than one hub | B64: {=SUMPRODUCT((tblNodes[node_type]="Organisation")*(COUNTIFS(tblEdges[source_id],tblNodes[node_id],tblEdges[edge_type],"LOCATED_IN")>1))} -> 52 | C64: Cross-border presence via multiple LOCATED_IN edges
A65: Edges with an unresolved source_id | B65: {=SUMPRODUCT(--(COUNTIF(tblNodes[node_id],tblEdges[source_id])=0))} -> 0 | C65: Must be 0
A66: Edges with an unresolved target_id | B66: {=SUMPRODUCT(--(COUNTIF(tblNodes[node_id],tblEdges[target_id])=0))} -> 0 | C66: Must be 0
A68: UK / LONDON DIAGNOSTICS | B68: Count
A69: Organisations with a London presence | B69: =COUNTIFS(tblEdges[target_id],"GEO_H_LON",tblEdges[edge_type],"LOCATED_IN") -> 87
A70: UK-domiciled orgs whose primary mechanism is the Spring Week pipeline | B70: =COUNTIF(tblNodes[entry_mechanism_id],"MECH_UK_SPRING") -> 16
A71: UK-domiciled orgs whose primary mechanism is direct autumn entry | B71: =COUNTIF(tblNodes[entry_mechanism_id],"MECH_UK_SCHEME") -> 36
A73: ESTIMATED ANNUAL INTAKE — HOW IT IS BUILT
A74: Column | B74: Nodes!intake_estimate_central (S) and intake_estimate_basis (T)
A75: Documented rows | B75: Where the source gives a cohort size, the estimate is the midpoint of annual_intake_low/high. Five organisations qualify.
A76: Modelled rows | B76: Everything else = size-band base x sector factor x mechanism factor, all three retunable on the Assumptions sheet.
A77: Zero rows | B77: Five organisations have no confirmed programme (Inbursa, Grupo Aval, Davivienda, BCI) or have been absorbed (Credit Suisse) and are modelled as zero intake.
A78: Health warning | B78: Only 5 of 246 figures are sourced. The other 241 are order-of-magnitude judgements. They are fit for sizing nodes in a visualisation; they are NOT fit for quoting as intake statistics.
A79: Retuning | B79: Change any factor on Assumptions and every estimate plus these totals recalculate.

Sheet Assumptions
A1: Intake estimation assumptions
B2: The intake_estimate_central column on Nodes is a FORMULA, not typed numbers. Where the source document gives a cohort size, the documented figure wins. Otherwise the estimate is: size-band base x sector factor x mechanism factor. Retune any cell below and every estimate updates.
B3: These are order-of-magnitude judgements, not sourced figures. Treat them as a starting point for weighting the graph, not as data.
B4: 1. Size-band base (graduates per year) | C4: Base
B5: Mega | C5: 400
B6: Large | C6: 120
B7: Mid | C7: 30
B8: Boutique | C8: 8
B9: TBC | C9: 30
B12: 2. Sector factor | C12: Factor
B13: Investment Banking - Bulge Bracket | C13: 2
B14: Investment Banking - Elite Boutique / Independent Advisory | C14: 0.8
B15: Proprietary Trading / Quant | C15: 2
B16: Commercial / Retail Banking | C16: 1
B17: Custodian / Asset Servicing / Fund Administration | C17: 1.5
B18: Investment / Asset Management | C18: 0.8
B19: Insurance | C19: 1
B20: Ratings Agencies & Financial Data | C20: 1.5
B21: Consulting / Professional Services | C21: 3
B22: Fintech / Tech-Finance | C22: 1
B23: Policy / Development Bank | C23: 0.4
B24: Central Bank / Supervisor | C24: 1
... B26: NBFC / Diversified Financial | C26: 0.8
B29: 3. Mechanism factor | C29: Factor | D29: Rationale
B30: MECH_US_CONV | C30: 1 | D30: Internship-to-full-time conversion; cohort sized to the bank
B31: MECH_ACTUARIAL | C31: 0.5 | D31: Narrow technical track
B32: MECH_IN_EXAM | C32: 1.4 | D32: Centralised mass exam - hundreds of seats per bank per year
B33: MECH_IN_PGDBF | C33: 1.2 | D33: Hire-and-train diplomas run large cohorts
B34: MECH_IN_GCC | C34: 1 | D34: Elite-campus analyst intake
B35: MECH_CN_CYCLE | C35: 3 | D35: Quota-influenced autumn cycle; the source notes thousands hired per cycle
B36: MECH_BR_TRAINEE | C36: 0.25 | D36: A single annual trainee cohort is small and highly selective
B37: MECH_LATAM_ESTAGIO | C37: 0.8 | D37: Multiple internship cycles per year
B38: MECH_LATAM_CONCURSO | C38: 0.6 | D38: Public exam, irregular and not graduate-specific
B39: MECH_EU_ROTATIONAL | C39: 0.8 | D39: National-hub rotational schemes are mid-sized
B40: MECH_UK_SPRING | C40: 1 | D40: Spring Week funnel feeding a September analyst class
B41: MECH_UK_SCHEME | C41: 1 | D41: Direct autumn-to-September entry
... B47: MECH_CA_ROTATIONAL | C47: 1 | D47: Canadian new-grad rotational program, summer-internship fed

Sheet JSON
A1: {
A2: "nodes": [
A3: {"node_id":"GEO_R_USA","label":"USA","node_type":"Region","region":"USA","country":null,"hub_city":null,"sector":null,"subsector_tier":null,"entry_mechanism_id":null,"program_name":null,"program_length_months":null,"org_size_band":null,"size_basis":null,"annual_intake_low":null,"annual_intake_high":null,"applications_per_cycle":null,"intake_estimate_central":null,"intake_estimate_basis":null,"confirmation_status":null,"data_confidence":null,"geo_source":null,"notes":"Source region"},
A4: {"node_id":"GEO_R_INDIA","label":"India","node_type":"Region","region":"India","country":null,"hub_city":null,"sector":null,"subsector_tier":null,"entry_mechanism_id":null,"program_name":null,"program_length_months":null,"org_size_band":null,"size_basis":null,"annual_intake_low":null,"annual_intake_high":null,"applications_per_cycle":null,"intake_estimate_central":null,"intake_estimate_basis":null,"confirmation_status":null,"data_confidence":null,"geo_source":null,"notes":"Source region"},
A5: {"node_id":"GEO_R_CHINA","label":"China","node_type":"Region","region":"China","country":null,"hub_city":null,"sector":null,"subsector_tier":null,"entry_mechanism_id":null,"program_name":null,"program_length_months":null,"org_size_band":null,"size_basis":null,"annual_intake_low":null,"annual_intake_high":null,"applications_per_cycle":null,"intake_estimate_central":null,"intake_estimate_basis":null,"confirmation_status":null,"data_confidence":null,"geo_source":null,"notes":"Source region"},
A6: {"node_id":"GEO_R_LATAM","label":"Latin America","node_type":"Region","region":"Latin America","country":null,"hub_city":null,"sector":null,"subsector_tier":null,"entry_mechanism_id":null,"program_name":null,"program_length_months":null,"org_size_band":null,"size_basis":null,"annual_intake_low":null,"annual_intake_high":null,"applications_per_cycle":null,"intake_estimate_central":null,"intake_estimate_basis":null,"confirmation_status":null,"data_confidence":null,"geo_source":null,"notes":"Source region"},
A7: {"node_id":"GEO_R_EUROPE","label":"Continental Europe","node_type":"Region","region":"Continental Europe","country":null,"hub_city":null,"sector":null,"subsector_tier":null,"entry_mechanism_id":null,"program_name":null,"program_length_months":null,"org_size_band":null,"size_basis":null,"annual_intake_low":null,"annual_intake_high":null,"applications_per_cycle":null,"intake_estimate_central":null,"intake_estimate_basis":null,"confirmation_status":null,"data_confidence":null,"geo_source":null,"notes":"Source region"},
A8: {"node_id":"GEO_R_UK","label":"United Kingdom","node_type":"Region","region":"United Kingdom","country":null,"hub_city":null,"sector":null,"subsector_tier":null,"entry_mechanism_id":null,"program_name":null,"program_length_months":null,"org_size_band":null,"size_basis":null,"annual_intake_low":null,"annual_intake_high":null,"applications_per_cycle":null,"intake_estimate_central":null,"intake_estimate_basis":null,"confirmation_status":null,"data_confidence":null,"geo_source":null,"notes":"Source region 6 - added by research, not present in the source document (the source covers five regions and treats the UK list as its structural template only)"},
A9: {"node_id":"GEO_C_US","label":"United States","node_type":"Country","region":"USA","country":"United States","hub_city":null,"sector":null,"subsector_tier":null,"entry_mechanism_id":null,"program_name":null,"program_length_months":null,"org_size_band":null,"size_basis":null,"annual_intake_low":null,"annual_intake_high":null,"applications_per_cycle":null,"intake_estimate_central":null,"intake_estimate_basis":null,"confirmation_status":null,"data_confidence":null,"geo_source":null,"notes":null},
A10: {"node_id":"GEO_C_IN","label":"India","node_type":"Country","region":"India","country":"India","hub_city":null,"sector":null,"subsector_tier":null,"entry_mechanism_id":null,"program_name":null,"program_length_months":null,"org_size_band":null,"size_basis":null,"annual_intake_low":null,"annual_intake_high":null,"applications_per_cycle":null,"intake_estimate_central":null,"intake_estimate_basis":null,"confirmation_status":null,"data_confidence":null,"geo_source":null,"notes":null},
A11: {"node_id":"GEO_C_CN","label":"China","node_type":"Country","region":"China","country":"China","hub_city":null,"sector":null,"subsector_tier":null,"entry_mechanism_id":null,"program_name":null,"program_length_months":null,"org_size_band":null,"size_basis":null,"annual_intake_low":null,"annual_intake_high":null,"applications_per_cycle":null,"intake_estimate_central":null,"intake_estimate_basis":null,"confirmation_status":null,"data_confidence":null,"geo_source":null,"notes":null},
A12: {"node_id":"GEO_C_BR","label":"Brazil","node_type":"Country","region":"Latin America","country":"Brazil","hub_city":null,"sector":null,"subsector_tier":null,"entry_mechanism_id":null,"program_name":null,"program_length_months":null,"org_size_band":null,"size_basis":null,"annual_intake_low":null,"annual_intake_high":null,"applications_per_cycle":null,"intake_estimate_central":null,"intake_estimate_basis":null,"confirmation_status":null,"data_confidence":null,"geo_source":null,"notes":null},
... A1291: }
